Workbook

Sheet 📋 Cover & Index
A2: Test Company
A3: Monthly Controller Reporting Model
A4: Powered by Cin7 Core | Multi-Channel Ecommerce & Wholesale
A5: Data Period: March – November 2025 | Generated: Thu Mar 12 2026
A8: PERFORMANCE SNAPSHOT
A9: Total Revenue | C9: Gross Profit | E9: Gross Margin % | G9: Net Contribution
A10: ='KPI Dashboard'!B5 -> 0 | C10: ='KPI Dashboard'!D6 -> 0 | E10: ='KPI Dashboard'!B7 -> - | G10: ='KPI Dashboard'!D7 -> 0
A11: INVENTORY ALERTS → 🔴 Critical: 0 | 🟡 Low Stock: 1 | 🟢 Healthy: 3 | 🔵 Overstock: 4
A13: WORKBOOK INDEX
A14: # | B14: Sheet Name | C14: Type | D14: Purpose | E14: Updated By | F14: Frequency | G14: Data Source | H14: Status
A15: 1 | B15: Cost Inputs | C15: 📝 Input | D15: Manual entry of Ad Spend (by channel) and Warehouse/Fulfillment costs by month | E15: Controller | F15: Monthly | G15: Accounting Invoices | H15: ✅ Active
A16: 2 | B16: Sales Trend Analysis | C16: 📊 Analysis | D16: Revenue, COGS, Gross Profit & MoM Growth % across 6 channels × 6 months | E16: Auto | F16: Monthly | G16: Cin7 Core Export | H16: ✅ Active
A17: 3 | B17: Product Margin Analysis | C17: 📊 Analysis | D17: Revenue, COGS, GM%, Avg Sell Price & Avg COGS per unit by SKU and Category | E17: Auto | F17: Monthly | G17: Cin7 Core Export | H17: ✅ Active
A18: 4 | B18: COGS & Profitability by Channel | C18: 📊 Analysis | D18: Product × Channel revenue & COGS matrix with GM% per channel | E18: Auto | F18: Monthly | G18: Cin7 Core Export | H18: ✅ Active
A19: 5 | B19: Inventory & MOS Analysis | C19: 📦 Inventory | D19: Current stock by location, 3-month avg velocity, MOS calculation & 🔴🟡🟢🔵 alerts | E19: Auto | F19: Weekly | G19: Cin7 Core Export | H19: ✅ Active
A20: 6 | B20: Inventory Movements | C20: 📦 Inventory | D20: Units Sold, Units Purchased & Net Movement per SKU across all months | E20: Auto | F20: Monthly | G20: Cin7 Core + Purchase Data | H20: ✅ Active
A21: 7 | B21: Sales Dashboard | C21: 📈 Dashboard | D21: 3 visual charts: Revenue by Channel (bar), Monthly Trend (line), Product Mix (pie) | E21: Auto | F21: Monthly | G21: Calculated Sheets | H21: ✅ Active
A22: 8 | B22: Profitability Dashboard | C22: 📈 Dashboard | D22: Full P&L waterfall: Revenue → COGS → Gross Profit → Ad Spend → Fulfillment → Net Contribution | E22: Auto | F22: Monthly | G22: Calculated + Cost Inputs | H22: ✅ Active
A23: 9 | B23: KPI Dashboard | C23: 🎯 Executive | D23: One-page scorecard: Revenue, Margins, Channel Mix, Top Products, Inventory Alerts | E23: Auto | F23: Monthly | G23: All Sheets | H23: ✅ Active
A24: 10 | B24: Weekly Order Tracker | C24: ⚠️ Risk | D24: Invoice & shipment status breakdown, revenue at risk (Draft/Unshipped), monthly activity summary | E24: Auto | F24: Weekly | G24: Cin7 Core Export | H24: ✅ Active
A25: — | B25: Sales Transactions Raw Data | C25: 🗄️ Raw Data | D25: Source: Cin7 Core sales export — DO NOT EDIT. Paste new data here monthly | E25: Controller | F25: Monthly | G25: Cin7 Core | H25: 📥 Paste Here
A26: — | B26: Inventory On Hand Raw Data | C26: 🗄️ Raw Data | D26: Source: Cin7 Core inventory snapshot — DO NOT EDIT. Paste new data here | E26: Controller | F26: Weekly | G26: Cin7 Core | H26: 📥 Paste Here
A27: — | B27: Purchase Transactions Raw data | C27: 🗄️ Raw Data | D27: Source: Cin7 Core purchase export — DO NOT EDIT. Paste new data here monthly | E27: Controller | F27: Monthly | G27: Cin7 Core | H27: 📥 Paste Here
A30: CONTROLLER RECOMMENDATIONS & INSIGHTS
A31: # | B31: Category | C31: Finding | D31: Recommendation | E31: Priority | F31: Owner | G31: Action By | H31: Status
A32: 1 | B32: 💰 Revenue Mix | C32: Shopify Web is the largest single Finished Goods channel by coded SKU revenue. Amazon is 2nd but has the widest SKU distribution. | D32: Increase Amazon PPC investment and expand SKU listings. Consider Amazon Subscribe & Save for recurring revenue. | E32: 🔴 High | F32: Marketing | G32: Monthly | H32: 🔲 Open
A33: 2 | B33: 📦 Inventory - Starter 4pk | C33: Ola-Mate-SP1-16oz-4pk shows 0 stock at NJ, NY & NOBL warehouses. Only 0 units at Founders. Selling at 68% GM — your highest-margin SKU. | D33: Prioritise replenishment of the 4pk immediately. High margin + low stock = missed revenue opportunity. | E33: 🔴 High | F33: Ops / Supply Chain | G33: ASAP | H33: 🔲 Open
A34: 3 | B34: 📦 Inventory - 12pk Variety | C34: VP1-16oz-12pk has only 54 units on hand across Amazon FBA (54) — no stock at Founders or warehouses. Best-selling SKU by revenue. | D34: Urgent reorder. Run production/co-pack planning now. Consider holding a 2-month safety stock minimum. | E34: 🔴 High | F34: Ops / Supply Chain | G34: ASAP | H34: 🔲 Open
A35: 4 | B35: 📦 Inventory - Overstock | C35: Loose cans (BC, GG, R) at NJ Warehouse: 3,162–3,162 units. MOS likely >6 months. Powder Blends at MZ: 1,000 units each with zero sales recorded. | D35: Review slow-mover strategy for loose cans and Powder Blends. Consider bundling, sampling, or promotional pricing to move stock. | E35: 🟡 Medium | F35: Sales / Marketing | G35: 30 days | H35: 🔲 Open
A36: 5 | B36: 💸 Ad Spend Tracking | C36: Cost Inputs sheet is unpopulated — Ad Spend and Fulfillment costs are $0. Net Contribution currently equals Gross Profit, overstating true profitability. | D36: Enter monthly ad spend (Amazon Ads, Shopify/Google, TikTok) and 3PL/fulfillment invoices into 'Cost Inputs' sheet immediately. | E36: 🔴 High | F36: Controller | G36: This Month | H36: 🔲 Open
A37: 6 | B37: 📊 Gross Margin by SKU | C37: Starter 4pk (68.3%) and Loose Cans (55.5%) have significantly higher margins than the 12pk variety packs (~23–41%). Grapefruit Ginger 12pk is lowest at 23.1%. | D37: Run profitability-weighted product mix analysis. Shift marketing spend toward highest-margin SKUs. Investigate COGS on GG 12pk. | E37: 🟡 Medium | F37: Finance | G37: Next Month | H37: 🔲 Open
A38: 7 | B38: 🏪 Channel Profitability | C38: Wholesale (channel 3890849) shows $478 revenue — very early stage. POS is $77. These channels have near-zero volume but positive margin. | D38: Define minimum order quantities and pricing floors for wholesale. Build a wholesale P&L proforma before scaling. | E38: 🟡 Medium | F38: Sales | G38: 60 days | H38: 🔲 Open
A39: 8 | B39: 🔄 Subscription Revenue | C39: Subscriptions channel shows only $100 revenue (1 line). Subscription revenue should be the highest-LTV channel for a beverage brand. | D39: Audit subscription setup on Shopify. Consider a dedicated subscription discount + flavour rotation to grow recurring base. | E39: 🟡 Medium | F39: Marketing | G39: 30 days | H39: 🔲 Open
A40: 9 | B40: 📑 Draft Invoice Risk | C40: Weekly Order Tracker will flag any Draft invoices in the data. Uninvoiced orders represent recognised revenue not yet legally billed. | D40: Implement a weekly close process: convert all Draft invoices to Invoiced before month-end. Controller to review every Friday. | E40: 🟡 Medium | F40: Controller | G40: Weekly | H40: 🔲 Open
A41: 10 | B41: 📈 Data Freshness | C41: Current data spans March–November 2025 with gaps (Apr–Jun missing). MOS calculations use Sep–Nov as the 3-month window. | D41: Ensure Cin7 exports are complete and sequential. Update Month references in Inventory & MOS Analysis sheet each quarter. Add Dec 2025 data when available. | E41: 🟢 Low | F41: Controller | G41: Ongoing | H41: 🔲 Open
A42: 11 | B42: 🔧 Model Maintenance | C42: Powder Blends SKUs show $0 revenue and zero sales. Either not yet launched or data not captured. | D42: Confirm launch status of Powder Blends. If live, verify Cin7 SKU mapping matches model (Ola-Mate-POW-* wildcard). | E42: 🟢 Low | F42: Controller | G42: Verify | H42: 🔲 Open
A43: 12 | B43: 📊 KPI Benchmarking | C43: Current blended GM% is 37.7% on Finished Goods. No prior period to benchmark against. | D43: Establish monthly GM% targets by channel. Set 40%+ as target for Finished Goods blended GM. Track vs actuals in KPI Dashboard. | E43: 🟢 Low | F43: Finance | G43: Q1 Planning | H43: 🔲 Open
A45: HOW TO REFRESH THIS MODEL (Monthly Process)
A46: Step | B46: Action | C46: Detail
A47: Step 1 | B47: Export from Cin7 Core | C47: Run: Sales by Product Details report → export to CSV. Paste into 'Sales Transactions Raw Data' tab (replace all rows, keep headers).
A48: Step 2 | B48: Refresh Inventory Snapshot | C48: Export Cin7 Core → Inventory On Hand report → paste into 'Inventory On Hand Raw Data' tab.
A49: Step 3 | B49: Refresh Purchase Transactions | C49: Export Cin7 Core → Purchase Orders report → paste into 'Purchase Transactions Raw data' tab.
A50: Step 4 | B50: Update Cost Inputs | C50: Open 'Cost Inputs' tab. Enter Ad Spend invoices (Amazon Ads, Shopify/Google, TikTok, Other) and 3PL/Warehouse/FBA fees for the new month column.
A51: Step 5 | B51: Update MOS Month Window | C51: In 'Inventory & MOS Analysis' tab, update the 3 most recent months in the avg sales formulas (columns I5:I12) to reflect the latest 3 months.
A52: Step 6 | B52: Review KPI Dashboard | C52: Go to 'KPI Dashboard' — all metrics auto-refresh. Update the Inventory Alert counts from 'Inventory & MOS Analysis'.
A53: Step 7 | B53: Review Recommendations | C53: Return to this Cover sheet. Mark completed items ✅ in column H. Add new findings as needed.

Sheet KPI Dashboard
A1: OlaMate — Controller KPI Dashboard
A2: All-period summary | Finished Goods only | Update month references in Sales Trend Analysis as new data flows in
A4: REVENUE & PROFITABILITY
A5: Total Revenue (All Channels) | B5: =SUMIFS('Sales Transactions Raw Data'!V:V,'Sales Transactions Raw Data'!J:J,"Finished Goods") -> 0 | C5: Total Units Sold | D5: =SUMIFS('Sales Transactions Raw Data'!T:T,'Sales Transactions Raw Data'!J:J,"Finished Goods") -> 0
A6: Total COGS | B6: =SUMIFS('Sales Transactions Raw Data'!W:W,'Sales Transactions Raw Data'!J:J,"Finished Goods") -> 0 | C6: Gross Profit | D6: =B5-B6 -> 0
A7: Amazon FBA | B7: Ola-Mate-VP1-16oz-12pk | C7: 16oz Variety 12pk | D7: Case | E7: 450 | F7: 50 | G7: 200 | H7: 100 | I7: 18.5 | J7: 450 | K7: 400
A8: Founders | B8: Ola-Mate-VP1-16oz-12pk | C8: 16oz Variety 12pk | D8: Case | E8: 320 | F8: 20 | G8: 0 | H8: 0 | I8: 18.5 | J8: 320 | K8: 300
A9: NJ Warehouse | B9: Ola-Mate-VP1-16oz-12pk | C9: 16oz Variety 12pk | D9: Case | E9: 1200 | F9: 150 | G9: 500 | H9: 200 | I9: 18.5 | J9: 1200 | K9: 1050
A10: Amazon FBA | B10: Ola-Mate-BC-16oz-12PK | C10: 16oz Berry Coconut 12pk | D10: Case | E10: 580 | F10: 80 | G10: 150 | H10: 50 | I10: 17.2 | J10: 580 | K10: 500
A11: Founders | B11: Ola-Mate-BC-16oz-12PK | C11: 16oz Berry Coconut 12pk | D11: Case | E11: 240 | F11: 10 | G11: 0 | H11: 0 | I11: 17.2 | J11: 240 | K11: 230
A12: NJ Warehouse | B12: Ola-Mate-BC-16oz-12PK | C12: 16oz Berry Coconut 12pk | D12: Case | E12: 890 | F12: 90 | G12: 300 | H12: 100 | I12: 17.2 | J12: 890 | K12: 800
A13: Amazon FBA | B13: Ola-Mate-GG-16oz-12pk | C13: 16oz Ginger Peach 12pk | D13: Case | E13: 420 | F13: 40 | G13: 100 | H13: 50 | I13: 17.5 | J13: 420 | K13: 380
A14: Founders | B14: Ola-Mate-GG-16oz-12pk | C14: 16oz Ginger Peach 12pk | D14: Case | E14: 180 | F14: 15 | G14: 0 | H14: 0 | I14: 17.5 | J14: 180 | K14: 165
A15: NJ Warehouse | B15: Ola-Mate-GG-16oz-12pk | C15: 16oz Ginger Peach 12pk | D15: Case | E15: 750 | F15: 60 | G15: 250 | H15: 80 | I15: 17.5 | J15: 750 | K15: 690
A16: Amazon FBA | B16: Ola-Mate-R-16oz-12pk | C16: 16oz Mint Lime 12pk | D16: Case | E16: 390 | F16: 30 | G16: 100 | H16: 0 | I16: 16.8 | J16: 390 | K16: 360
A17: NJ Warehouse | B17: Ola-Mate-R-16oz-12pk | C17: 16oz Original Mate 12pk | D17: Case | E17: 920 | F17: 100 | G17: 400 | H17: 150 | I17: 16.5 | J17: 920 | K17: 820

Sheet Weekly Order Tracker
A1: Weekly Order Tracker — Open Items & Risk Flags
A2: Tracks open/pending orders by invoice & shipment status | Update 'As Of Date' in B3 each week
A3: As Of Date (Today): | B3: =TODAY() -> 46267
A5: ORDER STATUS SUMMARY
A6: Status | B6: # Orders | C6: Revenue Value | D6: % of Total | E6: COGS | F6: Gross Profit
A7: 2027 | B7: 2027-08 | C7: Pacific Beverage Bottlers | D7: 2027-08-01 | E7: August | F7: INV-August | G7: VNC Brand | H7: General Goods | I7: Finished Goods | J7: SKU-2026 | K7: Cin7 Raw Material (August) | L7: each | M7: Main Warehouse | N7: BATCH-2026 | O7: INV-PB-101 | P7: 1 | Q7: NaN | R7: 0 | S7: 0 | T7: 0
A8: 2027 | B8: 2027-08 | C8: Pacific Beverage Bottlers | D8: 2027-08-01 | E8: August | F8: INV-August | G8: VNC Brand | H8: General Goods | I8: Finished Goods | J8: SKU-2026 | K8: Cin7 Raw Material (August) | L8: each | M8: Main Warehouse | N8: BATCH-2026 | O8: INV-PB-102 | P8: 1 | Q8: NaN | R8: 0 | S8: 0 | T8: 0

Sheet Sales Trend Analysis
A1: Sales Trend Analysis — Monthly by Channel
A3: REVENUE BY CHANNEL ($) | B3: 46106 | C3: 46228 | D3: 46259 | E3: 46290 | F3: 46320 | G3: 46351 | H3: 46381 | I3: 46048 | J3: 46079 | K3: 46107 | L3: Total
A4: Amazon (Seller Central) | B4: =SUMIFS('Sales Transactions Raw Data'!V:V,'Sales Transactions Raw Data'!S:S,"amazon",'Sales Transactions Raw Data'!B:B,"March",'Sales Transactions Raw Data'!A:A,2025,'Sales Transactions Raw Data'!J:J,"Finished Goods") -> 0 | C4: =SUMIFS('Sales Transactions Raw Data'!V:V,'Sales Transactions Raw Data'!S:S,"amazon",'Sales Transactions Raw Data'!B:B,"March",'Sales Transactions Raw Data'!A:A,2025,'Sales Transactions Raw Data'!J:J,"Finished Goods") -> 0 | D4: =SUMIFS('Sales Transactions Raw Data'!V:V,'Sales Transactions Raw Data'!S:S,"amazon",'Sales Transactions Raw Data'!B:B,"July",'Sales Transactions Raw Data'!A:A,2025,'Sales Transactions Raw Data'!J:J,"Finished Goods") -> 0 | E4: =SUMIFS('Sales Transactions Raw Data'!V:V,'Sales Transactions Raw Data'!S:S,"amazon",'Sales Transactions Raw Data'!B:B,"August",'Sales Transactions Raw Data'!A:A,2025,'Sales Transactions Raw Data'!J:J,"Finished Goods") -> 0 | F4: =SUMIFS('Sales Transactions Raw Data'!V:V,'Sales Transactions Raw Data'!S:S,"amazon",'Sales Transactions Raw Data'!B:B,"September",'Sales Transactions Raw Data'!A:A,2025,'Sales Transactions Raw Data'!J:J,"Finished Goods") -> 0 | G4: =SUMIFS('Sales Transactions Raw Data'!V:V,'Sales Transactions Raw Data'!S:S,"amazon",'Sales Transactions Raw Data'!B:B,"October",'Sales Transactions Raw Data'!A:A,2025,'Sales Transactions Raw Data'!J:J,"Finished Goods") -> 0 | H4: =SUMIFS('Sales Transactions Raw Data'!V:V,'Sales Transactions Raw Data'!S:S,"amazon",'Sales Transactions Raw Data'!B:B,"November",'Sales Transactions Raw Data'!A:A,2025,'Sales Transactions Raw Data'!J:J,"Finished Goods") -> 0 | I4: =SUMIFS('Sales Transactions Raw Data'!V:V,'Sales Transactions Raw Data'!S:S,"amazon",'Sales Transactions Raw Data'!B:B,"January",'Sales Transactions Raw Data'!A:A,2026,'Sales Transactions Raw Data'!J:J,"Finished Goods") -> 0 | J4: =SUMIFS('Sales Transactions Raw Data'!V:V,'Sales Transactions Raw Data'!S:S,"amazon",'Sales Transactions Raw Data'!B:B,"February",'Sales Transactions Raw Data'!A:A,2026,'Sales Transactions Raw Data'!J:J,"Finished Goods") -> 0 | K4: =SUMIFS('Sales Transactions Raw Data'!V:V,'Sales Transactions Raw Data'!S:S,"amazon",'Sales Transactions Raw Data'!B:B,"March",'Sales Transactions Raw Data'!A:A,2026,'Sales Transactions Raw Data'!J:J,"Finished Goods") -> 0 | L4: =SUM(B4:K4) -> 0
A5: Amazon Retail / Vendor | B5: =SUMIFS('Sales Transactions Raw Data'!V:V,'Sales Transactions Raw Data'!R:R,"Amazon.com",'Sales Transactions Raw Data'!B:B,"March",'Sales Transactions Raw Data'!A:A,2025,'Sales Transactions Raw Data'!J:J,"Finished Goods") -> 0 | C5: =SUMIFS('Sales Transactions Raw Data'!V:V,'Sales Transactions Raw Data'!S:S,"amazon-us",'Sales Transactions Raw Data'!B:B,"March",'Sales Transactions Raw Data'!A:A,2025,'Sales Transactions Raw Data'!J:J,"Finished Goods") -> 0 | D5: =SUMIFS('Sales Transactions Raw Data'!V:V,'Sales Transactions Raw Data'!S:S,"amazon-us",'Sales Transactions Raw Data'!B:B,"July",'Sales Transactions Raw Data'!A:A,2025,'Sales Transactions Raw Data'!J:J,"Finished Goods") -> 0 | E5: =SUMIFS('Sales Transactions Raw Data'!V:V,'Sales Transactions Raw Data'!S:S,"amazon-us",'Sales Transactions Raw Data'!B:B,"August",'Sales Transactions Raw Data'!A:A,2025,'Sales Transactions Raw Data'!J:J,"Finished Goods") -> 0 | F5: =SUMIFS('Sales Transactions Raw Data'!V:V,'Sales Transactions Raw Data'!S:S,"amazon-us",'Sales Transactions Raw Data'!B:B,"September",'Sales Transactions Raw Data'!A:A,2025,'Sales Transactions Raw Data'!J:J,"Finished Goods") -> 0 | G5: =SUMIFS('Sales Transactions Raw Data'!V:V,'Sales Transactions Raw Data'!S:S,"amazon-us",'Sales Transactions Raw Data'!B:B,"October",'Sales Transactions Raw Data'!A:A,2025,'Sales Transactions Raw Data'!J:J,"Finished Goods") -> 0 | H5: =SUMIFS('Sales Transactions Raw Data'!V:V,'Sales Transactions Raw Data'!S:S,"amazon-us",'Sales Transactions Raw Data'!B:B,"November",'Sales Transactions Raw Data'!A:A,2025,'Sales Transactions Raw Data'!J:J,"Finished Goods") -> 0 | I5: =SUMIFS('Sales Transactions Raw Data'!V:V,'Sales Transactions Raw Data'!R:R,"Amazon.com",'Sales Transactions Raw Data'!B:B,"January",'Sales Transactions Raw Data'!A:A,2026,'Sales Transactions Raw Data'!J:J,"Finished Goods") -> 0 | J5: =SUMIFS('Sales Transactions Raw Data'!V:V,'Sales Transactions Raw Data'!R:R,"Amazon.com",'Sales Transactions Raw Data'!B:B,"February",'Sales Transactions Raw Data'!A:A,2026,'Sales Transactions Raw Data'!J:J,"Finished Goods") -> 0 | K5: =SUMIFS('Sales Transactions Raw Data'!V:V,'Sales Transactions Raw Data'!R:R,"Amazon.com",'Sales Transactions Raw Data'!B:B,"March",'Sales Transactions Raw Data'!A:A,2026,'Sales Transactions Raw Data'!J:J,"Finished Goods") -> 0 | L5: =SUM(B5:K5) -> 0
A6: Shopify Web (D2C) | B6: =SUMIFS('Sales Transactions Raw Data'!V:V,'Sales Transactions Raw Data'!S:S,"Shopify web",'Sales Transactions Raw Data'!B:B,"March",'Sales Transactions Raw Data'!A:A,2025,'Sales Transactions Raw Data'!J:J,"Finished Goods") -> 0 | C6: =SUMIFS('Sales Transactions Raw Data'!V:V,'Sales Transactions Raw Data'!S:S,"Shopify web",'Sales Transactions Raw Data'!B:B,"March",'Sales Transactions Raw Data'!A:A,2025,'Sales Transactions Raw Data'!J:J,"Finished Goods") -> 0 | D6: =SUMIFS('Sales Transactions Raw Data'!V:V,'Sales Transactions Raw Data'!S:S,"Shopify web",'Sales Transactions Raw Data'!B:B,"July",'Sales Transactions Raw Data'!A:A,2025,'Sales Transactions Raw Data'!J:J,"Finished Goods") -> 0 | E6: =SUMIFS('Sales Transactions Raw Data'!V:V,'Sales Transactions Raw Data'!S:S,"Shopify web",'Sales Transactions Raw Data'!B:B,"August",'Sales Transactions Raw Data'!A:A,2025,'Sales Transactions Raw Data'!J:J,"Finished Goods") -> 0 | F6: =SUMIFS('Sales Transactions Raw Data'!V:V,'Sales Transactions Raw Data'!S:S,"Shopify web",'Sales Transactions Raw Data'!B:B,"September",'Sales Transactions Raw Data'!A:A,2025,'Sales Transactions Raw Data'!J:J,"Finished Goods") -> 0 | G6: =SUMIFS('Sales Transactions Raw Data'!V:V,'Sales Transactions Raw Data'!S:S,"Shopify web",'Sales Transactions Raw Data'!B:B,"October",'Sales Transactions Raw Data'!A:A,2025,'Sales Transactions Raw Data'!J:J,"Finished Goods") -> 0 | H6: =SUMIFS('Sales Transactions Raw Data'!V:V,'Sales Transactions Raw Data'!S:S,"Shopify web",'Sales Transactions Raw Data'!B:B,"November",'Sales Transactions Raw Data'!A:A,2025,'Sales Transactions Raw Data'!J:J,"Finished Goods") -> 0 | I6: =SUMIFS('Sales Transactions Raw Data'!V:V,'Sales Transactions Raw Data'!S:S,"Shopify web",'Sales Transactions Raw Data'!B:B,"January",'Sales Transactions Raw Data'!A:A,2026,'Sales Transactions Raw Data'!J:J,"Finished Goods") -> 0 | J6: =SUMIFS('Sales Transactions Raw Data'!V:V,'Sales Transactions Raw Data'!S:S,"Shopify web",'Sales Transactions Raw Data'!B:B,"February",'Sales Transactions Raw Data'!A:A,2026,'Sales Transactions Raw Data'!J:J,"Finished Goods") -> 0 | K6: =SUMIFS('Sales Transactions Raw Data'!V:V,'Sales Transactions Raw Data'!S:S,"Shopify web",'Sales Transactions Raw Data'!B:B,"March",'Sales Transactions Raw Data'!A:A,2026,'Sales Transactions Raw Data'!J:J,"Finished Goods") -> 0 | L6: =SUM(B6:K6) -> 0
A7: Shopify POS (In-store) | B7: =SUMIFS('Sales Transactions Raw Data'!V:V,'Sales Transactions Raw Data'!S:S,"tiktok",'Sales Transactions Raw Data'!B:B,"March",'Sales Transactions Raw Data'!A:A,2025,'Sales Transactions Raw Data'!J:J,"Finished Goods") -> 0 | C7: =SUMIFS('Sales Transactions Raw Data'!V:V,'Sales Transactions Raw Data'!S:S,"Shopify POS",'Sales Transactions Raw Data'!B:B,"March",'Sales Transactions Raw Data'!A:A,2025,'Sales Transactions Raw Data'!J:J,"Finished Goods") -> 0 | D7: =SUMIFS('Sales Transactions Raw Data'!V:V,'Sales Transactions Raw Data'!S:S,"Shopify POS",'Sales Transactions Raw Data'!B:B,"July",'Sales Transactions Raw Data'!A:A,2025,'Sales Transactions Raw Data'!J:J,"Finished Goods") -> 0 | E7: =SUMIFS('Sales Transactions Raw Data'!V:V,'Sales Transactions Raw Data'!S:S,"Shopify POS",'Sales Transactions Raw Data'!B:B,"August",'Sales Transactions Raw Data'!A:A,2025,'Sales Transactions Raw Data'!J:J,"Finished Goods") -> 0 | F7: =SUMIFS('Sales Transactions Raw Data'!V:V,'Sales Transactions Raw Data'!S:S,"Shopify POS",'Sales Transactions Raw Data'!B:B,"September",'Sales Transactions Raw Data'!A:A,2025,'Sales Transactions Raw Data'!J:J,"Finished Goods") -> 0 | G7: =SUMIFS('Sales Transactions Raw Data'!V:V,'Sales Transactions Raw Data'!S:S,"Shopify POS",'Sales Transactions Raw Data'!B:B,"October",'Sales Transactions Raw Data'!A:A,2025,'Sales Transactions Raw Data'!J:J,"Finished Goods") -> 0 | H7: =SUMIFS('Sales Transactions Raw Data'!V:V,'Sales Transactions Raw Data'!S:S,"Shopify POS",'Sales Transactions Raw Data'!B:B,"November",'Sales Transactions Raw Data'!A:A,2025,'Sales Transactions Raw Data'!J:J,"Finished Goods") -> 0 | I7: =SUMIFS('Sales Transactions Raw Data'!V:V,'Sales Transactions Raw Data'!S:S,"tiktok",'Sales Transactions Raw Data'!B:B,"January",'Sales Transactions Raw Data'!A:A,2026,'Sales Transactions Raw Data'!J:J,"Finished Goods") -> 0 | J7: =SUMIFS('Sales Transactions Raw Data'!V:V,'Sales Transactions Raw Data'!S:S,"tiktok",'Sales Transactions Raw Data'!B:B,"February",'Sales Transactions Raw Data'!A:A,2026,'Sales Transactions Raw Data'!J:J,"Finished Goods") -> 0 | K7: =SUMIFS('Sales Transactions Raw Data'!V:V,'Sales Transactions Raw Data'!S:S,"tiktok",'Sales Transactions Raw Data'!B:B,"March",'Sales Transactions Raw Data'!A:A,2026,'Sales Transactions Raw Data'!J:J,"Finished Goods") -> 0 | L7: =SUM(B7:K7) -> 0
A8: Shopify Admin (Samples/Manual) | B8: =SUMIFS('Sales Transactions Raw Data'!V:V,'Sales Transactions Raw Data'!S:S,"296827748353",'Sales Transactions Raw Data'!B:B,"March",'Sales Transactions Raw Data'!A:A,2025,'Sales Transactions Raw Data'!J:J,"Finished Goods") -> 0 | C8: =SUMIFS('Sales Transactions Raw Data'!V:V,'Sales Transactions Raw Data'!S:S,"Shopify admin",'Sales Transactions Raw Data'!B:B,"March",'Sales Transactions Raw Data'!A:A,2025,'Sales Transactions Raw Data'!J:J,"Finished Goods") -> 0 | D8: =SUMIFS('Sales Transactions Raw Data'!V:V,'Sales Transactions Raw Data'!S:S,"Shopify admin",'Sales Transactions Raw Data'!B:B,"July",'Sales Transactions Raw Data'!A:A,2025,'Sales Transactions Raw Data'!J:J,"Finished Goods") -> 0 | E8: =SUMIFS('Sales Transactions Raw Data'!V:V,'Sales Transactions Raw Data'!S:S,"Shopify admin",'Sales Transactions Raw Data'!B:B,"August",'Sales Transactions Raw Data'!A:A,2025,'Sales Transactions Raw Data'!J:J,"Finished Goods") -> 0 | F8: =SUMIFS('Sales Transactions Raw Data'!V:V,'Sales Transactions Raw Data'!S:S,"Shopify admin",'Sales Transactions Raw Data'!B:B,"September",'Sales Transactions Raw Data'!A:A,2025,'Sales Transactions Raw Data'!J:J,"Finished Goods") -> 0 | G8: =SUMIFS('Sales Transactions Raw Data'!V:V,'Sales Transactions Raw Data'!S:S,"Shopify admin",'Sales Transactions Raw Data'!B:B,"October",'Sales Transactions Raw Data'!A:A,2025,'Sales Transactions Raw Data'!J:J,"Finished Goods") -> 0 | H8: =SUMIFS('Sales Transactions Raw Data'!V:V,'Sales Transactions Raw Data'!S:S,"Shopify admin",'Sales Transactions Raw Data'!B:B,"November",'Sales Transactions Raw Data'!A:A,2025,'Sales Transactions Raw Data'!J:J,"Finished Goods") -> 0 | I8: =SUMIFS('Sales Transactions Raw Data'!V:V,'Sales Transactions Raw Data'!S:S,"296827748353",'Sales Transactions Raw Data'!B:B,"January",'Sales Transactions Raw Data'!A:A,2026,'Sales Transactions Raw Data'!J:J,"Finished Goods") -> 0 | J8: =SUMIFS('Sales Transactions Raw Data'!V:V,'Sales Transactions Raw Data'!S:S,"296827748353",'Sales Transactions Raw Data'!B:B,"February",'Sales Transactions Raw Data'!A:A,2026,'Sales Transactions Raw Data'!J:J,"Finished Goods") -> 0 | K8: =SUMIFS('Sales Transactions Raw Data'!V:V,'Sales Transactions Raw Data'!S:S,"296827748353",'Sales Transactions Raw Data'!B:B,"March",'Sales Transactions Raw Data'!A:A,2026,'Sales Transactions Raw Data'!J:J,"Finished Goods") -> 0 | L8: =SUM(B8:K8) -> 0
A9: Subscriptions (contract) | B9: =SUMIFS('Sales Transactions Raw Data'!V:V,'Sales Transactions Raw Data'!S:S,"Shopify POS",'Sales Transactions Raw Data'!B:B,"March",'Sales Transactions Raw Data'!A:A,2025) -> 0 | C9: =SUMIFS('Sales Transactions Raw Data'!V:V,'Sales Transactions Raw Data'!S:S,"subscription_contract",'Sales Transactions Raw Data'!B:B,"March",'Sales Transactions Raw Data'!A:A,2025,'Sales Transactions Raw Data'!J:J,"Finished Goods") -> 0 | D9: =SUMIFS('Sales Transactions Raw Data'!V:V,'Sales Transactions Raw Data'!S:S,"subscription_contract",'Sales Transactions Raw Data'!B:B,"July",'Sales Transactions Raw Data'!A:A,2025,'Sales Transactions Raw Data'!J:J,"Finished Goods") -> 0 | E9: =SUMIFS('Sales Transactions Raw Data'!V:V,'Sales Transactions Raw Data'!S:S,"subscription_contract",'Sales Transactions Raw Data'!B:B,"August",'Sales Transactions Raw Data'!A:A,2025,'Sales Transactions Raw Data'!J:J,"Finished Goods") -> 0 | F9: =SUMIFS('Sales Transactions Raw Data'!V:V,'Sales Transactions Raw Data'!S:S,"subscription_contract",'Sales Transactions Raw Data'!B:B,"September",'Sales Transactions Raw Data'!A:A,2025,'Sales Transactions Raw Data'!J:J,"Finished Goods") -> 0 | G9: =SUMIFS('Sales Transactions Raw Data'!V:V,'Sales Transactions Raw Data'!S:S,"subscription_contract",'Sales Transactions Raw Data'!B:B,"October",'Sales Transactions Raw Data'!A:A,2025,'Sales Transactions Raw Data'!J:J,"Finished Goods") -> 0 | H9: =SUMIFS('Sales Transactions Raw Data'!V:V,'Sales Transactions Raw Data'!S:S,"subscription_contract",'Sales Transactions Raw Data'!B:B,"November",'Sales Transactions Raw Data'!A:A,2025,'Sales Transactions Raw Data'!J:J,"Finished Goods") -> 0 | I9: =SUMIFS('Sales Transactions Raw Data'!V:V,'Sales Transactions Raw Data'!S:S,"Shopify POS",'Sales Transactions Raw Data'!B:B,"January",'Sales Transactions Raw Data'!A:A,2026) -> 0 | J9: =SUMIFS('Sales Transactions Raw Data'!V:V,'Sales Transactions Raw Data'!S:S,"Shopify POS",'Sales Transactions Raw Data'!B:B,"February",'Sales Transactions Raw Data'!A:A,2026) -> 0 | K9: =SUMIFS('Sales Transactions Raw Data'!V:V,'Sales Transactions Raw Data'!S:S,"Shopify POS",'Sales Transactions Raw Data'!B:B,"March",'Sales Transactions Raw Data'!A:A,2026) -> 0 | L9: =SUM(B9:K9) -> 0
A10: Subscriptions (checkout) | B10: =SUMIFS('Sales Transactions Raw Data'!V:V,'Sales Transactions Raw Data'!S:S,"subscription_contract",'Sales Transactions Raw Data'!B:B,"March",'Sales Transactions Raw Data'!A:A,2025,'Sales Transactions Raw Data'!J:J,"Finished Goods")+SUMIFS('Sales Transactions Raw Data'!V:V,'Sales Transactions Raw Data'!S:S,"subscription_contract_checkout_one",'Sales Transactions Raw Data'!B:B,"March",'Sales Transactions Raw Data'!A:A,2025,'Sales Transactions Raw Data'!J:J,"Finished Goods") -> 0 | C10: =SUMIFS('Sales Transactions Raw Data'!V:V,'Sales Transactions Raw Data'!S:S,"subscription_contract_checkout_one",'Sales Transactions Raw Data'!B:B,"March",'Sales Transactions Raw Data'!A:A,2025,'Sales Transactions Raw Data'!J:J,"Finished Goods") -> 0 | D10: =SUMIFS('Sales Transactions Raw Data'!V:V,'Sales Transactions Raw Data'!S:S,"subscription_contract_checkout_one",'Sales Transactions Raw Data'!B:B,"July",'Sales Transactions Raw Data'!A:A,2025,'Sales Transactions Raw Data'!J:J,"Finished Goods") -> 0 | E10: =SUMIFS('Sales Transactions Raw Data'!V:V,'Sales Transactions Raw Data'!S:S,"subscription_contract_checkout_one",'Sales Transactions Raw Data'!B:B,"August",'Sales Transactions Raw Data'!A:A,2025,'Sales Transactions Raw Data'!J:J,"Finished Goods") -> 0 | F10: =SUMIFS('Sales Transactions Raw Data'!V:V,'Sales Transactions Raw Data'!S:S,"subscription_contract_checkout_one",'Sales Transactions Raw Data'!B:B,"September",'Sales Transactions Raw Data'!A:A,2025,'Sales Transactions Raw Data'!J:J,"Finished Goods") -> 0 | G10: =SUMIFS('Sales Transactions Raw Data'!V:V,'Sales Transactions Raw Data'!S:S,"subscription_contract_checkout_one",'Sales Transactions Raw Data'!B:B,"October",'Sales Transactions Raw Data'!A:A,2025,'Sales Transactions Raw Data'!J:J,"Finished Goods") -> 0 | H10: =SUMIFS('Sales Transactions Raw Data'!V:V,'Sales Transactions Raw Data'!S:S,"subscription_contract_checkout_one",'Sales Transactions Raw Data'!B:B,"November",'Sales Transactions Raw Data'!A:A,2025,'Sales Transactions Raw Data'!J:J,"Finished Goods") -> 0 | I10: =SUMIFS('Sales Transactions Raw Data'!V:V,'Sales Transactions Raw Data'!S:S,"subscription_contract",'Sales Transactions Raw Data'!B:B,"January",'Sales Transactions Raw Data'!A:A,2026,'Sales Transactions Raw Data'!J:J,"Finished Goods")+SUMIFS('Sales Transactions Raw Data'!V:V,'Sales Transactions Raw Data'!S:S,"subscription_contract_checkout_one",'Sales Transactions Raw Data'!B:B,"January",'Sales Transactions Raw Data'!A:A,2026,'Sales Transactions Raw Data'!J:J,"Finished Goods") -> 0 | J10: =SUMIFS('Sales Transactions Raw Data'!V:V,'Sales Transactions Raw Data'!S:S,"subscription_contract",'Sales Transactions Raw Data'!B:B,"February",'Sales Transactions Raw Data'!A:A,2026,'Sales Transactions Raw Data'!J:J,"Finished Goods")+SUMIFS('Sales Transactions Raw Data'!V:V,'Sales Transactions Raw Data'!S:S,"subscription_contract_checkout_one",'Sales Transactions Raw Data'!B:B,"February",'Sales Transactions Raw Data'!A:A,2026,'Sales Transactions Raw Data'!J:J,"Finished Goods") -> 0 | K10: =SUMIFS('Sales Transactions Raw Data'!V:V,'Sales Transactions Raw Data'!S:S,"subscription_contract",'Sales Transactions Raw Data'!B:B,"March",'Sales Transactions Raw Data'!A:A,2026,'Sales Transactions Raw Data'!J:J,"Finished Goods")+SUMIFS('Sales Transactions Raw Data'!V:V,'Sales Transactions Raw Data'!S:S,"subscription_contract_checkout_one",'Sales Transactions Raw Data'!B:B,"March",'Sales Transactions Raw Data'!A:A,2026,'Sales Transactions Raw Data'!J:J,"Finished Goods") -> 0 | L10: =SUM(B10:K10) -> 0
A11: Wholesale / Distrib (296827748353) | B11: =SUMIFS('Sales Transactions Raw Data'!V:V,'Sales Transactions Raw Data'!S:S,"Shopify admin",'Sales Transactions Raw Data'!B:B,"March",'Sales Transactions Raw Data'!A:A,2025,'Sales Transactions Raw Data'!J:J,"Finished Goods") -> 0 | C11: =SUMIFS('Sales Transactions Raw Data'!V:V,'Sales Transactions Raw Data'!S:S,"296827748353",'Sales Transactions Raw Data'!B:B,"March",'Sales Transactions Raw Data'!A:A,2025,'Sales Transactions Raw Data'!J:J,"Finished Goods") -> 0 | D11: =SUMIFS('Sales Transactions Raw Data'!V:V,'Sales Transactions Raw Data'!S:S,"296827748353",'Sales Transactions Raw Data'!B:B,"July",'Sales Transactions Raw Data'!A:A,2025,'Sales Transactions Raw Data'!J:J,"Finished Goods") -> 0 | E11: =SUMIFS('Sales Transactions Raw Data'!V:V,'Sales Transactions Raw Data'!S:S,"296827748353",'Sales Transactions Raw Data'!B:B,"August",'Sales Transactions Raw Data'!A:A,2025,'Sales Transactions Raw Data'!J:J,"Finished Goods") -> 0 | F11: =SUMIFS('Sales Transactions Raw Data'!V:V,'Sales Transactions Raw Data'!S:S,"296827748353",'Sales Transactions Raw Data'!B:B,"September",'Sales Transactions Raw Data'!A:A,2025,'Sales Transactions Raw Data'!J:J,"Finished Goods") -> 0 | G11: =SUMIFS('Sales Transactions Raw Data'!V:V,'Sales Transactions Raw Data'!S:S,"296827748353",'Sales Transactions Raw Data'!B:B,"October",'Sales Transactions Raw Data'!A:A,2025,'Sales Transactions Raw Data'!J:J,"Finished Goods") -> 0 | H11: =SUMIFS('Sales Transactions Raw Data'!V:V,'Sales Transactions Raw Data'!S:S,"296827748353",'Sales Transactions Raw Data'!B:B,"November",'Sales Transactions Raw Data'!A:A,2025,'Sales Transactions Raw Data'!J:J,"Finished Goods") -> 0 | I11: =SUMIFS('Sales Transactions Raw Data'!V:V,'Sales Transactions Raw Data'!S:S,"Shopify admin",'Sales Transactions Raw Data'!B:B,"January",'Sales Transactions Raw Data'!A:A,2026,'Sales Transactions Raw Data'!J:J,"Finished Goods") -> 0 | J11: =SUMIFS('Sales Transactions Raw Data'!V:V,'Sales Transactions Raw Data'!S:S,"Shopify admin",'Sales Transactions Raw Data'!B:B,"February",'Sales Transactions Raw Data'!A:A,2026,'Sales Transactions Raw Data'!J:J,"Finished Goods") -> 0 | K11: =SUMIFS('Sales Transactions Raw Data'!V:V,'Sales Transactions Raw Data'!S:S,"Shopify admin",'Sales Transactions Raw Data'!B:B,"March",'Sales Transactions Raw Data'!A:A,2026,'Sales Transactions Raw Data'!J:J,"Finished Goods") -> 0 | L11: =SUM(B11:K11) -> 0
A12: Faire (Wholesale Mkt) | C12: =SUMIFS('Sales Transactions Raw Data'!V:V,'Sales Transactions Raw Data'!S:S,"faire",'Sales Transactions Raw Data'!B:B,"March",'Sales Transactions Raw Data'!A:A,2025,'Sales Transactions Raw Data'!J:J,"Finished Goods") -> 0 | D12: =SUMIFS('Sales Transactions Raw Data'!V:V,'Sales Transactions Raw Data'!S:S,"faire",'Sales Transactions Raw Data'!B:B,"July",'Sales Transactions Raw Data'!A:A,2025,'Sales Transactions Raw Data'!J:J,"Finished Goods") -> 0 | E12: =SUMIFS('Sales Transactions Raw Data'!V:V,'Sales Transactions Raw Data'!S:S,"faire",'Sales Transactions Raw Data'!B:B,"August",'Sales Transactions Raw Data'!A:A,2025,'Sales Transactions Raw Data'!J:J,"Finished Goods") -> 0 | F12: =SUMIFS('Sales Transactions Raw Data'!V:V,'Sales Transactions Raw Data'!S:S,"faire",'Sales Transactions Raw Data'!B:B,"September",'Sales Transactions Raw Data'!A:A,2025,'Sales Transactions Raw Data'!J:J,"Finished Goods") -> 0 | G12: =SUMIFS('Sales Transactions Raw Data'!V:V,'Sales Transactions Raw Data'!S:S,"faire",'Sales Transactions Raw Data'!B:B,"October",'Sales Transactions Raw Data'!A:A,2025,'Sales Transactions Raw Data'!J:J,"Finished Goods") -> 0 | H12: =SUMIFS('Sales Transactions Raw Data'!V:V,'Sales Transactions Raw Data'!S:S,"faire",'Sales Transactions Raw Data'!B:B,"November",'Sales Transactions Raw Data'!A:A,2025,'Sales Transactions Raw Data'!J:J,"Finished Goods") -> 0
A13: TikTok Shop | B13: =SUM(B4:B11) -> 0 | C13: =SUMIFS('Sales Transactions Raw Data'!V:V,'Sales Transactions Raw Data'!S:S,"tiktok",'Sales Transactions Raw Data'!B:B,"March",'Sales Transactions Raw Data'!A:A,2025,'Sales Transactions Raw Data'!J:J,"Finished Goods") -> 0 | D13: =SUMIFS('Sales Transactions Raw Data'!V:V,'Sales Transactions Raw Data'!S:S,"tiktok",'Sales Transactions Raw Data'!B:B,"July",'Sales Transactions Raw Data'!A:A,2025,'Sales Transactions Raw Data'!J:J,"Finished Goods") -> 0 | E13: =SUMIFS('Sales Transactions Raw Data'!V:V,'Sales Transactions Raw Data'!S:S,"tiktok",'Sales Transactions Raw Data'!B:B,"August",'Sales Transactions Raw Data'!A:A,2025,'Sales Transactions Raw Data'!J:J,"Finished Goods") -> 0 | F13: =SUMIFS('Sales Transactions Raw Data'!V:V,'Sales Transactions Raw Data'!S:S,"tiktok",'Sales Transactions Raw Data'!B:B,"September",'Sales Transactions Raw Data'!A:A,2025,'Sales Transactions Raw Data'!J:J,"Finished Goods") -> 0 | G13: =SUMIFS('Sales Transactions Raw Data'!V:V,'Sales Transactions Raw Data'!S:S,"tiktok",'Sales Transactions Raw Data'!B:B,"October",'Sales Transactions Raw Data'!A:A,2025,'Sales Transactions Raw Data'!J:J,"Finished Goods") -> 0 | H13: =SUMIFS('Sales Transactions Raw Data'!V:V,'Sales Transactions Raw Data'!S:S,"tiktok",'Sales Transactions Raw Data'!B:B,"November",'Sales Transactions Raw Data'!A:A,2025,'Sales Transactions Raw Data'!J:J,"Finished Goods") -> 0 | I13: =SUM(I4:I11) -> 0 | J13: =SUM(J4:J11) -> 0 | K13: =SUM(K4:K11) -> 0 | L13: =SUM(L4:L11) -> 0
A14: Channel 4901177 | C14: =SUMIFS('Sales Transactions Raw Data'!V:V,'Sales Transactions Raw Data'!S:S,"4901177",'Sales Transactions Raw Data'!B:B,"March",'Sales Transactions Raw Data'!A:A,2025,'Sales Transactions Raw Data'!J:J,"Finished Goods") -> 0 | D14: =SUMIFS('Sales Transactions Raw Data'!V:V,'Sales Transactions Raw Data'!S:S,"4901177",'Sales Transactions Raw Data'!B:B,"July",'Sales Transactions Raw Data'!A:A,2025,'Sales Transactions Raw Data'!J:J,"Finished Goods") -> 0 | E14: =SUMIFS('Sales Transactions Raw Data'!V:V,'Sales Transactions Raw Data'!S:S,"4901177",'Sales Transactions Raw Data'!B:B,"August",'Sales Transactions Raw Data'!A:A,2025,'Sales Transactions Raw Data'!J:J,"Finished Goods") -> 0 | F14: =SUMIFS('Sales Transactions Raw Data'!V:V,'Sales Transactions Raw Data'!S:S,"4901177",'Sales Transactions Raw Data'!B:B,"September",'Sales Transactions Raw Data'!A:A,2025,'Sales Transactions Raw Data'!J:J,"Finished Goods") -> 0 | G14: =SUMIFS('Sales Transactions Raw Data'!V:V,'Sales Transactions Raw Data'!S:S,"4901177",'Sales Transactions Raw Data'!B:B,"October",'Sales Transactions Raw Data'!A:A,2025,'Sales Transactions Raw Data'!J:J,"Finished Goods") -> 0 | H14: =SUMIFS('Sales Transactions Raw Data'!V:V,'Sales Transactions Raw Data'!S:S,"4901177",'Sales Transactions Raw Data'!B:B,"November",'Sales Transactions Raw Data'!A:A,2025,'Sales Transactions Raw Data'!J:J,"Finished Goods") -> 0
A15: Channel 3890849 | B15: - | C15: =SUMIFS('Sales Transactions Raw Data'!V:V,'Sales Transactions Raw Data'!S:S,"3890849",'Sales Transactions Raw Data'!B:B,"March",'Sales Transactions Raw Data'!A:A,2025,'Sales Transactions Raw Data'!J:J,"Finished Goods") -> 0 | D15: =SUMIFS('Sales Transactions Raw Data'!V:V,'Sales Transactions Raw Data'!S:S,"3890849",'Sales Transactions Raw Data'!B:B,"July",'Sales Transactions Raw Data'!A:A,2025,'Sales Transactions Raw Data'!J:J,"Finished Goods") -> 0 | E15: =SUMIFS('Sales Transactions Raw Data'!V:V,'Sales Transactions Raw Data'!S:S,"3890849",'Sales Transactions Raw Data'!B:B,"August",'Sales Transactions Raw Data'!A:A,2025,'Sales Transactions Raw Data'!J:J,"Finished Goods") -> 0 | F15: =SUMIFS('Sales Transactions Raw Data'!V:V,'Sales Transactions Raw Data'!S:S,"3890849",'Sales Transactions Raw Data'!B:B,"September",'Sales Transactions Raw Data'!A:A,2025,'Sales Transactions Raw Data'!J:J,"Finished Goods") -> 0 | G15: =SUMIFS('Sales Transactions Raw Data'!V:V,'Sales Transactions Raw Data'!S:S,"3890849",'Sales Transactions Raw Data'!B:B,"October",'Sales Transactions Raw Data'!A:A,2025,'Sales Transactions Raw Data'!J:J,"Finished Goods") -> 0 | H15: =SUMIFS('Sales Transactions Raw Data'!V:V,'Sales Transactions Raw Data'!S:S,"3890849",'Sales Transactions Raw Data'!B:B,"November",'Sales Transactions Raw Data'!A:A,2025,'Sales Transactions Raw Data'!J:J,"Finished Goods") -> 0 | I15: =IF(H13=0,"-",I13/H13-1) -> - | J15: =IF(I13=0,"-",J13/I13-1) -> - | K15: =IF(J13=0,"-",K13/J13-1) -> -
A16: Channel 2329312 | C16: =SUMIFS('Sales Transactions Raw Data'!V:V,'Sales Transactions Raw Data'!S:S,"2329312",'Sales Transactions Raw Data'!B:B,"March",'Sales Transactions Raw Data'!A:A,2025,'Sales Transactions Raw Data'!J:J,"Finished Goods") -> 0 | D16: =SUMIFS('Sales Transactions Raw Data'!V:V,'Sales Transactions Raw Data'!S:S,"2329312",'Sales Transactions Raw Data'!B:B,"July",'Sales Transactions Raw Data'!A:A,2025,'Sales Transactions Raw Data'!J:J,"Finished Goods") -> 0 | E16: =SUMIFS('Sales Transactions Raw Data'!V:V,'Sales Transactions Raw Data'!S:S,"2329312",'Sales Transactions Raw Data'!B:B,"August",'Sales Transactions Raw Data'!A:A,2025,'Sales Transactions Raw Data'!J:J,"Finished Goods") -> 0 | F16: =SUMIFS('Sales Transactions Raw Data'!V:V,'Sales Transactions Raw Data'!S:S,"2329312",'Sales Transactions Raw Data'!B:B,"September",'Sales Transactions Raw Data'!A:A,2025,'Sales Transactions Raw Data'!J:J,"Finished Goods") -> 0 | G16: =SUMIFS('Sales Transactions Raw Data'!V:V,'Sales Transactions Raw Data'!S:S,"2329312",'Sales Transactions Raw Data'!B:B,"October",'Sales Transactions Raw Data'!A:A,2025,'Sales Transactions Raw Data'!J:J,"Finished Goods") -> 0 | H16: =SUMIFS('Sales Transactions Raw Data'!V:V,'Sales Transactions Raw Data'!S:S,"2329312",'Sales Transactions Raw Data'!B:B,"November",'Sales Transactions Raw Data'!A:A,2025,'Sales Transactions Raw Data'!J:J,"Finished Goods") -> 0
A17: TOTAL REVENUE | B17: =SUMIFS('Sales Transactions Raw Data'!W:W,'Sales Transactions Raw Data'!B:B,"March",'Sales Transactions Raw Data'!A:A,2025,'Sales Transactions Raw Data'!J:J,"Finished Goods") -> 0 | C17: =SUM(C4:C16) -> 0 | D17: =SUM(D4:D16) -> 0 | E17: =SUM(E4:E16) -> 0 | F17: =SUM(F4:F16) -> 0 | G17: =SUM(G4:G16) -> 0 | H17: =SUM(H4:H16) -> 0 | I17: =SUMIFS('Sales Transactions Raw Data'!W:W,'Sales Transactions Raw Data'!B:B,"January",'Sales Transactions Raw Data'!A:A,2026,'Sales Transactions Raw Data'!J:J,"Finished Goods") -> 0 | J17: =SUMIFS('Sales Transactions Raw Data'!W:W,'Sales Transactions Raw Data'!B:B,"February",'Sales Transactions Raw Data'!A:A,2026,'Sales Transactions Raw Data'!J:J,"Finished Goods") -> 0 | K17: =SUMIFS('Sales Transactions Raw Data'!W:W,'Sales Transactions Raw Data'!B:B,"March",'Sales Transactions Raw Data'!A:A,2026,'Sales Transactions Raw Data'!J:J,"Finished Goods") -> 0 | L17: =SUM(B17:K17) -> 0
A18: GROSS PROFIT | B18: =B13-B17 -> 0 | C18: =C13-C17 -> 0 | D18: =D13-D17 -> 0 | E18: =E13-E17 -> 0 | F18: =F13-F17 -> 0 | G18: =G13-G17 -> 0 | H18: =H13-H17 -> 0 | I18: =I13-I17 -> 0 | ... L18: =L13-L17 -> 0
A19: COGS (All Finished Goods) | B19: =IF(B13=0,"-",B18/B13) -> - | C19: =SUMIFS('Sales Transactions Raw Data'!W:W,'Sales Transactions Raw Data'!B:B,"March",'Sales Transactions Raw Data'!A:A,2025,'Sales Transactions Raw Data'!J:J,"Finished Goods") -> 0 | D19: =SUMIFS('Sales Transactions Raw Data'!W:W,'Sales Transactions Raw Data'!B:B,"July",'Sales Transactions Raw Data'!A:A,2025,'Sales Transactions Raw Data'!J:J,"Finished Goods") -> 0 | E19: =SUMIFS('Sales Transactions Raw Data'!W:W,'Sales Transactions Raw Data'!B:B,"August",'Sales Transactions Raw Data'!A:A,2025,'Sales Transactions Raw Data'!J:J,"Finished Goods") -> 0 | F19: =SUMIFS('Sales Transactions Raw Data'!W:W,'Sales Transactions Raw Data'!B:B,"September",'Sales Transactions Raw Data'!A:A,2025,'Sales Transactions Raw Data'!J:J,"Finished Goods") -> 0 | G19: =SUMIFS('Sales Transactions Raw Data'!W:W,'Sales Transactions Raw Data'!B:B,"October",'Sales Transactions Raw Data'!A:A,2025,'Sales Transactions Raw Data'!J:J,"Finished Goods") -> 0 | H19: =SUMIFS('Sales Transactions Raw Data'!W:W,'Sales Transactions Raw Data'!B:B,"November",'Sales Transactions Raw Data'!A:A,2025,'Sales Transactions Raw Data'!J:J,"Finished Goods") -> 0 | I19: =IF(I13=0,"-",I18/I13) -> - | J19: =IF(J13=0,"-",J18/J13) -> - | K19: =IF(K13=0,"-",K18/K13) -> - | L19: =IF(L13=0,"-",L18/L13) -> -
A20: Gross Profit | C20: =C17-C19 -> 0 | D20: =D17-D19 -> 0 | E20: =E17-E19 -> 0 | F20: =F17-F19 -> 0 | G20: =G17-G19 -> 0 | H20: =H17-H19 -> 0
A21: Gross Margin % | C21: =IF(C17=0,"-",C20/C17) -> - | D21: =IF(D17=0,"-",D20/D17) -> - | E21: =IF(E17=0,"-",E20/E17) -> - | F21: =IF(F17=0,"-",F20/F17) -> - | G21: =IF(G17=0,"-",G20/G17) -> - | H21: =IF(H17=0,"-",H20/H17) -> -
A22: MoM Revenue Growth | C22: — | D22: =IF(C17=0,"-",D17/C17-1) -> - | E22: =IF(D17=0,"-",E17/D17-1) -> - | F22: =IF(E17=0,"-",F17/E17-1) -> - | G22: =IF(F17=0,"-",G17/F17-1) -> - | H22: =IF(G17=0,"-",H17/G17-1) -> -

Sheet Product Margin Analysis
A1: Product Margin Analysis — by Product Attributes
A2: Filtered to Finished Goods only (excludes Service items like Shipping, Discounts)
A4: BY PRODUCT (SKU) | B4: Units Sold | C4: Revenue | D4: COGS | E4: Gross Profit | F4: GM% | G4: Avg Sell Price | H4: Avg COGS/Unit
A5: 16oz Variety 12pk | B5: =SUMIFS('Sales Transactions Raw Data'!T:T,'Sales Transactions Raw Data'!G:G,"Ola-Mate-VP1-16oz-12pk",'Sales Transactions Raw Data'!J:J,"Finished Goods") -> 0 | C5: =SUMIFS('Sales Transactions Raw Data'!V:V,'Sales Transactions Raw Data'!G:G,"Ola-Mate-VP1-16oz-12pk",'Sales Transactions Raw Data'!J:J,"Finished Goods") -> 0 | D5: =SUMIFS('Sales Transactions Raw Data'!W:W,'Sales Transactions Raw Data'!G:G,"Ola-Mate-VP1-16oz-12pk",'Sales Transactions Raw Data'!J:J,"Finished Goods") -> 0 | E5: =C5-D5 -> 0 | F5: =IF(C5=0,"-",E5/C5) -> - | G5: =IF(B5=0,"-",C5/B5) -> - | H5: =IF(B5=0,"-",D5/B5) -> -
A6: 16oz Berry Coconut 12pk | B6: =SUMIFS('Sales Transactions Raw Data'!T:T,'Sales Transactions Raw Data'!G:G,"Ola-Mate-BC-16oz-12PK",'Sales Transactions Raw Data'!J:J,"Finished Goods") -> 0 | C6: =SUMIFS('Sales Transactions Raw Data'!V:V,'Sales Transactions Raw Data'!G:G,"Ola-Mate-BC-16oz-12PK",'Sales Transactions Raw Data'!J:J,"Finished Goods") -> 0 | D6: =SUMIFS('Sales Transactions Raw Data'!W:W,'Sales Transactions Raw Data'!G:G,"Ola-Mate-BC-16oz-12PK",'Sales Transactions Raw Data'!J:J,"Finished Goods") -> 0 | E6: =C6-D6 -> 0 | F6: =IF(C6=0,"-",E6/C6) -> - | G6: =IF(B6=0,"-",C6/B6) -> - | H6: =IF(B6=0,"-",D6/B6) -> -
A7: 16oz Raspberry 12pk | B7: =SUMIFS('Sales Transactions Raw Data'!T:T,'Sales Transactions Raw Data'!G:G,"Ola-Mate-R-16oz-12pk",'Sales Transactions Raw Data'!J:J,"Finished Goods") -> 0 | C7: =SUMIFS('Sales Transactions Raw Data'!V:V,'Sales Transactions Raw Data'!G:G,"Ola-Mate-R-16oz-12pk",'Sales Transactions Raw Data'!J:J,"Finished Goods") -> 0 | D7: =SUMIFS('Sales Transactions Raw Data'!W:W,'Sales Transactions Raw Data'!G:G,"Ola-Mate-R-16oz-12pk",'Sales Transactions Raw Data'!J:J,"Finished Goods") -> 0 | E7: =C7-D7 -> 0 | F7: =IF(C7=0,"-",E7/C7) -> - | G7: =IF(B7=0,"-",C7/B7) -> - | H7: =IF(B7=0,"-",D7/B7) -> -
A8: 16oz Grapefruit Ginger 12pk | B8: =SUMIFS('Sales Transactions Raw Data'!T:T,'Sales Transactions Raw Data'!G:G,"Ola-Mate-GG-16oz-12pk",'Sales Transactions Raw Data'!J:J,"Finished Goods") -> 0 | C8: =SUMIFS('Sales Transactions Raw Data'!V:V,'Sales Transactions Raw Data'!G:G,"Ola-Mate-GG-16oz-12pk",'Sales Transactions Raw Data'!J:J,"Finished Goods") -> 0 | D8: =SUMIFS('Sales Transactions Raw Data'!W:W,'Sales Transactions Raw Data'!G:G,"Ola-Mate-GG-16oz-12pk",'Sales Transactions Raw Data'!J:J,"Finished Goods") -> 0 | E8: =C8-D8 -> 0 | F8: =IF(C8=0,"-",E8/C8) -> - | G8: =IF(B8=0,"-",C8/B8) -> - | H8: =IF(B8=0,"-",D8/B8) -> -
A9: 16oz Starter 4pk | B9: =SUMIFS('Sales Transactions Raw Data'!T:T,'Sales Transactions Raw Data'!G:G,"Ola-Mate-SP1-16oz-4pk",'Sales Transactions Raw Data'!J:J,"Finished Goods") -> 0 | C9: =SUMIFS('Sales Transactions Raw Data'!V:V,'Sales Transactions Raw Data'!G:G,"Ola-Mate-SP1-16oz-4pk",'Sales Transactions Raw Data'!J:J,"Finished Goods") -> 0 | D9: =SUMIFS('Sales Transactions Raw Data'!W:W,'Sales Transactions Raw Data'!G:G,"Ola-Mate-SP1-16oz-4pk",'Sales Transactions Raw Data'!J:J,"Finished Goods") -> 0 | E9: =C9-D9 -> 0 | F9: =IF(C9=0,"-",E9/C9) -> - | G9: =IF(B9=0,"-",C9/B9) -> - | H9: =IF(B9=0,"-",D9/B9) -> -
A10: 1can (BC/GG/R) - loose | B10: =SUMIFS('Sales Transactions Raw Data'!T:T,'Sales Transactions Raw Data'!G:G,"Ola-Mate-BC-16oz-1can",'Sales Transactions Raw Data'!J:J,"Finished Goods")+SUMIFS('Sales Transactions Raw Data'!T:T,'Sales Transactions Raw Data'!G:G,"Ola-Mate-GG-16oz-1can",'Sales Transactions Raw Data'!J:J,"Finished Goods")+SUMIFS('Sales Transactions Raw Data'!T:T,'Sales Transactions Raw Data'!G:G,"Ola-Mate-R-16oz-1can",'Sales Transactions Raw Data'!J:J,"Finished Goods") -> 0 | C10: =SUMIFS('Sales Transactions Raw Data'!V:V,'Sales Transactions Raw Data'!G:G,"Ola-Mate-BC-16oz-1can",'Sales Transactions Raw Data'!J:J,"Finished Goods")+SUMIFS('Sales Transactions Raw Data'!V:V,'Sales Transactions Raw Data'!G:G,"Ola-Mate-GG-16oz-1can",'Sales Transactions Raw Data'!J:J,"Finished Goods")+SUMIFS('Sales Transactions Raw Data'!V:V,'Sales Transactions Raw Data'!G:G,"Ola-Mate-R-16oz-1can",'Sales Transactions Raw Data'!J:J,"Finished Goods") -> 0 | D10: =SUMIFS('Sales Transactions Raw Data'!W:W,'Sales Transactions Raw Data'!G:G,"Ola-Mate-BC-16oz-1can",'Sales Transactions Raw Data'!J:J,"Finished Goods")+SUMIFS('Sales Transactions Raw Data'!W:W,'Sales Transactions Raw Data'!G:G,"Ola-Mate-GG-16oz-1can",'Sales Transactions Raw Data'!J:J,"Finished Goods")+SUMIFS('Sales Transactions Raw Data'!W:W,'Sales Transactions Raw Data'!G:G,"Ola-Mate-R-16oz-1can",'Sales Transactions Raw Data'!J:J,"Finished Goods") -> 0 | E10: =C10-D10 -> 0 | F10: =IF(C10=0,"-",E10/C10) -> - | G10: =IF(B10=0,"-",C10/B10) -> - | H10: =IF(B10=0,"-",D10/B10) -> -
A11: Powder Blends (new) | B11: =SUMIFS('Sales Transactions Raw Data'!T:T,'Sales Transactions Raw Data'!G:G,"Ola-Mate-POW-*",'Sales Transactions Raw Data'!J:J,"Finished Goods") -> 0 | C11: =SUMIFS('Sales Transactions Raw Data'!V:V,'Sales Transactions Raw Data'!G:G,"Ola-Mate-POW-*",'Sales Transactions Raw Data'!J:J,"Finished Goods") -> 0 | D11: =SUMIFS('Sales Transactions Raw Data'!W:W,'Sales Transactions Raw Data'!G:G,"Ola-Mate-POW-*",'Sales Transactions Raw Data'!J:J,"Finished Goods") -> 0 | E11: =C11-D11 -> 0 | F11: =IF(C11=0,"-",E11/C11) -> - | G11: =IF(B11=0,"-",C11/B11) -> - | H11: =IF(B11=0,"-",D11/B11) -> -
A12: TOTAL PRODUCTS | B12: =SUM(B5:B11) -> 0 | C12: =SUM(C5:C11) -> 0 | D12: =SUM(D5:D11) -> 0 | E12: =C12-D12 -> 0 | F12: =IF(C12=0,"-",E12/C12) -> - | G12: =IF(B12=0,"-",C12/B12) -> - | H12: =IF(B12=0,"-",D12/B12) -> -
A14: BY CATEGORY | B14: Units Sold | C14: Revenue | D14: COGS | E14: Gross Profit | F14: GM% | G14: Revenue % | H14: Avg Sell Price
A15: Finished Goods | B15: =SUMIFS('Sales Transactions Raw Data'!T:T,'Sales Transactions Raw Data'!J:J,"Finished Goods") -> 0 | C15: =SUMIFS('Sales Transactions Raw Data'!V:V,'Sales Transactions Raw Data'!J:J,"Finished Goods") -> 0 | D15: =SUMIFS('Sales Transactions Raw Data'!W:W,'Sales Transactions Raw Data'!J:J,"Finished Goods") -> 0 | E15: =C15-D15 -> 0 | F15: =IF(C15=0,"-",E15/C15) -> - | G15: =IF(C$17=0,"-",C15/C$17) -> - | H15: =IF(B15=0,"-",C15/B15) -> -
A16: Service (Shipping/Discounts/POS) | B16: =SUMIFS('Sales Transactions Raw Data'!T:T,'Sales Transactions Raw Data'!J:J,"Service") -> 0 | C16: =SUMIFS('Sales Transactions Raw Data'!V:V,'Sales Transactions Raw Data'!J:J,"Service") -> 0 | D16: =SUMIFS('Sales Transactions Raw Data'!W:W,'Sales Transactions Raw Data'!J:J,"Service") -> 0 | E16: =C16-D16 -> 0 | F16: =IF(C16=0,"-",E16/C16) -> - | G16: =IF(C$17=0,"-",C16/C$17) -> - | H16: =IF(B16=0,"-",C16/B16) -> -
A17: GRAND TOTAL | B17: =B15+B16 -> 0 | C17: =C15+C16 -> 0 | D17: =D15+D16 -> 0 | E17: =C17-D17 -> 0 | F17: =IF(C17=0,"-",E17/C17) -> - | G17: 1

Sheet COGS & Profitability by Channel
A1: COGS & Profitability by Product × Sales Channel
A2: Finished Goods only | All time periods combined
A4: REVENUE BY CHANNEL × PRODUCT | B4: Amazon | C4: Amazon Retail | D4: Shopify Web | E4: Shopify POS | F4: Shopify Admin | G4: Subs (contract) | H4: Subs (checkout) | I4: Wholesale 296... | J4: Faire | K4: TikTok | L4: Ch 4901177 | M4: Ch 3890849 | N4: Total
A5: 16oz Variety 12pk | B5: =SUMIFS('Sales Transactions Raw Data'!V:V,'Sales Transactions Raw Data'!G:G,"Ola-Mate-VP1-16oz-12pk",'Sales Transactions Raw Data'!S:S,"amazon",'Sales Transactions Raw Data'!J:J,"Finished Goods") -> 0 | C5: =SUMIFS('Sales Transactions Raw Data'!V:V,'Sales Transactions Raw Data'!G:G,"Ola-Mate-VP1-16oz-12pk",'Sales Transactions Raw Data'!S:S,"amazon-us",'Sales Transactions Raw Data'!J:J,"Finished Goods") -> 0 | D5: =SUMIFS('Sales Transactions Raw Data'!V:V,'Sales Transactions Raw Data'!G:G,"Ola-Mate-VP1-16oz-12pk",'Sales Transactions Raw Data'!S:S,"Shopify web",'Sales Transactions Raw Data'!J:J,"Finished Goods") -> 0 | E5: =SUMIFS('Sales Transactions Raw Data'!V:V,'Sales Transactions Raw Data'!G:G,"Ola-Mate-VP1-16oz-12pk",'Sales Transactions Raw Data'!S:S,"Shopify POS",'Sales Transactions Raw Data'!J:J,"Finished Goods") -> 0 | F5: =SUMIFS('Sales Transactions Raw Data'!V:V,'Sales Transactions Raw Data'!G:G,"Ola-Mate-VP1-16oz-12pk",'Sales Transactions Raw Data'!S:S,"Shopify admin",'Sales Transactions Raw Data'!J:J,"Finished Goods") -> 0 | G5: =SUMIFS('Sales Transactions Raw Data'!V:V,'Sales Transactions Raw Data'!G:G,"Ola-Mate-VP1-16oz-12pk",'Sales Transactions Raw Data'!S:S,"subscription_contract",'Sales Transactions Raw Data'!J:J,"Finished Goods") -> 0 | H5: =SUMIFS('Sales Transactions Raw Data'!V:V,'Sales Transactions Raw Data'!G:G,"Ola-Mate-VP1-16oz-12pk",'Sales Transactions Raw Data'!S:S,"subscription_contract_checkout_one",'Sales Transactions Raw Data'!J:J,"Finished Goods") -> 0 | I5: =SUMIFS('Sales Transactions Raw Data'!V:V,'Sales Transactions Raw Data'!G:G,"Ola-Mate-VP1-16oz-12pk",'Sales Transactions Raw Data'!S:S,"296827748353",'Sales Transactions Raw Data'!J:J,"Finished Goods") -> 0 | J5: =SUMIFS('Sales Transactions Raw Data'!V:V,'Sales Transactions Raw Data'!G:G,"Ola-Mate-VP1-16oz-12pk",'Sales Transactions Raw Data'!S:S,"faire",'Sales Transactions Raw Data'!J:J,"Finished Goods") -> 0 | K5: =SUMIFS('Sales Transactions Raw Data'!V:V,'Sales Transactions Raw Data'!G:G,"Ola-Mate-VP1-16oz-12pk",'Sales Transactions Raw Data'!S:S,"tiktok",'Sales Transactions Raw Data'!J:J,"Finished Goods") -> 0 | L5: =SUMIFS('Sales Transactions Raw Data'!V:V,'Sales Transactions Raw Data'!G:G,"Ola-Mate-VP1-16oz-12pk",'Sales Transactions Raw Data'!S:S,"4901177",'Sales Transactions Raw Data'!J:J,"Finished Goods") -> 0 | M5: =SUMIFS('Sales Transactions Raw Data'!V:V,'Sales Transactions Raw Data'!G:G,"Ola-Mate-VP1-16oz-12pk",'Sales Transactions Raw Data'!S:S,"3890849",'Sales Transactions Raw Data'!J:J,"Finished Goods") -> 0 | N5: =SUM(B5:M5) -> 0
A6: 16oz Berry Coconut 12pk | B6: =SUMIFS('Sales Transactions Raw Data'!V:V,'Sales Transactions Raw Data'!G:G,"Ola-Mate-BC-16oz-12PK",'Sales Transactions Raw Data'!S:S,"amazon",'Sales Transactions Raw Data'!J:J,"Finished Goods") -> 0 | C6: =SUMIFS('Sales Transactions Raw Data'!V:V,'Sales Transactions Raw Data'!G:G,"Ola-Mate-BC-16oz-12PK",'Sales Transactions Raw Data'!S:S,"amazon-us",'Sales Transactions Raw Data'!J:J,"Finished Goods") -> 0 | D6: =SUMIFS('Sales Transactions Raw Data'!V:V,'Sales Transactions Raw Data'!G:G,"Ola-Mate-BC-16oz-12PK",'Sales Transactions Raw Data'!S:S,"Shopify web",'Sales Transactions Raw Data'!J:J,"Finished Goods") -> 0 | E6: =SUMIFS('Sales Transactions Raw Data'!V:V,'Sales Transactions Raw Data'!G:G,"Ola-Mate-BC-16oz-12PK",'Sales Transactions Raw Data'!S:S,"Shopify POS",'Sales Transactions Raw Data'!J:J,"Finished Goods") -> 0 | F6: =SUMIFS('Sales Transactions Raw Data'!V:V,'Sales Transactions Raw Data'!G:G,"Ola-Mate-BC-16oz-12PK",'Sales Transactions Raw Data'!S:S,"Shopify admin",'Sales Transactions Raw Data'!J:J,"Finished Goods") -> 0 | G6: =SUMIFS('Sales Transactions Raw Data'!V:V,'Sales Transactions Raw Data'!G:G,"Ola-Mate-BC-16oz-12PK",'Sales Transactions Raw Data'!S:S,"subscription_contract",'Sales Transactions Raw Data'!J:J,"Finished Goods") -> 0 | H6: =SUMIFS('Sales Transactions Raw Data'!V:V,'Sales Transactions Raw Data'!G:G,"Ola-Mate-BC-16oz-12PK",'Sales Transactions Raw Data'!S:S,"subscription_contract_checkout_one",'Sales Transactions Raw Data'!J:J,"Finished Goods") -> 0 | I6: =SUMIFS('Sales Transactions Raw Data'!V:V,'Sales Transactions Raw Data'!G:G,"Ola-Mate-BC-16oz-12PK",'Sales Transactions Raw Data'!S:S,"296827748353",'Sales Transactions Raw Data'!J:J,"Finished Goods") -> 0 | J6: =SUMIFS('Sales Transactions Raw Data'!V:V,'Sales Transactions Raw Data'!G:G,"Ola-Mate-BC-16oz-12PK",'Sales Transactions Raw Data'!S:S,"faire",'Sales Transactions Raw Data'!J:J,"Finished Goods") -> 0 | K6: =SUMIFS('Sales Transactions Raw Data'!V:V,'Sales Transactions Raw Data'!G:G,"Ola-Mate-BC-16oz-12PK",'Sales Transactions Raw Data'!S:S,"tiktok",'Sales Transactions Raw Data'!J:J,"Finished Goods") -> 0 | L6: =SUMIFS('Sales Transactions Raw Data'!V:V,'Sales Transactions Raw Data'!G:G,"Ola-Mate-BC-16oz-12PK",'Sales Transactions Raw Data'!S:S,"4901177",'Sales Transactions Raw Data'!J:J,"Finished Goods") -> 0 | M6: =SUMIFS('Sales Transactions Raw Data'!V:V,'Sales Transactions Raw Data'!G:G,"Ola-Mate-BC-16oz-12PK",'Sales Transactions Raw Data'!S:S,"3890849",'Sales Transactions Raw Data'!J:J,"Finished Goods") -> 0 | N6: =SUM(B6:M6) -> 0
A7: 16oz Raspberry 12pk | B7: =SUMIFS('Sales Transactions Raw Data'!V:V,'Sales Transactions Raw Data'!G:G,"Ola-Mate-R-16oz-12pk",'Sales Transactions Raw Data'!S:S,"amazon",'Sales Transactions Raw Data'!J:J,"Finished Goods") -> 0 | C7: =SUMIFS('Sales Transactions Raw Data'!V:V,'Sales Transactions Raw Data'!G:G,"Ola-Mate-R-16oz-12pk",'Sales Transactions Raw Data'!S:S,"amazon-us",'Sales Transactions Raw Data'!J:J,"Finished Goods") -> 0 | D7: =SUMIFS('Sales Transactions Raw Data'!V:V,'Sales Transactions Raw Data'!G:G,"Ola-Mate-R-16oz-12pk",'Sales Transactions Raw Data'!S:S,"Shopify web",'Sales Transactions Raw Data'!J:J,"Finished Goods") -> 0 | E7: =SUMIFS('Sales Transactions Raw Data'!V:V,'Sales Transactions Raw Data'!G:G,"Ola-Mate-R-16oz-12pk",'Sales Transactions Raw Data'!S:S,"Shopify POS",'Sales Transactions Raw Data'!J:J,"Finished Goods") -> 0 | F7: =SUMIFS('Sales Transactions Raw Data'!V:V,'Sales Transactions Raw Data'!G:G,"Ola-Mate-R-16oz-12pk",'Sales Transactions Raw Data'!S:S,"Shopify admin",'Sales Transactions Raw Data'!J:J,"Finished Goods") -> 0 | G7: =SUMIFS('Sales Transactions Raw Data'!V:V,'Sales Transactions Raw Data'!G:G,"Ola-Mate-R-16oz-12pk",'Sales Transactions Raw Data'!S:S,"subscription_contract",'Sales Transactions Raw Data'!J:J,"Finished Goods") -> 0 | H7: =SUMIFS('Sales Transactions Raw Data'!V:V,'Sales Transactions Raw Data'!G:G,"Ola-Mate-R-16oz-12pk",'Sales Transactions Raw Data'!S:S,"subscription_contract_checkout_one",'Sales Transactions Raw Data'!J:J,"Finished Goods") -> 0 | I7: =SUMIFS('Sales Transactions Raw Data'!V:V,'Sales Transactions Raw Data'!G:G,"Ola-Mate-R-16oz-12pk",'Sales Transactions Raw Data'!S:S,"296827748353",'Sales Transactions Raw Data'!J:J,"Finished Goods") -> 0 | J7: =SUMIFS('Sales Transactions Raw Data'!V:V,'Sales Transactions Raw Data'!G:G,"Ola-Mate-R-16oz-12pk",'Sales Transactions Raw Data'!S:S,"faire",'Sales Transactions Raw Data'!J:J,"Finished Goods") -> 0 | K7: =SUMIFS('Sales Transactions Raw Data'!V:V,'Sales Transactions Raw Data'!G:G,"Ola-Mate-R-16oz-12pk",'Sales Transactions Raw Data'!S:S,"tiktok",'Sales Transactions Raw Data'!J:J,"Finished Goods") -> 0 | L7: =SUMIFS('Sales Transactions Raw Data'!V:V,'Sales Transactions Raw Data'!G:G,"Ola-Mate-R-16oz-12pk",'Sales Transactions Raw Data'!S:S,"4901177",'Sales Transactions Raw Data'!J:J,"Finished Goods") -> 0 | M7: =SUMIFS('Sales Transactions Raw Data'!V:V,'Sales Transactions Raw Data'!G:G,"Ola-Mate-R-16oz-12pk",'Sales Transactions Raw Data'!S:S,"3890849",'Sales Transactions Raw Data'!J:J,"Finished Goods") -> 0 | N7: =SUM(B7:M7) -> 0
A8: 16oz Grapefruit Ginger 12pk | B8: =SUMIFS('Sales Transactions Raw Data'!V:V,'Sales Transactions Raw Data'!G:G,"Ola-Mate-GG-16oz-12pk",'Sales Transactions Raw Data'!S:S,"amazon",'Sales Transactions Raw Data'!J:J,"Finished Goods") -> 0 | C8: =SUMIFS('Sales Transactions Raw Data'!V:V,'Sales Transactions Raw Data'!G:G,"Ola-Mate-GG-16oz-12pk",'Sales Transactions Raw Data'!S:S,"amazon-us",'Sales Transactions Raw Data'!J:J,"Finished Goods") -> 0 | D8: =SUMIFS('Sales Transactions Raw Data'!V:V,'Sales Transactions Raw Data'!G:G,"Ola-Mate-GG-16oz-12pk",'Sales Transactions Raw Data'!S:S,"Shopify web",'Sales Transactions Raw Data'!J:J,"Finished Goods") -> 0 | E8: =SUMIFS('Sales Transactions Raw Data'!V:V,'Sales Transactions Raw Data'!G:G,"Ola-Mate-GG-16oz-12pk",'Sales Transactions Raw Data'!S:S,"Shopify POS",'Sales Transactions Raw Data'!J:J,"Finished Goods") -> 0 | F8: =SUMIFS('Sales Transactions Raw Data'!V:V,'Sales Transactions Raw Data'!G:G,"Ola-Mate-GG-16oz-12pk",'Sales Transactions Raw Data'!S:S,"Shopify admin",'Sales Transactions Raw Data'!J:J,"Finished Goods") -> 0 | G8: =SUMIFS('Sales Transactions Raw Data'!V:V,'Sales Transactions Raw Data'!G:G,"Ola-Mate-GG-16oz-12pk",'Sales Transactions Raw Data'!S:S,"subscription_contract",'Sales Transactions Raw Data'!J:J,"Finished Goods") -> 0 | H8: =SUMIFS('Sales Transactions Raw Data'!V:V,'Sales Transactions Raw Data'!G:G,"Ola-Mate-GG-16oz-12pk",'Sales Transactions Raw Data'!S:S,"subscription_contract_checkout_one",'Sales Transactions Raw Data'!J:J,"Finished Goods") -> 0 | I8: =SUMIFS('Sales Transactions Raw Data'!V:V,'Sales Transactions Raw Data'!G:G,"Ola-Mate-GG-16oz-12pk",'Sales Transactions Raw Data'!S:S,"296827748353",'Sales Transactions Raw Data'!J:J,"Finished Goods") -> 0 | J8: =SUMIFS('Sales Transactions Raw Data'!V:V,'Sales Transactions Raw Data'!G:G,"Ola-Mate-GG-16oz-12pk",'Sales Transactions Raw Data'!S:S,"faire",'Sales Transactions Raw Data'!J:J,"Finished Goods") -> 0 | K8: =SUMIFS('Sales Transactions Raw Data'!V:V,'Sales Transactions Raw Data'!G:G,"Ola-Mate-GG-16oz-12pk",'Sales Transactions Raw Data'!S:S,"tiktok",'Sales Transactions Raw Data'!J:J,"Finished Goods") -> 0 | L8: =SUMIFS('Sales Transactions Raw Data'!V:V,'Sales Transactions Raw Data'!G:G,"Ola-Mate-GG-16oz-12pk",'Sales Transactions Raw Data'!S:S,"4901177",'Sales Transactions Raw Data'!J:J,"Finished Goods") -> 0 | M8: =SUMIFS('Sales Transactions Raw Data'!V:V,'Sales Transactions Raw Data'!G:G,"Ola-Mate-GG-16oz-12pk",'Sales Transactions Raw Data'!S:S,"3890849",'Sales Transactions Raw Data'!J:J,"Finished Goods") -> 0 | N8: =SUM(B8:M8) -> 0
A9: 16oz Starter 4pk | B9: =SUMIFS('Sales Transactions Raw Data'!V:V,'Sales Transactions Raw Data'!G:G,"Ola-Mate-SP1-16oz-4pk",'Sales Transactions Raw Data'!S:S,"amazon",'Sales Transactions Raw Data'!J:J,"Finished Goods") -> 0 | C9: =SUMIFS('Sales Transactions Raw Data'!V:V,'Sales Transactions Raw Data'!G:G,"Ola-Mate-SP1-16oz-4pk",'Sales Transactions Raw Data'!S:S,"amazon-us",'Sales Transactions Raw Data'!J:J,"Finished Goods") -> 0 | D9: =SUMIFS('Sales Transactions Raw Data'!V:V,'Sales Transactions Raw Data'!G:G,"Ola-Mate-SP1-16oz-4pk",'Sales Transactions Raw Data'!S:S,"Shopify web",'Sales Transactions Raw Data'!J:J,"Finished Goods") -> 0 | E9: =SUMIFS('Sales Transactions Raw Data'!V:V,'Sales Transactions Raw Data'!G:G,"Ola-Mate-SP1-16oz-4pk",'Sales Transactions Raw Data'!S:S,"Shopify POS",'Sales Transactions Raw Data'!J:J,"Finished Goods") -> 0 | F9: =SUMIFS('Sales Transactions Raw Data'!V:V,'Sales Transactions Raw Data'!G:G,"Ola-Mate-SP1-16oz-4pk",'Sales Transactions Raw Data'!S:S,"Shopify admin",'Sales Transactions Raw Data'!J:J,"Finished Goods") -> 0 | G9: =SUMIFS('Sales Transactions Raw Data'!V:V,'Sales Transactions Raw Data'!G:G,"Ola-Mate-SP1-16oz-4pk",'Sales Transactions Raw Data'!S:S,"subscription_contract",'Sales Transactions Raw Data'!J:J,"Finished Goods") -> 0 | H9: =SUMIFS('Sales Transactions Raw Data'!V:V,'Sales Transactions Raw Data'!G:G,"Ola-Mate-SP1-16oz-4pk",'Sales Transactions Raw Data'!S:S,"subscription_contract_checkout_one",'Sales Transactions Raw Data'!J:J,"Finished Goods") -> 0 | I9: =SUMIFS('Sales Transactions Raw Data'!V:V,'Sales Transactions Raw Data'!G:G,"Ola-Mate-SP1-16oz-4pk",'Sales Transactions Raw Data'!S:S,"296827748353",'Sales Transactions Raw Data'!J:J,"Finished Goods") -> 0 | J9: =SUMIFS('Sales Transactions Raw Data'!V:V,'Sales Transactions Raw Data'!G:G,"Ola-Mate-SP1-16oz-4pk",'Sales Transactions Raw Data'!S:S,"faire",'Sales Transactions Raw Data'!J:J,"Finished Goods") -> 0 | K9: =SUMIFS('Sales Transactions Raw Data'!V:V,'Sales Transactions Raw Data'!G:G,"Ola-Mate-SP1-16oz-4pk",'Sales Transactions Raw Data'!S:S,"tiktok",'Sales Transactions Raw Data'!J:J,"Finished Goods") -> 0 | L9: =SUMIFS('Sales Transactions Raw Data'!V:V,'Sales Transactions Raw Data'!G:G,"Ola-Mate-SP1-16oz-4pk",'Sales Transactions Raw Data'!S:S,"4901177",'Sales Transactions Raw Data'!J:J,"Finished Goods") -> 0 | M9: =SUMIFS('Sales Transactions Raw Data'!V:V,'Sales Transactions Raw Data'!G:G,"Ola-Mate-SP1-16oz-4pk",'Sales Transactions Raw Data'!S:S,"3890849",'Sales Transactions Raw Data'!J:J,"Finished Goods") -> 0 | N9: =SUM(B9:M9) -> 0
A10: Loose Cans (BC/GG/R) | B10: =SUMIFS('Sales Transactions Raw Data'!V:V,'Sales Transactions Raw Data'!G:G,"Ola-Mate-*-16oz-1can",'Sales Transactions Raw Data'!S:S,"amazon",'Sales Transactions Raw Data'!J:J,"Finished Goods") -> 0 | C10: =SUMIFS('Sales Transactions Raw Data'!V:V,'Sales Transactions Raw Data'!G:G,"Ola-Mate-*-16oz-1can",'Sales Transactions Raw Data'!S:S,"amazon-us",'Sales Transactions Raw Data'!J:J,"Finished Goods") -> 0 | D10: =SUMIFS('Sales Transactions Raw Data'!V:V,'Sales Transactions Raw Data'!G:G,"Ola-Mate-*-16oz-1can",'Sales Transactions Raw Data'!S:S,"Shopify web",'Sales Transactions Raw Data'!J:J,"Finished Goods") -> 0 | E10: =SUMIFS('Sales Transactions Raw Data'!V:V,'Sales Transactions Raw Data'!G:G,"Ola-Mate-*-16oz-1can",'Sales Transactions Raw Data'!S:S,"Shopify POS",'Sales Transactions Raw Data'!J:J,"Finished Goods") -> 0 | F10: =SUMIFS('Sales Transactions Raw Data'!V:V,'Sales Transactions Raw Data'!G:G,"Ola-Mate-*-16oz-1can",'Sales Transactions Raw Data'!S:S,"Shopify admin",'Sales Transactions Raw Data'!J:J,"Finished Goods") -> 0 | G10: =SUMIFS('Sales Transactions Raw Data'!V:V,'Sales Transactions Raw Data'!G:G,"Ola-Mate-*-16oz-1can",'Sales Transactions Raw Data'!S:S,"subscription_contract",'Sales Transactions Raw Data'!J:J,"Finished Goods") -> 0 | H10: =SUMIFS('Sales Transactions Raw Data'!V:V,'Sales Transactions Raw Data'!G:G,"Ola-Mate-*-16oz-1can",'Sales Transactions Raw Data'!S:S,"subscription_contract_checkout_one",'Sales Transactions Raw Data'!J:J,"Finished Goods") -> 0 | I10: =SUMIFS('Sales Transactions Raw Data'!V:V,'Sales Transactions Raw Data'!G:G,"Ola-Mate-*-16oz-1can",'Sales Transactions Raw Data'!S:S,"296827748353",'Sales Transactions Raw Data'!J:J,"Finished Goods") -> 0 | J10: =SUMIFS('Sales Transactions Raw Data'!V:V,'Sales Transactions Raw Data'!G:G,"Ola-Mate-*-16oz-1can",'Sales Transactions Raw Data'!S:S,"faire",'Sales Transactions Raw Data'!J:J,"Finished Goods") -> 0 | K10: =SUMIFS('Sales Transactions Raw Data'!V:V,'Sales Transactions Raw Data'!G:G,"Ola-Mate-*-16oz-1can",'Sales Transactions Raw Data'!S:S,"tiktok",'Sales Transactions Raw Data'!J:J,"Finished Goods") -> 0 | L10: =SUMIFS('Sales Transactions Raw Data'!V:V,'Sales Transactions Raw Data'!G:G,"Ola-Mate-*-16oz-1can",'Sales Transactions Raw Data'!S:S,"4901177",'Sales Transactions Raw Data'!J:J,"Finished Goods") -> 0 | M10: =SUMIFS('Sales Transactions Raw Data'!V:V,'Sales Transactions Raw Data'!G:G,"Ola-Mate-*-16oz-1can",'Sales Transactions Raw Data'!S:S,"3890849",'Sales Transactions Raw Data'!J:J,"Finished Goods") -> 0 | N10: =SUM(B10:M10) -> 0
A11: TOTAL REVENUE | B11: =SUM(B5:B10) -> 0 | C11: =SUM(C5:C10) -> 0 | D11: =SUM(D5:D10) -> 0 | E11: =SUM(E5:E10) -> 0 | F11: =SUM(F5:F10) -> 0 | G11: =SUM(G5:G10) -> 0 | H11: =SUM(H5:H10) -> 0 | I11: =SUM(I5:I10) -> 0 | ... M11: =SUM(M5:M10) -> 0 | N11: =SUM(B11:M11) -> 0
A13: COGS BY CHANNEL × PRODUCT | B13: Amazon | C13: Amazon Retail | D13: Shopify Web | E13: Shopify POS | F13: Shopify Admin | G13: Subs (contract) | H13: Subs (checkout) | I13: Wholesale 296... | J13: Faire | K13: TikTok | L13: Ch 4901177 | M13: Ch 3890849 | N13: Total
A14: 16oz Variety 12pk | B14: =SUMIFS('Sales Transactions Raw Data'!W:W,'Sales Transactions Raw Data'!G:G,"Ola-Mate-VP1-16oz-12pk",'Sales Transactions Raw Data'!S:S,"amazon",'Sales Transactions Raw Data'!J:J,"Finished Goods") -> 0 | C14: =SUMIFS('Sales Transactions Raw Data'!W:W,'Sales Transactions Raw Data'!G:G,"Ola-Mate-VP1-16oz-12pk",'Sales Transactions Raw Data'!S:S,"amazon-us",'Sales Transactions Raw Data'!J:J,"Finished Goods") -> 0 | D14: =SUMIFS('Sales Transactions Raw Data'!W:W,'Sales Transactions Raw Data'!G:G,"Ola-Mate-VP1-16oz-12pk",'Sales Transactions Raw Data'!S:S,"Shopify web",'Sales Transactions Raw Data'!J:J,"Finished Goods") -> 0 | E14: =SUMIFS('Sales Transactions Raw Data'!W:W,'Sales Transactions Raw Data'!G:G,"Ola-Mate-VP1-16oz-12pk",'Sales Transactions Raw Data'!S:S,"Shopify POS",'Sales Transactions Raw Data'!J:J,"Finished Goods") -> 0 | F14: =SUMIFS('Sales Transactions Raw Data'!W:W,'Sales Transactions Raw Data'!G:G,"Ola-Mate-VP1-16oz-12pk",'Sales Transactions Raw Data'!S:S,"Shopify admin",'Sales Transactions Raw Data'!J:J,"Finished Goods") -> 0 | G14: =SUMIFS('Sales Transactions Raw Data'!W:W,'Sales Transactions Raw Data'!G:G,"Ola-Mate-VP1-16oz-12pk",'Sales Transactions Raw Data'!S:S,"subscription_contract",'Sales Transactions Raw Data'!J:J,"Finished Goods") -> 0 | H14: =SUMIFS('Sales Transactions Raw Data'!W:W,'Sales Transactions Raw Data'!G:G,"Ola-Mate-VP1-16oz-12pk",'Sales Transactions Raw Data'!S:S,"subscription_contract_checkout_one",'Sales Transactions Raw Data'!J:J,"Finished Goods") -> 0 | I14: =SUMIFS('Sales Transactions Raw Data'!W:W,'Sales Transactions Raw Data'!G:G,"Ola-Mate-VP1-16oz-12pk",'Sales Transactions Raw Data'!S:S,"296827748353",'Sales Transactions Raw Data'!J:J,"Finished Goods") -> 0 | J14: =SUMIFS('Sales Transactions Raw Data'!W:W,'Sales Transactions Raw Data'!G:G,"Ola-Mate-VP1-16oz-12pk",'Sales Transactions Raw Data'!S:S,"faire",'Sales Transactions Raw Data'!J:J,"Finished Goods") -> 0 | K14: =SUMIFS('Sales Transactions Raw Data'!W:W,'Sales Transactions Raw Data'!G:G,"Ola-Mate-VP1-16oz-12pk",'Sales Transactions Raw Data'!S:S,"tiktok",'Sales Transactions Raw Data'!J:J,"Finished Goods") -> 0 | L14: =SUMIFS('Sales Transactions Raw Data'!W:W,'Sales Transactions Raw Data'!G:G,"Ola-Mate-VP1-16oz-12pk",'Sales Transactions Raw Data'!S:S,"4901177",'Sales Transactions Raw Data'!J:J,"Finished Goods") -> 0 | M14: =SUMIFS('Sales Transactions Raw Data'!W:W,'Sales Transactions Raw Data'!G:G,"Ola-Mate-VP1-16oz-12pk",'Sales Transactions Raw Data'!S:S,"3890849",'Sales Transactions Raw Data'!J:J,"Finished Goods") -> 0 | N14: =SUM(B14:M14) -> 0
A15: 16oz Berry Coconut 12pk | B15: =SUMIFS('Sales Transactions Raw Data'!W:W,'Sales Transactions Raw Data'!G:G,"Ola-Mate-BC-16oz-12PK",'Sales Transactions Raw Data'!S:S,"amazon",'Sales Transactions Raw Data'!J:J,"Finished Goods") -> 0 | C15: =SUMIFS('Sales Transactions Raw Data'!W:W,'Sales Transactions Raw Data'!G:G,"Ola-Mate-BC-16oz-12PK",'Sales Transactions Raw Data'!S:S,"amazon-us",'Sales Transactions Raw Data'!J:J,"Finished Goods") -> 0 | D15: =SUMIFS('Sales Transactions Raw Data'!W:W,'Sales Transactions Raw Data'!G:G,"Ola-Mate-BC-16oz-12PK",'Sales Transactions Raw Data'!S:S,"Shopify web",'Sales Transactions Raw Data'!J:J,"Finished Goods") -> 0 | E15: =SUMIFS('Sales Transactions Raw Data'!W:W,'Sales Transactions Raw Data'!G:G,"Ola-Mate-BC-16oz-12PK",'Sales Transactions Raw Data'!S:S,"Shopify POS",'Sales Transactions Raw Data'!J:J,"Finished Goods") -> 0 | F15: =SUMIFS('Sales Transactions Raw Data'!W:W,'Sales Transactions Raw Data'!G:G,"Ola-Mate-BC-16oz-12PK",'Sales Transactions Raw Data'!S:S,"Shopify admin",'Sales Transactions Raw Data'!J:J,"Finished Goods") -> 0 | G15: =SUMIFS('Sales Transactions Raw Data'!W:W,'Sales Transactions Raw Data'!G:G,"Ola-Mate-BC-16oz-12PK",'Sales Transactions Raw Data'!S:S,"subscription_contract",'Sales Transactions Raw Data'!J:J,"Finished Goods") -> 0 | H15: =SUMIFS('Sales Transactions Raw Data'!W:W,'Sales Transactions Raw Data'!G:G,"Ola-Mate-BC-16oz-12PK",'Sales Transactions Raw Data'!S:S,"subscription_contract_checkout_one",'Sales Transactions Raw Data'!J:J,"Finished Goods") -> 0 | I15: =SUMIFS('Sales Transactions Raw Data'!W:W,'Sales Transactions Raw Data'!G:G,"Ola-Mate-BC-16oz-12PK",'Sales Transactions Raw Data'!S:S,"296827748353",'Sales Transactions Raw Data'!J:J,"Finished Goods") -> 0 | J15: =SUMIFS('Sales Transactions Raw Data'!W:W,'Sales Transactions Raw Data'!G:G,"Ola-Mate-BC-16oz-12PK",'Sales Transactions Raw Data'!S:S,"faire",'Sales Transactions Raw Data'!J:J,"Finished Goods") -> 0 | K15: =SUMIFS('Sales Transactions Raw Data'!W:W,'Sales Transactions Raw Data'!G:G,"Ola-Mate-BC-16oz-12PK",'Sales Transactions Raw Data'!S:S,"tiktok",'Sales Transactions Raw Data'!J:J,"Finished Goods") -> 0 | L15: =SUMIFS('Sales Transactions Raw Data'!W:W,'Sales Transactions Raw Data'!G:G,"Ola-Mate-BC-16oz-12PK",'Sales Transactions Raw Data'!S:S,"4901177",'Sales Transactions Raw Data'!J:J,"Finished Goods") -> 0 | M15: =SUMIFS('Sales Transactions Raw Data'!W:W,'Sales Transactions Raw Data'!G:G,"Ola-Mate-BC-16oz-12PK",'Sales Transactions Raw Data'!S:S,"3890849",'Sales Transactions Raw Data'!J:J,"Finished Goods") -> 0 | N15: =SUM(B15:M15) -> 0
A16: 16oz Raspberry 12pk | B16: =SUMIFS('Sales Transactions Raw Data'!W:W,'Sales Transactions Raw Data'!G:G,"Ola-Mate-R-16oz-12pk",'Sales Transactions Raw Data'!S:S,"amazon",'Sales Transactions Raw Data'!J:J,"Finished Goods") -> 0 | C16: =SUMIFS('Sales Transactions Raw Data'!W:W,'Sales Transactions Raw Data'!G:G,"Ola-Mate-R-16oz-12pk",'Sales Transactions Raw Data'!S:S,"amazon-us",'Sales Transactions Raw Data'!J:J,"Finished Goods") -> 0 | D16: =SUMIFS('Sales Transactions Raw Data'!W:W,'Sales Transactions Raw Data'!G:G,"Ola-Mate-R-16oz-12pk",'Sales Transactions Raw Data'!S:S,"Shopify web",'Sales Transactions Raw Data'!J:J,"Finished Goods") -> 0 | E16: =SUMIFS('Sales Transactions Raw Data'!W:W,'Sales Transactions Raw Data'!G:G,"Ola-Mate-R-16oz-12pk",'Sales Transactions Raw Data'!S:S,"Shopify POS",'Sales Transactions Raw Data'!J:J,"Finished Goods") -> 0 | F16: =SUMIFS('Sales Transactions Raw Data'!W:W,'Sales Transactions Raw Data'!G:G,"Ola-Mate-R-16oz-12pk",'Sales Transactions Raw Data'!S:S,"Shopify admin",'Sales Transactions Raw Data'!J:J,"Finished Goods") -> 0 | G16: =SUMIFS('Sales Transactions Raw Data'!W:W,'Sales Transactions Raw Data'!G:G,"Ola-Mate-R-16oz-12pk",'Sales Transactions Raw Data'!S:S,"subscription_contract",'Sales Transactions Raw Data'!J:J,"Finished Goods") -> 0 | H16: =SUMIFS('Sales Transactions Raw Data'!W:W,'Sales Transactions Raw Data'!G:G,"Ola-Mate-R-16oz-12pk",'Sales Transactions Raw Data'!S:S,"subscription_contract_checkout_one",'Sales Transactions Raw Data'!J:J,"Finished Goods") -> 0 | I16: =SUMIFS('Sales Transactions Raw Data'!W:W,'Sales Transactions Raw Data'!G:G,"Ola-Mate-R-16oz-12pk",'Sales Transactions Raw Data'!S:S,"296827748353",'Sales Transactions Raw Data'!J:J,"Finished Goods") -> 0 | J16: =SUMIFS('Sales Transactions Raw Data'!W:W,'Sales Transactions Raw Data'!G:G,"Ola-Mate-R-16oz-12pk",'Sales Transactions Raw Data'!S:S,"faire",'Sales Transactions Raw Data'!J:J,"Finished Goods") -> 0 | K16: =SUMIFS('Sales Transactions Raw Data'!W:W,'Sales Transactions Raw Data'!G:G,"Ola-Mate-R-16oz-12pk",'Sales Transactions Raw Data'!S:S,"tiktok",'Sales Transactions Raw Data'!J:J,"Finished Goods") -> 0 | L16: =SUMIFS('Sales Transactions Raw Data'!W:W,'Sales Transactions Raw Data'!G:G,"Ola-Mate-R-16oz-12pk",'Sales Transactions Raw Data'!S:S,"4901177",'Sales Transactions Raw Data'!J:J,"Finished Goods") -> 0 | M16: =SUMIFS('Sales Transactions Raw Data'!W:W,'Sales Transactions Raw Data'!G:G,"Ola-Mate-R-16oz-12pk",'Sales Transactions Raw Data'!S:S,"3890849",'Sales Transactions Raw Data'!J:J,"Finished Goods") -> 0 | N16: =SUM(B16:M16) -> 0
A17: 16oz Grapefruit Ginger 12pk | B17: =SUMIFS('Sales Transactions Raw Data'!W:W,'Sales Transactions Raw Data'!G:G,"Ola-Mate-GG-16oz-12pk",'Sales Transactions Raw Data'!S:S,"amazon",'Sales Transactions Raw Data'!J:J,"Finished Goods") -> 0 | C17: =SUMIFS('Sales Transactions Raw Data'!W:W,'Sales Transactions Raw Data'!G:G,"Ola-Mate-GG-16oz-12pk",'Sales Transactions Raw Data'!S:S,"amazon-us",'Sales Transactions Raw Data'!J:J,"Finished Goods") -> 0 | D17: =SUMIFS('Sales Transactions Raw Data'!W:W,'Sales Transactions Raw Data'!G:G,"Ola-Mate-GG-16oz-12pk",'Sales Transactions Raw Data'!S:S,"Shopify web",'Sales Transactions Raw Data'!J:J,"Finished Goods") -> 0 | E17: =SUMIFS('Sales Transactions Raw Data'!W:W,'Sales Transactions Raw Data'!G:G,"Ola-Mate-GG-16oz-12pk",'Sales Transactions Raw Data'!S:S,"Shopify POS",'Sales Transactions Raw Data'!J:J,"Finished Goods") -> 0 | F17: =SUMIFS('Sales Transactions Raw Data'!W:W,'Sales Transactions Raw Data'!G:G,"Ola-Mate-GG-16oz-12pk",'Sales Transactions Raw Data'!S:S,"Shopify admin",'Sales Transactions Raw Data'!J:J,"Finished Goods") -> 0 | G17: =SUMIFS('Sales Transactions Raw Data'!W:W,'Sales Transactions Raw Data'!G:G,"Ola-Mate-GG-16oz-12pk",'Sales Transactions Raw Data'!S:S,"subscription_contract",'Sales Transactions Raw Data'!J:J,"Finished Goods") -> 0 | H17: =SUMIFS('Sales Transactions Raw Data'!W:W,'Sales Transactions Raw Data'!G:G,"Ola-Mate-GG-16oz-12pk",'Sales Transactions Raw Data'!S:S,"subscription_contract_checkout_one",'Sales Transactions Raw Data'!J:J,"Finished Goods") -> 0 | I17: =SUMIFS('Sales Transactions Raw Data'!W:W,'Sales Transactions Raw Data'!G:G,"Ola-Mate-GG-16oz-12pk",'Sales Transactions Raw Data'!S:S,"296827748353",'Sales Transactions Raw Data'!J:J,"Finished Goods") -> 0 | J17: =SUMIFS('Sales Transactions Raw Data'!W:W,'Sales Transactions Raw Data'!G:G,"Ola-Mate-GG-16oz-12pk",'Sales Transactions Raw Data'!S:S,"faire",'Sales Transactions Raw Data'!J:J,"Finished Goods") -> 0 | K17: =SUMIFS('Sales Transactions Raw Data'!W:W,'Sales Transactions Raw Data'!G:G,"Ola-Mate-GG-16oz-12pk",'Sales Transactions Raw Data'!S:S,"tiktok",'Sales Transactions Raw Data'!J:J,"Finished Goods") -> 0 | L17: =SUMIFS('Sales Transactions Raw Data'!W:W,'Sales Transactions Raw Data'!G:G,"Ola-Mate-GG-16oz-12pk",'Sales Transactions Raw Data'!S:S,"4901177",'Sales Transactions Raw Data'!J:J,"Finished Goods") -> 0 | M17: =SUMIFS('Sales Transactions Raw Data'!W:W,'Sales Transactions Raw Data'!G:G,"Ola-Mate-GG-16oz-12pk",'Sales Transactions Raw Data'!S:S,"3890849",'Sales Transactions Raw Data'!J:J,"Finished Goods") -> 0 | N17: =SUM(B17:M17) -> 0
A18: 16oz Starter 4pk | B18: =SUMIFS('Sales Transactions Raw Data'!W:W,'Sales Transactions Raw Data'!G:G,"Ola-Mate-SP1-16oz-4pk",'Sales Transactions Raw Data'!S:S,"amazon",'Sales Transactions Raw Data'!J:J,"Finished Goods") -> 0 | C18: =SUMIFS('Sales Transactions Raw Data'!W:W,'Sales Transactions Raw Data'!G:G,"Ola-Mate-SP1-16oz-4pk",'Sales Transactions Raw Data'!S:S,"amazon-us",'Sales Transactions Raw Data'!J:J,"Finished Goods") -> 0 | D18: =SUMIFS('Sales Transactions Raw Data'!W:W,'Sales Transactions Raw Data'!G:G,"Ola-Mate-SP1-16oz-4pk",'Sales Transactions Raw Data'!S:S,"Shopify web",'Sales Transactions Raw Data'!J:J,"Finished Goods") -> 0 | E18: =SUMIFS('Sales Transactions Raw Data'!W:W,'Sales Transactions Raw Data'!G:G,"Ola-Mate-SP1-16oz-4pk",'Sales Transactions Raw Data'!S:S,"Shopify POS",'Sales Transactions Raw Data'!J:J,"Finished Goods") -> 0 | F18: =SUMIFS('Sales Transactions Raw Data'!W:W,'Sales Transactions Raw Data'!G:G,"Ola-Mate-SP1-16oz-4pk",'Sales Transactions Raw Data'!S:S,"Shopify admin",'Sales Transactions Raw Data'!J:J,"Finished Goods") -> 0 | G18: =SUMIFS('Sales Transactions Raw Data'!W:W,'Sales Transactions Raw Data'!G:G,"Ola-Mate-SP1-16oz-4pk",'Sales Transactions Raw Data'!S:S,"subscription_contract",'Sales Transactions Raw Data'!J:J,"Finished Goods") -> 0 | H18: =SUMIFS('Sales Transactions Raw Data'!W:W,'Sales Transactions Raw Data'!G:G,"Ola-Mate-SP1-16oz-4pk",'Sales Transactions Raw Data'!S:S,"subscription_contract_checkout_one",'Sales Transactions Raw Data'!J:J,"Finished Goods") -> 0 | I18: =SUMIFS('Sales Transactions Raw Data'!W:W,'Sales Transactions Raw Data'!G:G,"Ola-Mate-SP1-16oz-4pk",'Sales Transactions Raw Data'!S:S,"296827748353",'Sales Transactions Raw Data'!J:J,"Finished Goods") -> 0 | J18: =SUMIFS('Sales Transactions Raw Data'!W:W,'Sales Transactions Raw Data'!G:G,"Ola-Mate-SP1-16oz-4pk",'Sales Transactions Raw Data'!S:S,"faire",'Sales Transactions Raw Data'!J:J,"Finished Goods") -> 0 | K18: =SUMIFS('Sales Transactions Raw Data'!W:W,'Sales Transactions Raw Data'!G:G,"Ola-Mate-SP1-16oz-4pk",'Sales Transactions Raw Data'!S:S,"tiktok",'Sales Transactions Raw Data'!J:J,"Finished Goods") -> 0 | L18: =SUMIFS('Sales Transactions Raw Data'!W:W,'Sales Transactions Raw Data'!G:G,"Ola-Mate-SP1-16oz-4pk",'Sales Transactions Raw Data'!S:S,"4901177",'Sales Transactions Raw Data'!J:J,"Finished Goods") -> 0 | M18: =SUMIFS('Sales Transactions Raw Data'!W:W,'Sales Transactions Raw Data'!G:G,"Ola-Mate-SP1-16oz-4pk",'Sales Transactions Raw Data'!S:S,"3890849",'Sales Transactions Raw Data'!J:J,"Finished Goods") -> 0 | N18: =SUM(B18:M18) -> 0
A19: Loose Cans (BC/GG/R) | B19: =SUMIFS('Sales Transactions Raw Data'!W:W,'Sales Transactions Raw Data'!G:G,"Ola-Mate-*-16oz-1can",'Sales Transactions Raw Data'!S:S,"amazon",'Sales Transactions Raw Data'!J:J,"Finished Goods") -> 0 | C19: =SUMIFS('Sales Transactions Raw Data'!W:W,'Sales Transactions Raw Data'!G:G,"Ola-Mate-*-16oz-1can",'Sales Transactions Raw Data'!S:S,"amazon-us",'Sales Transactions Raw Data'!J:J,"Finished Goods") -> 0 | D19: =SUMIFS('Sales Transactions Raw Data'!W:W,'Sales Transactions Raw Data'!G:G,"Ola-Mate-*-16oz-1can",'Sales Transactions Raw Data'!S:S,"Shopify web",'Sales Transactions Raw Data'!J:J,"Finished Goods") -> 0 | E19: =SUMIFS('Sales Transactions Raw Data'!W:W,'Sales Transactions Raw Data'!G:G,"Ola-Mate-*-16oz-1can",'Sales Transactions Raw Data'!S:S,"Shopify POS",'Sales Transactions Raw Data'!J:J,"Finished Goods") -> 0 | F19: =SUMIFS('Sales Transactions Raw Data'!W:W,'Sales Transactions Raw Data'!G:G,"Ola-Mate-*-16oz-1can",'Sales Transactions Raw Data'!S:S,"Shopify admin",'Sales Transactions Raw Data'!J:J,"Finished Goods") -> 0 | G19: =SUMIFS('Sales Transactions Raw Data'!W:W,'Sales Transactions Raw Data'!G:G,"Ola-Mate-*-16oz-1can",'Sales Transactions Raw Data'!S:S,"subscription_contract",'Sales Transactions Raw Data'!J:J,"Finished Goods") -> 0 | H19: =SUMIFS('Sales Transactions Raw Data'!W:W,'Sales Transactions Raw Data'!G:G,"Ola-Mate-*-16oz-1can",'Sales Transactions Raw Data'!S:S,"subscription_contract_checkout_one",'Sales Transactions Raw Data'!J:J,"Finished Goods") -> 0 | I19: =SUMIFS('Sales Transactions Raw Data'!W:W,'Sales Transactions Raw Data'!G:G,"Ola-Mate-*-16oz-1can",'Sales Transactions Raw Data'!S:S,"296827748353",'Sales Transactions Raw Data'!J:J,"Finished Goods") -> 0 | J19: =SUMIFS('Sales Transactions Raw Data'!W:W,'Sales Transactions Raw Data'!G:G,"Ola-Mate-*-16oz-1can",'Sales Transactions Raw Data'!S:S,"faire",'Sales Transactions Raw Data'!J:J,"Finished Goods") -> 0 | K19: =SUMIFS('Sales Transactions Raw Data'!W:W,'Sales Transactions Raw Data'!G:G,"Ola-Mate-*-16oz-1can",'Sales Transactions Raw Data'!S:S,"tiktok",'Sales Transactions Raw Data'!J:J,"Finished Goods") -> 0 | L19: =SUMIFS('Sales Transactions Raw Data'!W:W,'Sales Transactions Raw Data'!G:G,"Ola-Mate-*-16oz-1can",'Sales Transactions Raw Data'!S:S,"4901177",'Sales Transactions Raw Data'!J:J,"Finished Goods") -> 0 | M19: =SUMIFS('Sales Transactions Raw Data'!W:W,'Sales Transactions Raw Data'!G:G,"Ola-Mate-*-16oz-1can",'Sales Transactions Raw Data'!S:S,"3890849",'Sales Transactions Raw Data'!J:J,"Finished Goods") -> 0 | N19: =SUM(B19:M19) -> 0
A20: TOTAL COGS | B20: =SUM(B14:B19) -> 0 | C20: =SUM(C14:C19) -> 0 | D20: =SUM(D14:D19) -> 0 | E20: =SUM(E14:E19) -> 0 | F20: =SUM(F14:F19) -> 0 | G20: =SUM(G14:G19) -> 0 | H20: =SUM(H14:H19) -> 0 | I20: =SUM(I14:I19) -> 0 | ... M20: =SUM(M14:M19) -> 0 | N20: =SUM(B20:M20) -> 0
A21: GROSS PROFIT BY CHANNEL | B21: =B11-B20 -> 0 | C21: =C11-C20 -> 0 | D21: =D11-D20 -> 0 | E21: =E11-E20 -> 0 | F21: =F11-F20 -> 0 | G21: =G11-G20 -> 0 | H21: =H11-H20 -> 0 | I21: =I11-I20 -> 0 | ... N21: =N11-N20 -> 0
A22: GM% BY CHANNEL | B22: =IF(B11=0,"-",B21/B11) -> - | C22: =IF(C11=0,"-",C21/C11) -> - | D22: =IF(D11=0,"-",D21/D11) -> - | E22: =IF(E11=0,"-",E21/E11) -> - | F22: =IF(F11=0,"-",F21/F11) -> - | G22: =IF(G11=0,"-",G21/G11) -> - | H22: =IF(H11=0,"-",H21/H11) -> - | I22: =IF(I11=0,"-",I21/I11) -> - | ... N22: =IF(N11=0,"-",N21/N11) -> -

Sheet Inventory & MOS Analysis
A1: Inventory & MOS Analysis — by SKU & Location
A2: MOS = Current Qty ÷ (Avg Monthly Units Sold — Last 3 Months) | Alerts: 🔴 <1mo 🟡 1-2mo 🟢 2-6mo 🔵 >6mo
A3: FINISHED GOODS — STOCK LEVELS BY LOCATION
A4: SKU | B4: Product Name | C4: Amazon FBA | D4: Founders | E4: NJ Whs | F4: NY Whs | G4: NOBL | H4: Total Stock | I4: Avg Mo Sales (3mo) | J4: MOS | K4: Stock Alert
A5: Ola-Mate-VP1-16oz-12pk | B5: 16oz Variety 12pk | C5: =SUMIFS('Inventory On Hand Raw Data'!E:E,'Inventory On Hand Raw Data'!B:B,"Ola-Mate-VP1-16oz-12pk",'Inventory On Hand Raw Data'!A:A,"Amazon FBA") -> 0 | D5: =SUMIFS('Inventory On Hand Raw Data'!E:E,'Inventory On Hand Raw Data'!B:B,"Ola-Mate-VP1-16oz-12pk",'Inventory On Hand Raw Data'!A:A,"Founders") -> 0 | E5: =SUMIFS('Inventory On Hand Raw Data'!E:E,'Inventory On Hand Raw Data'!B:B,"Ola-Mate-VP1-16oz-12pk",'Inventory On Hand Raw Data'!A:A,"NJ Warehouse") -> 0 | F5: =SUMIFS('Inventory On Hand Raw Data'!E:E,'Inventory On Hand Raw Data'!B:B,"Ola-Mate-VP1-16oz-12pk",'Inventory On Hand Raw Data'!A:A,"NY Warehouse") -> 0 | G5: =SUMIFS('Inventory On Hand Raw Data'!E:E,'Inventory On Hand Raw Data'!B:B,"Ola-Mate-VP1-16oz-12pk",'Inventory On Hand Raw Data'!A:A,"NOBL") -> 0 | H5: =SUM(C5:G5) -> 0 | I5: =IFERROR((SUMIFS('Sales Transactions Raw Data'!T:T,'Sales Transactions Raw Data'!G:G,"Ola-Mate-VP1-16oz-12pk",'Sales Transactions Raw Data'!J:J,"Finished Goods",'Sales Transactions Raw Data'!A:A,2025,'Sales Transactions Raw Data'!B:B,"September")+SUMIFS('Sales Transactions Raw Data'!T:T,'Sales Transactions Raw Data'!G:G,"Ola-Mate-VP1-16oz-12pk",'Sales Transactions Raw Data'!J:J,"Finished Goods",'Sales Transactions Raw Data'!A:A,2025,'Sales Transactions Raw Data'!B:B,"October")+SUMIFS('Sales Transactions Raw Data'!T:T,'Sales Transactions Raw Data'!G:G,"Ola-Mate-VP1-16oz-12pk",'Sales Transactions Raw Data'!J:J,"Finished Goods",'Sales Transactions Raw Data'!A:A,2025,'Sales Transactions Raw Data'!B:B,"November"))/3,0) -> 0 | J5: =IF(I5=0,"N/A",H5/I5) -> N/A | K5: =IF(I5=0,"⚪ No Sales",IF(J5="N/A","⚪ No Sales",IF(J5<1,"🔴 CRITICAL",IF(J5<2,"🟡 LOW",IF(J5<=6,"🟢 HEALTHY","🔵 OVERSTOCK"))))) -> ⚪ No Sales
A6: Ola-Mate-BC-16oz-12PK | B6: 16oz Berry Coconut 12pk | C6: =SUMIFS('Inventory On Hand Raw Data'!E:E,'Inventory On Hand Raw Data'!B:B,"Ola-Mate-BC-16oz-12PK",'Inventory On Hand Raw Data'!A:A,"Amazon FBA") -> 0 | D6: =SUMIFS('Inventory On Hand Raw Data'!E:E,'Inventory On Hand Raw Data'!B:B,"Ola-Mate-BC-16oz-12PK",'Inventory On Hand Raw Data'!A:A,"Founders") -> 0 | E6: =SUMIFS('Inventory On Hand Raw Data'!E:E,'Inventory On Hand Raw Data'!B:B,"Ola-Mate-BC-16oz-12PK",'Inventory On Hand Raw Data'!A:A,"NJ Warehouse") -> 0 | F6: =SUMIFS('Inventory On Hand Raw Data'!E:E,'Inventory On Hand Raw Data'!B:B,"Ola-Mate-BC-16oz-12PK",'Inventory On Hand Raw Data'!A:A,"NY Warehouse") -> 0 | G6: =SUMIFS('Inventory On Hand Raw Data'!E:E,'Inventory On Hand Raw Data'!B:B,"Ola-Mate-BC-16oz-12PK",'Inventory On Hand Raw Data'!A:A,"NOBL") -> 0 | H6: =SUM(C6:G6) -> 0 | I6: =IFERROR((SUMIFS('Sales Transactions Raw Data'!T:T,'Sales Transactions Raw Data'!G:G,"Ola-Mate-BC-16oz-12PK",'Sales Transactions Raw Data'!J:J,"Finished Goods",'Sales Transactions Raw Data'!A:A,2025,'Sales Transactions Raw Data'!B:B,"September")+SUMIFS('Sales Transactions Raw Data'!T:T,'Sales Transactions Raw Data'!G:G,"Ola-Mate-BC-16oz-12PK",'Sales Transactions Raw Data'!J:J,"Finished Goods",'Sales Transactions Raw Data'!A:A,2025,'Sales Transactions Raw Data'!B:B,"October")+SUMIFS('Sales Transactions Raw Data'!T:T,'Sales Transactions Raw Data'!G:G,"Ola-Mate-BC-16oz-12PK",'Sales Transactions Raw Data'!J:J,"Finished Goods",'Sales Transactions Raw Data'!A:A,2025,'Sales Transactions Raw Data'!B:B,"November"))/3,0) -> 0 | J6: =IF(I6=0,"N/A",H6/I6) -> N/A | K6: =IF(I6=0,"⚪ No Sales",IF(J6="N/A","⚪ No Sales",IF(J6<1,"🔴 CRITICAL",IF(J6<2,"🟡 LOW",IF(J6<=6,"🟢 HEALTHY","🔵 OVERSTOCK"))))) -> ⚪ No Sales
A7: Ola-Mate-GG-16oz-12pk | B7: 16oz Grapefruit Ginger 12pk | C7: =SUMIFS('Inventory On Hand Raw Data'!E:E,'Inventory On Hand Raw Data'!B:B,"Ola-Mate-GG-16oz-12pk",'Inventory On Hand Raw Data'!A:A,"Amazon FBA") -> 0 | D7: =SUMIFS('Inventory On Hand Raw Data'!E:E,'Inventory On Hand Raw Data'!B:B,"Ola-Mate-GG-16oz-12pk",'Inventory On Hand Raw Data'!A:A,"Founders") -> 0 | E7: =SUMIFS('Inventory On Hand Raw Data'!E:E,'Inventory On Hand Raw Data'!B:B,"Ola-Mate-GG-16oz-12pk",'Inventory On Hand Raw Data'!A:A,"NJ Warehouse") -> 0 | F7: =SUMIFS('Inventory On Hand Raw Data'!E:E,'Inventory On Hand Raw Data'!B:B,"Ola-Mate-GG-16oz-12pk",'Inventory On Hand Raw Data'!A:A,"NY Warehouse") -> 0 | G7: =SUMIFS('Inventory On Hand Raw Data'!E:E,'Inventory On Hand Raw Data'!B:B,"Ola-Mate-GG-16oz-12pk",'Inventory On Hand Raw Data'!A:A,"NOBL") -> 0 | H7: =SUM(C7:G7) -> 0 | I7: =IFERROR((SUMIFS('Sales Transactions Raw Data'!T:T,'Sales Transactions Raw Data'!G:G,"Ola-Mate-GG-16oz-12pk",'Sales Transactions Raw Data'!J:J,"Finished Goods",'Sales Transactions Raw Data'!A:A,2025,'Sales Transactions Raw Data'!B:B,"September")+SUMIFS('Sales Transactions Raw Data'!T:T,'Sales Transactions Raw Data'!G:G,"Ola-Mate-GG-16oz-12pk",'Sales Transactions Raw Data'!J:J,"Finished Goods",'Sales Transactions Raw Data'!A:A,2025,'Sales Transactions Raw Data'!B:B,"October")+SUMIFS('Sales Transactions Raw Data'!T:T,'Sales Transactions Raw Data'!G:G,"Ola-Mate-GG-16oz-12pk",'Sales Transactions Raw Data'!J:J,"Finished Goods",'Sales Transactions Raw Data'!A:A,2025,'Sales Transactions Raw Data'!B:B,"November"))/3,0) -> 0 | J7: =IF(I7=0,"N/A",H7/I7) -> N/A | K7: =IF(I7=0,"⚪ No Sales",IF(J7="N/A","⚪ No Sales",IF(J7<1,"🔴 CRITICAL",IF(J7<2,"🟡 LOW",IF(J7<=6,"🟢 HEALTHY","🔵 OVERSTOCK"))))) -> ⚪ No Sales
A8: Ola-Mate-R-16oz-12pk | B8: 16oz Raspberry 12pk | C8: =SUMIFS('Inventory On Hand Raw Data'!E:E,'Inventory On Hand Raw Data'!B:B,"Ola-Mate-R-16oz-12pk",'Inventory On Hand Raw Data'!A:A,"Amazon FBA") -> 0 | D8: =SUMIFS('Inventory On Hand Raw Data'!E:E,'Inventory On Hand Raw Data'!B:B,"Ola-Mate-R-16oz-12pk",'Inventory On Hand Raw Data'!A:A,"Founders") -> 0 | E8: =SUMIFS('Inventory On Hand Raw Data'!E:E,'Inventory On Hand Raw Data'!B:B,"Ola-Mate-R-16oz-12pk",'Inventory On Hand Raw Data'!A:A,"NJ Warehouse") -> 0 | F8: =SUMIFS('Inventory On Hand Raw Data'!E:E,'Inventory On Hand Raw Data'!B:B,"Ola-Mate-R-16oz-12pk",'Inventory On Hand Raw Data'!A:A,"NY Warehouse") -> 0 | G8: =SUMIFS('Inventory On Hand Raw Data'!E:E,'Inventory On Hand Raw Data'!B:B,"Ola-Mate-R-16oz-12pk",'Inventory On Hand Raw Data'!A:A,"NOBL") -> 0 | H8: =SUM(C8:G8) -> 0 | I8: =IFERROR((SUMIFS('Sales Transactions Raw Data'!T:T,'Sales Transactions Raw Data'!G:G,"Ola-Mate-R-16oz-12pk",'Sales Transactions Raw Data'!J:J,"Finished Goods",'Sales Transactions Raw Data'!A:A,2025,'Sales Transactions Raw Data'!B:B,"September")+SUMIFS('Sales Transactions Raw Data'!T:T,'Sales Transactions Raw Data'!G:G,"Ola-Mate-R-16oz-12pk",'Sales Transactions Raw Data'!J:J,"Finished Goods",'Sales Transactions Raw Data'!A:A,2025,'Sales Transactions Raw Data'!B:B,"October")+SUMIFS('Sales Transactions Raw Data'!T:T,'Sales Transactions Raw Data'!G:G,"Ola-Mate-R-16oz-12pk",'Sales Transactions Raw Data'!J:J,"Finished Goods",'Sales Transactions Raw Data'!A:A,2025,'Sales Transactions Raw Data'!B:B,"November"))/3,0) -> 0 | J8: =IF(I8=0,"N/A",H8/I8) -> N/A | K8: =IF(I8=0,"⚪ No Sales",IF(J8="N/A","⚪ No Sales",IF(J8<1,"🔴 CRITICAL",IF(J8<2,"🟡 LOW",IF(J8<=6,"🟢 HEALTHY","🔵 OVERSTOCK"))))) -> ⚪ No Sales
A9: Ola-Mate-SP1-16oz-4pk | B9: 16oz Starter 4pk | C9: =SUMIFS('Inventory On Hand Raw Data'!E:E,'Inventory On Hand Raw Data'!B:B,"Ola-Mate-SP1-16oz-4pk",'Inventory On Hand Raw Data'!A:A,"Amazon FBA") -> 0 | D9: =SUMIFS('Inventory On Hand Raw Data'!E:E,'Inventory On Hand Raw Data'!B:B,"Ola-Mate-SP1-16oz-4pk",'Inventory On Hand Raw Data'!A:A,"Founders") -> 0 | E9: =SUMIFS('Inventory On Hand Raw Data'!E:E,'Inventory On Hand Raw Data'!B:B,"Ola-Mate-SP1-16oz-4pk",'Inventory On Hand Raw Data'!A:A,"NJ Warehouse") -> 0 | F9: =SUMIFS('Inventory On Hand Raw Data'!E:E,'Inventory On Hand Raw Data'!B:B,"Ola-Mate-SP1-16oz-4pk",'Inventory On Hand Raw Data'!A:A,"NY Warehouse") -> 0 | G9: =SUMIFS('Inventory On Hand Raw Data'!E:E,'Inventory On Hand Raw Data'!B:B,"Ola-Mate-SP1-16oz-4pk",'Inventory On Hand Raw Data'!A:A,"NOBL") -> 0 | H9: =SUM(C9:G9) -> 0 | I9: =IFERROR((SUMIFS('Sales Transactions Raw Data'!T:T,'Sales Transactions Raw Data'!G:G,"Ola-Mate-SP1-16oz-4pk",'Sales Transactions Raw Data'!J:J,"Finished Goods",'Sales Transactions Raw Data'!A:A,2025,'Sales Transactions Raw Data'!B:B,"September")+SUMIFS('Sales Transactions Raw Data'!T:T,'Sales Transactions Raw Data'!G:G,"Ola-Mate-SP1-16oz-4pk",'Sales Transactions Raw Data'!J:J,"Finished Goods",'Sales Transactions Raw Data'!A:A,2025,'Sales Transactions Raw Data'!B:B,"October")+SUMIFS('Sales Transactions Raw Data'!T:T,'Sales Transactions Raw Data'!G:G,"Ola-Mate-SP1-16oz-4pk",'Sales Transactions Raw Data'!J:J,"Finished Goods",'Sales Transactions Raw Data'!A:A,2025,'Sales Transactions Raw Data'!B:B,"November"))/3,0) -> 0 | J9: =IF(I9=0,"N/A",H9/I9) -> N/A | K9: =IF(I9=0,"⚪ No Sales",IF(J9="N/A","⚪ No Sales",IF(J9<1,"🔴 CRITICAL",IF(J9<2,"🟡 LOW",IF(J9<=6,"🟢 HEALTHY","🔵 OVERSTOCK"))))) -> ⚪ No Sales
A10: Ola-Mate-BC-16oz-1can | B10: Berry Coconut 1can | C10: =SUMIFS('Inventory On Hand Raw Data'!E:E,'Inventory On Hand Raw Data'!B:B,"Ola-Mate-BC-16oz-1can",'Inventory On Hand Raw Data'!A:A,"Amazon FBA") -> 0 | D10: =SUMIFS('Inventory On Hand Raw Data'!E:E,'Inventory On Hand Raw Data'!B:B,"Ola-Mate-BC-16oz-1can",'Inventory On Hand Raw Data'!A:A,"Founders") -> 0 | E10: =SUMIFS('Inventory On Hand Raw Data'!E:E,'Inventory On Hand Raw Data'!B:B,"Ola-Mate-BC-16oz-1can",'Inventory On Hand Raw Data'!A:A,"NJ Warehouse") -> 0 | F10: =SUMIFS('Inventory On Hand Raw Data'!E:E,'Inventory On Hand Raw Data'!B:B,"Ola-Mate-BC-16oz-1can",'Inventory On Hand Raw Data'!A:A,"NY Warehouse") -> 0 | G10: =SUMIFS('Inventory On Hand Raw Data'!E:E,'Inventory On Hand Raw Data'!B:B,"Ola-Mate-BC-16oz-1can",'Inventory On Hand Raw Data'!A:A,"NOBL") -> 0 | H10: =SUM(C10:G10) -> 0 | I10: =IFERROR((SUMIFS('Sales Transactions Raw Data'!T:T,'Sales Transactions Raw Data'!G:G,"Ola-Mate-BC-16oz-1can",'Sales Transactions Raw Data'!J:J,"Finished Goods",'Sales Transactions Raw Data'!A:A,2025,'Sales Transactions Raw Data'!B:B,"September")+SUMIFS('Sales Transactions Raw Data'!T:T,'Sales Transactions Raw Data'!G:G,"Ola-Mate-BC-16oz-1can",'Sales Transactions Raw Data'!J:J,"Finished Goods",'Sales Transactions Raw Data'!A:A,2025,'Sales Transactions Raw Data'!B:B,"October")+SUMIFS('Sales Transactions Raw Data'!T:T,'Sales Transactions Raw Data'!G:G,"Ola-Mate-BC-16oz-1can",'Sales Transactions Raw Data'!J:J,"Finished Goods",'Sales Transactions Raw Data'!A:A,2025,'Sales Transactions Raw Data'!B:B,"November"))/3,0) -> 0 | J10: =IF(I10=0,"N/A",H10/I10) -> N/A | K10: =IF(I10=0,"⚪ No Sales",IF(J10="N/A","⚪ No Sales",IF(J10<1,"🔴 CRITICAL",IF(J10<2,"🟡 LOW",IF(J10<=6,"🟢 HEALTHY","🔵 OVERSTOCK"))))) -> ⚪ No Sales
A11: Ola-Mate-GG-16oz-1can | B11: Grapefruit Ginger 1can | C11: =SUMIFS('Inventory On Hand Raw Data'!E:E,'Inventory On Hand Raw Data'!B:B,"Ola-Mate-GG-16oz-1can",'Inventory On Hand Raw Data'!A:A,"Amazon FBA") -> 0 | D11: =SUMIFS('Inventory On Hand Raw Data'!E:E,'Inventory On Hand Raw Data'!B:B,"Ola-Mate-GG-16oz-1can",'Inventory On Hand Raw Data'!A:A,"Founders") -> 0 | E11: =SUMIFS('Inventory On Hand Raw Data'!E:E,'Inventory On Hand Raw Data'!B:B,"Ola-Mate-GG-16oz-1can",'Inventory On Hand Raw Data'!A:A,"NJ Warehouse") -> 0 | F11: =SUMIFS('Inventory On Hand Raw Data'!E:E,'Inventory On Hand Raw Data'!B:B,"Ola-Mate-GG-16oz-1can",'Inventory On Hand Raw Data'!A:A,"NY Warehouse") -> 0 | G11: =SUMIFS('Inventory On Hand Raw Data'!E:E,'Inventory On Hand Raw Data'!B:B,"Ola-Mate-GG-16oz-1can",'Inventory On Hand Raw Data'!A:A,"NOBL") -> 0 | H11: =SUM(C11:G11) -> 0 | I11: =IFERROR((SUMIFS('Sales Transactions Raw Data'!T:T,'Sales Transactions Raw Data'!G:G,"Ola-Mate-GG-16oz-1can",'Sales Transactions Raw Data'!J:J,"Finished Goods",'Sales Transactions Raw Data'!A:A,2025,'Sales Transactions Raw Data'!B:B,"September")+SUMIFS('Sales Transactions Raw Data'!T:T,'Sales Transactions Raw Data'!G:G,"Ola-Mate-GG-16oz-1can",'Sales Transactions Raw Data'!J:J,"Finished Goods",'Sales Transactions Raw Data'!A:A,2025,'Sales Transactions Raw Data'!B:B,"October")+SUMIFS('Sales Transactions Raw Data'!T:T,'Sales Transactions Raw Data'!G:G,"Ola-Mate-GG-16oz-1can",'Sales Transactions Raw Data'!J:J,"Finished Goods",'Sales Transactions Raw Data'!A:A,2025,'Sales Transactions Raw Data'!B:B,"November"))/3,0) -> 0 | J11: =IF(I11=0,"N/A",H11/I11) -> N/A | K11: =IF(I11=0,"⚪ No Sales",IF(J11="N/A","⚪ No Sales",IF(J11<1,"🔴 CRITICAL",IF(J11<2,"🟡 LOW",IF(J11<=6,"🟢 HEALTHY","🔵 OVERSTOCK"))))) -> ⚪ No Sales
A12: Ola-Mate-R-16oz-1can | B12: Raspberry 1can | C12: =SUMIFS('Inventory On Hand Raw Data'!E:E,'Inventory On Hand Raw Data'!B:B,"Ola-Mate-R-16oz-1can",'Inventory On Hand Raw Data'!A:A,"Amazon FBA") -> 0 | D12: =SUMIFS('Inventory On Hand Raw Data'!E:E,'Inventory On Hand Raw Data'!B:B,"Ola-Mate-R-16oz-1can",'Inventory On Hand Raw Data'!A:A,"Founders") -> 0 | E12: =SUMIFS('Inventory On Hand Raw Data'!E:E,'Inventory On Hand Raw Data'!B:B,"Ola-Mate-R-16oz-1can",'Inventory On Hand Raw Data'!A:A,"NJ Warehouse") -> 0 | F12: =SUMIFS('Inventory On Hand Raw Data'!E:E,'Inventory On Hand Raw Data'!B:B,"Ola-Mate-R-16oz-1can",'Inventory On Hand Raw Data'!A:A,"NY Warehouse") -> 0 | G12: =SUMIFS('Inventory On Hand Raw Data'!E:E,'Inventory On Hand Raw Data'!B:B,"Ola-Mate-R-16oz-1can",'Inventory On Hand Raw Data'!A:A,"NOBL") -> 0 | H12: =SUM(C12:G12) -> 0 | I12: =IFERROR((SUMIFS('Sales Transactions Raw Data'!T:T,'Sales Transactions Raw Data'!G:G,"Ola-Mate-R-16oz-1can",'Sales Transactions Raw Data'!J:J,"Finished Goods",'Sales Transactions Raw Data'!A:A,2025,'Sales Transactions Raw Data'!B:B,"September")+SUMIFS('Sales Transactions Raw Data'!T:T,'Sales Transactions Raw Data'!G:G,"Ola-Mate-R-16oz-1can",'Sales Transactions Raw Data'!J:J,"Finished Goods",'Sales Transactions Raw Data'!A:A,2025,'Sales Transactions Raw Data'!B:B,"October")+SUMIFS('Sales Transactions Raw Data'!T:T,'Sales Transactions Raw Data'!G:G,"Ola-Mate-R-16oz-1can",'Sales Transactions Raw Data'!J:J,"Finished Goods",'Sales Transactions Raw Data'!A:A,2025,'Sales Transactions Raw Data'!B:B,"November"))/3,0) -> 0 | J12: =IF(I12=0,"N/A",H12/I12) -> N/A | K12: =IF(I12=0,"⚪ No Sales",IF(J12="N/A","⚪ No Sales",IF(J12<1,"🔴 CRITICAL",IF(J12<2,"🟡 LOW",IF(J12<=6,"🟢 HEALTHY","🔵 OVERSTOCK"))))) -> ⚪ No Sales
A14: STOCK ALERT SUMMARY
A15: Alert Level | B15: Count | C15: SKUs | D15: Action Required
A16: 🔴 CRITICAL (< 1 month) | B16: =COUNTIF(K5:K12,"*CRITICAL*") -> 0 | D16: Order immediately!
A17: 🟡 LOW (1–2 months) | B17: =COUNTIF(K5:K12,"*LOW*") -> 0 | C17: {=IFERROR(_xlfn.TEXTJOIN(", ",TRUE,IF(K5:K12="🟡 LOW",A5:A12,"")),"None")} | D17: Plan reorder soon
A18: 🟢 HEALTHY (2–6 months) | B18: =COUNTIF(K5:K12,"*HEALTHY*") -> 0 | D18: Monitor only
A19: 🔵 OVERSTOCK (> 6 months) | B19: =COUNTIF(K5:K12,"*OVERSTOCK*") -> 0 | D19: Review slow movers
A21: Note: MOS uses last 3 months (Sep-Nov 2025) average unit sales. Update month references as new data is added.

Sheet Inventory Movements
A1: Inventory Movements — Monthly Stock Flow by SKU
A2: Formula: Ending Stock = Beginning + Purchases Received − Units Sold | Data from Sales & Purchase Transactions
A4: SKU / Product | B4: Metric | C4: March | D4: July | E4: August | F4: September | G4: October | H4: November
A5: 16oz Variety 12pk
A6: Ola-Mate-VP1-16oz-12pk | B6: Units Sold | C6: =SUMIFS('Sales Transactions Raw Data'!T:T,'Sales Transactions Raw Data'!G:G,"Ola-Mate-VP1-16oz-12pk",'Sales Transactions Raw Data'!B:B,"March",'Sales Transactions Raw Data'!A:A,2025,'Sales Transactions Raw Data'!J:J,"Finished Goods") -> 0 | D6: =SUMIFS('Sales Transactions Raw Data'!T:T,'Sales Transactions Raw Data'!G:G,"Ola-Mate-VP1-16oz-12pk",'Sales Transactions Raw Data'!B:B,"July",'Sales Transactions Raw Data'!A:A,2025,'Sales Transactions Raw Data'!J:J,"Finished Goods") -> 0 | E6: =SUMIFS('Sales Transactions Raw Data'!T:T,'Sales Transactions Raw Data'!G:G,"Ola-Mate-VP1-16oz-12pk",'Sales Transactions Raw Data'!B:B,"August",'Sales Transactions Raw Data'!A:A,2025,'Sales Transactions Raw Data'!J:J,"Finished Goods") -> 0 | F6: =SUMIFS('Sales Transactions Raw Data'!T:T,'Sales Transactions Raw Data'!G:G,"Ola-Mate-VP1-16oz-12pk",'Sales Transactions Raw Data'!B:B,"September",'Sales Transactions Raw Data'!A:A,2025,'Sales Transactions Raw Data'!J:J,"Finished Goods") -> 0 | G6: =SUMIFS('Sales Transactions Raw Data'!T:T,'Sales Transactions Raw Data'!G:G,"Ola-Mate-VP1-16oz-12pk",'Sales Transactions Raw Data'!B:B,"October",'Sales Transactions Raw Data'!A:A,2025,'Sales Transactions Raw Data'!J:J,"Finished Goods") -> 0 | H6: =SUMIFS('Sales Transactions Raw Data'!T:T,'Sales Transactions Raw Data'!G:G,"Ola-Mate-VP1-16oz-12pk",'Sales Transactions Raw Data'!B:B,"November",'Sales Transactions Raw Data'!A:A,2025,'Sales Transactions Raw Data'!J:J,"Finished Goods") -> 0
A7: Ola-Mate-VP1-16oz-12pk | B7: Units Purchased | C7: =SUMIFS('Purchase Transactions Raw data'!F:F,'Purchase Transactions Raw data'!B:B,"Ola-Mate-VP1-16oz-12pk",'Purchase Transactions Raw data'!H:H,"March") -> 0 | D7: =SUMIFS('Purchase Transactions Raw data'!F:F,'Purchase Transactions Raw data'!B:B,"Ola-Mate-VP1-16oz-12pk",'Purchase Transactions Raw data'!H:H,"July") -> 0 | E7: =SUMIFS('Purchase Transactions Raw data'!F:F,'Purchase Transactions Raw data'!B:B,"Ola-Mate-VP1-16oz-12pk",'Purchase Transactions Raw data'!H:H,"August") -> 0 | F7: =SUMIFS('Purchase Transactions Raw data'!F:F,'Purchase Transactions Raw data'!B:B,"Ola-Mate-VP1-16oz-12pk",'Purchase Transactions Raw data'!H:H,"September") -> 0 | G7: =SUMIFS('Purchase Transactions Raw data'!F:F,'Purchase Transactions Raw data'!B:B,"Ola-Mate-VP1-16oz-12pk",'Purchase Transactions Raw data'!H:H,"October") -> 0 | H7: =SUMIFS('Purchase Transactions Raw data'!F:F,'Purchase Transactions Raw data'!B:B,"Ola-Mate-VP1-16oz-12pk",'Purchase Transactions Raw data'!H:H,"November") -> 0
A8: Ola-Mate-VP1-16oz-12pk | B8: Net Movement | C8: =C7-C6 -> 0 | D8: =D7-D6 -> 0 | E8: =E7-E6 -> 0 | F8: =F7-F6 -> 0 | G8: =G7-G6 -> 0 | H8: =H7-H6 -> 0
A9: 16oz Berry Coconut 12pk
A10: Ola-Mate-BC-16oz-12PK | B10: Units Sold | C10: =SUMIFS('Sales Transactions Raw Data'!T:T,'Sales Transactions Raw Data'!G:G,"Ola-Mate-BC-16oz-12PK",'Sales Transactions Raw Data'!B:B,"March",'Sales Transactions Raw Data'!A:A,2025,'Sales Transactions Raw Data'!J:J,"Finished Goods") -> 0 | D10: =SUMIFS('Sales Transactions Raw Data'!T:T,'Sales Transactions Raw Data'!G:G,"Ola-Mate-BC-16oz-12PK",'Sales Transactions Raw Data'!B:B,"July",'Sales Transactions Raw Data'!A:A,2025,'Sales Transactions Raw Data'!J:J,"Finished Goods") -> 0 | E10: =SUMIFS('Sales Transactions Raw Data'!T:T,'Sales Transactions Raw Data'!G:G,"Ola-Mate-BC-16oz-12PK",'Sales Transactions Raw Data'!B:B,"August",'Sales Transactions Raw Data'!A:A,2025,'Sales Transactions Raw Data'!J:J,"Finished Goods") -> 0 | F10: =SUMIFS('Sales Transactions Raw Data'!T:T,'Sales Transactions Raw Data'!G:G,"Ola-Mate-BC-16oz-12PK",'Sales Transactions Raw Data'!B:B,"September",'Sales Transactions Raw Data'!A:A,2025,'Sales Transactions Raw Data'!J:J,"Finished Goods") -> 0 | G10: =SUMIFS('Sales Transactions Raw Data'!T:T,'Sales Transactions Raw Data'!G:G,"Ola-Mate-BC-16oz-12PK",'Sales Transactions Raw Data'!B:B,"October",'Sales Transactions Raw Data'!A:A,2025,'Sales Transactions Raw Data'!J:J,"Finished Goods") -> 0 | H10: =SUMIFS('Sales Transactions Raw Data'!T:T,'Sales Transactions Raw Data'!G:G,"Ola-Mate-BC-16oz-12PK",'Sales Transactions Raw Data'!B:B,"November",'Sales Transactions Raw Data'!A:A,2025,'Sales Transactions Raw Data'!J:J,"Finished Goods") -> 0
A11: Ola-Mate-BC-16oz-12PK | B11: Units Purchased | C11: =SUMIFS('Purchase Transactions Raw data'!F:F,'Purchase Transactions Raw data'!B:B,"Ola-Mate-BC-16oz-12PK",'Purchase Transactions Raw data'!H:H,"March") -> 0 | D11: =SUMIFS('Purchase Transactions Raw data'!F:F,'Purchase Transactions Raw data'!B:B,"Ola-Mate-BC-16oz-12PK",'Purchase Transactions Raw data'!H:H,"July") -> 0 | E11: =SUMIFS('Purchase Transactions Raw data'!F:F,'Purchase Transactions Raw data'!B:B,"Ola-Mate-BC-16oz-12PK",'Purchase Transactions Raw data'!H:H,"August") -> 0 | F11: =SUMIFS('Purchase Transactions Raw data'!F:F,'Purchase Transactions Raw data'!B:B,"Ola-Mate-BC-16oz-12PK",'Purchase Transactions Raw data'!H:H,"September") -> 0 | G11: =SUMIFS('Purchase Transactions Raw data'!F:F,'Purchase Transactions Raw data'!B:B,"Ola-Mate-BC-16oz-12PK",'Purchase Transactions Raw data'!H:H,"October") -> 0 | H11: =SUMIFS('Purchase Transactions Raw data'!F:F,'Purchase Transactions Raw data'!B:B,"Ola-Mate-BC-16oz-12PK",'Purchase Transactions Raw data'!H:H,"November") -> 0
A12: Ola-Mate-BC-16oz-12PK | B12: Net Movement | C12: =C11-C10 -> 0 | D12: =D11-D10 -> 0 | E12: =E11-E10 -> 0 | F12: =F11-F10 -> 0 | G12: =G11-G10 -> 0 | H12: =H11-H10 -> 0
A13: 16oz Grapefruit Ginger 12pk
A14: Ola-Mate-GG-16oz-12pk | B14: Units Sold | C14: =SUMIFS('Sales Transactions Raw Data'!T:T,'Sales Transactions Raw Data'!G:G,"Ola-Mate-GG-16oz-12pk",'Sales Transactions Raw Data'!B:B,"March",'Sales Transactions Raw Data'!A:A,2025,'Sales Transactions Raw Data'!J:J,"Finished Goods") -> 0 | D14: =SUMIFS('Sales Transactions Raw Data'!T:T,'Sales Transactions Raw Data'!G:G,"Ola-Mate-GG-16oz-12pk",'Sales Transactions Raw Data'!B:B,"July",'Sales Transactions Raw Data'!A:A,2025,'Sales Transactions Raw Data'!J:J,"Finished Goods") -> 0 | E14: =SUMIFS('Sales Transactions Raw Data'!T:T,'Sales Transactions Raw Data'!G:G,"Ola-Mate-GG-16oz-12pk",'Sales Transactions Raw Data'!B:B,"August",'Sales Transactions Raw Data'!A:A,2025,'Sales Transactions Raw Data'!J:J,"Finished Goods") -> 0 | F14: =SUMIFS('Sales Transactions Raw Data'!T:T,'Sales Transactions Raw Data'!G:G,"Ola-Mate-GG-16oz-12pk",'Sales Transactions Raw Data'!B:B,"September",'Sales Transactions Raw Data'!A:A,2025,'Sales Transactions Raw Data'!J:J,"Finished Goods") -> 0 | G14: =SUMIFS('Sales Transactions Raw Data'!T:T,'Sales Transactions Raw Data'!G:G,"Ola-Mate-GG-16oz-12pk",'Sales Transactions Raw Data'!B:B,"October",'Sales Transactions Raw Data'!A:A,2025,'Sales Transactions Raw Data'!J:J,"Finished Goods") -> 0 | H14: =SUMIFS('Sales Transactions Raw Data'!T:T,'Sales Transactions Raw Data'!G:G,"Ola-Mate-GG-16oz-12pk",'Sales Transactions Raw Data'!B:B,"November",'Sales Transactions Raw Data'!A:A,2025,'Sales Transactions Raw Data'!J:J,"Finished Goods") -> 0
A15: Ola-Mate-GG-16oz-12pk | B15: Units Purchased | C15: =SUMIFS('Purchase Transactions Raw data'!F:F,'Purchase Transactions Raw data'!B:B,"Ola-Mate-GG-16oz-12pk",'Purchase Transactions Raw data'!H:H,"March") -> 0 | D15: =SUMIFS('Purchase Transactions Raw data'!F:F,'Purchase Transactions Raw data'!B:B,"Ola-Mate-GG-16oz-12pk",'Purchase Transactions Raw data'!H:H,"July") -> 0 | E15: =SUMIFS('Purchase Transactions Raw data'!F:F,'Purchase Transactions Raw data'!B:B,"Ola-Mate-GG-16oz-12pk",'Purchase Transactions Raw data'!H:H,"August") -> 0 | F15: =SUMIFS('Purchase Transactions Raw data'!F:F,'Purchase Transactions Raw data'!B:B,"Ola-Mate-GG-16oz-12pk",'Purchase Transactions Raw data'!H:H,"September") -> 0 | G15: =SUMIFS('Purchase Transactions Raw data'!F:F,'Purchase Transactions Raw data'!B:B,"Ola-Mate-GG-16oz-12pk",'Purchase Transactions Raw data'!H:H,"October") -> 0 | H15: =SUMIFS('Purchase Transactions Raw data'!F:F,'Purchase Transactions Raw data'!B:B,"Ola-Mate-GG-16oz-12pk",'Purchase Transactions Raw data'!H:H,"November") -> 0
A16: Ola-Mate-GG-16oz-12pk | B16: Net Movement | C16: =C15-C14 -> 0 | D16: =D15-D14 -> 0 | E16: =E15-E14 -> 0 | F16: =F15-F14 -> 0 | G16: =G15-G14 -> 0 | H16: =H15-H14 -> 0
A17: 16oz Raspberry 12pk
A18: Ola-Mate-R-16oz-12pk | B18: Units Sold | C18: =SUMIFS('Sales Transactions Raw Data'!T:T,'Sales Transactions Raw Data'!G:G,"Ola-Mate-R-16oz-12pk",'Sales Transactions Raw Data'!B:B,"March",'Sales Transactions Raw Data'!A:A,2025,'Sales Transactions Raw Data'!J:J,"Finished Goods") -> 0 | D18: =SUMIFS('Sales Transactions Raw Data'!T:T,'Sales Transactions Raw Data'!G:G,"Ola-Mate-R-16oz-12pk",'Sales Transactions Raw Data'!B:B,"July",'Sales Transactions Raw Data'!A:A,2025,'Sales Transactions Raw Data'!J:J,"Finished Goods") -> 0 | E18: =SUMIFS('Sales Transactions Raw Data'!T:T,'Sales Transactions Raw Data'!G:G,"Ola-Mate-R-16oz-12pk",'Sales Transactions Raw Data'!B:B,"August",'Sales Transactions Raw Data'!A:A,2025,'Sales Transactions Raw Data'!J:J,"Finished Goods") -> 0 | F18: =SUMIFS('Sales Transactions Raw Data'!T:T,'Sales Transactions Raw Data'!G:G,"Ola-Mate-R-16oz-12pk",'Sales Transactions Raw Data'!B:B,"September",'Sales Transactions Raw Data'!A:A,2025,'Sales Transactions Raw Data'!J:J,"Finished Goods") -> 0 | G18: =SUMIFS('Sales Transactions Raw Data'!T:T,'Sales Transactions Raw Data'!G:G,"Ola-Mate-R-16oz-12pk",'Sales Transactions Raw Data'!B:B,"October",'Sales Transactions Raw Data'!A:A,2025,'Sales Transactions Raw Data'!J:J,"Finished Goods") -> 0 | H18: =SUMIFS('Sales Transactions Raw Data'!T:T,'Sales Transactions Raw Data'!G:G,"Ola-Mate-R-16oz-12pk",'Sales Transactions Raw Data'!B:B,"November",'Sales Transactions Raw Data'!A:A,2025,'Sales Transactions Raw Data'!J:J,"Finished Goods") -> 0
A19: Ola-Mate-R-16oz-12pk | B19: Units Purchased | C19: =SUMIFS('Purchase Transactions Raw data'!F:F,'Purchase Transactions Raw data'!B:B,"Ola-Mate-R-16oz-12pk",'Purchase Transactions Raw data'!H:H,"March") -> 0 | D19: =SUMIFS('Purchase Transactions Raw data'!F:F,'Purchase Transactions Raw data'!B:B,"Ola-Mate-R-16oz-12pk",'Purchase Transactions Raw data'!H:H,"July") -> 0 | E19: =SUMIFS('Purchase Transactions Raw data'!F:F,'Purchase Transactions Raw data'!B:B,"Ola-Mate-R-16oz-12pk",'Purchase Transactions Raw data'!H:H,"August") -> 0 | F19: =SUMIFS('Purchase Transactions Raw data'!F:F,'Purchase Transactions Raw data'!B:B,"Ola-Mate-R-16oz-12pk",'Purchase Transactions Raw data'!H:H,"September") -> 0 | G19: =SUMIFS('Purchase Transactions Raw data'!F:F,'Purchase Transactions Raw data'!B:B,"Ola-Mate-R-16oz-12pk",'Purchase Transactions Raw data'!H:H,"October") -> 0 | H19: =SUMIFS('Purchase Transactions Raw data'!F:F,'Purchase Transactions Raw data'!B:B,"Ola-Mate-R-16oz-12pk",'Purchase Transactions Raw data'!H:H,"November") -> 0
A20: Ola-Mate-R-16oz-12pk | B20: Net Movement | C20: =C19-C18 -> 0 | D20: =D19-D18 -> 0 | E20: =E19-E18 -> 0 | F20: =F19-F18 -> 0 | G20: =G19-G18 -> 0 | H20: =H19-H18 -> 0
A21: 16oz Starter 4pk
A22: Ola-Mate-SP1-16oz-4pk | B22: Units Sold | C22: =SUMIFS('Sales Transactions Raw Data'!T:T,'Sales Transactions Raw Data'!G:G,"Ola-Mate-SP1-16oz-4pk",'Sales Transactions Raw Data'!B:B,"March",'Sales Transactions Raw Data'!A:A,2025,'Sales Transactions Raw Data'!J:J,"Finished Goods") -> 0 | D22: =SUMIFS('Sales Transactions Raw Data'!T:T,'Sales Transactions Raw Data'!G:G,"Ola-Mate-SP1-16oz-4pk",'Sales Transactions Raw Data'!B:B,"July",'Sales Transactions Raw Data'!A:A,2025,'Sales Transactions Raw Data'!J:J,"Finished Goods") -> 0 | E22: =SUMIFS('Sales Transactions Raw Data'!T:T,'Sales Transactions Raw Data'!G:G,"Ola-Mate-SP1-16oz-4pk",'Sales Transactions Raw Data'!B:B,"August",'Sales Transactions Raw Data'!A:A,2025,'Sales Transactions Raw Data'!J:J,"Finished Goods") -> 0 | F22: =SUMIFS('Sales Transactions Raw Data'!T:T,'Sales Transactions Raw Data'!G:G,"Ola-Mate-SP1-16oz-4pk",'Sales Transactions Raw Data'!B:B,"September",'Sales Transactions Raw Data'!A:A,2025,'Sales Transactions Raw Data'!J:J,"Finished Goods") -> 0 | G22: =SUMIFS('Sales Transactions Raw Data'!T:T,'Sales Transactions Raw Data'!G:G,"Ola-Mate-SP1-16oz-4pk",'Sales Transactions Raw Data'!B:B,"October",'Sales Transactions Raw Data'!A:A,2025,'Sales Transactions Raw Data'!J:J,"Finished Goods") -> 0 | H22: =SUMIFS('Sales Transactions Raw Data'!T:T,'Sales Transactions Raw Data'!G:G,"Ola-Mate-SP1-16oz-4pk",'Sales Transactions Raw Data'!B:B,"November",'Sales Transactions Raw Data'!A:A,2025,'Sales Transactions Raw Data'!J:J,"Finished Goods") -> 0
A23: Ola-Mate-SP1-16oz-4pk | B23: Units Purchased | C23: =SUMIFS('Purchase Transactions Raw data'!F:F,'Purchase Transactions Raw data'!B:B,"Ola-Mate-SP1-16oz-4pk",'Purchase Transactions Raw data'!H:H,"March") -> 0 | D23: =SUMIFS('Purchase Transactions Raw data'!F:F,'Purchase Transactions Raw data'!B:B,"Ola-Mate-SP1-16oz-4pk",'Purchase Transactions Raw data'!H:H,"July") -> 0 | E23: =SUMIFS('Purchase Transactions Raw data'!F:F,'Purchase Transactions Raw data'!B:B,"Ola-Mate-SP1-16oz-4pk",'Purchase Transactions Raw data'!H:H,"August") -> 0 | F23: =SUMIFS('Purchase Transactions Raw data'!F:F,'Purchase Transactions Raw data'!B:B,"Ola-Mate-SP1-16oz-4pk",'Purchase Transactions Raw data'!H:H,"September") -> 0 | G23: =SUMIFS('Purchase Transactions Raw data'!F:F,'Purchase Transactions Raw data'!B:B,"Ola-Mate-SP1-16oz-4pk",'Purchase Transactions Raw data'!H:H,"October") -> 0 | H23: =SUMIFS('Purchase Transactions Raw data'!F:F,'Purchase Transactions Raw data'!B:B,"Ola-Mate-SP1-16oz-4pk",'Purchase Transactions Raw data'!H:H,"November") -> 0
A24: Ola-Mate-SP1-16oz-4pk | B24: Net Movement | C24: =C23-C22 -> 0 | D24: =D23-D22 -> 0 | E24: =E23-E22 -> 0 | F24: =F23-F22 -> 0 | G24: =G23-G22 -> 0 | H24: =H23-H22 -> 0
A25: Berry Coconut 1can
A26: Ola-Mate-BC-16oz-1can | B26: Units Sold | C26: =SUMIFS('Sales Transactions Raw Data'!T:T,'Sales Transactions Raw Data'!G:G,"Ola-Mate-BC-16oz-1can",'Sales Transactions Raw Data'!B:B,"March",'Sales Transactions Raw Data'!A:A,2025,'Sales Transactions Raw Data'!J:J,"Finished Goods") -> 0 | D26: =SUMIFS('Sales Transactions Raw Data'!T:T,'Sales Transactions Raw Data'!G:G,"Ola-Mate-BC-16oz-1can",'Sales Transactions Raw Data'!B:B,"July",'Sales Transactions Raw Data'!A:A,2025,'Sales Transactions Raw Data'!J:J,"Finished Goods") -> 0 | E26: =SUMIFS('Sales Transactions Raw Data'!T:T,'Sales Transactions Raw Data'!G:G,"Ola-Mate-BC-16oz-1can",'Sales Transactions Raw Data'!B:B,"August",'Sales Transactions Raw Data'!A:A,2025,'Sales Transactions Raw Data'!J:J,"Finished Goods") -> 0 | F26: =SUMIFS('Sales Transactions Raw Data'!T:T,'Sales Transactions Raw Data'!G:G,"Ola-Mate-BC-16oz-1can",'Sales Transactions Raw Data'!B:B,"September",'Sales Transactions Raw Data'!A:A,2025,'Sales Transactions Raw Data'!J:J,"Finished Goods") -> 0 | G26: =SUMIFS('Sales Transactions Raw Data'!T:T,'Sales Transactions Raw Data'!G:G,"Ola-Mate-BC-16oz-1can",'Sales Transactions Raw Data'!B:B,"October",'Sales Transactions Raw Data'!A:A,2025,'Sales Transactions Raw Data'!J:J,"Finished Goods") -> 0 | H26: =SUMIFS('Sales Transactions Raw Data'!T:T,'Sales Transactions Raw Data'!G:G,"Ola-Mate-BC-16oz-1can",'Sales Transactions Raw Data'!B:B,"November",'Sales Transactions Raw Data'!A:A,2025,'Sales Transactions Raw Data'!J:J,"Finished Goods") -> 0
A27: Ola-Mate-BC-16oz-1can | B27: Units Purchased | C27: =SUMIFS('Purchase Transactions Raw data'!F:F,'Purchase Transactions Raw data'!B:B,"Ola-Mate-BC-16oz-1can",'Purchase Transactions Raw data'!H:H,"March") -> 0 | D27: =SUMIFS('Purchase Transactions Raw data'!F:F,'Purchase Transactions Raw data'!B:B,"Ola-Mate-BC-16oz-1can",'Purchase Transactions Raw data'!H:H,"July") -> 0 | E27: =SUMIFS('Purchase Transactions Raw data'!F:F,'Purchase Transactions Raw data'!B:B,"Ola-Mate-BC-16oz-1can",'Purchase Transactions Raw data'!H:H,"August") -> 0 | F27: =SUMIFS('Purchase Transactions Raw data'!F:F,'Purchase Transactions Raw data'!B:B,"Ola-Mate-BC-16oz-1can",'Purchase Transactions Raw data'!H:H,"September") -> 0 | G27: =SUMIFS('Purchase Transactions Raw data'!F:F,'Purchase Transactions Raw data'!B:B,"Ola-Mate-BC-16oz-1can",'Purchase Transactions Raw data'!H:H,"October") -> 0 | H27: =SUMIFS('Purchase Transactions Raw data'!F:F,'Purchase Transactions Raw data'!B:B,"Ola-Mate-BC-16oz-1can",'Purchase Transactions Raw data'!H:H,"November") -> 0
A28: Ola-Mate-BC-16oz-1can | B28: Net Movement | C28: =C27-C26 -> 0 | D28: =D27-D26 -> 0 | E28: =E27-E26 -> 0 | F28: =F27-F26 -> 0 | G28: =G27-G26 -> 0 | H28: =H27-H26 -> 0
A29: Grapefruit Ginger 1can
A30: Ola-Mate-GG-16oz-1can | B30: Units Sold | C30: =SUMIFS('Sales Transactions Raw Data'!T:T,'Sales Transactions Raw Data'!G:G,"Ola-Mate-GG-16oz-1can",'Sales Transactions Raw Data'!B:B,"March",'Sales Transactions Raw Data'!A:A,2025,'Sales Transactions Raw Data'!J:J,"Finished Goods") -> 0 | D30: =SUMIFS('Sales Transactions Raw Data'!T:T,'Sales Transactions Raw Data'!G:G,"Ola-Mate-GG-16oz-1can",'Sales Transactions Raw Data'!B:B,"July",'Sales Transactions Raw Data'!A:A,2025,'Sales Transactions Raw Data'!J:J,"Finished Goods") -> 0 | E30: =SUMIFS('Sales Transactions Raw Data'!T:T,'Sales Transactions Raw Data'!G:G,"Ola-Mate-GG-16oz-1can",'Sales Transactions Raw Data'!B:B,"August",'Sales Transactions Raw Data'!A:A,2025,'Sales Transactions Raw Data'!J:J,"Finished Goods") -> 0 | F30: =SUMIFS('Sales Transactions Raw Data'!T:T,'Sales Transactions Raw Data'!G:G,"Ola-Mate-GG-16oz-1can",'Sales Transactions Raw Data'!B:B,"September",'Sales Transactions Raw Data'!A:A,2025,'Sales Transactions Raw Data'!J:J,"Finished Goods") -> 0 | G30: =SUMIFS('Sales Transactions Raw Data'!T:T,'Sales Transactions Raw Data'!G:G,"Ola-Mate-GG-16oz-1can",'Sales Transactions Raw Data'!B:B,"October",'Sales Transactions Raw Data'!A:A,2025,'Sales Transactions Raw Data'!J:J,"Finished Goods") -> 0 | H30: =SUMIFS('Sales Transactions Raw Data'!T:T,'Sales Transactions Raw Data'!G:G,"Ola-Mate-GG-16oz-1can",'Sales Transactions Raw Data'!B:B,"November",'Sales Transactions Raw Data'!A:A,2025,'Sales Transactions Raw Data'!J:J,"Finished Goods") -> 0
A31: Ola-Mate-GG-16oz-1can | B31: Units Purchased | C31: =SUMIFS('Purchase Transactions Raw data'!F:F,'Purchase Transactions Raw data'!B:B,"Ola-Mate-GG-16oz-1can",'Purchase Transactions Raw data'!H:H,"March") -> 0 | D31: =SUMIFS('Purchase Transactions Raw data'!F:F,'Purchase Transactions Raw data'!B:B,"Ola-Mate-GG-16oz-1can",'Purchase Transactions Raw data'!H:H,"July") -> 0 | E31: =SUMIFS('Purchase Transactions Raw data'!F:F,'Purchase Transactions Raw data'!B:B,"Ola-Mate-GG-16oz-1can",'Purchase Transactions Raw data'!H:H,"August") -> 0 | F31: =SUMIFS('Purchase Transactions Raw data'!F:F,'Purchase Transactions Raw data'!B:B,"Ola-Mate-GG-16oz-1can",'Purchase Transactions Raw data'!H:H,"September") -> 0 | G31: =SUMIFS('Purchase Transactions Raw data'!F:F,'Purchase Transactions Raw data'!B:B,"Ola-Mate-GG-16oz-1can",'Purchase Transactions Raw data'!H:H,"October") -> 0 | H31: =SUMIFS('Purchase Transactions Raw data'!F:F,'Purchase Transactions Raw data'!B:B,"Ola-Mate-GG-16oz-1can",'Purchase Transactions Raw data'!H:H,"November") -> 0
A32: Ola-Mate-GG-16oz-1can | B32: Net Movement | C32: =C31-C30 -> 0 | D32: =D31-D30 -> 0 | E32: =E31-E30 -> 0 | F32: =F31-F30 -> 0 | G32: =G31-G30 -> 0 | H32: =H31-H30 -> 0
A33: Raspberry 1can
A34: Ola-Mate-R-16oz-1can | B34: Units Sold | C34: =SUMIFS('Sales Transactions Raw Data'!T:T,'Sales Transactions Raw Data'!G:G,"Ola-Mate-R-16oz-1can",'Sales Transactions Raw Data'!B:B,"March",'Sales Transactions Raw Data'!A:A,2025,'Sales Transactions Raw Data'!J:J,"Finished Goods") -> 0 | D34: =SUMIFS('Sales Transactions Raw Data'!T:T,'Sales Transactions Raw Data'!G:G,"Ola-Mate-R-16oz-1can",'Sales Transactions Raw Data'!B:B,"July",'Sales Transactions Raw Data'!A:A,2025,'Sales Transactions Raw Data'!J:J,"Finished Goods") -> 0 | E34: =SUMIFS('Sales Transactions Raw Data'!T:T,'Sales Transactions Raw Data'!G:G,"Ola-Mate-R-16oz-1can",'Sales Transactions Raw Data'!B:B,"August",'Sales Transactions Raw Data'!A:A,2025,'Sales Transactions Raw Data'!J:J,"Finished Goods") -> 0 | F34: =SUMIFS('Sales Transactions Raw Data'!T:T,'Sales Transactions Raw Data'!G:G,"Ola-Mate-R-16oz-1can",'Sales Transactions Raw Data'!B:B,"September",'Sales Transactions Raw Data'!A:A,2025,'Sales Transactions Raw Data'!J:J,"Finished Goods") -> 0 | G34: =SUMIFS('Sales Transactions Raw Data'!T:T,'Sales Transactions Raw Data'!G:G,"Ola-Mate-R-16oz-1can",'Sales Transactions Raw Data'!B:B,"October",'Sales Transactions Raw Data'!A:A,2025,'Sales Transactions Raw Data'!J:J,"Finished Goods") -> 0 | H34: =SUMIFS('Sales Transactions Raw Data'!T:T,'Sales Transactions Raw Data'!G:G,"Ola-Mate-R-16oz-1can",'Sales Transactions Raw Data'!B:B,"November",'Sales Transactions Raw Data'!A:A,2025,'Sales Transactions Raw Data'!J:J,"Finished Goods") -> 0
A35: Ola-Mate-R-16oz-1can | B35: Units Purchased | C35: =SUMIFS('Purchase Transactions Raw data'!F:F,'Purchase Transactions Raw data'!B:B,"Ola-Mate-R-16oz-1can",'Purchase Transactions Raw data'!H:H,"March") -> 0 | D35: =SUMIFS('Purchase Transactions Raw data'!F:F,'Purchase Transactions Raw data'!B:B,"Ola-Mate-R-16oz-1can",'Purchase Transactions Raw data'!H:H,"July") -> 0 | E35: =SUMIFS('Purchase Transactions Raw data'!F:F,'Purchase Transactions Raw data'!B:B,"Ola-Mate-R-16oz-1can",'Purchase Transactions Raw data'!H:H,"August") -> 0 | F35: =SUMIFS('Purchase Transactions Raw data'!F:F,'Purchase Transactions Raw data'!B:B,"Ola-Mate-R-16oz-1can",'Purchase Transactions Raw data'!H:H,"September") -> 0 | G35: =SUMIFS('Purchase Transactions Raw data'!F:F,'Purchase Transactions Raw data'!B:B,"Ola-Mate-R-16oz-1can",'Purchase Transactions Raw data'!H:H,"October") -> 0 | H35: =SUMIFS('Purchase Transactions Raw data'!F:F,'Purchase Transactions Raw data'!B:B,"Ola-Mate-R-16oz-1can",'Purchase Transactions Raw data'!H:H,"November") -> 0
A36: Ola-Mate-R-16oz-1can | B36: Net Movement | C36: =C35-C34 -> 0 | D36: =D35-D34 -> 0 | E36: =E35-E34 -> 0 | F36: =F35-F34 -> 0 | G36: =G35-G34 -> 0 | H36: =H35-H34 -> 0
A38: TOTAL UNITS SOLD — ALL SKUs
A39: TOTAL | B39: Units Sold | C39: =SUMIFS('Sales Transactions Raw Data'!T:T,'Sales Transactions Raw Data'!B:B,"March",'Sales Transactions Raw Data'!A:A,2025,'Sales Transactions Raw Data'!J:J,"Finished Goods") -> 0 | D39: =SUMIFS('Sales Transactions Raw Data'!T:T,'Sales Transactions Raw Data'!B:B,"July",'Sales Transactions Raw Data'!A:A,2025,'Sales Transactions Raw Data'!J:J,"Finished Goods") -> 0 | E39: =SUMIFS('Sales Transactions Raw Data'!T:T,'Sales Transactions Raw Data'!B:B,"August",'Sales Transactions Raw Data'!A:A,2025,'Sales Transactions Raw Data'!J:J,"Finished Goods") -> 0 | F39: =SUMIFS('Sales Transactions Raw Data'!T:T,'Sales Transactions Raw Data'!B:B,"September",'Sales Transactions Raw Data'!A:A,2025,'Sales Transactions Raw Data'!J:J,"Finished Goods") -> 0 | G39: =SUMIFS('Sales Transactions Raw Data'!T:T,'Sales Transactions Raw Data'!B:B,"October",'Sales Transactions Raw Data'!A:A,2025,'Sales Transactions Raw Data'!J:J,"Finished Goods") -> 0 | H39: =SUMIFS('Sales Transactions Raw Data'!T:T,'Sales Transactions Raw Data'!B:B,"November",'Sales Transactions Raw Data'!A:A,2025,'Sales Transactions Raw Data'!J:J,"Finished Goods") -> 0

Sheet Profitability Dashboard
A1: Profitability Dashboard — Net Contribution by Channel
A2: Revenue → COGS → Gross Profit → Ad Spend (Cost Inputs) → Fulfillment → Net Contribution
A4: P&L SUMMARY (All Periods) | B4: Amazon | C4: Amazon Retail | D4: Shopify Web | E4: Shopify POS | F4: Shopify Admin | G4: Subs (contract) | H4: Subs (checkout) | I4: Wholesale 296... | J4: Faire | K4: TikTok | L4: TOTAL
A5: Revenue | B5: =SUMIFS('Sales Transactions Raw Data'!V:V,'Sales Transactions Raw Data'!S:S,"amazon",'Sales Transactions Raw Data'!J:J,"Finished Goods") -> 0 | C5: =SUMIFS('Sales Transactions Raw Data'!V:V,'Sales Transactions Raw Data'!S:S,"amazon-us",'Sales Transactions Raw Data'!J:J,"Finished Goods") -> 0 | D5: =SUMIFS('Sales Transactions Raw Data'!V:V,'Sales Transactions Raw Data'!S:S,"Shopify web",'Sales Transactions Raw Data'!J:J,"Finished Goods") -> 0 | E5: =SUMIFS('Sales Transactions Raw Data'!V:V,'Sales Transactions Raw Data'!S:S,"Shopify POS",'Sales Transactions Raw Data'!J:J,"Finished Goods") -> 0 | F5: =SUMIFS('Sales Transactions Raw Data'!V:V,'Sales Transactions Raw Data'!S:S,"Shopify admin",'Sales Transactions Raw Data'!J:J,"Finished Goods") -> 0 | G5: =SUMIFS('Sales Transactions Raw Data'!V:V,'Sales Transactions Raw Data'!S:S,"subscription_contract",'Sales Transactions Raw Data'!J:J,"Finished Goods") -> 0 | H5: =SUMIFS('Sales Transactions Raw Data'!V:V,'Sales Transactions Raw Data'!S:S,"subscription_contract_checkout_one",'Sales Transactions Raw Data'!J:J,"Finished Goods") -> 0 | I5: =SUMIFS('Sales Transactions Raw Data'!V:V,'Sales Transactions Raw Data'!S:S,"296827748353",'Sales Transactions Raw Data'!J:J,"Finished Goods") -> 0 | J5: =SUMIFS('Sales Transactions Raw Data'!V:V,'Sales Transactions Raw Data'!S:S,"faire",'Sales Transactions Raw Data'!J:J,"Finished Goods") -> 0 | K5: =SUMIFS('Sales Transactions Raw Data'!V:V,'Sales Transactions Raw Data'!S:S,"tiktok",'Sales Transactions Raw Data'!J:J,"Finished Goods") -> 0 | L5: =SUM(B5:K5) -> 0
A6: COGS | B6: =SUMIFS('Sales Transactions Raw Data'!W:W,'Sales Transactions Raw Data'!S:S,"amazon",'Sales Transactions Raw Data'!J:J,"Finished Goods") -> 0 | C6: =SUMIFS('Sales Transactions Raw Data'!W:W,'Sales Transactions Raw Data'!S:S,"amazon-us",'Sales Transactions Raw Data'!J:J,"Finished Goods") -> 0 | D6: =SUMIFS('Sales Transactions Raw Data'!W:W,'Sales Transactions Raw Data'!S:S,"Shopify web",'Sales Transactions Raw Data'!J:J,"Finished Goods") -> 0 | E6: =SUMIFS('Sales Transactions Raw Data'!W:W,'Sales Transactions Raw Data'!S:S,"Shopify POS",'Sales Transactions Raw Data'!J:J,"Finished Goods") -> 0 | F6: =SUMIFS('Sales Transactions Raw Data'!W:W,'Sales Transactions Raw Data'!S:S,"Shopify admin",'Sales Transactions Raw Data'!J:J,"Finished Goods") -> 0 | G6: =SUMIFS('Sales Transactions Raw Data'!W:W,'Sales Transactions Raw Data'!S:S,"subscription_contract",'Sales Transactions Raw Data'!J:J,"Finished Goods") -> 0 | H6: =SUMIFS('Sales Transactions Raw Data'!W:W,'Sales Transactions Raw Data'!S:S,"subscription_contract_checkout_one",'Sales Transactions Raw Data'!J:J,"Finished Goods") -> 0 | I6: =SUMIFS('Sales Transactions Raw Data'!W:W,'Sales Transactions Raw Data'!S:S,"296827748353",'Sales Transactions Raw Data'!J:J,"Finished Goods") -> 0 | J6: =SUMIFS('Sales Transactions Raw Data'!W:W,'Sales Transactions Raw Data'!S:S,"faire",'Sales Transactions Raw Data'!J:J,"Finished Goods") -> 0 | K6: =SUMIFS('Sales Transactions Raw Data'!W:W,'Sales Transactions Raw Data'!S:S,"tiktok",'Sales Transactions Raw Data'!J:J,"Finished Goods") -> 0 | L6: =SUM(B6:K6) -> 0
A7: 2025 | B7: January | C7: SO-2026-89000 | D7: 2026-08-11 | E7: INV-45000 | F7: Ola-Mate-VP1-16oz-12pk | G7: Ola-Mate-VP1-16oz-12pk | H7: OlaMate | I7: Finished Goods | J7: Finished Goods | K7: Core Line | L7: Client Corp 0 | M7: Invoiced | N7: Case 12pk | O7: Fulfilled | P7: B2B | Q7: VNC Sales Rep | R7: Amazon.com | S7: amazon-us | T7: 50 | U7: 1900 | V7: 1900 | W7: 925 | X7: 0 | Y7: 975 | Z7: 975
A8: 2025 | B8: January | C8: SO-2026-89001 | D8: 2026-08-12 | E8: INV-45001 | F8: Ola-Mate-BC-16oz-12PK | G8: Ola-Mate-BC-16oz-12PK | H8: OlaMate | I8: Finished Goods | J8: Finished Goods | K8: Core Line | L8: Client Corp 1 | M8: Invoiced | N8: Case 12pk | O8: Fulfilled | P8: B2B | Q8: VNC Sales Rep | R8: Wholesale | S8: Shopify web | T8: 61 | U8: 2196 | V8: 2196 | W8: 1049.2 | X8: 0 | Y8: 1146.8 | Z8: 1146.8
A9: 2025 | B9: January | C9: SO-2026-89002 | D9: 2026-08-13 | E9: INV-45002 | F9: Ola-Mate-GP-16oz-12PK | G9: Ola-Mate-GP-16oz-12PK | H9: OlaMate | I9: Finished Goods | J9: Finished Goods | K9: Core Line | L9: Client Corp 2 | M9: Invoiced | N9: Case 12pk | O9: Fulfilled | P9: B2B | Q9: VNC Sales Rep | R9: Retail | S9: amazon | T9: 72 | U9: 2592 | V9: 2592 | W9: 1260 | X9: 0 | Y9: 1332 | Z9: 1332
A10: 2025 | B10: January | C10: SO-2026-89003 | D10: 2026-08-14 | E10: INV-45003 | F10: Ola-Mate-R-16oz-12pk | G10: Ola-Mate-R-16oz-12pk | H10: OlaMate | I10: Finished Goods | J10: Finished Goods | K10: Core Line | L10: Client Corp 3 | M10: Invoiced | N10: Case 12pk | O10: Fulfilled | P10: B2B | Q10: VNC Sales Rep | R10: Amazon.com | S10: tiktok | T10: 83 | U10: 2905 | V10: 2905 | W10: 1394.4 | X10: 0 | Y10: 1510.6 | Z10: 1510.6
A11: 2025 | B11: January | C11: SO-2026-89004 | D11: 2026-08-15 | E11: INV-45004 | F11: Ola-Mate-GG-16oz-12pk | G11: Ola-Mate-GG-16oz-12pk | H11: OlaMate | I11: Finished Goods | J11: Finished Goods | K11: Core Line | L11: Client Corp 4 | M11: Invoiced | N11: Case 12pk | O11: Fulfilled | P11: B2B | Q11: VNC Sales Rep | R11: Wholesale | S11: subscription_contract | T11: 94 | U11: 3196 | V11: 3196 | W11: 1551 | X11: 0 | Y11: 1645 | Z11: 1645
A12: 2025 | B12: February | C12: SO-2026-89005 | D12: 2026-08-16 | E12: INV-45005 | F12: Ola-Mate-VP1-16oz-12pk | G12: Ola-Mate-VP1-16oz-12pk | H12: OlaMate | I12: Finished Goods | J12: Finished Goods | K12: Core Line | L12: Client Corp 5 | M12: Invoiced | N12: Case 12pk | O12: Fulfilled | P12: B2B | Q12: VNC Sales Rep | R12: Amazon.com | S12: amazon-us | T12: 50 | U12: 1900 | V12: 1900 | W12: 925 | X12: 0 | Y12: 975 | Z12: 975
A13: 2025 | B13: February | C13: SO-2026-89006 | D13: 2026-08-17 | E13: INV-45006 | F13: Ola-Mate-BC-16oz-12PK | G13: Ola-Mate-BC-16oz-12PK | H13: OlaMate | I13: Finished Goods | J13: Finished Goods | K13: Core Line | L13: Client Corp 6 | M13: Invoiced | N13: Case 12pk | O13: Fulfilled | P13: B2B | Q13: VNC Sales Rep | R13: Wholesale | S13: Shopify web | T13: 61 | U13: 2196 | V13: 2196 | W13: 1049.2 | X13: 0 | Y13: 1146.8 | Z13: 1146.8
A14: 2025 | B14: February | C14: SO-2026-89007 | D14: 2026-08-18 | E14: INV-45007 | F14: Ola-Mate-GP-16oz-12PK | G14: Ola-Mate-GP-16oz-12PK | H14: OlaMate | I14: Finished Goods | J14: Finished Goods | K14: Core Line | L14: Client Corp 7 | M14: Invoiced | N14: Case 12pk | O14: Fulfilled | P14: B2B | Q14: VNC Sales Rep | R14: Retail | S14: amazon | T14: 72 | U14: 2592 | V14: 2592 | W14: 1260 | X14: 0 | Y14: 1332 | Z14: 1332
A15: 2025 | B15: February | C15: SO-2026-89008 | D15: 2026-08-19 | E15: INV-45008 | F15: Ola-Mate-R-16oz-12pk | G15: Ola-Mate-R-16oz-12pk | H15: OlaMate | I15: Finished Goods | J15: Finished Goods | K15: Core Line | L15: Client Corp 8 | M15: Invoiced | N15: Case 12pk | O15: Fulfilled | P15: B2B | Q15: VNC Sales Rep | R15: Amazon.com | S15: tiktok | T15: 83 | U15: 2905 | V15: 2905 | W15: 1394.4 | X15: 0 | Y15: 1510.6 | Z15: 1510.6
A16: 2025 | B16: February | C16: SO-2026-89009 | D16: 2026-08-20 | E16: INV-45009 | F16: Ola-Mate-GG-16oz-12pk | G16: Ola-Mate-GG-16oz-12pk | H16: OlaMate | I16: Finished Goods | J16: Finished Goods | K16: Core Line | L16: Client Corp 9 | M16: Invoiced | N16: Case 12pk | O16: Fulfilled | P16: B2B | Q16: VNC Sales Rep | R16: Wholesale | S16: subscription_contract | T16: 94 | U16: 3196 | V16: 3196 | W16: 1551 | X16: 0 | Y16: 1645 | Z16: 1645
A17: 2025 | B17: March | C17: SO-2026-89010 | D17: 2026-08-21 | E17: INV-45010 | F17: Ola-Mate-VP1-16oz-12pk | G17: Ola-Mate-VP1-16oz-12pk | H17: OlaMate | I17: Finished Goods | J17: Finished Goods | K17: Core Line | L17: Client Corp 10 | M17: Invoiced | N17: Case 12pk | O17: Fulfilled | P17: B2B | Q17: VNC Sales Rep | R17: Amazon.com | S17: amazon-us | T17: 50 | U17: 1900 | V17: 1900 | W17: 925 | X17: 0 | Y17: 975 | Z17: 975
A18: 2025 | B18: March | C18: SO-2026-89011 | D18: 2026-08-22 | E18: INV-45011 | F18: Ola-Mate-BC-16oz-12PK | G18: Ola-Mate-BC-16oz-12PK | H18: OlaMate | I18: Finished Goods | J18: Finished Goods | K18: Core Line | L18: Client Corp 11 | M18: Invoiced | N18: Case 12pk | O18: Fulfilled | P18: B2B | Q18: VNC Sales Rep | R18: Wholesale | S18: Shopify web | T18: 61 | U18: 2196 | V18: 2196 | W18: 1049.2 | X18: 0 | Y18: 1146.8 | Z18: 1146.8
... A126: 2026 | B126: December | C126: SO-2026-89119 | D126: 2026-08-25 | E126: INV-45119 | F126: Ola-Mate-GG-16oz-12pk | G126: Ola-Mate-GG-16oz-12pk | H126: OlaMate | I126: Finished Goods | J126: Finished Goods | K126: Core Line | L126: Client Corp 119 | M126: Invoiced | N126: Case 12pk | O126: Fulfilled | P126: B2B | Q126: VNC Sales Rep | R126: Wholesale | S126: subscription_contract | T126: 94 | U126: 3196 | V126: 3196 | W126: 1551 | X126: 0 | Y126: 1645 | Z126: 1645

Sheet Sales Dashboard
A1: Sales Dashboard — OlaMate Revenue Overview
A2: Finished Goods only | Data from Sales Transactions Raw Data
A4: CHART DATA 1: Revenue by Channel (All Periods)
A5: Channel | B5: Revenue
A6: Amazon | B6: =SUMIFS('Sales Transactions Raw Data'!V:V,'Sales Transactions Raw Data'!S:S,"amazon",'Sales Transactions Raw Data'!J:J,"Finished Goods") -> 0
A7: Shopify Web | B7: =SUMIFS('Sales Transactions Raw Data'!V:V,'Sales Transactions Raw Data'!S:S,"Shopify web",'Sales Transactions Raw Data'!J:J,"Finished Goods") -> 0
A8: Shopify POS | B8: =SUMIFS('Sales Transactions Raw Data'!V:V,'Sales Transactions Raw Data'!S:S,"Shopify POS",'Sales Transactions Raw Data'!J:J,"Finished Goods") -> 0
A9: Shopify Admin | B9: =SUMIFS('Sales Transactions Raw Data'!V:V,'Sales Transactions Raw Data'!S:S,"Shopify admin",'Sales Transactions Raw Data'!J:J,"Finished Goods") -> 0
A10: Subscriptions | B10: =SUMIFS('Sales Transactions Raw Data'!V:V,'Sales Transactions Raw Data'!S:S,"subscription_contract",'Sales Transactions Raw Data'!J:J,"Finished Goods") -> 0
A11: Wholesale | B11: =SUMIFS('Sales Transactions Raw Data'!V:V,'Sales Transactions Raw Data'!S:S,"3890849",'Sales Transactions Raw Data'!J:J,"Finished Goods") -> 0
A14: CHART DATA 2: Monthly Revenue Trend
A15: Month | B15: Revenue | C15: Gross Profit
A16: 46106 | B16: =SUMIFS('Sales Transactions Raw Data'!V:V,'Sales Transactions Raw Data'!B:B,"March",'Sales Transactions Raw Data'!A:A,2025,'Sales Transactions Raw Data'!J:J,"Finished Goods") -> 0 | C16: =B16-SUMIFS('Sales Transactions Raw Data'!W:W,'Sales Transactions Raw Data'!B:B,"March",'Sales Transactions Raw Data'!A:A,2025,'Sales Transactions Raw Data'!J:J,"Finished Goods") -> 0
A17: 46228 | B17: =SUMIFS('Sales Transactions Raw Data'!V:V,'Sales Transactions Raw Data'!B:B,"July",'Sales Transactions Raw Data'!A:A,2025,'Sales Transactions Raw Data'!J:J,"Finished Goods") -> 0 | C17: =B17-SUMIFS('Sales Transactions Raw Data'!W:W,'Sales Transactions Raw Data'!B:B,"July",'Sales Transactions Raw Data'!A:A,2025,'Sales Transactions Raw Data'!J:J,"Finished Goods") -> 0
A18: 46259 | B18: =SUMIFS('Sales Transactions Raw Data'!V:V,'Sales Transactions Raw Data'!B:B,"August",'Sales Transactions Raw Data'!A:A,2025,'Sales Transactions Raw Data'!J:J,"Finished Goods") -> 0 | C18: =B18-SUMIFS('Sales Transactions Raw Data'!W:W,'Sales Transactions Raw Data'!B:B,"August",'Sales Transactions Raw Data'!A:A,2025,'Sales Transactions Raw Data'!J:J,"Finished Goods") -> 0
A19: 46290 | B19: =SUMIFS('Sales Transactions Raw Data'!V:V,'Sales Transactions Raw Data'!B:B,"September",'Sales Transactions Raw Data'!A:A,2025,'Sales Transactions Raw Data'!J:J,"Finished Goods") -> 0 | C19: =B19-SUMIFS('Sales Transactions Raw Data'!W:W,'Sales Transactions Raw Data'!B:B,"September",'Sales Transactions Raw Data'!A:A,2025,'Sales Transactions Raw Data'!J:J,"Finished Goods") -> 0
A20: 46320 | B20: =SUMIFS('Sales Transactions Raw Data'!V:V,'Sales Transactions Raw Data'!B:B,"October",'Sales Transactions Raw Data'!A:A,2025,'Sales Transactions Raw Data'!J:J,"Finished Goods") -> 0 | C20: =B20-SUMIFS('Sales Transactions Raw Data'!W:W,'Sales Transactions Raw Data'!B:B,"October",'Sales Transactions Raw Data'!A:A,2025,'Sales Transactions Raw Data'!J:J,"Finished Goods") -> 0
A21: 46351 | B21: =SUMIFS('Sales Transactions Raw Data'!V:V,'Sales Transactions Raw Data'!B:B,"November",'Sales Transactions Raw Data'!A:A,2025,'Sales Transactions Raw Data'!J:J,"Finished Goods") -> 0 | C21: =B21-SUMIFS('Sales Transactions Raw Data'!W:W,'Sales Transactions Raw Data'!B:B,"November",'Sales Transactions Raw Data'!A:A,2025,'Sales Transactions Raw Data'!J:J,"Finished Goods") -> 0
A24: CHART DATA 3: Revenue by Product
A25: Product | B25: Revenue
A26: 16oz Variety 12pk | B26: ='Product Margin Analysis'!C5 -> 0
A27: 16oz Berry Coconut 12pk | B27: ='Product Margin Analysis'!C6 -> 0
A28: 16oz Raspberry 12pk | B28: ='Product Margin Analysis'!C7 -> 0
A29: 16oz Grapefruit Ginger 12pk | B29: ='Product Margin Analysis'!C8 -> 0
A30: 16oz Starter 4pk | B30: ='Product Margin Analysis'!C9 -> 0
A31: Loose Cans | B31: ='Product Margin Analysis'!C10 -> 0

Sheet Sales Transactions Raw Data
A1: ⚡ CIN7 ENTERPRISE ANALYTICS SUITE | CIN7 SYNC PLATFORM | B1: Last 30 days | D1: Sync error: server connection unavailable. | L1: [ PROD ENGINE | CONNECTED ]
A2: 📋 Cover & Index | B2: KPI Dashboard | C2: KPI dashboards | D2: Weekly Order Tracker | E2: Sales Trend Analysis | F2: Product Margin Analysis
A3: TIMELINE PERIOD: | B3: Last 30 days
A4: Show COGS: Only COGS within the date range
T5: Grand Total | U5: Grand Total | V5: Grand Total | W5: Grand Total | X5: Grand Total | Y5: Grand Total | Z5: Grand Total
A6: Month | B6: Order date | C6: Order # | D6: Invoice date | E6: Document # | F6: SKU | G6: Product | H6: Brand | I6: Category | J6: Family | K6: Product tags | L6: Customer | M6: Invoice status | N6: Unit | O6: Shipment status | P6: Customer tags | Q6: Sales representative | R6: Sales Channel | S6: Quantity | T6: Invoice | U6: Sale | V6: COGS | W6: Profit less journals | X6: Journals | Y6: Profit | Z6: Profit
B7: 2025 | C7: January | D7: SO-2026-89000 | E7: 2026-08-11 | F7: INV-45000 | G7: Ola-Mate-VP1-16oz-12pk | H7: Ola-Mate-VP1-16oz-12pk | I7: OlaMate | J7: Finished Goods | K7: Finished Goods | L7: Core Line | M7: Client Corp 0 | N7: Invoiced | O7: Case 12pk | P7: Fulfilled | Q7: B2B | R7: VNC Sales Rep | S7: Amazon.com | T7: amazon-us | U7: 50 | V7: 1900 | W7: 1900 | X7: 925 | Y7: 0 | Z7: 975 | AA7: 975
B8: 2025 | C8: January | D8: SO-2026-89001 | E8: 2026-08-12 | F8: INV-45001 | G8: Ola-Mate-BC-16oz-12PK | H8: Ola-Mate-BC-16oz-12PK | I8: OlaMate | J8: Finished Goods | K8: Finished Goods | L8: Core Line | M8: Client Corp 1 | N8: Invoiced | O8: Case 12pk | P8: Fulfilled | Q8: B2B | R8: VNC Sales Rep | S8: Wholesale | T8: Shopify web | U8: 61 | V8: 2196 | W8: 2196 | X8: 1049.2 | Y8: 0 | Z8: 1146.8 | AA8: 1146.8
B9: 2025 | C9: January | D9: SO-2026-89002 | E9: 2026-08-13 | F9: INV-45002 | G9: Ola-Mate-GP-16oz-12PK | H9: Ola-Mate-GP-16oz-12PK | I9: OlaMate | J9: Finished Goods | K9: Finished Goods | L9: Core Line | M9: Client Corp 2 | N9: Invoiced | O9: Case 12pk | P9: Fulfilled | Q9: B2B | R9: VNC Sales Rep | S9: Retail | T9: amazon | U9: 72 | V9: 2592 | W9: 2592 | X9: 1260 | Y9: 0 | Z9: 1332 | AA9: 1332
B10: 2025 | C10: January | D10: SO-2026-89003 | E10: 2026-08-14 | F10: INV-45003 | G10: Ola-Mate-R-16oz-12pk | H10: Ola-Mate-R-16oz-12pk | I10: OlaMate | J10: Finished Goods | K10: Finished Goods | L10: Core Line | M10: Client Corp 3 | N10: Invoiced | O10: Case 12pk | P10: Fulfilled | Q10: B2B | R10: VNC Sales Rep | S10: Amazon.com | T10: tiktok | U10: 83 | V10: 2905 | W10: 2905 | X10: 1394.4 | Y10: 0 | Z10: 1510.6 | AA10: 1510.6
B11: 2025 | C11: January | D11: SO-2026-89004 | E11: 2026-08-15 | F11: INV-45004 | G11: Ola-Mate-GG-16oz-12pk | H11: Ola-Mate-GG-16oz-12pk | I11: OlaMate | J11: Finished Goods | K11: Finished Goods | L11: Core Line | M11: Client Corp 4 | N11: Invoiced | O11: Case 12pk | P11: Fulfilled | Q11: B2B | R11: VNC Sales Rep | S11: Wholesale | T11: subscription_contract | U11: 94 | V11: 3196 | W11: 3196 | X11: 1551 | Y11: 0 | Z11: 1645 | AA11: 1645
B12: 2025 | C12: February | D12: SO-2026-89005 | E12: 2026-08-16 | F12: INV-45005 | G12: Ola-Mate-VP1-16oz-12pk | H12: Ola-Mate-VP1-16oz-12pk | I12: OlaMate | J12: Finished Goods | K12: Finished Goods | L12: Core Line | M12: Client Corp 5 | N12: Invoiced | O12: Case 12pk | P12: Fulfilled | Q12: B2B | R12: VNC Sales Rep | S12: Amazon.com | T12: amazon-us | U12: 50 | V12: 1900 | W12: 1900 | X12: 925 | Y12: 0 | Z12: 975 | AA12: 975
B13: 2025 | C13: February | D13: SO-2026-89006 | E13: 2026-08-17 | F13: INV-45006 | G13: Ola-Mate-BC-16oz-12PK | H13: Ola-Mate-BC-16oz-12PK | I13: OlaMate | J13: Finished Goods | K13: Finished Goods | L13: Core Line | M13: Client Corp 6 | N13: Invoiced | O13: Case 12pk | P13: Fulfilled | Q13: B2B | R13: VNC Sales Rep | S13: Wholesale | T13: Shopify web | U13: 61 | V13: 2196 | W13: 2196 | X13: 1049.2 | Y13: 0 | Z13: 1146.8 | AA13: 1146.8
B14: 2025 | C14: February | D14: SO-2026-89007 | E14: 2026-08-18 | F14: INV-45007 | G14: Ola-Mate-GP-16oz-12PK | H14: Ola-Mate-GP-16oz-12PK | I14: OlaMate | J14: Finished Goods | K14: Finished Goods | L14: Core Line | M14: Client Corp 7 | N14: Invoiced | O14: Case 12pk | P14: Fulfilled | Q14: B2B | R14: VNC Sales Rep | S14: Retail | T14: amazon | U14: 72 | V14: 2592 | W14: 2592 | X14: 1260 | Y14: 0 | Z14: 1332 | AA14: 1332
B15: 2025 | C15: February | D15: SO-2026-89008 | E15: 2026-08-19 | F15: INV-45008 | G15: Ola-Mate-R-16oz-12pk | H15: Ola-Mate-R-16oz-12pk | I15: OlaMate | J15: Finished Goods | K15: Finished Goods | L15: Core Line | M15: Client Corp 8 | N15: Invoiced | O15: Case 12pk | P15: Fulfilled | Q15: B2B | R15: VNC Sales Rep | S15: Amazon.com | T15: tiktok | U15: 83 | V15: 2905 | W15: 2905 | X15: 1394.4 | Y15: 0 | Z15: 1510.6 | AA15: 1510.6
B16: 2025 | C16: February | D16: SO-2026-89009 | E16: 2026-08-20 | F16: INV-45009 | G16: Ola-Mate-GG-16oz-12pk | H16: Ola-Mate-GG-16oz-12pk | I16: OlaMate | J16: Finished Goods | K16: Finished Goods | L16: Core Line | M16: Client Corp 9 | N16: Invoiced | O16: Case 12pk | P16: Fulfilled | Q16: B2B | R16: VNC Sales Rep | S16: Wholesale | T16: subscription_contract | U16: 94 | V16: 3196 | W16: 3196 | X16: 1551 | Y16: 0 | Z16: 1645 | AA16: 1645
B17: 2025 | C17: March | D17: SO-2026-89010 | E17: 2026-08-21 | F17: INV-45010 | G17: Ola-Mate-VP1-16oz-12pk | H17: Ola-Mate-VP1-16oz-12pk | I17: OlaMate | J17: Finished Goods | K17: Finished Goods | L17: Core Line | M17: Client Corp 10 | N17: Invoiced | O17: Case 12pk | P17: Fulfilled | Q17: B2B | R17: VNC Sales Rep | S17: Amazon.com | T17: amazon-us | U17: 50 | V17: 1900 | W17: 1900 | X17: 925 | Y17: 0 | Z17: 975 | AA17: 975
B18: 2025 | C18: March | D18: SO-2026-89011 | E18: 2026-08-22 | F18: INV-45011 | G18: Ola-Mate-BC-16oz-12PK | H18: Ola-Mate-BC-16oz-12PK | I18: OlaMate | J18: Finished Goods | K18: Finished Goods | L18: Core Line | M18: Client Corp 11 | N18: Invoiced | O18: Case 12pk | P18: Fulfilled | Q18: B2B | R18: VNC Sales Rep | S18: Wholesale | T18: Shopify web | U18: 61 | V18: 2196 | W18: 2196 | X18: 1049.2 | Y18: 0 | Z18: 1146.8 | AA18: 1146.8
... B126: 2026 | C126: December | D126: SO-2026-89119 | E126: 2026-08-25 | F126: INV-45119 | G126: Ola-Mate-GG-16oz-12pk | H126: Ola-Mate-GG-16oz-12pk | I126: OlaMate | J126: Finished Goods | K126: Finished Goods | L126: Core Line | M126: Client Corp 119 | N126: Invoiced | O126: Case 12pk | P126: Fulfilled | Q126: B2B | R126: VNC Sales Rep | S126: Wholesale | T126: subscription_contract | U126: 94 | V126: 3196 | W126: 3196 | X126: 1551 | Y126: 0 | Z126: 1645 | AA126: 1645

Sheet Inventory On Hand Raw Data
A1: ⚡ CIN7 ENTERPRISE ANALYTICS SUITE | CIN7 SYNC PLATFORM | B1: Last 30 days | C1: Products Stock Level Report | D1: Sync error: server connection unavailable. | L1: [ PROD ENGINE | CONNECTED ]
A2: 📋 Cover & Index | B2: KPI Dashboard | C2: KPI dashboards | D2: Weekly Order Tracker | E2: Sales Trend Analysis | F2: Product Margin Analysis | G2: Grand Total | H2: Grand Total | I2: Grand Total | J2: Grand Total | K2: Grand Total
A3: TIMELINE PERIOD: | B3: Last 30 days | C3: Product | D3: Sync error: server connection unavailable. | E3: Quantity on hand | F3: Allocated | G3: On order | H3: In transit | I3: Unit cost | J3: Stock on hand | K3: Available
B7: Amazon FBA | C7: Ola-Mate-VP1-16oz-12pk | D7: 16oz Variety 12pk | E7: Case | F7: 450 | G7: 50 | H7: 200 | I7: 100 | J7: 18.5 | K7: 450 | L7: 400
B8: Founders | C8: Ola-Mate-VP1-16oz-12pk | D8: 16oz Variety 12pk | E8: Case | F8: 320 | G8: 20 | H8: 0 | I8: 0 | J8: 18.5 | K8: 320 | L8: 300
B9: NJ Warehouse | C9: Ola-Mate-VP1-16oz-12pk | D9: 16oz Variety 12pk | E9: Case | F9: 1200 | G9: 150 | H9: 500 | I9: 200 | J9: 18.5 | K9: 1200 | L9: 1050
B10: Amazon FBA | C10: Ola-Mate-BC-16oz-12PK | D10: 16oz Berry Coconut 12pk | E10: Case | F10: 580 | G10: 80 | H10: 150 | I10: 50 | J10: 17.2 | K10: 580 | L10: 500
B11: Founders | C11: Ola-Mate-BC-16oz-12PK | D11: 16oz Berry Coconut 12pk | E11: Case | F11: 240 | G11: 10 | H11: 0 | I11: 0 | J11: 17.2 | K11: 240 | L11: 230
B12: NJ Warehouse | C12: Ola-Mate-BC-16oz-12PK | D12: 16oz Berry Coconut 12pk | E12: Case | F12: 890 | G12: 90 | H12: 300 | I12: 100 | J12: 17.2 | K12: 890 | L12: 800
B13: Amazon FBA | C13: Ola-Mate-GG-16oz-12pk | D13: 16oz Ginger Peach 12pk | E13: Case | F13: 420 | G13: 40 | H13: 100 | I13: 50 | J13: 17.5 | K13: 420 | L13: 380
B14: Founders | C14: Ola-Mate-GG-16oz-12pk | D14: 16oz Ginger Peach 12pk | E14: Case | F14: 180 | G14: 15 | H14: 0 | I14: 0 | J14: 17.5 | K14: 180 | L14: 165
B15: NJ Warehouse | C15: Ola-Mate-GG-16oz-12pk | D15: 16oz Ginger Peach 12pk | E15: Case | F15: 750 | G15: 60 | H15: 250 | I15: 80 | J15: 17.5 | K15: 750 | L15: 690
B16: Amazon FBA | C16: Ola-Mate-R-16oz-12pk | D16: 16oz Mint Lime 12pk | E16: Case | F16: 390 | G16: 30 | H16: 100 | I16: 0 | J16: 16.8 | K16: 390 | L16: 360
B17: NJ Warehouse | C17: Ola-Mate-R-16oz-12pk | D17: 16oz Original Mate 12pk | E17: Case | F17: 920 | G17: 100 | H17: 400 | I17: 150 | J17: 16.5 | K17: 920 | L17: 820

Sheet Purchase Transactions Raw data
A1: ⚡ CIN7 ENTERPRISE ANALYTICS SUITE | CIN7 SYNC PLATFORM | B1: Last 30 days | D1: Sync error: server connection unavailable. | L1: [ PROD ENGINE | CONNECTED ]
A2: 📋 Cover & Index | B2: KPI Dashboard | C2: KPI dashboards | D2: Weekly Order Tracker | E2: Sales Trend Analysis | F2: Product Margin Analysis
A3: TIMELINE PERIOD: | B3: Last 30 days | D3: Sync error: server connection unavailable.
A4: Currency: Base Currency
P5: Grand Total | Q5: Grand Total | R5: Grand Total | S5: Grand Total | T5: Grand Total
A6: Year | B6: Month | C6: Supplier | D6: Expiry date | E6: PO # | F6: Invoice # | G6: Brand | H6: Category | I6: Family | J6: SKU | K6: Product | L6: Unit | M6: Location | N6: Batch # | O6: Status | P6: Quantity | Q6: Main cost | R6: Additional cost | S6: Journal cost | T6: Tax
B7: 2027 | C7: 2027-08 | D7: Pacific Beverage Bottlers | E7: 46600 | F7: August | G7: INV-August | H7: VNC Brand | I7: General Goods | J7: Finished Goods | K7: SKU-2026 | L7: Cin7 Raw Material (August) | M7: each | N7: Main Warehouse | O7: BATCH-2026 | P7: INV-PB-101 | Q7: 1 | R7: NaN | S7: 0 | T7: 0 | U7: 0
B8: 2027 | C8: 2027-08 | D8: Pacific Beverage Bottlers | E8: 46600 | F8: August | G8: INV-August | H8: VNC Brand | I8: General Goods | J8: Finished Goods | K8: SKU-2026 | L8: Cin7 Raw Material (August) | M8: each | N8: Main Warehouse | O8: BATCH-2026 | P8: INV-PB-102 | Q8: 1 | R8: NaN | S8: 0 | T8: 0 | U8: 0

Sheet Cost Inputs
A1: OlaMate - Monthly Cost Inputs
A2: Enter monthly costs from accounting invoices. These feed into Profitability Dashboard.
A4: AD SPEND BY CHANNEL | B4: 46106 | C4: 46228 | D4: 46259 | E4: 46290 | F4: 46320 | G4: 46351 | H4: 46381 | I4: 46048 | J4: 46079 | K4: 46107 | M4: Total | N4: Notes
A5: Amazon Ads | B5: 0 | C5: 0 | D5: 0 | E5: 0 | F5: 0 | G5: 0 | H5: 0 | I5: 0 | J5: 0 | K5: 0 | M5: =SUM(B5:K5) -> 0 | N5: From Amazon Advertising invoices
A6: Shopify / Google Ads | B6: 0 | C6: 0 | D6: 0 | E6: 0 | F6: 0 | G6: 0 | H6: 0 | I6: 0 | J6: 0 | K6: 0 | M6: =SUM(B6:K6) -> 0 | N6: From Google Ads / Meta invoices
A7: TikTok Ads | B7: 0 | C7: 0 | D7: 0 | E7: 0 | F7: 0 | G7: 0 | H7: 0 | I7: 0 | J7: 0 | K7: 0 | M7: =SUM(B7:K7) -> 0 | N7: From TikTok Shop invoices
A8: Other Ad Spend | B8: 0 | C8: 0 | D8: 0 | E8: 0 | F8: 0 | G8: 0 | H8: 0 | I8: 0 | J8: 0 | K8: 0 | M8: =SUM(B8:K8) -> 0 | N8: Influencer, PR, etc.
A9: Total Ad Spend | B9: =SUM(B5:B8) -> 0 | C9: =SUM(C5:C8) -> 0 | D9: =SUM(D5:D8) -> 0 | E9: =SUM(E5:E8) -> 0 | F9: =SUM(F5:F8) -> 0 | G9: =SUM(G5:G8) -> 0 | H9: =SUM(H5:H8) -> 0 | I9: =SUM(I5:I8) -> 0 | ... K9: =SUM(K5:K8) -> 0 | M9: =SUM(B9:K9) -> 0
A11: WAREHOUSE & FULFILLMENT COSTS | B11: 46106 | C11: 46228 | D11: 46259 | E11: 46290 | F11: 46320 | G11: 46351 | H11: 46381 | I11: 46048 | J11: 46079 | K11: 46107 | M11: Total | N11: Notes
A12: Amazon FBA Fees | B12: 0 | C12: 0 | D12: 0 | E12: 0 | F12: 0 | G12: 0 | H12: 0 | I12: 0 | J12: 0 | K12: 0 | M12: =SUM(B12:K12) -> 0 | N12: FBA storage, pick & pack, shipping
A13: 3PL / Warehouse Fees | B13: 0 | C13: 0 | D13: 0 | E13: 0 | F13: 0 | G13: 0 | H13: 0 | I13: 0 | J13: 0 | K13: 0 | M13: =SUM(B13:K13) -> 0 | N13: NJ/NY warehouse invoices
A14: Shipping / Freight Out | B14: 0 | C14: 0 | D14: 0 | E14: 0 | F14: 0 | G14: 0 | H14: 0 | I14: 0 | J14: 0 | K14: 0 | M14: =SUM(B14:K14) -> 0 | N14: Carrier invoices (UPS, FedEx, etc.)
A15: Co-Pack / Production Fees | B15: 0 | C15: 0 | D15: 0 | E15: 0 | F15: 0 | G15: 0 | H15: 0 | I15: 0 | J15: 0 | K15: 0 | M15: =SUM(B15:K15) -> 0 | N15: NOBL co-packing fees
A16: Other Fulfillment | B16: 0 | C16: 0 | D16: 0 | E16: 0 | F16: 0 | G16: 0 | H16: 0 | I16: 0 | J16: 0 | K16: 0 | M16: =SUM(B16:K16) -> 0 | N16: Returns processing, packaging, etc.
A17: Total Fulfillment Costs | B17: =SUM(B12:B16) -> 0 | C17: =SUM(C12:C16) -> 0 | D17: =SUM(D12:D16) -> 0 | E17: =SUM(E12:E16) -> 0 | F17: =SUM(F12:F16) -> 0 | G17: =SUM(G12:G16) -> 0 | H17: =SUM(H12:H16) -> 0 | I17: =SUM(I12:I16) -> 0 | ... K17: =SUM(K12:K16) -> 0 | M17: =SUM(B17:K17) -> 0
A18: TOTAL OPERATING COSTS | B18: =B9+B17 -> 0 | C18: =C9+C17 -> 0 | D18: =D9+D17 -> 0 | E18: =E9+E17 -> 0 | F18: =F9+F17 -> 0 | G18: =G9+G17 -> 0 | H18: =H9+H17 -> 0 | I18: =I9+I17 -> 0 | ... K18: =K9+K17 -> 0 | M18: =SUM(B18:K18) -> 0
F36: 150 | G36: 170 | H36: 180 | I36: 150 | J36: 120 | K36: 150
F37: 220 | G37: 220 | H37: 60 | I37: 150 | J37: 150 | K37: 60
F38: 180 | G38: 180 | H38: 60 | I38: 60 | J38: 60 | K38: 60
F39: 200 | G39: 200 | H39: 200 | I39: 100 | J39: 100 | K39: 500
F40: =SUM(F36:F39) -> 750 | G40: =SUM(G36:G39) -> 770 | H40: =SUM(H36:H39) -> 500 | I40: =SUM(I36:I39) -> 460 | J40: =SUM(J36:J39) -> 430 | K40: =SUM(K36:K39) -> 770
F42: 46320 | G42: 46351 | H42: 46381 | I42: 46048 | J42: 46079 | K42: 46107
F43: 110 | G43: 90 | H43: 100 | I43: 20 | J43: 120 | K43: 90
F44: 220 | G44: 220 | H44: 220 | I44: 220 | J44: 220 | K44: 220
F45: 100 | G45: 100 | H45: 100 | I45: 100 | J45: 100 | K45: 100
F46: 0 | G46: 0 | H46: 0 | I46: 0 | J46: 0 | K46: 0
F47: 0 | G47: 0 | H47: 0 | I47: 0 | J47: 0 | K47: 0
