Workbook

Sheet 📋 Cover & Index
A2: {{COMPANY_NAME}}
A3: Monthly Controller Reporting Model
A4: Powered by Cin7 Core | Multi-Channel Ecommerce & Wholesale
A5: Data Period: {{DATA_PERIOD}} | Generated: {{GENERATED_DATE}}
A8: PERFORMANCE SNAPSHOT
A9: Total Revenue | C9: Gross Profit | E9: Gross Margin % | G9: Net Contribution
A10: ='KPI Dashboard'!B5 -> 0 | C10: ='KPI Dashboard'!D6 -> 0 | E10: ='KPI Dashboard'!B7 -> - | G10: ='KPI Dashboard'!D7 -> 0
A11: INVENTORY ALERTS → 🔴 Critical: 0 | 🟡 Low Stock: 1 | 🟢 Healthy: 3 | 🔵 Overstock: 4
A13: WORKBOOK INDEX
A14: # | B14: Sheet Name | C14: Type | D14: Purpose | E14: Updated By | F14: Frequency | G14: Data Source | H14: Status
A15: 1 | B15: Cost Inputs | C15: 📝 Input | D15: Manual entry of Ad Spend (by channel) and Warehouse/Fulfillment costs by month | E15: Controller | F15: Monthly | G15: Accounting Invoices | H15: ✅ Active
A16: 2 | B16: Sales Trend Analysis | C16: 📊 Analysis | D16: Revenue, COGS, Gross Profit & MoM Growth % across 6 channels × 6 months | E16: Auto | F16: Monthly | G16: Cin7 Core Export | H16: ✅ Active
A17: 3 | B17: Product Margin Analysis | C17: 📊 Analysis | D17: Revenue, COGS, GM%, Avg Sell Price & Avg COGS per unit by SKU and Category | E17: Auto | F17: Monthly | G17: Cin7 Core Export | H17: ✅ Active
A18: 4 | B18: COGS & Profitability by Channel | C18: 📊 Analysis | D18: Product × Channel revenue & COGS matrix with GM% per channel | E18: Auto | F18: Monthly | G18: Cin7 Core Export | H18: ✅ Active
A19: 5 | B19: Inventory & MOS Analysis | C19: 📦 Inventory | D19: Current stock by location, 3-month avg velocity, MOS calculation & 🔴🟡🟢🔵 alerts | E19: Auto | F19: Weekly | G19: Cin7 Core Export | H19: ✅ Active
A20: 6 | B20: Inventory Movements | C20: 📦 Inventory | D20: Units Sold, Units Purchased & Net Movement per SKU across all months | E20: Auto | F20: Monthly | G20: Cin7 Core + Purchase Data | H20: ✅ Active
A21: 7 | B21: Sales Dashboard | C21: 📈 Dashboard | D21: 3 visual charts: Revenue by Channel (bar), Monthly Trend (line), Product Mix (pie) | E21: Auto | F21: Monthly | G21: Calculated Sheets | H21: ✅ Active
A22: 8 | B22: Profitability Dashboard | C22: 📈 Dashboard | D22: Full P&L waterfall: Revenue → COGS → Gross Profit → Ad Spend → Fulfillment → Net Contribution | E22: Auto | F22: Monthly | G22: Calculated + Cost Inputs | H22: ✅ Active
A23: 9 | B23: KPI Dashboard | C23: 🎯 Executive | D23: One-page scorecard: Revenue, Margins, Channel Mix, Top Products, Inventory Alerts | E23: Auto | F23: Monthly | G23: All Sheets | H23: ✅ Active
A24: 10 | B24: Weekly Order Tracker | C24: ⚠️ Risk | D24: Invoice & shipment status breakdown, revenue at risk (Draft/Unshipped), monthly activity summary | E24: Auto | F24: Weekly | G24: Cin7 Core Export | H24: ✅ Active
A25: — | B25: Sales Transactions Raw Data | C25: 🗄️ Raw Data | D25: Source: Cin7 Core sales export — DO NOT EDIT. Paste new data here monthly | E25: Controller | F25: Monthly | G25: Cin7 Core | H25: 📥 Paste Here
A26: — | B26: Inventory On Hand Raw Data | C26: 🗄️ Raw Data | D26: Source: Cin7 Core inventory snapshot — DO NOT EDIT. Paste new data here | E26: Controller | F26: Weekly | G26: Cin7 Core | H26: 📥 Paste Here
A27: — | B27: Purchase Transactions Raw data | C27: 🗄️ Raw Data | D27: Source: Cin7 Core purchase export — DO NOT EDIT. Paste new data here monthly | E27: Controller | F27: Monthly | G27: Cin7 Core | H27: 📥 Paste Here
A30: CONTROLLER RECOMMENDATIONS & INSIGHTS
A31: # | B31: Category | C31: Finding | D31: Recommendation | E31: Priority | F31: Owner | G31: Action By | H31: Status
A32: 1 | B32: Example | C32: EXAMPLE — TEMPLATE INSTRUCTION | D32: Example recommendation | E32: Medium | F32: Unassigned | G32: Pending | H32: Not Started
A45: HOW TO REFRESH THIS MODEL (Monthly Process)
A46: Step | B46: Action | C46: Detail
A47: Step 1 | B47: Export from Cin7 Core | C47: Run: Sales by Product Details report → export to CSV. Paste into 'Sales Transactions Raw Data' tab (replace all rows, keep headers).
A48: Step 2 | B48: Refresh Inventory Snapshot | C48: Export Cin7 Core → Inventory On Hand report → paste into 'Inventory On Hand Raw Data' tab.
A49: Step 3 | B49: Refresh Purchase Transactions | C49: Export Cin7 Core → Purchase Orders report → paste into 'Purchase Transactions Raw data' tab.
A50: Step 4 | B50: Update Cost Inputs | C50: Open 'Cost Inputs' tab. Enter Ad Spend invoices (Amazon Ads, Shopify/Google, TikTok, Other) and 3PL/Warehouse/FBA fees for the new month column.
A51: Step 5 | B51: Update MOS Month Window | C51: In 'Inventory & MOS Analysis' tab, update the 3 most recent months in the avg sales formulas (columns I5:I12) to reflect the latest 3 months.
A52: Step 6 | B52: Review KPI Dashboard | C52: Go to 'KPI Dashboard' — all metrics auto-refresh. Update the Inventory Alert counts from 'Inventory & MOS Analysis'.
A53: Step 7 | B53: Review Recommendations | C53: Return to this Cover sheet. Mark completed items ✅ in column H. Add new findings as needed.

Sheet KPI Dashboard
A1: {{COMPANY_NAME}} — Controller KPI Dashboard
A2: All-period summary | Finished Goods only | Update month references in Sales Trend Analysis as new data flows in
A4: REVENUE & PROFITABILITY
A5: Total Revenue (All Channels) | B5: =SUMIFS('Sales Transactions Raw Data'!V:V,'Sales Transactions Raw Data'!J:J,"Finished Goods") -> 0 | C5: Total Units Sold | D5: =SUMIFS('Sales Transactions Raw Data'!T:T,'Sales Transactions Raw Data'!J:J,"Finished Goods") -> 0
A6: Total COGS | B6: =SUMIFS('Sales Transactions Raw Data'!W:W,'Sales Transactions Raw Data'!J:J,"Finished Goods") -> 0 | C6: Gross Profit | D6: =B5-B6 -> 0
A7: Gross Margin % | B7: =IF(B5=0,"-",D6/B5) -> - | C7: Net Contribution (after Ad+Fulfillment) | D7: ='Profitability Dashboard'!L12 -> 0
A8: Net Margin % | B8: =IF(B5=0,"-",'Profitability Dashboard'!L13) -> - | C8: Avg Sell Price / Unit | D8: =IF(D5=0,"-",B5/D5) -> -
A10: CHANNEL PERFORMANCE
A11: Channel | B11: Revenue | C11: GM% | D11: Revenue Mix
A12: Amazon | B12: =SUMIFS('Sales Transactions Raw Data'!V:V,'Sales Transactions Raw Data'!S:S,"amazon",'Sales Transactions Raw Data'!J:J,"Finished Goods") -> 0 | C12: ='COGS & Profitability by Channel'!B22 -> - | D12: =IF($B$5=0,"-",B12/$B$5) -> -
A13: Amazon Retail (amazon-us) | B13: =SUMIFS('Sales Transactions Raw Data'!V:V,'Sales Transactions Raw Data'!S:S,"amazon-us",'Sales Transactions Raw Data'!J:J,"Finished Goods") -> 0 | C13: ='COGS & Profitability by Channel'!C22 -> - | D13: =IF($B$5=0,"-",B13/$B$5) -> -
A14: Shopify Web | B14: =SUMIFS('Sales Transactions Raw Data'!V:V,'Sales Transactions Raw Data'!S:S,"Shopify web",'Sales Transactions Raw Data'!J:J,"Finished Goods") -> 0 | C14: ='COGS & Profitability by Channel'!D22 -> - | D14: =IF($B$5=0,"-",B14/$B$5) -> -
A15: Shopify POS | B15: =SUMIFS('Sales Transactions Raw Data'!V:V,'Sales Transactions Raw Data'!S:S,"Shopify POS",'Sales Transactions Raw Data'!J:J,"Finished Goods") -> 0 | C15: ='COGS & Profitability by Channel'!E22 -> - | D15: =IF($B$5=0,"-",B15/$B$5) -> -
A16: Shopify Admin | B16: =SUMIFS('Sales Transactions Raw Data'!V:V,'Sales Transactions Raw Data'!S:S,"Shopify admin",'Sales Transactions Raw Data'!J:J,"Finished Goods") -> 0 | C16: ='COGS & Profitability by Channel'!F22 -> - | D16: =IF($B$5=0,"-",B16/$B$5) -> -
A17: Subscriptions (contract) | B17: =SUMIFS('Sales Transactions Raw Data'!V:V,'Sales Transactions Raw Data'!S:S,"subscription_contract",'Sales Transactions Raw Data'!J:J,"Finished Goods") -> 0 | C17: ='COGS & Profitability by Channel'!G22 -> - | D17: =IF($B$5=0,"-",B17/$B$5) -> -
A18: Subscriptions (checkout) | B18: =SUMIFS('Sales Transactions Raw Data'!V:V,'Sales Transactions Raw Data'!S:S,"subscription_contract_checkout_one",'Sales Transactions Raw Data'!J:J,"Finished Goods") -> 0 | C18: ='COGS & Profitability by Channel'!H22 -> - | D18: =IF($B$5=0,"-",B18/$B$5) -> -
A19: Wholesale (296827748353) | B19: =SUMIFS('Sales Transactions Raw Data'!V:V,'Sales Transactions Raw Data'!S:S,"296827748353",'Sales Transactions Raw Data'!J:J,"Finished Goods") -> 0 | C19: ='COGS & Profitability by Channel'!I22 -> - | D19: =IF($B$5=0,"-",B19/$B$5) -> -
A20: Faire (Wholesale Mkt) | B20: =SUMIFS('Sales Transactions Raw Data'!V:V,'Sales Transactions Raw Data'!S:S,"faire",'Sales Transactions Raw Data'!J:J,"Finished Goods") -> 0 | C20: ='COGS & Profitability by Channel'!J22 -> - | D20: =IF($B$5=0,"-",B20/$B$5) -> -
A21: TikTok Shop | B21: =SUMIFS('Sales Transactions Raw Data'!V:V,'Sales Transactions Raw Data'!S:S,"tiktok",'Sales Transactions Raw Data'!J:J,"Finished Goods") -> 0 | C21: ='COGS & Profitability by Channel'!K22 -> - | D21: =IF($B$5=0,"-",B21/$B$5) -> -
A22: 16oz Variety 12pk | B22: ='Product Margin Analysis'!C5 -> 0 | C22: ='Product Margin Analysis'!F5 -> - | D22: ='Product Margin Analysis'!B5 -> 0
A23: 16oz Berry Coconut 12pk | B23: ='Product Margin Analysis'!C6 -> 0 | C23: ='Product Margin Analysis'!F6 -> - | D23: ='Product Margin Analysis'!B6 -> 0
A24: 16oz Raspberry 12pk | B24: ='Product Margin Analysis'!C7 -> 0 | C24: ='Product Margin Analysis'!F7 -> - | D24: ='Product Margin Analysis'!B7 -> 0
A25: 16oz Grapefruit Ginger 12pk | B25: ='Product Margin Analysis'!C8 -> 0 | C25: ='Product Margin Analysis'!F8 -> - | D25: ='Product Margin Analysis'!B8 -> 0
A26: 16oz Starter 4pk | B26: ='Product Margin Analysis'!C9 -> 0 | C26: ='Product Margin Analysis'!F9 -> - | D26: ='Product Margin Analysis'!B9 -> 0
A27: Loose Cans (all flavours) | B27: ='Product Margin Analysis'!C10 -> 0 | C27: ='Product Margin Analysis'!F10 -> - | D27: ='Product Margin Analysis'!B10 -> 0
A30: INVENTORY STOCK ALERTS (Current Snapshot)
A31: 🔴 CRITICAL (< 1 month) | B31: ='Inventory & MOS Analysis'!B16 -> 0 | C31: SKUs
A32: 🟡 LOW (1–2 months) | B32: ='Inventory & MOS Analysis'!B17 -> 0 | C32: SKUs
A33: 🟢 HEALTHY (2–6 months) | B33: ='Inventory & MOS Analysis'!B18 -> 0 | C33: SKUs
A34: 🔵 OVERSTOCK (> 6 months) | B34: ='Inventory & MOS Analysis'!B19 -> 0 | C34: SKUs

Sheet Weekly Order Tracker
A1: Weekly Order Tracker — Open Items & Risk Flags
A2: Tracks open/pending orders by invoice & shipment status | Update 'As Of Date' in B3 each week
A3: As Of Date (Today): | B3: =TODAY() -> 46258
A5: ORDER STATUS SUMMARY
A6: Status | B6: # Orders | C6: Revenue Value | D6: % of Total | E6: COGS | F6: Gross Profit
A7: Invoiced | B7: =COUNTIFS('Sales Transactions Raw Data'!N:N,"Invoiced") -> 0 | C7: =SUMIFS('Sales Transactions Raw Data'!V:V,'Sales Transactions Raw Data'!N:N,"Invoiced") -> 0 | D7: =IF(C9=0,"-",C7/C9) -> - | E7: =SUMIFS('Sales Transactions Raw Data'!W:W,'Sales Transactions Raw Data'!N:N,"Invoiced") -> 0 | F7: =C7-E7 -> 0
A8: Invoiced / credited | B8: =COUNTIFS('Sales Transactions Raw Data'!N:N,"Invoiced / credited") -> 0 | C8: =SUMIFS('Sales Transactions Raw Data'!V:V,'Sales Transactions Raw Data'!N:N,"Invoiced / credited") -> 0 | D8: =IF(C9=0,"-",C8/C9) -> - | E8: =SUMIFS('Sales Transactions Raw Data'!W:W,'Sales Transactions Raw Data'!N:N,"Invoiced / credited") -> 0 | F8: =C8-E8 -> 0
A9: TOTAL | B9: =SUM(B7:B8) -> 0 | C9: =SUM(C7:C8) -> 0 | D9: 1 | E9: =SUM(E7:E8) -> 0 | F9: =SUM(F7:F8) -> 0
A11: SHIPMENT STATUS SUMMARY
A12: Shipment Status | B12: # Lines | C12: Revenue Value | D12: % of Total | E12: COGS | F12: Gross Profit
A13: Shipped | B13: =COUNTIFS('Sales Transactions Raw Data'!P:P,"Shipped") -> 0 | C13: =SUMIFS('Sales Transactions Raw Data'!V:V,'Sales Transactions Raw Data'!P:P,"Shipped") -> 0 | D13: =IF(C16=0,"-",C13/C16) -> - | E13: =SUMIFS('Sales Transactions Raw Data'!W:W,'Sales Transactions Raw Data'!P:P,"Shipped") -> 0 | F13: =C13-E13 -> 0
A14: Unshipped / Pending | B14: =COUNTIFS('Sales Transactions Raw Data'!P:P,"<>Shipped",'Sales Transactions Raw Data'!P:P,"<>") -> 1 | C14: =SUMIFS('Sales Transactions Raw Data'!V:V,'Sales Transactions Raw Data'!P:P,"<>Shipped",'Sales Transactions Raw Data'!P:P,"<>") -> 0 | D14: =IF(C16=0,"-",C14/C16) -> - | E14: =SUMIFS('Sales Transactions Raw Data'!W:W,'Sales Transactions Raw Data'!P:P,"<>Shipped",'Sales Transactions Raw Data'!P:P,"<>") -> 0 | F14: =C14-E14 -> 0
A15: Partially Shipped | B15: =0 -> 0 | C15: 0 | D15: =IF(C16=0,"-",C15/C16) -> - | E15: 0 | F15: =C15-E15 -> 0
A16: TOTAL | B16: =SUM(B13:B15) -> 1 | C16: =SUM(C13:C15) -> 0 | D16: 1 | E16: =SUM(E13:E15) -> 0 | F16: =SUM(F13:F15) -> 0
A18: OPEN & PENDING ORDERS — RISK TRACKER
A19: Note: The list below summarises open orders (Invoice Status = Draft or Shipment Status ≠ Shipped). For the full transaction-level view, apply filters on the raw data sheet (columns N & O).
A21: Risk Category | B21: # Orders | C21: Revenue at Risk | D21: Avg Order Value | E21: % of Total Revenue | F21: Months Active | G21: Action
A22: 📋 Invoiced / credited (adjustments) | B22: =COUNTIFS('Sales Transactions Raw Data'!N:N,"Invoiced / credited") -> 0 | C22: =SUMIFS('Sales Transactions Raw Data'!V:V,'Sales Transactions Raw Data'!N:N,"Invoiced / credited") -> 0 | D22: =IFERROR(C22/B22,"-") -> - | E22: =IFERROR(C22/'KPI Dashboard'!B5,"-") -> - | F22: Credits/adjustments | G22: Review credit memos
A23: ⚠️ Unshipped / Pending lines (col P ≠ Shipped) | B23: =COUNTIFS('Sales Transactions Raw Data'!P:P,"<>Shipped",'Sales Transactions Raw Data'!P:P,"<>") -> 1 | C23: =SUMIFS('Sales Transactions Raw Data'!V:V,'Sales Transactions Raw Data'!P:P,"<>Shipped",'Sales Transactions Raw Data'!P:P,"<>") -> 0 | D23: =IFERROR(C23/B23,"-") -> 0 | E23: =IFERROR(C23/'KPI Dashboard'!B5,"-") -> - | F23: Fulfillment risk | G23: Chase fulfillment immediately
A24: 📦 Partially Shipped | B24: =COUNTIFS('Sales Transactions Raw Data'!O:O,"Partially Shipped") -> 0 | C24: =SUMIFS('Sales Transactions Raw Data'!V:V,'Sales Transactions Raw Data'!O:O,"Partially Shipped") -> 0 | D24: =IFERROR(C24/B24,"-") -> - | E24: =IFERROR(C24/'KPI Dashboard'!B5,"-") -> - | F24: "" | G24: Follow up on remainder
A27: MONTHLY ORDER ACTIVITY SUMMARY
A28: Month | B28: Total Orders | C28: Invoiced Orders | D28: Draft Orders | E28: Shipped (col P) | F28: Not Shipped (col P) | G28: Revenue | H28: COGS
A29: 45717 | B29: =COUNTIFS('Sales Transactions Raw Data'!B:B,"March",'Sales Transactions Raw Data'!A:A,2025) -> 0 | C29: =COUNTIFS('Sales Transactions Raw Data'!B:B,"March",'Sales Transactions Raw Data'!A:A,2025,'Sales Transactions Raw Data'!N:N,"Invoiced")+COUNTIFS('Sales Transactions Raw Data'!B:B,"March",'Sales Transactions Raw Data'!A:A,2025,'Sales Transactions Raw Data'!N:N,"Invoiced / credited") -> 0 | D29: =0 -> 0 | E29: =COUNTIFS('Sales Transactions Raw Data'!B:B,"March",'Sales Transactions Raw Data'!A:A,2025,'Sales Transactions Raw Data'!P:P,"Shipped") -> 0 | F29: =COUNTIFS('Sales Transactions Raw Data'!B:B,"March",'Sales Transactions Raw Data'!A:A,2025,'Sales Transactions Raw Data'!P:P,"<>Shipped",'Sales Transactions Raw Data'!P:P,"<>") -> 0 | G29: =SUMIFS('Sales Transactions Raw Data'!V:V,'Sales Transactions Raw Data'!B:B,"March",'Sales Transactions Raw Data'!A:A,2025) -> 0 | H29: =SUMIFS('Sales Transactions Raw Data'!W:W,'Sales Transactions Raw Data'!B:B,"March",'Sales Transactions Raw Data'!A:A,2025) -> 0
A30: 45839 | B30: =COUNTIFS('Sales Transactions Raw Data'!B:B,"July",'Sales Transactions Raw Data'!A:A,2025) -> 0 | C30: =COUNTIFS('Sales Transactions Raw Data'!B:B,"July",'Sales Transactions Raw Data'!A:A,2025,'Sales Transactions Raw Data'!N:N,"Invoiced")+COUNTIFS('Sales Transactions Raw Data'!B:B,"July",'Sales Transactions Raw Data'!A:A,2025,'Sales Transactions Raw Data'!N:N,"Invoiced / credited") -> 0 | D30: =0 -> 0 | E30: =COUNTIFS('Sales Transactions Raw Data'!B:B,"July",'Sales Transactions Raw Data'!A:A,2025,'Sales Transactions Raw Data'!P:P,"Shipped") -> 0 | F30: =COUNTIFS('Sales Transactions Raw Data'!B:B,"July",'Sales Transactions Raw Data'!A:A,2025,'Sales Transactions Raw Data'!P:P,"<>Shipped",'Sales Transactions Raw Data'!P:P,"<>") -> 0 | G30: =SUMIFS('Sales Transactions Raw Data'!V:V,'Sales Transactions Raw Data'!B:B,"July",'Sales Transactions Raw Data'!A:A,2025) -> 0 | H30: =SUMIFS('Sales Transactions Raw Data'!W:W,'Sales Transactions Raw Data'!B:B,"July",'Sales Transactions Raw Data'!A:A,2025) -> 0
A31: 45870 | B31: =COUNTIFS('Sales Transactions Raw Data'!B:B,"August",'Sales Transactions Raw Data'!A:A,2025) -> 0 | C31: =COUNTIFS('Sales Transactions Raw Data'!B:B,"August",'Sales Transactions Raw Data'!A:A,2025,'Sales Transactions Raw Data'!N:N,"Invoiced")+COUNTIFS('Sales Transactions Raw Data'!B:B,"August",'Sales Transactions Raw Data'!A:A,2025,'Sales Transactions Raw Data'!N:N,"Invoiced / credited") -> 0 | D31: =0 -> 0 | E31: =COUNTIFS('Sales Transactions Raw Data'!B:B,"August",'Sales Transactions Raw Data'!A:A,2025,'Sales Transactions Raw Data'!P:P,"Shipped") -> 0 | F31: =COUNTIFS('Sales Transactions Raw Data'!B:B,"August",'Sales Transactions Raw Data'!A:A,2025,'Sales Transactions Raw Data'!P:P,"<>Shipped",'Sales Transactions Raw Data'!P:P,"<>") -> 0 | G31: =SUMIFS('Sales Transactions Raw Data'!V:V,'Sales Transactions Raw Data'!B:B,"August",'Sales Transactions Raw Data'!A:A,2025) -> 0 | H31: =SUMIFS('Sales Transactions Raw Data'!W:W,'Sales Transactions Raw Data'!B:B,"August",'Sales Transactions Raw Data'!A:A,2025) -> 0
A32: 45901 | B32: =COUNTIFS('Sales Transactions Raw Data'!B:B,"September",'Sales Transactions Raw Data'!A:A,2025) -> 0 | C32: =COUNTIFS('Sales Transactions Raw Data'!B:B,"September",'Sales Transactions Raw Data'!A:A,2025,'Sales Transactions Raw Data'!N:N,"Invoiced")+COUNTIFS('Sales Transactions Raw Data'!B:B,"September",'Sales Transactions Raw Data'!A:A,2025,'Sales Transactions Raw Data'!N:N,"Invoiced / credited") -> 0 | D32: =0 -> 0 | E32: =COUNTIFS('Sales Transactions Raw Data'!B:B,"September",'Sales Transactions Raw Data'!A:A,2025,'Sales Transactions Raw Data'!P:P,"Shipped") -> 0 | F32: =COUNTIFS('Sales Transactions Raw Data'!B:B,"September",'Sales Transactions Raw Data'!A:A,2025,'Sales Transactions Raw Data'!P:P,"<>Shipped",'Sales Transactions Raw Data'!P:P,"<>") -> 0 | G32: =SUMIFS('Sales Transactions Raw Data'!V:V,'Sales Transactions Raw Data'!B:B,"September",'Sales Transactions Raw Data'!A:A,2025) -> 0 | H32: =SUMIFS('Sales Transactions Raw Data'!W:W,'Sales Transactions Raw Data'!B:B,"September",'Sales Transactions Raw Data'!A:A,2025) -> 0
A33: 45931 | B33: =COUNTIFS('Sales Transactions Raw Data'!B:B,"October",'Sales Transactions Raw Data'!A:A,2025) -> 0 | C33: =COUNTIFS('Sales Transactions Raw Data'!B:B,"October",'Sales Transactions Raw Data'!A:A,2025,'Sales Transactions Raw Data'!N:N,"Invoiced")+COUNTIFS('Sales Transactions Raw Data'!B:B,"October",'Sales Transactions Raw Data'!A:A,2025,'Sales Transactions Raw Data'!N:N,"Invoiced / credited") -> 0 | D33: =0 -> 0 | E33: =COUNTIFS('Sales Transactions Raw Data'!B:B,"October",'Sales Transactions Raw Data'!A:A,2025,'Sales Transactions Raw Data'!P:P,"Shipped") -> 0 | F33: =COUNTIFS('Sales Transactions Raw Data'!B:B,"October",'Sales Transactions Raw Data'!A:A,2025,'Sales Transactions Raw Data'!P:P,"<>Shipped",'Sales Transactions Raw Data'!P:P,"<>") -> 0 | G33: =SUMIFS('Sales Transactions Raw Data'!V:V,'Sales Transactions Raw Data'!B:B,"October",'Sales Transactions Raw Data'!A:A,2025) -> 0 | H33: =SUMIFS('Sales Transactions Raw Data'!W:W,'Sales Transactions Raw Data'!B:B,"October",'Sales Transactions Raw Data'!A:A,2025) -> 0
A34: 45962 | B34: =COUNTIFS('Sales Transactions Raw Data'!B:B,"November",'Sales Transactions Raw Data'!A:A,2025) -> 0 | C34: =COUNTIFS('Sales Transactions Raw Data'!B:B,"November",'Sales Transactions Raw Data'!A:A,2025,'Sales Transactions Raw Data'!N:N,"Invoiced")+COUNTIFS('Sales Transactions Raw Data'!B:B,"November",'Sales Transactions Raw Data'!A:A,2025,'Sales Transactions Raw Data'!N:N,"Invoiced / credited") -> 0 | D34: =0 -> 0 | E34: =COUNTIFS('Sales Transactions Raw Data'!B:B,"November",'Sales Transactions Raw Data'!A:A,2025,'Sales Transactions Raw Data'!P:P,"Shipped") -> 0 | F34: =COUNTIFS('Sales Transactions Raw Data'!B:B,"November",'Sales Transactions Raw Data'!A:A,2025,'Sales Transactions Raw Data'!P:P,"<>Shipped",'Sales Transactions Raw Data'!P:P,"<>") -> 0 | G34: =SUMIFS('Sales Transactions Raw Data'!V:V,'Sales Transactions Raw Data'!B:B,"November",'Sales Transactions Raw Data'!A:A,2025) -> 0 | H34: =SUMIFS('Sales Transactions Raw Data'!W:W,'Sales Transactions Raw Data'!B:B,"November",'Sales Transactions Raw Data'!A:A,2025) -> 0
A35: TOTAL | B35: =SUM(B29:B34) -> 0 | C35: =SUM(C29:C34) -> 0 | D35: =SUM(D29:D34) -> 0 | E35: =SUM(E29:E34) -> 0 | F35: =SUM(F29:F34) -> 0 | G35: =SUM(G29:G34) -> 0 | H35: =SUM(H29:H34) -> 0

Sheet Sales Trend Analysis
A1: Sales Trend Analysis — Monthly by Channel
A3: REVENUE BY CHANNEL ($) | B3: 46106 | C3: 46228 | D3: 46259 | E3: 46290 | F3: 46320 | G3: 46351 | H3: 46381 | I3: 46048 | J3: 46079 | K3: 46107 | L3: Total
A4: Amazon (Seller Central) | B4: =SUMIFS('Sales Transactions Raw Data'!V:V,'Sales Transactions Raw Data'!S:S,"amazon",'Sales Transactions Raw Data'!B:B,"March",'Sales Transactions Raw Data'!A:A,2025,'Sales Transactions Raw Data'!J:J,"Finished Goods") -> 0 | C4: =SUMIFS('Sales Transactions Raw Data'!V:V,'Sales Transactions Raw Data'!S:S,"amazon",'Sales Transactions Raw Data'!B:B,"March",'Sales Transactions Raw Data'!A:A,2025,'Sales Transactions Raw Data'!J:J,"Finished Goods") -> 0 | D4: =SUMIFS('Sales Transactions Raw Data'!V:V,'Sales Transactions Raw Data'!S:S,"amazon",'Sales Transactions Raw Data'!B:B,"July",'Sales Transactions Raw Data'!A:A,2025,'Sales Transactions Raw Data'!J:J,"Finished Goods") -> 0 | E4: =SUMIFS('Sales Transactions Raw Data'!V:V,'Sales Transactions Raw Data'!S:S,"amazon",'Sales Transactions Raw Data'!B:B,"August",'Sales Transactions Raw Data'!A:A,2025,'Sales Transactions Raw Data'!J:J,"Finished Goods") -> 0 | F4: =SUMIFS('Sales Transactions Raw Data'!V:V,'Sales Transactions Raw Data'!S:S,"amazon",'Sales Transactions Raw Data'!B:B,"September",'Sales Transactions Raw Data'!A:A,2025,'Sales Transactions Raw Data'!J:J,"Finished Goods") -> 0 | G4: =SUMIFS('Sales Transactions Raw Data'!V:V,'Sales Transactions Raw Data'!S:S,"amazon",'Sales Transactions Raw Data'!B:B,"October",'Sales Transactions Raw Data'!A:A,2025,'Sales Transactions Raw Data'!J:J,"Finished Goods") -> 0 | H4: =SUMIFS('Sales Transactions Raw Data'!V:V,'Sales Transactions Raw Data'!S:S,"amazon",'Sales Transactions Raw Data'!B:B,"November",'Sales Transactions Raw Data'!A:A,2025,'Sales Transactions Raw Data'!J:J,"Finished Goods") -> 0 | I4: =SUMIFS('Sales Transactions Raw Data'!V:V,'Sales Transactions Raw Data'!S:S,"amazon",'Sales Transactions Raw Data'!B:B,"January",'Sales Transactions Raw Data'!A:A,2026,'Sales Transactions Raw Data'!J:J,"Finished Goods") -> 0 | J4: =SUMIFS('Sales Transactions Raw Data'!V:V,'Sales Transactions Raw Data'!S:S,"amazon",'Sales Transactions Raw Data'!B:B,"February",'Sales Transactions Raw Data'!A:A,2026,'Sales Transactions Raw Data'!J:J,"Finished Goods") -> 0 | K4: =SUMIFS('Sales Transactions Raw Data'!V:V,'Sales Transactions Raw Data'!S:S,"amazon",'Sales Transactions Raw Data'!B:B,"March",'Sales Transactions Raw Data'!A:A,2026,'Sales Transactions Raw Data'!J:J,"Finished Goods") -> 0 | L4: =SUM(B4:K4) -> 0
A5: Amazon Retail / Vendor | B5: =SUMIFS('Sales Transactions Raw Data'!V:V,'Sales Transactions Raw Data'!R:R,"Amazon.com",'Sales Transactions Raw Data'!B:B,"March",'Sales Transactions Raw Data'!A:A,2025,'Sales Transactions Raw Data'!J:J,"Finished Goods") -> 0 | C5: =SUMIFS('Sales Transactions Raw Data'!V:V,'Sales Transactions Raw Data'!S:S,"amazon-us",'Sales Transactions Raw Data'!B:B,"March",'Sales Transactions Raw Data'!A:A,2025,'Sales Transactions Raw Data'!J:J,"Finished Goods") -> 0 | D5: =SUMIFS('Sales Transactions Raw Data'!V:V,'Sales Transactions Raw Data'!S:S,"amazon-us",'Sales Transactions Raw Data'!B:B,"July",'Sales Transactions Raw Data'!A:A,2025,'Sales Transactions Raw Data'!J:J,"Finished Goods") -> 0 | E5: =SUMIFS('Sales Transactions Raw Data'!V:V,'Sales Transactions Raw Data'!S:S,"amazon-us",'Sales Transactions Raw Data'!B:B,"August",'Sales Transactions Raw Data'!A:A,2025,'Sales Transactions Raw Data'!J:J,"Finished Goods") -> 0 | F5: =SUMIFS('Sales Transactions Raw Data'!V:V,'Sales Transactions Raw Data'!S:S,"amazon-us",'Sales Transactions Raw Data'!B:B,"September",'Sales Transactions Raw Data'!A:A,2025,'Sales Transactions Raw Data'!J:J,"Finished Goods") -> 0 | G5: =SUMIFS('Sales Transactions Raw Data'!V:V,'Sales Transactions Raw Data'!S:S,"amazon-us",'Sales Transactions Raw Data'!B:B,"October",'Sales Transactions Raw Data'!A:A,2025,'Sales Transactions Raw Data'!J:J,"Finished Goods") -> 0 | H5: =SUMIFS('Sales Transactions Raw Data'!V:V,'Sales Transactions Raw Data'!S:S,"amazon-us",'Sales Transactions Raw Data'!B:B,"November",'Sales Transactions Raw Data'!A:A,2025,'Sales Transactions Raw Data'!J:J,"Finished Goods") -> 0 | I5: =SUMIFS('Sales Transactions Raw Data'!V:V,'Sales Transactions Raw Data'!R:R,"Amazon.com",'Sales Transactions Raw Data'!B:B,"January",'Sales Transactions Raw Data'!A:A,2026,'Sales Transactions Raw Data'!J:J,"Finished Goods") -> 0 | J5: =SUMIFS('Sales Transactions Raw Data'!V:V,'Sales Transactions Raw Data'!R:R,"Amazon.com",'Sales Transactions Raw Data'!B:B,"February",'Sales Transactions Raw Data'!A:A,2026,'Sales Transactions Raw Data'!J:J,"Finished Goods") -> 0 | K5: =SUMIFS('Sales Transactions Raw Data'!V:V,'Sales Transactions Raw Data'!R:R,"Amazon.com",'Sales Transactions Raw Data'!B:B,"March",'Sales Transactions Raw Data'!A:A,2026,'Sales Transactions Raw Data'!J:J,"Finished Goods") -> 0 | L5: =SUM(B5:K5) -> 0
A6: Shopify Web (D2C) | B6: =SUMIFS('Sales Transactions Raw Data'!V:V,'Sales Transactions Raw Data'!S:S,"Shopify web",'Sales Transactions Raw Data'!B:B,"March",'Sales Transactions Raw Data'!A:A,2025,'Sales Transactions Raw Data'!J:J,"Finished Goods") -> 0 | C6: =SUMIFS('Sales Transactions Raw Data'!V:V,'Sales Transactions Raw Data'!S:S,"Shopify web",'Sales Transactions Raw Data'!B:B,"March",'Sales Transactions Raw Data'!A:A,2025,'Sales Transactions Raw Data'!J:J,"Finished Goods") -> 0 | D6: =SUMIFS('Sales Transactions Raw Data'!V:V,'Sales Transactions Raw Data'!S:S,"Shopify web",'Sales Transactions Raw Data'!B:B,"July",'Sales Transactions Raw Data'!A:A,2025,'Sales Transactions Raw Data'!J:J,"Finished Goods") -> 0 | E6: =SUMIFS('Sales Transactions Raw Data'!V:V,'Sales Transactions Raw Data'!S:S,"Shopify web",'Sales Transactions Raw Data'!B:B,"August",'Sales Transactions Raw Data'!A:A,2025,'Sales Transactions Raw Data'!J:J,"Finished Goods") -> 0 | F6: =SUMIFS('Sales Transactions Raw Data'!V:V,'Sales Transactions Raw Data'!S:S,"Shopify web",'Sales Transactions Raw Data'!B:B,"September",'Sales Transactions Raw Data'!A:A,2025,'Sales Transactions Raw Data'!J:J,"Finished Goods") -> 0 | G6: =SUMIFS('Sales Transactions Raw Data'!V:V,'Sales Transactions Raw Data'!S:S,"Shopify web",'Sales Transactions Raw Data'!B:B,"October",'Sales Transactions Raw Data'!A:A,2025,'Sales Transactions Raw Data'!J:J,"Finished Goods") -> 0 | H6: =SUMIFS('Sales Transactions Raw Data'!V:V,'Sales Transactions Raw Data'!S:S,"Shopify web",'Sales Transactions Raw Data'!B:B,"November",'Sales Transactions Raw Data'!A:A,2025,'Sales Transactions Raw Data'!J:J,"Finished Goods") -> 0 | I6: =SUMIFS('Sales Transactions Raw Data'!V:V,'Sales Transactions Raw Data'!S:S,"Shopify web",'Sales Transactions Raw Data'!B:B,"January",'Sales Transactions Raw Data'!A:A,2026,'Sales Transactions Raw Data'!J:J,"Finished Goods") -> 0 | J6: =SUMIFS('Sales Transactions Raw Data'!V:V,'Sales Transactions Raw Data'!S:S,"Shopify web",'Sales Transactions Raw Data'!B:B,"February",'Sales Transactions Raw Data'!A:A,2026,'Sales Transactions Raw Data'!J:J,"Finished Goods") -> 0 | K6: =SUMIFS('Sales Transactions Raw Data'!V:V,'Sales Transactions Raw Data'!S:S,"Shopify web",'Sales Transactions Raw Data'!B:B,"March",'Sales Transactions Raw Data'!A:A,2026,'Sales Transactions Raw Data'!J:J,"Finished Goods") -> 0 | L6: =SUM(B6:K6) -> 0
A7: Shopify POS (In-store) | B7: =SUMIFS('Sales Transactions Raw Data'!V:V,'Sales Transactions Raw Data'!S:S,"tiktok",'Sales Transactions Raw Data'!B:B,"March",'Sales Transactions Raw Data'!A:A,2025,'Sales Transactions Raw Data'!J:J,"Finished Goods") -> 0 | C7: =SUMIFS('Sales Transactions Raw Data'!V:V,'Sales Transactions Raw Data'!S:S,"Shopify POS",'Sales Transactions Raw Data'!B:B,"March",'Sales Transactions Raw Data'!A:A,2025,'Sales Transactions Raw Data'!J:J,"Finished Goods") -> 0 | D7: =SUMIFS('Sales Transactions Raw Data'!V:V,'Sales Transactions Raw Data'!S:S,"Shopify POS",'Sales Transactions Raw Data'!B:B,"July",'Sales Transactions Raw Data'!A:A,2025,'Sales Transactions Raw Data'!J:J,"Finished Goods") -> 0 | E7: =SUMIFS('Sales Transactions Raw Data'!V:V,'Sales Transactions Raw Data'!S:S,"Shopify POS",'Sales Transactions Raw Data'!B:B,"August",'Sales Transactions Raw Data'!A:A,2025,'Sales Transactions Raw Data'!J:J,"Finished Goods") -> 0 | F7: =SUMIFS('Sales Transactions Raw Data'!V:V,'Sales Transactions Raw Data'!S:S,"Shopify POS",'Sales Transactions Raw Data'!B:B,"September",'Sales Transactions Raw Data'!A:A,2025,'Sales Transactions Raw Data'!J:J,"Finished Goods") -> 0 | G7: =SUMIFS('Sales Transactions Raw Data'!V:V,'Sales Transactions Raw Data'!S:S,"Shopify POS",'Sales Transactions Raw Data'!B:B,"October",'Sales Transactions Raw Data'!A:A,2025,'Sales Transactions Raw Data'!J:J,"Finished Goods") -> 0 | H7: =SUMIFS('Sales Transactions Raw Data'!V:V,'Sales Transactions Raw Data'!S:S,"Shopify POS",'Sales Transactions Raw Data'!B:B,"November",'Sales Transactions Raw Data'!A:A,2025,'Sales Transactions Raw Data'!J:J,"Finished Goods") -> 0 | I7: =SUMIFS('Sales Transactions Raw Data'!V:V,'Sales Transactions Raw Data'!S:S,"tiktok",'Sales Transactions Raw Data'!B:B,"January",'Sales Transactions Raw Data'!A:A,2026,'Sales Transactions Raw Data'!J:J,"Finished Goods") -> 0 | J7: =SUMIFS('Sales Transactions Raw Data'!V:V,'Sales Transactions Raw Data'!S:S,"tiktok",'Sales Transactions Raw Data'!B:B,"February",'Sales Transactions Raw Data'!A:A,2026,'Sales Transactions Raw Data'!J:J,"Finished Goods") -> 0 | K7: =SUMIFS('Sales Transactions Raw Data'!V:V,'Sales Transactions Raw Data'!S:S,"tiktok",'Sales Transactions Raw Data'!B:B,"March",'Sales Transactions Raw Data'!A:A,2026,'Sales Transactions Raw Data'!J:J,"Finished Goods") -> 0 | L7: =SUM(B7:K7) -> 0
A8: Shopify Admin (Samples/Manual) | B8: =SUMIFS('Sales Transactions Raw Data'!V:V,'Sales Transactions Raw Data'!S:S,"296827748353",'Sales Transactions Raw Data'!B:B,"March",'Sales Transactions Raw Data'!A:A,2025,'Sales Transactions Raw Data'!J:J,"Finished Goods") -> 0 | C8: =SUMIFS('Sales Transactions Raw Data'!V:V,'Sales Transactions Raw Data'!S:S,"Shopify admin",'Sales Transactions Raw Data'!B:B,"March",'Sales Transactions Raw Data'!A:A,2025,'Sales Transactions Raw Data'!J:J,"Finished Goods") -> 0 | D8: =SUMIFS('Sales Transactions Raw Data'!V:V,'Sales Transactions Raw Data'!S:S,"Shopify admin",'Sales Transactions Raw Data'!B:B,"July",'Sales Transactions Raw Data'!A:A,2025,'Sales Transactions Raw Data'!J:J,"Finished Goods") -> 0 | E8: =SUMIFS('Sales Transactions Raw Data'!V:V,'Sales Transactions Raw Data'!S:S,"Shopify admin",'Sales Transactions Raw Data'!B:B,"August",'Sales Transactions Raw Data'!A:A,2025,'Sales Transactions Raw Data'!J:J,"Finished Goods") -> 0 | F8: =SUMIFS('Sales Transactions Raw Data'!V:V,'Sales Transactions Raw Data'!S:S,"Shopify admin",'Sales Transactions Raw Data'!B:B,"September",'Sales Transactions Raw Data'!A:A,2025,'Sales Transactions Raw Data'!J:J,"Finished Goods") -> 0 | G8: =SUMIFS('Sales Transactions Raw Data'!V:V,'Sales Transactions Raw Data'!S:S,"Shopify admin",'Sales Transactions Raw Data'!B:B,"October",'Sales Transactions Raw Data'!A:A,2025,'Sales Transactions Raw Data'!J:J,"Finished Goods") -> 0 | H8: =SUMIFS('Sales Transactions Raw Data'!V:V,'Sales Transactions Raw Data'!S:S,"Shopify admin",'Sales Transactions Raw Data'!B:B,"November",'Sales Transactions Raw Data'!A:A,2025,'Sales Transactions Raw Data'!J:J,"Finished Goods") -> 0 | I8: =SUMIFS('Sales Transactions Raw Data'!V:V,'Sales Transactions Raw Data'!S:S,"296827748353",'Sales Transactions Raw Data'!B:B,"January",'Sales Transactions Raw Data'!A:A,2026,'Sales Transactions Raw Data'!J:J,"Finished Goods") -> 0 | J8: =SUMIFS('Sales Transactions Raw Data'!V:V,'Sales Transactions Raw Data'!S:S,"296827748353",'Sales Transactions Raw Data'!B:B,"February",'Sales Transactions Raw Data'!A:A,2026,'Sales Transactions Raw Data'!J:J,"Finished Goods") -> 0 | K8: =SUMIFS('Sales Transactions Raw Data'!V:V,'Sales Transactions Raw Data'!S:S,"296827748353",'Sales Transactions Raw Data'!B:B,"March",'Sales Transactions Raw Data'!A:A,2026,'Sales Transactions Raw Data'!J:J,"Finished Goods") -> 0 | L8: =SUM(B8:K8) -> 0
A9: Subscriptions (contract) | B9: =SUMIFS('Sales Transactions Raw Data'!V:V,'Sales Transactions Raw Data'!S:S,"Shopify POS",'Sales Transactions Raw Data'!B:B,"March",'Sales Transactions Raw Data'!A:A,2025) -> 0 | C9: =SUMIFS('Sales Transactions Raw Data'!V:V,'Sales Transactions Raw Data'!S:S,"subscription_contract",'Sales Transactions Raw Data'!B:B,"March",'Sales Transactions Raw Data'!A:A,2025,'Sales Transactions Raw Data'!J:J,"Finished Goods") -> 0 | D9: =SUMIFS('Sales Transactions Raw Data'!V:V,'Sales Transactions Raw Data'!S:S,"subscription_contract",'Sales Transactions Raw Data'!B:B,"July",'Sales Transactions Raw Data'!A:A,2025,'Sales Transactions Raw Data'!J:J,"Finished Goods") -> 0 | E9: =SUMIFS('Sales Transactions Raw Data'!V:V,'Sales Transactions Raw Data'!S:S,"subscription_contract",'Sales Transactions Raw Data'!B:B,"August",'Sales Transactions Raw Data'!A:A,2025,'Sales Transactions Raw Data'!J:J,"Finished Goods") -> 0 | F9: =SUMIFS('Sales Transactions Raw Data'!V:V,'Sales Transactions Raw Data'!S:S,"subscription_contract",'Sales Transactions Raw Data'!B:B,"September",'Sales Transactions Raw Data'!A:A,2025,'Sales Transactions Raw Data'!J:J,"Finished Goods") -> 0 | G9: =SUMIFS('Sales Transactions Raw Data'!V:V,'Sales Transactions Raw Data'!S:S,"subscription_contract",'Sales Transactions Raw Data'!B:B,"October",'Sales Transactions Raw Data'!A:A,2025,'Sales Transactions Raw Data'!J:J,"Finished Goods") -> 0 | H9: =SUMIFS('Sales Transactions Raw Data'!V:V,'Sales Transactions Raw Data'!S:S,"subscription_contract",'Sales Transactions Raw Data'!B:B,"November",'Sales Transactions Raw Data'!A:A,2025,'Sales Transactions Raw Data'!J:J,"Finished Goods") -> 0 | I9: =SUMIFS('Sales Transactions Raw Data'!V:V,'Sales Transactions Raw Data'!S:S,"Shopify POS",'Sales Transactions Raw Data'!B:B,"January",'Sales Transactions Raw Data'!A:A,2026) -> 0 | J9: =SUMIFS('Sales Transactions Raw Data'!V:V,'Sales Transactions Raw Data'!S:S,"Shopify POS",'Sales Transactions Raw Data'!B:B,"February",'Sales Transactions Raw Data'!A:A,2026) -> 0 | K9: =SUMIFS('Sales Transactions Raw Data'!V:V,'Sales Transactions Raw Data'!S:S,"Shopify POS",'Sales Transactions Raw Data'!B:B,"March",'Sales Transactions Raw Data'!A:A,2026) -> 0 | L9: =SUM(B9:K9) -> 0
A10: Subscriptions (checkout) | B10: =SUMIFS('Sales Transactions Raw Data'!V:V,'Sales Transactions Raw Data'!S:S,"subscription_contract",'Sales Transactions Raw Data'!B:B,"March",'Sales Transactions Raw Data'!A:A,2025,'Sales Transactions Raw Data'!J:J,"Finished Goods")+SUMIFS('Sales Transactions Raw Data'!V:V,'Sales Transactions Raw Data'!S:S,"subscription_contract_checkout_one",'Sales Transactions Raw Data'!B:B,"March",'Sales Transactions Raw Data'!A:A,2025,'Sales Transactions Raw Data'!J:J,"Finished Goods") -> 0 | C10: =SUMIFS('Sales Transactions Raw Data'!V:V,'Sales Transactions Raw Data'!S:S,"subscription_contract_checkout_one",'Sales Transactions Raw Data'!B:B,"March",'Sales Transactions Raw Data'!A:A,2025,'Sales Transactions Raw Data'!J:J,"Finished Goods") -> 0 | D10: =SUMIFS('Sales Transactions Raw Data'!V:V,'Sales Transactions Raw Data'!S:S,"subscription_contract_checkout_one",'Sales Transactions Raw Data'!B:B,"July",'Sales Transactions Raw Data'!A:A,2025,'Sales Transactions Raw Data'!J:J,"Finished Goods") -> 0 | E10: =SUMIFS('Sales Transactions Raw Data'!V:V,'Sales Transactions Raw Data'!S:S,"subscription_contract_checkout_one",'Sales Transactions Raw Data'!B:B,"August",'Sales Transactions Raw Data'!A:A,2025,'Sales Transactions Raw Data'!J:J,"Finished Goods") -> 0 | F10: =SUMIFS('Sales Transactions Raw Data'!V:V,'Sales Transactions Raw Data'!S:S,"subscription_contract_checkout_one",'Sales Transactions Raw Data'!B:B,"September",'Sales Transactions Raw Data'!A:A,2025,'Sales Transactions Raw Data'!J:J,"Finished Goods") -> 0 | G10: =SUMIFS('Sales Transactions Raw Data'!V:V,'Sales Transactions Raw Data'!S:S,"subscription_contract_checkout_one",'Sales Transactions Raw Data'!B:B,"October",'Sales Transactions Raw Data'!A:A,2025,'Sales Transactions Raw Data'!J:J,"Finished Goods") -> 0 | H10: =SUMIFS('Sales Transactions Raw Data'!V:V,'Sales Transactions Raw Data'!S:S,"subscription_contract_checkout_one",'Sales Transactions Raw Data'!B:B,"November",'Sales Transactions Raw Data'!A:A,2025,'Sales Transactions Raw Data'!J:J,"Finished Goods") -> 0 | I10: =SUMIFS('Sales Transactions Raw Data'!V:V,'Sales Transactions Raw Data'!S:S,"subscription_contract",'Sales Transactions Raw Data'!B:B,"January",'Sales Transactions Raw Data'!A:A,2026,'Sales Transactions Raw Data'!J:J,"Finished Goods")+SUMIFS('Sales Transactions Raw Data'!V:V,'Sales Transactions Raw Data'!S:S,"subscription_contract_checkout_one",'Sales Transactions Raw Data'!B:B,"January",'Sales Transactions Raw Data'!A:A,2026,'Sales Transactions Raw Data'!J:J,"Finished Goods") -> 0 | J10: =SUMIFS('Sales Transactions Raw Data'!V:V,'Sales Transactions Raw Data'!S:S,"subscription_contract",'Sales Transactions Raw Data'!B:B,"February",'Sales Transactions Raw Data'!A:A,2026,'Sales Transactions Raw Data'!J:J,"Finished Goods")+SUMIFS('Sales Transactions Raw Data'!V:V,'Sales Transactions Raw Data'!S:S,"subscription_contract_checkout_one",'Sales Transactions Raw Data'!B:B,"February",'Sales Transactions Raw Data'!A:A,2026,'Sales Transactions Raw Data'!J:J,"Finished Goods") -> 0 | K10: =SUMIFS('Sales Transactions Raw Data'!V:V,'Sales Transactions Raw Data'!S:S,"subscription_contract",'Sales Transactions Raw Data'!B:B,"March",'Sales Transactions Raw Data'!A:A,2026,'Sales Transactions Raw Data'!J:J,"Finished Goods")+SUMIFS('Sales Transactions Raw Data'!V:V,'Sales Transactions Raw Data'!S:S,"subscription_contract_checkout_one",'Sales Transactions Raw Data'!B:B,"March",'Sales Transactions Raw Data'!A:A,2026,'Sales Transactions Raw Data'!J:J,"Finished Goods") -> 0 | L10: =SUM(B10:K10) -> 0
A11: Wholesale / Distrib (296827748353) | B11: =SUMIFS('Sales Transactions Raw Data'!V:V,'Sales Transactions Raw Data'!S:S,"Shopify admin",'Sales Transactions Raw Data'!B:B,"March",'Sales Transactions Raw Data'!A:A,2025,'Sales Transactions Raw Data'!J:J,"Finished Goods") -> 0 | C11: =SUMIFS('Sales Transactions Raw Data'!V:V,'Sales Transactions Raw Data'!S:S,"296827748353",'Sales Transactions Raw Data'!B:B,"March",'Sales Transactions Raw Data'!A:A,2025,'Sales Transactions Raw Data'!J:J,"Finished Goods") -> 0 | D11: =SUMIFS('Sales Transactions Raw Data'!V:V,'Sales Transactions Raw Data'!S:S,"296827748353",'Sales Transactions Raw Data'!B:B,"July",'Sales Transactions Raw Data'!A:A,2025,'Sales Transactions Raw Data'!J:J,"Finished Goods") -> 0 | E11: =SUMIFS('Sales Transactions Raw Data'!V:V,'Sales Transactions Raw Data'!S:S,"296827748353",'Sales Transactions Raw Data'!B:B,"August",'Sales Transactions Raw Data'!A:A,2025,'Sales Transactions Raw Data'!J:J,"Finished Goods") -> 0 | F11: =SUMIFS('Sales Transactions Raw Data'!V:V,'Sales Transactions Raw Data'!S:S,"296827748353",'Sales Transactions Raw Data'!B:B,"September",'Sales Transactions Raw Data'!A:A,2025,'Sales Transactions Raw Data'!J:J,"Finished Goods") -> 0 | G11: =SUMIFS('Sales Transactions Raw Data'!V:V,'Sales Transactions Raw Data'!S:S,"296827748353",'Sales Transactions Raw Data'!B:B,"October",'Sales Transactions Raw Data'!A:A,2025,'Sales Transactions Raw Data'!J:J,"Finished Goods") -> 0 | H11: =SUMIFS('Sales Transactions Raw Data'!V:V,'Sales Transactions Raw Data'!S:S,"296827748353",'Sales Transactions Raw Data'!B:B,"November",'Sales Transactions Raw Data'!A:A,2025,'Sales Transactions Raw Data'!J:J,"Finished Goods") -> 0 | I11: =SUMIFS('Sales Transactions Raw Data'!V:V,'Sales Transactions Raw Data'!S:S,"Shopify admin",'Sales Transactions Raw Data'!B:B,"January",'Sales Transactions Raw Data'!A:A,2026,'Sales Transactions Raw Data'!J:J,"Finished Goods") -> 0 | J11: =SUMIFS('Sales Transactions Raw Data'!V:V,'Sales Transactions Raw Data'!S:S,"Shopify admin",'Sales Transactions Raw Data'!B:B,"February",'Sales Transactions Raw Data'!A:A,2026,'Sales Transactions Raw Data'!J:J,"Finished Goods") -> 0 | K11: =SUMIFS('Sales Transactions Raw Data'!V:V,'Sales Transactions Raw Data'!S:S,"Shopify admin",'Sales Transactions Raw Data'!B:B,"March",'Sales Transactions Raw Data'!A:A,2026,'Sales Transactions Raw Data'!J:J,"Finished Goods") -> 0 | L11: =SUM(B11:K11) -> 0
A12: Faire (Wholesale Mkt) | C12: =SUMIFS('Sales Transactions Raw Data'!V:V,'Sales Transactions Raw Data'!S:S,"faire",'Sales Transactions Raw Data'!B:B,"March",'Sales Transactions Raw Data'!A:A,2025,'Sales Transactions Raw Data'!J:J,"Finished Goods") -> 0 | D12: =SUMIFS('Sales Transactions Raw Data'!V:V,'Sales Transactions Raw Data'!S:S,"faire",'Sales Transactions Raw Data'!B:B,"July",'Sales Transactions Raw Data'!A:A,2025,'Sales Transactions Raw Data'!J:J,"Finished Goods") -> 0 | E12: =SUMIFS('Sales Transactions Raw Data'!V:V,'Sales Transactions Raw Data'!S:S,"faire",'Sales Transactions Raw Data'!B:B,"August",'Sales Transactions Raw Data'!A:A,2025,'Sales Transactions Raw Data'!J:J,"Finished Goods") -> 0 | F12: =SUMIFS('Sales Transactions Raw Data'!V:V,'Sales Transactions Raw Data'!S:S,"faire",'Sales Transactions Raw Data'!B:B,"September",'Sales Transactions Raw Data'!A:A,2025,'Sales Transactions Raw Data'!J:J,"Finished Goods") -> 0 | G12: =SUMIFS('Sales Transactions Raw Data'!V:V,'Sales Transactions Raw Data'!S:S,"faire",'Sales Transactions Raw Data'!B:B,"October",'Sales Transactions Raw Data'!A:A,2025,'Sales Transactions Raw Data'!J:J,"Finished Goods") -> 0 | H12: =SUMIFS('Sales Transactions Raw Data'!V:V,'Sales Transactions Raw Data'!S:S,"faire",'Sales Transactions Raw Data'!B:B,"November",'Sales Transactions Raw Data'!A:A,2025,'Sales Transactions Raw Data'!J:J,"Finished Goods") -> 0
A13: TikTok Shop | B13: =SUM(B4:B11) -> 0 | C13: =SUMIFS('Sales Transactions Raw Data'!V:V,'Sales Transactions Raw Data'!S:S,"tiktok",'Sales Transactions Raw Data'!B:B,"March",'Sales Transactions Raw Data'!A:A,2025,'Sales Transactions Raw Data'!J:J,"Finished Goods") -> 0 | D13: =SUMIFS('Sales Transactions Raw Data'!V:V,'Sales Transactions Raw Data'!S:S,"tiktok",'Sales Transactions Raw Data'!B:B,"July",'Sales Transactions Raw Data'!A:A,2025,'Sales Transactions Raw Data'!J:J,"Finished Goods") -> 0 | E13: =SUMIFS('Sales Transactions Raw Data'!V:V,'Sales Transactions Raw Data'!S:S,"tiktok",'Sales Transactions Raw Data'!B:B,"August",'Sales Transactions Raw Data'!A:A,2025,'Sales Transactions Raw Data'!J:J,"Finished Goods") -> 0 | F13: =SUMIFS('Sales Transactions Raw Data'!V:V,'Sales Transactions Raw Data'!S:S,"tiktok",'Sales Transactions Raw Data'!B:B,"September",'Sales Transactions Raw Data'!A:A,2025,'Sales Transactions Raw Data'!J:J,"Finished Goods") -> 0 | G13: =SUMIFS('Sales Transactions Raw Data'!V:V,'Sales Transactions Raw Data'!S:S,"tiktok",'Sales Transactions Raw Data'!B:B,"October",'Sales Transactions Raw Data'!A:A,2025,'Sales Transactions Raw Data'!J:J,"Finished Goods") -> 0 | H13: =SUMIFS('Sales Transactions Raw Data'!V:V,'Sales Transactions Raw Data'!S:S,"tiktok",'Sales Transactions Raw Data'!B:B,"November",'Sales Transactions Raw Data'!A:A,2025,'Sales Transactions Raw Data'!J:J,"Finished Goods") -> 0 | I13: =SUM(I4:I11) -> 0 | J13: =SUM(J4:J11) -> 0 | K13: =SUM(K4:K11) -> 0 | L13: =SUM(L4:L11) -> 0
A14: Channel 4901177 | C14: =SUMIFS('Sales Transactions Raw Data'!V:V,'Sales Transactions Raw Data'!S:S,"4901177",'Sales Transactions Raw Data'!B:B,"March",'Sales Transactions Raw Data'!A:A,2025,'Sales Transactions Raw Data'!J:J,"Finished Goods") -> 0 | D14: =SUMIFS('Sales Transactions Raw Data'!V:V,'Sales Transactions Raw Data'!S:S,"4901177",'Sales Transactions Raw Data'!B:B,"July",'Sales Transactions Raw Data'!A:A,2025,'Sales Transactions Raw Data'!J:J,"Finished Goods") -> 0 | E14: =SUMIFS('Sales Transactions Raw Data'!V:V,'Sales Transactions Raw Data'!S:S,"4901177",'Sales Transactions Raw Data'!B:B,"August",'Sales Transactions Raw Data'!A:A,2025,'Sales Transactions Raw Data'!J:J,"Finished Goods") -> 0 | F14: =SUMIFS('Sales Transactions Raw Data'!V:V,'Sales Transactions Raw Data'!S:S,"4901177",'Sales Transactions Raw Data'!B:B,"September",'Sales Transactions Raw Data'!A:A,2025,'Sales Transactions Raw Data'!J:J,"Finished Goods") -> 0 | G14: =SUMIFS('Sales Transactions Raw Data'!V:V,'Sales Transactions Raw Data'!S:S,"4901177",'Sales Transactions Raw Data'!B:B,"October",'Sales Transactions Raw Data'!A:A,2025,'Sales Transactions Raw Data'!J:J,"Finished Goods") -> 0 | H14: =SUMIFS('Sales Transactions Raw Data'!V:V,'Sales Transactions Raw Data'!S:S,"4901177",'Sales Transactions Raw Data'!B:B,"November",'Sales Transactions Raw Data'!A:A,2025,'Sales Transactions Raw Data'!J:J,"Finished Goods") -> 0
A15: Channel 3890849 | B15: - | C15: =SUMIFS('Sales Transactions Raw Data'!V:V,'Sales Transactions Raw Data'!S:S,"3890849",'Sales Transactions Raw Data'!B:B,"March",'Sales Transactions Raw Data'!A:A,2025,'Sales Transactions Raw Data'!J:J,"Finished Goods") -> 0 | D15: =SUMIFS('Sales Transactions Raw Data'!V:V,'Sales Transactions Raw Data'!S:S,"3890849",'Sales Transactions Raw Data'!B:B,"July",'Sales Transactions Raw Data'!A:A,2025,'Sales Transactions Raw Data'!J:J,"Finished Goods") -> 0 | E15: =SUMIFS('Sales Transactions Raw Data'!V:V,'Sales Transactions Raw Data'!S:S,"3890849",'Sales Transactions Raw Data'!B:B,"August",'Sales Transactions Raw Data'!A:A,2025,'Sales Transactions Raw Data'!J:J,"Finished Goods") -> 0 | F15: =SUMIFS('Sales Transactions Raw Data'!V:V,'Sales Transactions Raw Data'!S:S,"3890849",'Sales Transactions Raw Data'!B:B,"September",'Sales Transactions Raw Data'!A:A,2025,'Sales Transactions Raw Data'!J:J,"Finished Goods") -> 0 | G15: =SUMIFS('Sales Transactions Raw Data'!V:V,'Sales Transactions Raw Data'!S:S,"3890849",'Sales Transactions Raw Data'!B:B,"October",'Sales Transactions Raw Data'!A:A,2025,'Sales Transactions Raw Data'!J:J,"Finished Goods") -> 0 | H15: =SUMIFS('Sales Transactions Raw Data'!V:V,'Sales Transactions Raw Data'!S:S,"3890849",'Sales Transactions Raw Data'!B:B,"November",'Sales Transactions Raw Data'!A:A,2025,'Sales Transactions Raw Data'!J:J,"Finished Goods") -> 0 | I15: =IF(H13=0,"-",I13/H13-1) -> - | J15: =IF(I13=0,"-",J13/I13-1) -> - | K15: =IF(J13=0,"-",K13/J13-1) -> -
A16: Channel 2329312 | C16: =SUMIFS('Sales Transactions Raw Data'!V:V,'Sales Transactions Raw Data'!S:S,"2329312",'Sales Transactions Raw Data'!B:B,"March",'Sales Transactions Raw Data'!A:A,2025,'Sales Transactions Raw Data'!J:J,"Finished Goods") -> 0 | D16: =SUMIFS('Sales Transactions Raw Data'!V:V,'Sales Transactions Raw Data'!S:S,"2329312",'Sales Transactions Raw Data'!B:B,"July",'Sales Transactions Raw Data'!A:A,2025,'Sales Transactions Raw Data'!J:J,"Finished Goods") -> 0 | E16: =SUMIFS('Sales Transactions Raw Data'!V:V,'Sales Transactions Raw Data'!S:S,"2329312",'Sales Transactions Raw Data'!B:B,"August",'Sales Transactions Raw Data'!A:A,2025,'Sales Transactions Raw Data'!J:J,"Finished Goods") -> 0 | F16: =SUMIFS('Sales Transactions Raw Data'!V:V,'Sales Transactions Raw Data'!S:S,"2329312",'Sales Transactions Raw Data'!B:B,"September",'Sales Transactions Raw Data'!A:A,2025,'Sales Transactions Raw Data'!J:J,"Finished Goods") -> 0 | G16: =SUMIFS('Sales Transactions Raw Data'!V:V,'Sales Transactions Raw Data'!S:S,"2329312",'Sales Transactions Raw Data'!B:B,"October",'Sales Transactions Raw Data'!A:A,2025,'Sales Transactions Raw Data'!J:J,"Finished Goods") -> 0 | H16: =SUMIFS('Sales Transactions Raw Data'!V:V,'Sales Transactions Raw Data'!S:S,"2329312",'Sales Transactions Raw Data'!B:B,"November",'Sales Transactions Raw Data'!A:A,2025,'Sales Transactions Raw Data'!J:J,"Finished Goods") -> 0
A17: TOTAL REVENUE | B17: =SUMIFS('Sales Transactions Raw Data'!W:W,'Sales Transactions Raw Data'!B:B,"March",'Sales Transactions Raw Data'!A:A,2025,'Sales Transactions Raw Data'!J:J,"Finished Goods") -> 0 | C17: =SUM(C4:C16) -> 0 | D17: =SUM(D4:D16) -> 0 | E17: =SUM(E4:E16) -> 0 | F17: =SUM(F4:F16) -> 0 | G17: =SUM(G4:G16) -> 0 | H17: =SUM(H4:H16) -> 0 | I17: =SUMIFS('Sales Transactions Raw Data'!W:W,'Sales Transactions Raw Data'!B:B,"January",'Sales Transactions Raw Data'!A:A,2026,'Sales Transactions Raw Data'!J:J,"Finished Goods") -> 0 | J17: =SUMIFS('Sales Transactions Raw Data'!W:W,'Sales Transactions Raw Data'!B:B,"February",'Sales Transactions Raw Data'!A:A,2026,'Sales Transactions Raw Data'!J:J,"Finished Goods") -> 0 | K17: =SUMIFS('Sales Transactions Raw Data'!W:W,'Sales Transactions Raw Data'!B:B,"March",'Sales Transactions Raw Data'!A:A,2026,'Sales Transactions Raw Data'!J:J,"Finished Goods") -> 0 | L17: =SUM(B17:K17) -> 0
A18: GROSS PROFIT | B18: =B13-B17 -> 0 | C18: =C13-C17 -> 0 | D18: =D13-D17 -> 0 | E18: =E13-E17 -> 0 | F18: =F13-F17 -> 0 | G18: =G13-G17 -> 0 | H18: =H13-H17 -> 0 | I18: =I13-I17 -> 0 | ... L18: =L13-L17 -> 0
A19: COGS (All Finished Goods) | B19: =IF(B13=0,"-",B18/B13) -> - | C19: =SUMIFS('Sales Transactions Raw Data'!W:W,'Sales Transactions Raw Data'!B:B,"March",'Sales Transactions Raw Data'!A:A,2025,'Sales Transactions Raw Data'!J:J,"Finished Goods") -> 0 | D19: =SUMIFS('Sales Transactions Raw Data'!W:W,'Sales Transactions Raw Data'!B:B,"July",'Sales Transactions Raw Data'!A:A,2025,'Sales Transactions Raw Data'!J:J,"Finished Goods") -> 0 | E19: =SUMIFS('Sales Transactions Raw Data'!W:W,'Sales Transactions Raw Data'!B:B,"August",'Sales Transactions Raw Data'!A:A,2025,'Sales Transactions Raw Data'!J:J,"Finished Goods") -> 0 | F19: =SUMIFS('Sales Transactions Raw Data'!W:W,'Sales Transactions Raw Data'!B:B,"September",'Sales Transactions Raw Data'!A:A,2025,'Sales Transactions Raw Data'!J:J,"Finished Goods") -> 0 | G19: =SUMIFS('Sales Transactions Raw Data'!W:W,'Sales Transactions Raw Data'!B:B,"October",'Sales Transactions Raw Data'!A:A,2025,'Sales Transactions Raw Data'!J:J,"Finished Goods") -> 0 | H19: =SUMIFS('Sales Transactions Raw Data'!W:W,'Sales Transactions Raw Data'!B:B,"November",'Sales Transactions Raw Data'!A:A,2025,'Sales Transactions Raw Data'!J:J,"Finished Goods") -> 0 | I19: =IF(I13=0,"-",I18/I13) -> - | J19: =IF(J13=0,"-",J18/J13) -> - | K19: =IF(K13=0,"-",K18/K13) -> - | L19: =IF(L13=0,"-",L18/L13) -> -
A20: Gross Profit | C20: =C17-C19 -> 0 | D20: =D17-D19 -> 0 | E20: =E17-E19 -> 0 | F20: =F17-F19 -> 0 | G20: =G17-G19 -> 0 | H20: =H17-H19 -> 0
A21: Gross Margin % | C21: =IF(C17=0,"-",C20/C17) -> - | D21: =IF(D17=0,"-",D20/D17) -> - | E21: =IF(E17=0,"-",E20/E17) -> - | F21: =IF(F17=0,"-",F20/F17) -> - | G21: =IF(G17=0,"-",G20/G17) -> - | H21: =IF(H17=0,"-",H20/H17) -> -
A22: MoM Revenue Growth | C22: — | D22: =IF(C17=0,"-",D17/C17-1) -> - | E22: =IF(D17=0,"-",E17/D17-1) -> - | F22: =IF(E17=0,"-",F17/E17-1) -> - | G22: =IF(F17=0,"-",G17/F17-1) -> - | H22: =IF(G17=0,"-",H17/G17-1) -> -

Sheet Product Margin Analysis
A1: Product Margin Analysis — by Product Attributes
A2: Filtered to Finished Goods only (excludes Service items like Shipping, Discounts)
A4: BY PRODUCT (SKU) | B4: Units Sold | C4: Revenue | D4: COGS | E4: Gross Profit | F4: GM% | G4: Avg Sell Price | H4: Avg COGS/Unit
A5: 16oz Variety 12pk | B5: =SUMIFS('Sales Transactions Raw Data'!T:T,'Sales Transactions Raw Data'!G:G,"Ola-Mate-VP1-16oz-12pk",'Sales Transactions Raw Data'!J:J,"Finished Goods") -> 0 | C5: =SUMIFS('Sales Transactions Raw Data'!V:V,'Sales Transactions Raw Data'!G:G,"Ola-Mate-VP1-16oz-12pk",'Sales Transactions Raw Data'!J:J,"Finished Goods") -> 0 | D5: =SUMIFS('Sales Transactions Raw Data'!W:W,'Sales Transactions Raw Data'!G:G,"Ola-Mate-VP1-16oz-12pk",'Sales Transactions Raw Data'!J:J,"Finished Goods") -> 0 | E5: =C5-D5 -> 0 | F5: =IF(C5=0,"-",E5/C5) -> - | G5: =IF(B5=0,"-",C5/B5) -> - | H5: =IF(B5=0,"-",D5/B5) -> -
A6: 16oz Berry Coconut 12pk | B6: =SUMIFS('Sales Transactions Raw Data'!T:T,'Sales Transactions Raw Data'!G:G,"Ola-Mate-BC-16oz-12PK",'Sales Transactions Raw Data'!J:J,"Finished Goods") -> 0 | C6: =SUMIFS('Sales Transactions Raw Data'!V:V,'Sales Transactions Raw Data'!G:G,"Ola-Mate-BC-16oz-12PK",'Sales Transactions Raw Data'!J:J,"Finished Goods") -> 0 | D6: =SUMIFS('Sales Transactions Raw Data'!W:W,'Sales Transactions Raw Data'!G:G,"Ola-Mate-BC-16oz-12PK",'Sales Transactions Raw Data'!J:J,"Finished Goods") -> 0 | E6: =C6-D6 -> 0 | F6: =IF(C6=0,"-",E6/C6) -> - | G6: =IF(B6=0,"-",C6/B6) -> - | H6: =IF(B6=0,"-",D6/B6) -> -
A7: 16oz Raspberry 12pk | B7: =SUMIFS('Sales Transactions Raw Data'!T:T,'Sales Transactions Raw Data'!G:G,"Ola-Mate-R-16oz-12pk",'Sales Transactions Raw Data'!J:J,"Finished Goods") -> 0 | C7: =SUMIFS('Sales Transactions Raw Data'!V:V,'Sales Transactions Raw Data'!G:G,"Ola-Mate-R-16oz-12pk",'Sales Transactions Raw Data'!J:J,"Finished Goods") -> 0 | D7: =SUMIFS('Sales Transactions Raw Data'!W:W,'Sales Transactions Raw Data'!G:G,"Ola-Mate-R-16oz-12pk",'Sales Transactions Raw Data'!J:J,"Finished Goods") -> 0 | E7: =C7-D7 -> 0 | F7: =IF(C7=0,"-",E7/C7) -> - | G7: =IF(B7=0,"-",C7/B7) -> - | H7: =IF(B7=0,"-",D7/B7) -> -
A8: 16oz Grapefruit Ginger 12pk | B8: =SUMIFS('Sales Transactions Raw Data'!T:T,'Sales Transactions Raw Data'!G:G,"Ola-Mate-GG-16oz-12pk",'Sales Transactions Raw Data'!J:J,"Finished Goods") -> 0 | C8: =SUMIFS('Sales Transactions Raw Data'!V:V,'Sales Transactions Raw Data'!G:G,"Ola-Mate-GG-16oz-12pk",'Sales Transactions Raw Data'!J:J,"Finished Goods") -> 0 | D8: =SUMIFS('Sales Transactions Raw Data'!W:W,'Sales Transactions Raw Data'!G:G,"Ola-Mate-GG-16oz-12pk",'Sales Transactions Raw Data'!J:J,"Finished Goods") -> 0 | E8: =C8-D8 -> 0 | F8: =IF(C8=0,"-",E8/C8) -> - | G8: =IF(B8=0,"-",C8/B8) -> - | H8: =IF(B8=0,"-",D8/B8) -> -
A9: 16oz Starter 4pk | B9: =SUMIFS('Sales Transactions Raw Data'!T:T,'Sales Transactions Raw Data'!G:G,"Ola-Mate-SP1-16oz-4pk",'Sales Transactions Raw Data'!J:J,"Finished Goods") -> 0 | C9: =SUMIFS('Sales Transactions Raw Data'!V:V,'Sales Transactions Raw Data'!G:G,"Ola-Mate-SP1-16oz-4pk",'Sales Transactions Raw Data'!J:J,"Finished Goods") -> 0 | D9: =SUMIFS('Sales Transactions Raw Data'!W:W,'Sales Transactions Raw Data'!G:G,"Ola-Mate-SP1-16oz-4pk",'Sales Transactions Raw Data'!J:J,"Finished Goods") -> 0 | E9: =C9-D9 -> 0 | F9: =IF(C9=0,"-",E9/C9) -> - | G9: =IF(B9=0,"-",C9/B9) -> - | H9: =IF(B9=0,"-",D9/B9) -> -
A10: 1can (BC/GG/R) - loose | B10: =SUMIFS('Sales Transactions Raw Data'!T:T,'Sales Transactions Raw Data'!G:G,"Ola-Mate-BC-16oz-1can",'Sales Transactions Raw Data'!J:J,"Finished Goods")+SUMIFS('Sales Transactions Raw Data'!T:T,'Sales Transactions Raw Data'!G:G,"Ola-Mate-GG-16oz-1can",'Sales Transactions Raw Data'!J:J,"Finished Goods")+SUMIFS('Sales Transactions Raw Data'!T:T,'Sales Transactions Raw Data'!G:G,"Ola-Mate-R-16oz-1can",'Sales Transactions Raw Data'!J:J,"Finished Goods") -> 0 | C10: =SUMIFS('Sales Transactions Raw Data'!V:V,'Sales Transactions Raw Data'!G:G,"Ola-Mate-BC-16oz-1can",'Sales Transactions Raw Data'!J:J,"Finished Goods")+SUMIFS('Sales Transactions Raw Data'!V:V,'Sales Transactions Raw Data'!G:G,"Ola-Mate-GG-16oz-1can",'Sales Transactions Raw Data'!J:J,"Finished Goods")+SUMIFS('Sales Transactions Raw Data'!V:V,'Sales Transactions Raw Data'!G:G,"Ola-Mate-R-16oz-1can",'Sales Transactions Raw Data'!J:J,"Finished Goods") -> 0 | D10: =SUMIFS('Sales Transactions Raw Data'!W:W,'Sales Transactions Raw Data'!G:G,"Ola-Mate-BC-16oz-1can",'Sales Transactions Raw Data'!J:J,"Finished Goods")+SUMIFS('Sales Transactions Raw Data'!W:W,'Sales Transactions Raw Data'!G:G,"Ola-Mate-GG-16oz-1can",'Sales Transactions Raw Data'!J:J,"Finished Goods")+SUMIFS('Sales Transactions Raw Data'!W:W,'Sales Transactions Raw Data'!G:G,"Ola-Mate-R-16oz-1can",'Sales Transactions Raw Data'!J:J,"Finished Goods") -> 0 | E10: =C10-D10 -> 0 | F10: =IF(C10=0,"-",E10/C10) -> - | G10: =IF(B10=0,"-",C10/B10) -> - | H10: =IF(B10=0,"-",D10/B10) -> -
A11: Powder Blends (new) | B11: =SUMIFS('Sales Transactions Raw Data'!T:T,'Sales Transactions Raw Data'!G:G,"Ola-Mate-POW-*",'Sales Transactions Raw Data'!J:J,"Finished Goods") -> 0 | C11: =SUMIFS('Sales Transactions Raw Data'!V:V,'Sales Transactions Raw Data'!G:G,"Ola-Mate-POW-*",'Sales Transactions Raw Data'!J:J,"Finished Goods") -> 0 | D11: =SUMIFS('Sales Transactions Raw Data'!W:W,'Sales Transactions Raw Data'!G:G,"Ola-Mate-POW-*",'Sales Transactions Raw Data'!J:J,"Finished Goods") -> 0 | E11: =C11-D11 -> 0 | F11: =IF(C11=0,"-",E11/C11) -> - | G11: =IF(B11=0,"-",C11/B11) -> - | H11: =IF(B11=0,"-",D11/B11) -> -
A12: TOTAL PRODUCTS | B12: =SUM(B5:B11) -> 0 | C12: =SUM(C5:C11) -> 0 | D12: =SUM(D5:D11) -> 0 | E12: =C12-D12 -> 0 | F12: =IF(C12=0,"-",E12/C12) -> - | G12: =IF(B12=0,"-",C12/B12) -> - | H12: =IF(B12=0,"-",D12/B12) -> -
A14: BY CATEGORY | B14: Units Sold | C14: Revenue | D14: COGS | E14: Gross Profit | F14: GM% | G14: Revenue % | H14: Avg Sell Price
A15: Finished Goods | B15: =SUMIFS('Sales Transactions Raw Data'!T:T,'Sales Transactions Raw Data'!J:J,"Finished Goods") -> 0 | C15: =SUMIFS('Sales Transactions Raw Data'!V:V,'Sales Transactions Raw Data'!J:J,"Finished Goods") -> 0 | D15: =SUMIFS('Sales Transactions Raw Data'!W:W,'Sales Transactions Raw Data'!J:J,"Finished Goods") -> 0 | E15: =C15-D15 -> 0 | F15: =IF(C15=0,"-",E15/C15) -> - | G15: =IF(C$17=0,"-",C15/C$17) -> - | H15: =IF(B15=0,"-",C15/B15) -> -
A16: Service (Shipping/Discounts/POS) | B16: =SUMIFS('Sales Transactions Raw Data'!T:T,'Sales Transactions Raw Data'!J:J,"Service") -> 0 | C16: =SUMIFS('Sales Transactions Raw Data'!V:V,'Sales Transactions Raw Data'!J:J,"Service") -> 0 | D16: =SUMIFS('Sales Transactions Raw Data'!W:W,'Sales Transactions Raw Data'!J:J,"Service") -> 0 | E16: =C16-D16 -> 0 | F16: =IF(C16=0,"-",E16/C16) -> - | G16: =IF(C$17=0,"-",C16/C$17) -> - | H16: =IF(B16=0,"-",C16/B16) -> -
A17: GRAND TOTAL | B17: =B15+B16 -> 0 | C17: =C15+C16 -> 0 | D17: =D15+D16 -> 0 | E17: =C17-D17 -> 0 | F17: =IF(C17=0,"-",E17/C17) -> - | G17: 1

Sheet COGS & Profitability by Channel
A1: COGS & Profitability by Product × Sales Channel
A2: Finished Goods only | All time periods combined
A4: REVENUE BY CHANNEL × PRODUCT | B4: Amazon | C4: Amazon Retail | D4: Shopify Web | E4: Shopify POS | F4: Shopify Admin | G4: Subs (contract) | H4: Subs (checkout) | I4: Wholesale 296... | J4: Faire | K4: TikTok | L4: Ch 4901177 | M4: Ch 3890849 | N4: Total
A5: 16oz Variety 12pk | B5: =SUMIFS('Sales Transactions Raw Data'!V:V,'Sales Transactions Raw Data'!G:G,"Ola-Mate-VP1-16oz-12pk",'Sales Transactions Raw Data'!S:S,"amazon",'Sales Transactions Raw Data'!J:J,"Finished Goods") -> 0 | C5: =SUMIFS('Sales Transactions Raw Data'!V:V,'Sales Transactions Raw Data'!G:G,"Ola-Mate-VP1-16oz-12pk",'Sales Transactions Raw Data'!S:S,"amazon-us",'Sales Transactions Raw Data'!J:J,"Finished Goods") -> 0 | D5: =SUMIFS('Sales Transactions Raw Data'!V:V,'Sales Transactions Raw Data'!G:G,"Ola-Mate-VP1-16oz-12pk",'Sales Transactions Raw Data'!S:S,"Shopify web",'Sales Transactions Raw Data'!J:J,"Finished Goods") -> 0 | E5: =SUMIFS('Sales Transactions Raw Data'!V:V,'Sales Transactions Raw Data'!G:G,"Ola-Mate-VP1-16oz-12pk",'Sales Transactions Raw Data'!S:S,"Shopify POS",'Sales Transactions Raw Data'!J:J,"Finished Goods") -> 0 | F5: =SUMIFS('Sales Transactions Raw Data'!V:V,'Sales Transactions Raw Data'!G:G,"Ola-Mate-VP1-16oz-12pk",'Sales Transactions Raw Data'!S:S,"Shopify admin",'Sales Transactions Raw Data'!J:J,"Finished Goods") -> 0 | G5: =SUMIFS('Sales Transactions Raw Data'!V:V,'Sales Transactions Raw Data'!G:G,"Ola-Mate-VP1-16oz-12pk",'Sales Transactions Raw Data'!S:S,"subscription_contract",'Sales Transactions Raw Data'!J:J,"Finished Goods") -> 0 | H5: =SUMIFS('Sales Transactions Raw Data'!V:V,'Sales Transactions Raw Data'!G:G,"Ola-Mate-VP1-16oz-12pk",'Sales Transactions Raw Data'!S:S,"subscription_contract_checkout_one",'Sales Transactions Raw Data'!J:J,"Finished Goods") -> 0 | I5: =SUMIFS('Sales Transactions Raw Data'!V:V,'Sales Transactions Raw Data'!G:G,"Ola-Mate-VP1-16oz-12pk",'Sales Transactions Raw Data'!S:S,"296827748353",'Sales Transactions Raw Data'!J:J,"Finished Goods") -> 0 | J5: =SUMIFS('Sales Transactions Raw Data'!V:V,'Sales Transactions Raw Data'!G:G,"Ola-Mate-VP1-16oz-12pk",'Sales Transactions Raw Data'!S:S,"faire",'Sales Transactions Raw Data'!J:J,"Finished Goods") -> 0 | K5: =SUMIFS('Sales Transactions Raw Data'!V:V,'Sales Transactions Raw Data'!G:G,"Ola-Mate-VP1-16oz-12pk",'Sales Transactions Raw Data'!S:S,"tiktok",'Sales Transactions Raw Data'!J:J,"Finished Goods") -> 0 | L5: =SUMIFS('Sales Transactions Raw Data'!V:V,'Sales Transactions Raw Data'!G:G,"Ola-Mate-VP1-16oz-12pk",'Sales Transactions Raw Data'!S:S,"4901177",'Sales Transactions Raw Data'!J:J,"Finished Goods") -> 0 | M5: =SUMIFS('Sales Transactions Raw Data'!V:V,'Sales Transactions Raw Data'!G:G,"Ola-Mate-VP1-16oz-12pk",'Sales Transactions Raw Data'!S:S,"3890849",'Sales Transactions Raw Data'!J:J,"Finished Goods") -> 0 | N5: =SUM(B5:M5) -> 0
A6: 16oz Berry Coconut 12pk | B6: =SUMIFS('Sales Transactions Raw Data'!V:V,'Sales Transactions Raw Data'!G:G,"Ola-Mate-BC-16oz-12PK",'Sales Transactions Raw Data'!S:S,"amazon",'Sales Transactions Raw Data'!J:J,"Finished Goods") -> 0 | C6: =SUMIFS('Sales Transactions Raw Data'!V:V,'Sales Transactions Raw Data'!G:G,"Ola-Mate-BC-16oz-12PK",'Sales Transactions Raw Data'!S:S,"amazon-us",'Sales Transactions Raw Data'!J:J,"Finished Goods") -> 0 | D6: =SUMIFS('Sales Transactions Raw Data'!V:V,'Sales Transactions Raw Data'!G:G,"Ola-Mate-BC-16oz-12PK",'Sales Transactions Raw Data'!S:S,"Shopify web",'Sales Transactions Raw Data'!J:J,"Finished Goods") -> 0 | E6: =SUMIFS('Sales Transactions Raw Data'!V:V,'Sales Transactions Raw Data'!G:G,"Ola-Mate-BC-16oz-12PK",'Sales Transactions Raw Data'!S:S,"Shopify POS",'Sales Transactions Raw Data'!J:J,"Finished Goods") -> 0 | F6: =SUMIFS('Sales Transactions Raw Data'!V:V,'Sales Transactions Raw Data'!G:G,"Ola-Mate-BC-16oz-12PK",'Sales Transactions Raw Data'!S:S,"Shopify admin",'Sales Transactions Raw Data'!J:J,"Finished Goods") -> 0 | G6: =SUMIFS('Sales Transactions Raw Data'!V:V,'Sales Transactions Raw Data'!G:G,"Ola-Mate-BC-16oz-12PK",'Sales Transactions Raw Data'!S:S,"subscription_contract",'Sales Transactions Raw Data'!J:J,"Finished Goods") -> 0 | H6: =SUMIFS('Sales Transactions Raw Data'!V:V,'Sales Transactions Raw Data'!G:G,"Ola-Mate-BC-16oz-12PK",'Sales Transactions Raw Data'!S:S,"subscription_contract_checkout_one",'Sales Transactions Raw Data'!J:J,"Finished Goods") -> 0 | I6: =SUMIFS('Sales Transactions Raw Data'!V:V,'Sales Transactions Raw Data'!G:G,"Ola-Mate-BC-16oz-12PK",'Sales Transactions Raw Data'!S:S,"296827748353",'Sales Transactions Raw Data'!J:J,"Finished Goods") -> 0 | J6: =SUMIFS('Sales Transactions Raw Data'!V:V,'Sales Transactions Raw Data'!G:G,"Ola-Mate-BC-16oz-12PK",'Sales Transactions Raw Data'!S:S,"faire",'Sales Transactions Raw Data'!J:J,"Finished Goods") -> 0 | K6: =SUMIFS('Sales Transactions Raw Data'!V:V,'Sales Transactions Raw Data'!G:G,"Ola-Mate-BC-16oz-12PK",'Sales Transactions Raw Data'!S:S,"tiktok",'Sales Transactions Raw Data'!J:J,"Finished Goods") -> 0 | L6: =SUMIFS('Sales Transactions Raw Data'!V:V,'Sales Transactions Raw Data'!G:G,"Ola-Mate-BC-16oz-12PK",'Sales Transactions Raw Data'!S:S,"4901177",'Sales Transactions Raw Data'!J:J,"Finished Goods") -> 0 | M6: =SUMIFS('Sales Transactions Raw Data'!V:V,'Sales Transactions Raw Data'!G:G,"Ola-Mate-BC-16oz-12PK",'Sales Transactions Raw Data'!S:S,"3890849",'Sales Transactions Raw Data'!J:J,"Finished Goods") -> 0 | N6: =SUM(B6:M6) -> 0
A7: 16oz Raspberry 12pk | B7: =SUMIFS('Sales Transactions Raw Data'!V:V,'Sales Transactions Raw Data'!G:G,"Ola-Mate-R-16oz-12pk",'Sales Transactions Raw Data'!S:S,"amazon",'Sales Transactions Raw Data'!J:J,"Finished Goods") -> 0 | C7: =SUMIFS('Sales Transactions Raw Data'!V:V,'Sales Transactions Raw Data'!G:G,"Ola-Mate-R-16oz-12pk",'Sales Transactions Raw Data'!S:S,"amazon-us",'Sales Transactions Raw Data'!J:J,"Finished Goods") -> 0 | D7: =SUMIFS('Sales Transactions Raw Data'!V:V,'Sales Transactions Raw Data'!G:G,"Ola-Mate-R-16oz-12pk",'Sales Transactions Raw Data'!S:S,"Shopify web",'Sales Transactions Raw Data'!J:J,"Finished Goods") -> 0 | E7: =SUMIFS('Sales Transactions Raw Data'!V:V,'Sales Transactions Raw Data'!G:G,"Ola-Mate-R-16oz-12pk",'Sales Transactions Raw Data'!S:S,"Shopify POS",'Sales Transactions Raw Data'!J:J,"Finished Goods") -> 0 | F7: =SUMIFS('Sales Transactions Raw Data'!V:V,'Sales Transactions Raw Data'!G:G,"Ola-Mate-R-16oz-12pk",'Sales Transactions Raw Data'!S:S,"Shopify admin",'Sales Transactions Raw Data'!J:J,"Finished Goods") -> 0 | G7: =SUMIFS('Sales Transactions Raw Data'!V:V,'Sales Transactions Raw Data'!G:G,"Ola-Mate-R-16oz-12pk",'Sales Transactions Raw Data'!S:S,"subscription_contract",'Sales Transactions Raw Data'!J:J,"Finished Goods") -> 0 | H7: =SUMIFS('Sales Transactions Raw Data'!V:V,'Sales Transactions Raw Data'!G:G,"Ola-Mate-R-16oz-12pk",'Sales Transactions Raw Data'!S:S,"subscription_contract_checkout_one",'Sales Transactions Raw Data'!J:J,"Finished Goods") -> 0 | I7: =SUMIFS('Sales Transactions Raw Data'!V:V,'Sales Transactions Raw Data'!G:G,"Ola-Mate-R-16oz-12pk",'Sales Transactions Raw Data'!S:S,"296827748353",'Sales Transactions Raw Data'!J:J,"Finished Goods") -> 0 | J7: =SUMIFS('Sales Transactions Raw Data'!V:V,'Sales Transactions Raw Data'!G:G,"Ola-Mate-R-16oz-12pk",'Sales Transactions Raw Data'!S:S,"faire",'Sales Transactions Raw Data'!J:J,"Finished Goods") -> 0 | K7: =SUMIFS('Sales Transactions Raw Data'!V:V,'Sales Transactions Raw Data'!G:G,"Ola-Mate-R-16oz-12pk",'Sales Transactions Raw Data'!S:S,"tiktok",'Sales Transactions Raw Data'!J:J,"Finished Goods") -> 0 | L7: =SUMIFS('Sales Transactions Raw Data'!V:V,'Sales Transactions Raw Data'!G:G,"Ola-Mate-R-16oz-12pk",'Sales Transactions Raw Data'!S:S,"4901177",'Sales Transactions Raw Data'!J:J,"Finished Goods") -> 0 | M7: =SUMIFS('Sales Transactions Raw Data'!V:V,'Sales Transactions Raw Data'!G:G,"Ola-Mate-R-16oz-12pk",'Sales Transactions Raw Data'!S:S,"3890849",'Sales Transactions Raw Data'!J:J,"Finished Goods") -> 0 | N7: =SUM(B7:M7) -> 0
A8: 16oz Grapefruit Ginger 12pk | B8: =SUMIFS('Sales Transactions Raw Data'!V:V,'Sales Transactions Raw Data'!G:G,"Ola-Mate-GG-16oz-12pk",'Sales Transactions Raw Data'!S:S,"amazon",'Sales Transactions Raw Data'!J:J,"Finished Goods") -> 0 | C8: =SUMIFS('Sales Transactions Raw Data'!V:V,'Sales Transactions Raw Data'!G:G,"Ola-Mate-GG-16oz-12pk",'Sales Transactions Raw Data'!S:S,"amazon-us",'Sales Transactions Raw Data'!J:J,"Finished Goods") -> 0 | D8: =SUMIFS('Sales Transactions Raw Data'!V:V,'Sales Transactions Raw Data'!G:G,"Ola-Mate-GG-16oz-12pk",'Sales Transactions Raw Data'!S:S,"Shopify web",'Sales Transactions Raw Data'!J:J,"Finished Goods") -> 0 | E8: =SUMIFS('Sales Transactions Raw Data'!V:V,'Sales Transactions Raw Data'!G:G,"Ola-Mate-GG-16oz-12pk",'Sales Transactions Raw Data'!S:S,"Shopify POS",'Sales Transactions Raw Data'!J:J,"Finished Goods") -> 0 | F8: =SUMIFS('Sales Transactions Raw Data'!V:V,'Sales Transactions Raw Data'!G:G,"Ola-Mate-GG-16oz-12pk",'Sales Transactions Raw Data'!S:S,"Shopify admin",'Sales Transactions Raw Data'!J:J,"Finished Goods") -> 0 | G8: =SUMIFS('Sales Transactions Raw Data'!V:V,'Sales Transactions Raw Data'!G:G,"Ola-Mate-GG-16oz-12pk",'Sales Transactions Raw Data'!S:S,"subscription_contract",'Sales Transactions Raw Data'!J:J,"Finished Goods") -> 0 | H8: =SUMIFS('Sales Transactions Raw Data'!V:V,'Sales Transactions Raw Data'!G:G,"Ola-Mate-GG-16oz-12pk",'Sales Transactions Raw Data'!S:S,"subscription_contract_checkout_one",'Sales Transactions Raw Data'!J:J,"Finished Goods") -> 0 | I8: =SUMIFS('Sales Transactions Raw Data'!V:V,'Sales Transactions Raw Data'!G:G,"Ola-Mate-GG-16oz-12pk",'Sales Transactions Raw Data'!S:S,"296827748353",'Sales Transactions Raw Data'!J:J,"Finished Goods") -> 0 | J8: =SUMIFS('Sales Transactions Raw Data'!V:V,'Sales Transactions Raw Data'!G:G,"Ola-Mate-GG-16oz-12pk",'Sales Transactions Raw Data'!S:S,"faire",'Sales Transactions Raw Data'!J:J,"Finished Goods") -> 0 | K8: =SUMIFS('Sales Transactions Raw Data'!V:V,'Sales Transactions Raw Data'!G:G,"Ola-Mate-GG-16oz-12pk",'Sales Transactions Raw Data'!S:S,"tiktok",'Sales Transactions Raw Data'!J:J,"Finished Goods") -> 0 | L8: =SUMIFS('Sales Transactions Raw Data'!V:V,'Sales Transactions Raw Data'!G:G,"Ola-Mate-GG-16oz-12pk",'Sales Transactions Raw Data'!S:S,"4901177",'Sales Transactions Raw Data'!J:J,"Finished Goods") -> 0 | M8: =SUMIFS('Sales Transactions Raw Data'!V:V,'Sales Transactions Raw Data'!G:G,"Ola-Mate-GG-16oz-12pk",'Sales Transactions Raw Data'!S:S,"3890849",'Sales Transactions Raw Data'!J:J,"Finished Goods") -> 0 | N8: =SUM(B8:M8) -> 0
A9: 16oz Starter 4pk | B9: =SUMIFS('Sales Transactions Raw Data'!V:V,'Sales Transactions Raw Data'!G:G,"Ola-Mate-SP1-16oz-4pk",'Sales Transactions Raw Data'!S:S,"amazon",'Sales Transactions Raw Data'!J:J,"Finished Goods") -> 0 | C9: =SUMIFS('Sales Transactions Raw Data'!V:V,'Sales Transactions Raw Data'!G:G,"Ola-Mate-SP1-16oz-4pk",'Sales Transactions Raw Data'!S:S,"amazon-us",'Sales Transactions Raw Data'!J:J,"Finished Goods") -> 0 | D9: =SUMIFS('Sales Transactions Raw Data'!V:V,'Sales Transactions Raw Data'!G:G,"Ola-Mate-SP1-16oz-4pk",'Sales Transactions Raw Data'!S:S,"Shopify web",'Sales Transactions Raw Data'!J:J,"Finished Goods") -> 0 | E9: =SUMIFS('Sales Transactions Raw Data'!V:V,'Sales Transactions Raw Data'!G:G,"Ola-Mate-SP1-16oz-4pk",'Sales Transactions Raw Data'!S:S,"Shopify POS",'Sales Transactions Raw Data'!J:J,"Finished Goods") -> 0 | F9: =SUMIFS('Sales Transactions Raw Data'!V:V,'Sales Transactions Raw Data'!G:G,"Ola-Mate-SP1-16oz-4pk",'Sales Transactions Raw Data'!S:S,"Shopify admin",'Sales Transactions Raw Data'!J:J,"Finished Goods") -> 0 | G9: =SUMIFS('Sales Transactions Raw Data'!V:V,'Sales Transactions Raw Data'!G:G,"Ola-Mate-SP1-16oz-4pk",'Sales Transactions Raw Data'!S:S,"subscription_contract",'Sales Transactions Raw Data'!J:J,"Finished Goods") -> 0 | H9: =SUMIFS('Sales Transactions Raw Data'!V:V,'Sales Transactions Raw Data'!G:G,"Ola-Mate-SP1-16oz-4pk",'Sales Transactions Raw Data'!S:S,"subscription_contract_checkout_one",'Sales Transactions Raw Data'!J:J,"Finished Goods") -> 0 | I9: =SUMIFS('Sales Transactions Raw Data'!V:V,'Sales Transactions Raw Data'!G:G,"Ola-Mate-SP1-16oz-4pk",'Sales Transactions Raw Data'!S:S,"296827748353",'Sales Transactions Raw Data'!J:J,"Finished Goods") -> 0 | J9: =SUMIFS('Sales Transactions Raw Data'!V:V,'Sales Transactions Raw Data'!G:G,"Ola-Mate-SP1-16oz-4pk",'Sales Transactions Raw Data'!S:S,"faire",'Sales Transactions Raw Data'!J:J,"Finished Goods") -> 0 | K9: =SUMIFS('Sales Transactions Raw Data'!V:V,'Sales Transactions Raw Data'!G:G,"Ola-Mate-SP1-16oz-4pk",'Sales Transactions Raw Data'!S:S,"tiktok",'Sales Transactions Raw Data'!J:J,"Finished Goods") -> 0 | L9: =SUMIFS('Sales Transactions Raw Data'!V:V,'Sales Transactions Raw Data'!G:G,"Ola-Mate-SP1-16oz-4pk",'Sales Transactions Raw Data'!S:S,"4901177",'Sales Transactions Raw Data'!J:J,"Finished Goods") -> 0 | M9: =SUMIFS('Sales Transactions Raw Data'!V:V,'Sales Transactions Raw Data'!G:G,"Ola-Mate-SP1-16oz-4pk",'Sales Transactions Raw Data'!S:S,"3890849",'Sales Transactions Raw Data'!J:J,"Finished Goods") -> 0 | N9: =SUM(B9:M9) -> 0
A10: Loose Cans (BC/GG/R) | B10: =SUMIFS('Sales Transactions Raw Data'!V:V,'Sales Transactions Raw Data'!G:G,"Ola-Mate-*-16oz-1can",'Sales Transactions Raw Data'!S:S,"amazon",'Sales Transactions Raw Data'!J:J,"Finished Goods") -> 0 | C10: =SUMIFS('Sales Transactions Raw Data'!V:V,'Sales Transactions Raw Data'!G:G,"Ola-Mate-*-16oz-1can",'Sales Transactions Raw Data'!S:S,"amazon-us",'Sales Transactions Raw Data'!J:J,"Finished Goods") -> 0 | D10: =SUMIFS('Sales Transactions Raw Data'!V:V,'Sales Transactions Raw Data'!G:G,"Ola-Mate-*-16oz-1can",'Sales Transactions Raw Data'!S:S,"Shopify web",'Sales Transactions Raw Data'!J:J,"Finished Goods") -> 0 | E10: =SUMIFS('Sales Transactions Raw Data'!V:V,'Sales Transactions Raw Data'!G:G,"Ola-Mate-*-16oz-1can",'Sales Transactions Raw Data'!S:S,"Shopify POS",'Sales Transactions Raw Data'!J:J,"Finished Goods") -> 0 | F10: =SUMIFS('Sales Transactions Raw Data'!V:V,'Sales Transactions Raw Data'!G:G,"Ola-Mate-*-16oz-1can",'Sales Transactions Raw Data'!S:S,"Shopify admin",'Sales Transactions Raw Data'!J:J,"Finished Goods") -> 0 | G10: =SUMIFS('Sales Transactions Raw Data'!V:V,'Sales Transactions Raw Data'!G:G,"Ola-Mate-*-16oz-1can",'Sales Transactions Raw Data'!S:S,"subscription_contract",'Sales Transactions Raw Data'!J:J,"Finished Goods") -> 0 | H10: =SUMIFS('Sales Transactions Raw Data'!V:V,'Sales Transactions Raw Data'!G:G,"Ola-Mate-*-16oz-1can",'Sales Transactions Raw Data'!S:S,"subscription_contract_checkout_one",'Sales Transactions Raw Data'!J:J,"Finished Goods") -> 0 | I10: =SUMIFS('Sales Transactions Raw Data'!V:V,'Sales Transactions Raw Data'!G:G,"Ola-Mate-*-16oz-1can",'Sales Transactions Raw Data'!S:S,"296827748353",'Sales Transactions Raw Data'!J:J,"Finished Goods") -> 0 | J10: =SUMIFS('Sales Transactions Raw Data'!V:V,'Sales Transactions Raw Data'!G:G,"Ola-Mate-*-16oz-1can",'Sales Transactions Raw Data'!S:S,"faire",'Sales Transactions Raw Data'!J:J,"Finished Goods") -> 0 | K10: =SUMIFS('Sales Transactions Raw Data'!V:V,'Sales Transactions Raw Data'!G:G,"Ola-Mate-*-16oz-1can",'Sales Transactions Raw Data'!S:S,"tiktok",'Sales Transactions Raw Data'!J:J,"Finished Goods") -> 0 | L10: =SUMIFS('Sales Transactions Raw Data'!V:V,'Sales Transactions Raw Data'!G:G,"Ola-Mate-*-16oz-1can",'Sales Transactions Raw Data'!S:S,"4901177",'Sales Transactions Raw Data'!J:J,"Finished Goods") -> 0 | M10: =SUMIFS('Sales Transactions Raw Data'!V:V,'Sales Transactions Raw Data'!G:G,"Ola-Mate-*-16oz-1can",'Sales Transactions Raw Data'!S:S,"3890849",'Sales Transactions Raw Data'!J:J,"Finished Goods") -> 0 | N10: =SUM(B10:M10) -> 0
A11: TOTAL REVENUE | B11: =SUM(B5:B10) -> 0 | C11: =SUM(C5:C10) -> 0 | D11: =SUM(D5:D10) -> 0 | E11: =SUM(E5:E10) -> 0 | F11: =SUM(F5:F10) -> 0 | G11: =SUM(G5:G10) -> 0 | H11: =SUM(H5:H10) -> 0 | I11: =SUM(I5:I10) -> 0 | ... M11: =SUM(M5:M10) -> 0 | N11: =SUM(B11:M11) -> 0
A13: COGS BY CHANNEL × PRODUCT | B13: Amazon | C13: Amazon Retail | D13: Shopify Web | E13: Shopify POS | F13: Shopify Admin | G13: Subs (contract) | H13: Subs (checkout) | I13: Wholesale 296... | J13: Faire | K13: TikTok | L13: Ch 4901177 | M13: Ch 3890849 | N13: Total
A14: 16oz Variety 12pk | B14: =SUMIFS('Sales Transactions Raw Data'!W:W,'Sales Transactions Raw Data'!G:G,"Ola-Mate-VP1-16oz-12pk",'Sales Transactions Raw Data'!S:S,"amazon",'Sales Transactions Raw Data'!J:J,"Finished Goods") -> 0 | C14: =SUMIFS('Sales Transactions Raw Data'!W:W,'Sales Transactions Raw Data'!G:G,"Ola-Mate-VP1-16oz-12pk",'Sales Transactions Raw Data'!S:S,"amazon-us",'Sales Transactions Raw Data'!J:J,"Finished Goods") -> 0 | D14: =SUMIFS('Sales Transactions Raw Data'!W:W,'Sales Transactions Raw Data'!G:G,"Ola-Mate-VP1-16oz-12pk",'Sales Transactions Raw Data'!S:S,"Shopify web",'Sales Transactions Raw Data'!J:J,"Finished Goods") -> 0 | E14: =SUMIFS('Sales Transactions Raw Data'!W:W,'Sales Transactions Raw Data'!G:G,"Ola-Mate-VP1-16oz-12pk",'Sales Transactions Raw Data'!S:S,"Shopify POS",'Sales Transactions Raw Data'!J:J,"Finished Goods") -> 0 | F14: =SUMIFS('Sales Transactions Raw Data'!W:W,'Sales Transactions Raw Data'!G:G,"Ola-Mate-VP1-16oz-12pk",'Sales Transactions Raw Data'!S:S,"Shopify admin",'Sales Transactions Raw Data'!J:J,"Finished Goods") -> 0 | G14: =SUMIFS('Sales Transactions Raw Data'!W:W,'Sales Transactions Raw Data'!G:G,"Ola-Mate-VP1-16oz-12pk",'Sales Transactions Raw Data'!S:S,"subscription_contract",'Sales Transactions Raw Data'!J:J,"Finished Goods") -> 0 | H14: =SUMIFS('Sales Transactions Raw Data'!W:W,'Sales Transactions Raw Data'!G:G,"Ola-Mate-VP1-16oz-12pk",'Sales Transactions Raw Data'!S:S,"subscription_contract_checkout_one",'Sales Transactions Raw Data'!J:J,"Finished Goods") -> 0 | I14: =SUMIFS('Sales Transactions Raw Data'!W:W,'Sales Transactions Raw Data'!G:G,"Ola-Mate-VP1-16oz-12pk",'Sales Transactions Raw Data'!S:S,"296827748353",'Sales Transactions Raw Data'!J:J,"Finished Goods") -> 0 | J14: =SUMIFS('Sales Transactions Raw Data'!W:W,'Sales Transactions Raw Data'!G:G,"Ola-Mate-VP1-16oz-12pk",'Sales Transactions Raw Data'!S:S,"faire",'Sales Transactions Raw Data'!J:J,"Finished Goods") -> 0 | K14: =SUMIFS('Sales Transactions Raw Data'!W:W,'Sales Transactions Raw Data'!G:G,"Ola-Mate-VP1-16oz-12pk",'Sales Transactions Raw Data'!S:S,"tiktok",'Sales Transactions Raw Data'!J:J,"Finished Goods") -> 0 | L14: =SUMIFS('Sales Transactions Raw Data'!W:W,'Sales Transactions Raw Data'!G:G,"Ola-Mate-VP1-16oz-12pk",'Sales Transactions Raw Data'!S:S,"4901177",'Sales Transactions Raw Data'!J:J,"Finished Goods") -> 0 | M14: =SUMIFS('Sales Transactions Raw Data'!W:W,'Sales Transactions Raw Data'!G:G,"Ola-Mate-VP1-16oz-12pk",'Sales Transactions Raw Data'!S:S,"3890849",'Sales Transactions Raw Data'!J:J,"Finished Goods") -> 0 | N14: =SUM(B14:M14) -> 0
A15: 16oz Berry Coconut 12pk | B15: =SUMIFS('Sales Transactions Raw Data'!W:W,'Sales Transactions Raw Data'!G:G,"Ola-Mate-BC-16oz-12PK",'Sales Transactions Raw Data'!S:S,"amazon",'Sales Transactions Raw Data'!J:J,"Finished Goods") -> 0 | C15: =SUMIFS('Sales Transactions Raw Data'!W:W,'Sales Transactions Raw Data'!G:G,"Ola-Mate-BC-16oz-12PK",'Sales Transactions Raw Data'!S:S,"amazon-us",'Sales Transactions Raw Data'!J:J,"Finished Goods") -> 0 | D15: =SUMIFS('Sales Transactions Raw Data'!W:W,'Sales Transactions Raw Data'!G:G,"Ola-Mate-BC-16oz-12PK",'Sales Transactions Raw Data'!S:S,"Shopify web",'Sales Transactions Raw Data'!J:J,"Finished Goods") -> 0 | E15: =SUMIFS('Sales Transactions Raw Data'!W:W,'Sales Transactions Raw Data'!G:G,"Ola-Mate-BC-16oz-12PK",'Sales Transactions Raw Data'!S:S,"Shopify POS",'Sales Transactions Raw Data'!J:J,"Finished Goods") -> 0 | F15: =SUMIFS('Sales Transactions Raw Data'!W:W,'Sales Transactions Raw Data'!G:G,"Ola-Mate-BC-16oz-12PK",'Sales Transactions Raw Data'!S:S,"Shopify admin",'Sales Transactions Raw Data'!J:J,"Finished Goods") -> 0 | G15: =SUMIFS('Sales Transactions Raw Data'!W:W,'Sales Transactions Raw Data'!G:G,"Ola-Mate-BC-16oz-12PK",'Sales Transactions Raw Data'!S:S,"subscription_contract",'Sales Transactions Raw Data'!J:J,"Finished Goods") -> 0 | H15: =SUMIFS('Sales Transactions Raw Data'!W:W,'Sales Transactions Raw Data'!G:G,"Ola-Mate-BC-16oz-12PK",'Sales Transactions Raw Data'!S:S,"subscription_contract_checkout_one",'Sales Transactions Raw Data'!J:J,"Finished Goods") -> 0 | I15: =SUMIFS('Sales Transactions Raw Data'!W:W,'Sales Transactions Raw Data'!G:G,"Ola-Mate-BC-16oz-12PK",'Sales Transactions Raw Data'!S:S,"296827748353",'Sales Transactions Raw Data'!J:J,"Finished Goods") -> 0 | J15: =SUMIFS('Sales Transactions Raw Data'!W:W,'Sales Transactions Raw Data'!G:G,"Ola-Mate-BC-16oz-12PK",'Sales Transactions Raw Data'!S:S,"faire",'Sales Transactions Raw Data'!J:J,"Finished Goods") -> 0 | K15: =SUMIFS('Sales Transactions Raw Data'!W:W,'Sales Transactions Raw Data'!G:G,"Ola-Mate-BC-16oz-12PK",'Sales Transactions Raw Data'!S:S,"tiktok",'Sales Transactions Raw Data'!J:J,"Finished Goods") -> 0 | L15: =SUMIFS('Sales Transactions Raw Data'!W:W,'Sales Transactions Raw Data'!G:G,"Ola-Mate-BC-16oz-12PK",'Sales Transactions Raw Data'!S:S,"4901177",'Sales Transactions Raw Data'!J:J,"Finished Goods") -> 0 | M15: =SUMIFS('Sales Transactions Raw Data'!W:W,'Sales Transactions Raw Data'!G:G,"Ola-Mate-BC-16oz-12PK",'Sales Transactions Raw Data'!S:S,"3890849",'Sales Transactions Raw Data'!J:J,"Finished Goods") -> 0 | N15: =SUM(B15:M15) -> 0
A16: 16oz Raspberry 12pk | B16: =SUMIFS('Sales Transactions Raw Data'!W:W,'Sales Transactions Raw Data'!G:G,"Ola-Mate-R-16oz-12pk",'Sales Transactions Raw Data'!S:S,"amazon",'Sales Transactions Raw Data'!J:J,"Finished Goods") -> 0 | C16: =SUMIFS('Sales Transactions Raw Data'!W:W,'Sales Transactions Raw Data'!G:G,"Ola-Mate-R-16oz-12pk",'Sales Transactions Raw Data'!S:S,"amazon-us",'Sales Transactions Raw Data'!J:J,"Finished Goods") -> 0 | D16: =SUMIFS('Sales Transactions Raw Data'!W:W,'Sales Transactions Raw Data'!G:G,"Ola-Mate-R-16oz-12pk",'Sales Transactions Raw Data'!S:S,"Shopify web",'Sales Transactions Raw Data'!J:J,"Finished Goods") -> 0 | E16: =SUMIFS('Sales Transactions Raw Data'!W:W,'Sales Transactions Raw Data'!G:G,"Ola-Mate-R-16oz-12pk",'Sales Transactions Raw Data'!S:S,"Shopify POS",'Sales Transactions Raw Data'!J:J,"Finished Goods") -> 0 | F16: =SUMIFS('Sales Transactions Raw Data'!W:W,'Sales Transactions Raw Data'!G:G,"Ola-Mate-R-16oz-12pk",'Sales Transactions Raw Data'!S:S,"Shopify admin",'Sales Transactions Raw Data'!J:J,"Finished Goods") -> 0 | G16: =SUMIFS('Sales Transactions Raw Data'!W:W,'Sales Transactions Raw Data'!G:G,"Ola-Mate-R-16oz-12pk",'Sales Transactions Raw Data'!S:S,"subscription_contract",'Sales Transactions Raw Data'!J:J,"Finished Goods") -> 0 | H16: =SUMIFS('Sales Transactions Raw Data'!W:W,'Sales Transactions Raw Data'!G:G,"Ola-Mate-R-16oz-12pk",'Sales Transactions Raw Data'!S:S,"subscription_contract_checkout_one",'Sales Transactions Raw Data'!J:J,"Finished Goods") -> 0 | I16: =SUMIFS('Sales Transactions Raw Data'!W:W,'Sales Transactions Raw Data'!G:G,"Ola-Mate-R-16oz-12pk",'Sales Transactions Raw Data'!S:S,"296827748353",'Sales Transactions Raw Data'!J:J,"Finished Goods") -> 0 | J16: =SUMIFS('Sales Transactions Raw Data'!W:W,'Sales Transactions Raw Data'!G:G,"Ola-Mate-R-16oz-12pk",'Sales Transactions Raw Data'!S:S,"faire",'Sales Transactions Raw Data'!J:J,"Finished Goods") -> 0 | K16: =SUMIFS('Sales Transactions Raw Data'!W:W,'Sales Transactions Raw Data'!G:G,"Ola-Mate-R-16oz-12pk",'Sales Transactions Raw Data'!S:S,"tiktok",'Sales Transactions Raw Data'!J:J,"Finished Goods") -> 0 | L16: =SUMIFS('Sales Transactions Raw Data'!W:W,'Sales Transactions Raw Data'!G:G,"Ola-Mate-R-16oz-12pk",'Sales Transactions Raw Data'!S:S,"4901177",'Sales Transactions Raw Data'!J:J,"Finished Goods") -> 0 | M16: =SUMIFS('Sales Transactions Raw Data'!W:W,'Sales Transactions Raw Data'!G:G,"Ola-Mate-R-16oz-12pk",'Sales Transactions Raw Data'!S:S,"3890849",'Sales Transactions Raw Data'!J:J,"Finished Goods") -> 0 | N16: =SUM(B16:M16) -> 0
A17: 16oz Grapefruit Ginger 12pk | B17: =SUMIFS('Sales Transactions Raw Data'!W:W,'Sales Transactions Raw Data'!G:G,"Ola-Mate-GG-16oz-12pk",'Sales Transactions Raw Data'!S:S,"amazon",'Sales Transactions Raw Data'!J:J,"Finished Goods") -> 0 | C17: =SUMIFS('Sales Transactions Raw Data'!W:W,'Sales Transactions Raw Data'!G:G,"Ola-Mate-GG-16oz-12pk",'Sales Transactions Raw Data'!S:S,"amazon-us",'Sales Transactions Raw Data'!J:J,"Finished Goods") -> 0 | D17: =SUMIFS('Sales Transactions Raw Data'!W:W,'Sales Transactions Raw Data'!G:G,"Ola-Mate-GG-16oz-12pk",'Sales Transactions Raw Data'!S:S,"Shopify web",'Sales Transactions Raw Data'!J:J,"Finished Goods") -> 0 | E17: =SUMIFS('Sales Transactions Raw Data'!W:W,'Sales Transactions Raw Data'!G:G,"Ola-Mate-GG-16oz-12pk",'Sales Transactions Raw Data'!S:S,"Shopify POS",'Sales Transactions Raw Data'!J:J,"Finished Goods") -> 0 | F17: =SUMIFS('Sales Transactions Raw Data'!W:W,'Sales Transactions Raw Data'!G:G,"Ola-Mate-GG-16oz-12pk",'Sales Transactions Raw Data'!S:S,"Shopify admin",'Sales Transactions Raw Data'!J:J,"Finished Goods") -> 0 | G17: =SUMIFS('Sales Transactions Raw Data'!W:W,'Sales Transactions Raw Data'!G:G,"Ola-Mate-GG-16oz-12pk",'Sales Transactions Raw Data'!S:S,"subscription_contract",'Sales Transactions Raw Data'!J:J,"Finished Goods") -> 0 | H17: =SUMIFS('Sales Transactions Raw Data'!W:W,'Sales Transactions Raw Data'!G:G,"Ola-Mate-GG-16oz-12pk",'Sales Transactions Raw Data'!S:S,"subscription_contract_checkout_one",'Sales Transactions Raw Data'!J:J,"Finished Goods") -> 0 | I17: =SUMIFS('Sales Transactions Raw Data'!W:W,'Sales Transactions Raw Data'!G:G,"Ola-Mate-GG-16oz-12pk",'Sales Transactions Raw Data'!S:S,"296827748353",'Sales Transactions Raw Data'!J:J,"Finished Goods") -> 0 | J17: =SUMIFS('Sales Transactions Raw Data'!W:W,'Sales Transactions Raw Data'!G:G,"Ola-Mate-GG-16oz-12pk",'Sales Transactions Raw Data'!S:S,"faire",'Sales Transactions Raw Data'!J:J,"Finished Goods") -> 0 | K17: =SUMIFS('Sales Transactions Raw Data'!W:W,'Sales Transactions Raw Data'!G:G,"Ola-Mate-GG-16oz-12pk",'Sales Transactions Raw Data'!S:S,"tiktok",'Sales Transactions Raw Data'!J:J,"Finished Goods") -> 0 | L17: =SUMIFS('Sales Transactions Raw Data'!W:W,'Sales Transactions Raw Data'!G:G,"Ola-Mate-GG-16oz-12pk",'Sales Transactions Raw Data'!S:S,"4901177",'Sales Transactions Raw Data'!J:J,"Finished Goods") -> 0 | M17: =SUMIFS('Sales Transactions Raw Data'!W:W,'Sales Transactions Raw Data'!G:G,"Ola-Mate-GG-16oz-12pk",'Sales Transactions Raw Data'!S:S,"3890849",'Sales Transactions Raw Data'!J:J,"Finished Goods") -> 0 | N17: =SUM(B17:M17) -> 0
A18: 16oz Starter 4pk | B18: =SUMIFS('Sales Transactions Raw Data'!W:W,'Sales Transactions Raw Data'!G:G,"Ola-Mate-SP1-16oz-4pk",'Sales Transactions Raw Data'!S:S,"amazon",'Sales Transactions Raw Data'!J:J,"Finished Goods") -> 0 | C18: =SUMIFS('Sales Transactions Raw Data'!W:W,'Sales Transactions Raw Data'!G:G,"Ola-Mate-SP1-16oz-4pk",'Sales Transactions Raw Data'!S:S,"amazon-us",'Sales Transactions Raw Data'!J:J,"Finished Goods") -> 0 | D18: =SUMIFS('Sales Transactions Raw Data'!W:W,'Sales Transactions Raw Data'!G:G,"Ola-Mate-SP1-16oz-4pk",'Sales Transactions Raw Data'!S:S,"Shopify web",'Sales Transactions Raw Data'!J:J,"Finished Goods") -> 0 | E18: =SUMIFS('Sales Transactions Raw Data'!W:W,'Sales Transactions Raw Data'!G:G,"Ola-Mate-SP1-16oz-4pk",'Sales Transactions Raw Data'!S:S,"Shopify POS",'Sales Transactions Raw Data'!J:J,"Finished Goods") -> 0 | F18: =SUMIFS('Sales Transactions Raw Data'!W:W,'Sales Transactions Raw Data'!G:G,"Ola-Mate-SP1-16oz-4pk",'Sales Transactions Raw Data'!S:S,"Shopify admin",'Sales Transactions Raw Data'!J:J,"Finished Goods") -> 0 | G18: =SUMIFS('Sales Transactions Raw Data'!W:W,'Sales Transactions Raw Data'!G:G,"Ola-Mate-SP1-16oz-4pk",'Sales Transactions Raw Data'!S:S,"subscription_contract",'Sales Transactions Raw Data'!J:J,"Finished Goods") -> 0 | H18: =SUMIFS('Sales Transactions Raw Data'!W:W,'Sales Transactions Raw Data'!G:G,"Ola-Mate-SP1-16oz-4pk",'Sales Transactions Raw Data'!S:S,"subscription_contract_checkout_one",'Sales Transactions Raw Data'!J:J,"Finished Goods") -> 0 | I18: =SUMIFS('Sales Transactions Raw Data'!W:W,'Sales Transactions Raw Data'!G:G,"Ola-Mate-SP1-16oz-4pk",'Sales Transactions Raw Data'!S:S,"296827748353",'Sales Transactions Raw Data'!J:J,"Finished Goods") -> 0 | J18: =SUMIFS('Sales Transactions Raw Data'!W:W,'Sales Transactions Raw Data'!G:G,"Ola-Mate-SP1-16oz-4pk",'Sales Transactions Raw Data'!S:S,"faire",'Sales Transactions Raw Data'!J:J,"Finished Goods") -> 0 | K18: =SUMIFS('Sales Transactions Raw Data'!W:W,'Sales Transactions Raw Data'!G:G,"Ola-Mate-SP1-16oz-4pk",'Sales Transactions Raw Data'!S:S,"tiktok",'Sales Transactions Raw Data'!J:J,"Finished Goods") -> 0 | L18: =SUMIFS('Sales Transactions Raw Data'!W:W,'Sales Transactions Raw Data'!G:G,"Ola-Mate-SP1-16oz-4pk",'Sales Transactions Raw Data'!S:S,"4901177",'Sales Transactions Raw Data'!J:J,"Finished Goods") -> 0 | M18: =SUMIFS('Sales Transactions Raw Data'!W:W,'Sales Transactions Raw Data'!G:G,"Ola-Mate-SP1-16oz-4pk",'Sales Transactions Raw Data'!S:S,"3890849",'Sales Transactions Raw Data'!J:J,"Finished Goods") -> 0 | N18: =SUM(B18:M18) -> 0
A19: Loose Cans (BC/GG/R) | B19: =SUMIFS('Sales Transactions Raw Data'!W:W,'Sales Transactions Raw Data'!G:G,"Ola-Mate-*-16oz-1can",'Sales Transactions Raw Data'!S:S,"amazon",'Sales Transactions Raw Data'!J:J,"Finished Goods") -> 0 | C19: =SUMIFS('Sales Transactions Raw Data'!W:W,'Sales Transactions Raw Data'!G:G,"Ola-Mate-*-16oz-1can",'Sales Transactions Raw Data'!S:S,"amazon-us",'Sales Transactions Raw Data'!J:J,"Finished Goods") -> 0 | D19: =SUMIFS('Sales Transactions Raw Data'!W:W,'Sales Transactions Raw Data'!G:G,"Ola-Mate-*-16oz-1can",'Sales Transactions Raw Data'!S:S,"Shopify web",'Sales Transactions Raw Data'!J:J,"Finished Goods") -> 0 | E19: =SUMIFS('Sales Transactions Raw Data'!W:W,'Sales Transactions Raw Data'!G:G,"Ola-Mate-*-16oz-1can",'Sales Transactions Raw Data'!S:S,"Shopify POS",'Sales Transactions Raw Data'!J:J,"Finished Goods") -> 0 | F19: =SUMIFS('Sales Transactions Raw Data'!W:W,'Sales Transactions Raw Data'!G:G,"Ola-Mate-*-16oz-1can",'Sales Transactions Raw Data'!S:S,"Shopify admin",'Sales Transactions Raw Data'!J:J,"Finished Goods") -> 0 | G19: =SUMIFS('Sales Transactions Raw Data'!W:W,'Sales Transactions Raw Data'!G:G,"Ola-Mate-*-16oz-1can",'Sales Transactions Raw Data'!S:S,"subscription_contract",'Sales Transactions Raw Data'!J:J,"Finished Goods") -> 0 | H19: =SUMIFS('Sales Transactions Raw Data'!W:W,'Sales Transactions Raw Data'!G:G,"Ola-Mate-*-16oz-1can",'Sales Transactions Raw Data'!S:S,"subscription_contract_checkout_one",'Sales Transactions Raw Data'!J:J,"Finished Goods") -> 0 | I19: =SUMIFS('Sales Transactions Raw Data'!W:W,'Sales Transactions Raw Data'!G:G,"Ola-Mate-*-16oz-1can",'Sales Transactions Raw Data'!S:S,"296827748353",'Sales Transactions Raw Data'!J:J,"Finished Goods") -> 0 | J19: =SUMIFS('Sales Transactions Raw Data'!W:W,'Sales Transactions Raw Data'!G:G,"Ola-Mate-*-16oz-1can",'Sales Transactions Raw Data'!S:S,"faire",'Sales Transactions Raw Data'!J:J,"Finished Goods") -> 0 | K19: =SUMIFS('Sales Transactions Raw Data'!W:W,'Sales Transactions Raw Data'!G:G,"Ola-Mate-*-16oz-1can",'Sales Transactions Raw Data'!S:S,"tiktok",'Sales Transactions Raw Data'!J:J,"Finished Goods") -> 0 | L19: =SUMIFS('Sales Transactions Raw Data'!W:W,'Sales Transactions Raw Data'!G:G,"Ola-Mate-*-16oz-1can",'Sales Transactions Raw Data'!S:S,"4901177",'Sales Transactions Raw Data'!J:J,"Finished Goods") -> 0 | M19: =SUMIFS('Sales Transactions Raw Data'!W:W,'Sales Transactions Raw Data'!G:G,"Ola-Mate-*-16oz-1can",'Sales Transactions Raw Data'!S:S,"3890849",'Sales Transactions Raw Data'!J:J,"Finished Goods") -> 0 | N19: =SUM(B19:M19) -> 0
A20: TOTAL COGS | B20: =SUM(B14:B19) -> 0 | C20: =SUM(C14:C19) -> 0 | D20: =SUM(D14:D19) -> 0 | E20: =SUM(E14:E19) -> 0 | F20: =SUM(F14:F19) -> 0 | G20: =SUM(G14:G19) -> 0 | H20: =SUM(H14:H19) -> 0 | I20: =SUM(I14:I19) -> 0 | ... M20: =SUM(M14:M19) -> 0 | N20: =SUM(B20:M20) -> 0
A21: GROSS PROFIT BY CHANNEL | B21: =B11-B20 -> 0 | C21: =C11-C20 -> 0 | D21: =D11-D20 -> 0 | E21: =E11-E20 -> 0 | F21: =F11-F20 -> 0 | G21: =G11-G20 -> 0 | H21: =H11-H20 -> 0 | I21: =I11-I20 -> 0 | ... N21: =N11-N20 -> 0
A22: GM% BY CHANNEL | B22: =IF(B11=0,"-",B21/B11) -> - | C22: =IF(C11=0,"-",C21/C11) -> - | D22: =IF(D11=0,"-",D21/D11) -> - | E22: =IF(E11=0,"-",E21/E11) -> - | F22: =IF(F11=0,"-",F21/F11) -> - | G22: =IF(G11=0,"-",G21/G11) -> - | H22: =IF(H11=0,"-",H21/H11) -> - | I22: =IF(I11=0,"-",I21/I11) -> - | ... N22: =IF(N11=0,"-",N21/N11) -> -

Sheet Inventory & MOS Analysis
A1: Inventory & MOS Analysis — by SKU & Location
A2: MOS = Current Qty ÷ (Avg Monthly Units Sold — Last 3 Months) | Alerts: 🔴 <1mo 🟡 1-2mo 🟢 2-6mo 🔵 >6mo
A3: FINISHED GOODS — STOCK LEVELS BY LOCATION
A4: SKU | B4: Product Name | C4: Amazon FBA | D4: Founders | E4: NJ Whs | F4: NY Whs | G4: NOBL | H4: Total Stock | I4: Avg Mo Sales (3mo) | J4: MOS | K4: Stock Alert
A5: Ola-Mate-VP1-16oz-12pk | B5: 16oz Variety 12pk | C5: =SUMIFS('Inventory On Hand Raw Data'!E:E,'Inventory On Hand Raw Data'!B:B,"Ola-Mate-VP1-16oz-12pk",'Inventory On Hand Raw Data'!A:A,"Amazon FBA") -> 0 | D5: =SUMIFS('Inventory On Hand Raw Data'!E:E,'Inventory On Hand Raw Data'!B:B,"Ola-Mate-VP1-16oz-12pk",'Inventory On Hand Raw Data'!A:A,"Founders") -> 0 | E5: =SUMIFS('Inventory On Hand Raw Data'!E:E,'Inventory On Hand Raw Data'!B:B,"Ola-Mate-VP1-16oz-12pk",'Inventory On Hand Raw Data'!A:A,"NJ Warehouse") -> 0 | F5: =SUMIFS('Inventory On Hand Raw Data'!E:E,'Inventory On Hand Raw Data'!B:B,"Ola-Mate-VP1-16oz-12pk",'Inventory On Hand Raw Data'!A:A,"NY Warehouse") -> 0 | G5: =SUMIFS('Inventory On Hand Raw Data'!E:E,'Inventory On Hand Raw Data'!B:B,"Ola-Mate-VP1-16oz-12pk",'Inventory On Hand Raw Data'!A:A,"NOBL") -> 0 | H5: =SUM(C5:G5) -> 0 | I5: =IFERROR((SUMIFS('Sales Transactions Raw Data'!T:T,'Sales Transactions Raw Data'!G:G,"Ola-Mate-VP1-16oz-12pk",'Sales Transactions Raw Data'!J:J,"Finished Goods",'Sales Transactions Raw Data'!A:A,2025,'Sales Transactions Raw Data'!B:B,"September")+SUMIFS('Sales Transactions Raw Data'!T:T,'Sales Transactions Raw Data'!G:G,"Ola-Mate-VP1-16oz-12pk",'Sales Transactions Raw Data'!J:J,"Finished Goods",'Sales Transactions Raw Data'!A:A,2025,'Sales Transactions Raw Data'!B:B,"October")+SUMIFS('Sales Transactions Raw Data'!T:T,'Sales Transactions Raw Data'!G:G,"Ola-Mate-VP1-16oz-12pk",'Sales Transactions Raw Data'!J:J,"Finished Goods",'Sales Transactions Raw Data'!A:A,2025,'Sales Transactions Raw Data'!B:B,"November"))/3,0) -> 0 | J5: =IF(I5=0,"N/A",H5/I5) -> N/A | K5: =IF(I5=0,"⚪ No Sales",IF(J5="N/A","⚪ No Sales",IF(J5<1,"🔴 CRITICAL",IF(J5<2,"🟡 LOW",IF(J5<=6,"🟢 HEALTHY","🔵 OVERSTOCK"))))) -> ⚪ No Sales
A6: Ola-Mate-BC-16oz-12PK | B6: 16oz Berry Coconut 12pk | C6: =SUMIFS('Inventory On Hand Raw Data'!E:E,'Inventory On Hand Raw Data'!B:B,"Ola-Mate-BC-16oz-12PK",'Inventory On Hand Raw Data'!A:A,"Amazon FBA") -> 0 | D6: =SUMIFS('Inventory On Hand Raw Data'!E:E,'Inventory On Hand Raw Data'!B:B,"Ola-Mate-BC-16oz-12PK",'Inventory On Hand Raw Data'!A:A,"Founders") -> 0 | E6: =SUMIFS('Inventory On Hand Raw Data'!E:E,'Inventory On Hand Raw Data'!B:B,"Ola-Mate-BC-16oz-12PK",'Inventory On Hand Raw Data'!A:A,"NJ Warehouse") -> 0 | F6: =SUMIFS('Inventory On Hand Raw Data'!E:E,'Inventory On Hand Raw Data'!B:B,"Ola-Mate-BC-16oz-12PK",'Inventory On Hand Raw Data'!A:A,"NY Warehouse") -> 0 | G6: =SUMIFS('Inventory On Hand Raw Data'!E:E,'Inventory On Hand Raw Data'!B:B,"Ola-Mate-BC-16oz-12PK",'Inventory On Hand Raw Data'!A:A,"NOBL") -> 0 | H6: =SUM(C6:G6) -> 0 | I6: =IFERROR((SUMIFS('Sales Transactions Raw Data'!T:T,'Sales Transactions Raw Data'!G:G,"Ola-Mate-BC-16oz-12PK",'Sales Transactions Raw Data'!J:J,"Finished Goods",'Sales Transactions Raw Data'!A:A,2025,'Sales Transactions Raw Data'!B:B,"September")+SUMIFS('Sales Transactions Raw Data'!T:T,'Sales Transactions Raw Data'!G:G,"Ola-Mate-BC-16oz-12PK",'Sales Transactions Raw Data'!J:J,"Finished Goods",'Sales Transactions Raw Data'!A:A,2025,'Sales Transactions Raw Data'!B:B,"October")+SUMIFS('Sales Transactions Raw Data'!T:T,'Sales Transactions Raw Data'!G:G,"Ola-Mate-BC-16oz-12PK",'Sales Transactions Raw Data'!J:J,"Finished Goods",'Sales Transactions Raw Data'!A:A,2025,'Sales Transactions Raw Data'!B:B,"November"))/3,0) -> 0 | J6: =IF(I6=0,"N/A",H6/I6) -> N/A | K6: =IF(I6=0,"⚪ No Sales",IF(J6="N/A","⚪ No Sales",IF(J6<1,"🔴 CRITICAL",IF(J6<2,"🟡 LOW",IF(J6<=6,"🟢 HEALTHY","🔵 OVERSTOCK"))))) -> ⚪ No Sales
A7: Ola-Mate-GG-16oz-12pk | B7: 16oz Grapefruit Ginger 12pk | C7: =SUMIFS('Inventory On Hand Raw Data'!E:E,'Inventory On Hand Raw Data'!B:B,"Ola-Mate-GG-16oz-12pk",'Inventory On Hand Raw Data'!A:A,"Amazon FBA") -> 0 | D7: =SUMIFS('Inventory On Hand Raw Data'!E:E,'Inventory On Hand Raw Data'!B:B,"Ola-Mate-GG-16oz-12pk",'Inventory On Hand Raw Data'!A:A,"Founders") -> 0 | E7: =SUMIFS('Inventory On Hand Raw Data'!E:E,'Inventory On Hand Raw Data'!B:B,"Ola-Mate-GG-16oz-12pk",'Inventory On Hand Raw Data'!A:A,"NJ Warehouse") -> 0 | F7: =SUMIFS('Inventory On Hand Raw Data'!E:E,'Inventory On Hand Raw Data'!B:B,"Ola-Mate-GG-16oz-12pk",'Inventory On Hand Raw Data'!A:A,"NY Warehouse") -> 0 | G7: =SUMIFS('Inventory On Hand Raw Data'!E:E,'Inventory On Hand Raw Data'!B:B,"Ola-Mate-GG-16oz-12pk",'Inventory On Hand Raw Data'!A:A,"NOBL") -> 0 | H7: =SUM(C7:G7) -> 0 | I7: =IFERROR((SUMIFS('Sales Transactions Raw Data'!T:T,'Sales Transactions Raw Data'!G:G,"Ola-Mate-GG-16oz-12pk",'Sales Transactions Raw Data'!J:J,"Finished Goods",'Sales Transactions Raw Data'!A:A,2025,'Sales Transactions Raw Data'!B:B,"September")+SUMIFS('Sales Transactions Raw Data'!T:T,'Sales Transactions Raw Data'!G:G,"Ola-Mate-GG-16oz-12pk",'Sales Transactions Raw Data'!J:J,"Finished Goods",'Sales Transactions Raw Data'!A:A,2025,'Sales Transactions Raw Data'!B:B,"October")+SUMIFS('Sales Transactions Raw Data'!T:T,'Sales Transactions Raw Data'!G:G,"Ola-Mate-GG-16oz-12pk",'Sales Transactions Raw Data'!J:J,"Finished Goods",'Sales Transactions Raw Data'!A:A,2025,'Sales Transactions Raw Data'!B:B,"November"))/3,0) -> 0 | J7: =IF(I7=0,"N/A",H7/I7) -> N/A | K7: =IF(I7=0,"⚪ No Sales",IF(J7="N/A","⚪ No Sales",IF(J7<1,"🔴 CRITICAL",IF(J7<2,"🟡 LOW",IF(J7<=6,"🟢 HEALTHY","🔵 OVERSTOCK"))))) -> ⚪ No Sales
A8: Ola-Mate-R-16oz-12pk | B8: 16oz Raspberry 12pk | C8: =SUMIFS('Inventory On Hand Raw Data'!E:E,'Inventory On Hand Raw Data'!B:B,"Ola-Mate-R-16oz-12pk",'Inventory On Hand Raw Data'!A:A,"Amazon FBA") -> 0 | D8: =SUMIFS('Inventory On Hand Raw Data'!E:E,'Inventory On Hand Raw Data'!B:B,"Ola-Mate-R-16oz-12pk",'Inventory On Hand Raw Data'!A:A,"Founders") -> 0 | E8: =SUMIFS('Inventory On Hand Raw Data'!E:E,'Inventory On Hand Raw Data'!B:B,"Ola-Mate-R-16oz-12pk",'Inventory On Hand Raw Data'!A:A,"NJ Warehouse") -> 0 | F8: =SUMIFS('Inventory On Hand Raw Data'!E:E,'Inventory On Hand Raw Data'!B:B,"Ola-Mate-R-16oz-12pk",'Inventory On Hand Raw Data'!A:A,"NY Warehouse") -> 0 | G8: =SUMIFS('Inventory On Hand Raw Data'!E:E,'Inventory On Hand Raw Data'!B:B,"Ola-Mate-R-16oz-12pk",'Inventory On Hand Raw Data'!A:A,"NOBL") -> 0 | H8: =SUM(C8:G8) -> 0 | I8: =IFERROR((SUMIFS('Sales Transactions Raw Data'!T:T,'Sales Transactions Raw Data'!G:G,"Ola-Mate-R-16oz-12pk",'Sales Transactions Raw Data'!J:J,"Finished Goods",'Sales Transactions Raw Data'!A:A,2025,'Sales Transactions Raw Data'!B:B,"September")+SUMIFS('Sales Transactions Raw Data'!T:T,'Sales Transactions Raw Data'!G:G,"Ola-Mate-R-16oz-12pk",'Sales Transactions Raw Data'!J:J,"Finished Goods",'Sales Transactions Raw Data'!A:A,2025,'Sales Transactions Raw Data'!B:B,"October")+SUMIFS('Sales Transactions Raw Data'!T:T,'Sales Transactions Raw Data'!G:G,"Ola-Mate-R-16oz-12pk",'Sales Transactions Raw Data'!J:J,"Finished Goods",'Sales Transactions Raw Data'!A:A,2025,'Sales Transactions Raw Data'!B:B,"November"))/3,0) -> 0 | J8: =IF(I8=0,"N/A",H8/I8) -> N/A | K8: =IF(I8=0,"⚪ No Sales",IF(J8="N/A","⚪ No Sales",IF(J8<1,"🔴 CRITICAL",IF(J8<2,"🟡 LOW",IF(J8<=6,"🟢 HEALTHY","🔵 OVERSTOCK"))))) -> ⚪ No Sales
A9: Ola-Mate-SP1-16oz-4pk | B9: 16oz Starter 4pk | C9: =SUMIFS('Inventory On Hand Raw Data'!E:E,'Inventory On Hand Raw Data'!B:B,"Ola-Mate-SP1-16oz-4pk",'Inventory On Hand Raw Data'!A:A,"Amazon FBA") -> 0 | D9: =SUMIFS('Inventory On Hand Raw Data'!E:E,'Inventory On Hand Raw Data'!B:B,"Ola-Mate-SP1-16oz-4pk",'Inventory On Hand Raw Data'!A:A,"Founders") -> 0 | E9: =SUMIFS('Inventory On Hand Raw Data'!E:E,'Inventory On Hand Raw Data'!B:B,"Ola-Mate-SP1-16oz-4pk",'Inventory On Hand Raw Data'!A:A,"NJ Warehouse") -> 0 | F9: =SUMIFS('Inventory On Hand Raw Data'!E:E,'Inventory On Hand Raw Data'!B:B,"Ola-Mate-SP1-16oz-4pk",'Inventory On Hand Raw Data'!A:A,"NY Warehouse") -> 0 | G9: =SUMIFS('Inventory On Hand Raw Data'!E:E,'Inventory On Hand Raw Data'!B:B,"Ola-Mate-SP1-16oz-4pk",'Inventory On Hand Raw Data'!A:A,"NOBL") -> 0 | H9: =SUM(C9:G9) -> 0 | I9: =IFERROR((SUMIFS('Sales Transactions Raw Data'!T:T,'Sales Transactions Raw Data'!G:G,"Ola-Mate-SP1-16oz-4pk",'Sales Transactions Raw Data'!J:J,"Finished Goods",'Sales Transactions Raw Data'!A:A,2025,'Sales Transactions Raw Data'!B:B,"September")+SUMIFS('Sales Transactions Raw Data'!T:T,'Sales Transactions Raw Data'!G:G,"Ola-Mate-SP1-16oz-4pk",'Sales Transactions Raw Data'!J:J,"Finished Goods",'Sales Transactions Raw Data'!A:A,2025,'Sales Transactions Raw Data'!B:B,"October")+SUMIFS('Sales Transactions Raw Data'!T:T,'Sales Transactions Raw Data'!G:G,"Ola-Mate-SP1-16oz-4pk",'Sales Transactions Raw Data'!J:J,"Finished Goods",'Sales Transactions Raw Data'!A:A,2025,'Sales Transactions Raw Data'!B:B,"November"))/3,0) -> 0 | J9: =IF(I9=0,"N/A",H9/I9) -> N/A | K9: =IF(I9=0,"⚪ No Sales",IF(J9="N/A","⚪ No Sales",IF(J9<1,"🔴 CRITICAL",IF(J9<2,"🟡 LOW",IF(J9<=6,"🟢 HEALTHY","🔵 OVERSTOCK"))))) -> ⚪ No Sales
A10: Ola-Mate-BC-16oz-1can | B10: Berry Coconut 1can | C10: =SUMIFS('Inventory On Hand Raw Data'!E:E,'Inventory On Hand Raw Data'!B:B,"Ola-Mate-BC-16oz-1can",'Inventory On Hand Raw Data'!A:A,"Amazon FBA") -> 0 | D10: =SUMIFS('Inventory On Hand Raw Data'!E:E,'Inventory On Hand Raw Data'!B:B,"Ola-Mate-BC-16oz-1can",'Inventory On Hand Raw Data'!A:A,"Founders") -> 0 | E10: =SUMIFS('Inventory On Hand Raw Data'!E:E,'Inventory On Hand Raw Data'!B:B,"Ola-Mate-BC-16oz-1can",'Inventory On Hand Raw Data'!A:A,"NJ Warehouse") -> 0 | F10: =SUMIFS('Inventory On Hand Raw Data'!E:E,'Inventory On Hand Raw Data'!B:B,"Ola-Mate-BC-16oz-1can",'Inventory On Hand Raw Data'!A:A,"NY Warehouse") -> 0 | G10: =SUMIFS('Inventory On Hand Raw Data'!E:E,'Inventory On Hand Raw Data'!B:B,"Ola-Mate-BC-16oz-1can",'Inventory On Hand Raw Data'!A:A,"NOBL") -> 0 | H10: =SUM(C10:G10) -> 0 | I10: =IFERROR((SUMIFS('Sales Transactions Raw Data'!T:T,'Sales Transactions Raw Data'!G:G,"Ola-Mate-BC-16oz-1can",'Sales Transactions Raw Data'!J:J,"Finished Goods",'Sales Transactions Raw Data'!A:A,2025,'Sales Transactions Raw Data'!B:B,"September")+SUMIFS('Sales Transactions Raw Data'!T:T,'Sales Transactions Raw Data'!G:G,"Ola-Mate-BC-16oz-1can",'Sales Transactions Raw Data'!J:J,"Finished Goods",'Sales Transactions Raw Data'!A:A,2025,'Sales Transactions Raw Data'!B:B,"October")+SUMIFS('Sales Transactions Raw Data'!T:T,'Sales Transactions Raw Data'!G:G,"Ola-Mate-BC-16oz-1can",'Sales Transactions Raw Data'!J:J,"Finished Goods",'Sales Transactions Raw Data'!A:A,2025,'Sales Transactions Raw Data'!B:B,"November"))/3,0) -> 0 | J10: =IF(I10=0,"N/A",H10/I10) -> N/A | K10: =IF(I10=0,"⚪ No Sales",IF(J10="N/A","⚪ No Sales",IF(J10<1,"🔴 CRITICAL",IF(J10<2,"🟡 LOW",IF(J10<=6,"🟢 HEALTHY","🔵 OVERSTOCK"))))) -> ⚪ No Sales
A11: Ola-Mate-GG-16oz-1can | B11: Grapefruit Ginger 1can | C11: =SUMIFS('Inventory On Hand Raw Data'!E:E,'Inventory On Hand Raw Data'!B:B,"Ola-Mate-GG-16oz-1can",'Inventory On Hand Raw Data'!A:A,"Amazon FBA") -> 0 | D11: =SUMIFS('Inventory On Hand Raw Data'!E:E,'Inventory On Hand Raw Data'!B:B,"Ola-Mate-GG-16oz-1can",'Inventory On Hand Raw Data'!A:A,"Founders") -> 0 | E11: =SUMIFS('Inventory On Hand Raw Data'!E:E,'Inventory On Hand Raw Data'!B:B,"Ola-Mate-GG-16oz-1can",'Inventory On Hand Raw Data'!A:A,"NJ Warehouse") -> 0 | F11: =SUMIFS('Inventory On Hand Raw Data'!E:E,'Inventory On Hand Raw Data'!B:B,"Ola-Mate-GG-16oz-1can",'Inventory On Hand Raw Data'!A:A,"NY Warehouse") -> 0 | G11: =SUMIFS('Inventory On Hand Raw Data'!E:E,'Inventory On Hand Raw Data'!B:B,"Ola-Mate-GG-16oz-1can",'Inventory On Hand Raw Data'!A:A,"NOBL") -> 0 | H11: =SUM(C11:G11) -> 0 | I11: =IFERROR((SUMIFS('Sales Transactions Raw Data'!T:T,'Sales Transactions Raw Data'!G:G,"Ola-Mate-GG-16oz-1can",'Sales Transactions Raw Data'!J:J,"Finished Goods",'Sales Transactions Raw Data'!A:A,2025,'Sales Transactions Raw Data'!B:B,"September")+SUMIFS('Sales Transactions Raw Data'!T:T,'Sales Transactions Raw Data'!G:G,"Ola-Mate-GG-16oz-1can",'Sales Transactions Raw Data'!J:J,"Finished Goods",'Sales Transactions Raw Data'!A:A,2025,'Sales Transactions Raw Data'!B:B,"October")+SUMIFS('Sales Transactions Raw Data'!T:T,'Sales Transactions Raw Data'!G:G,"Ola-Mate-GG-16oz-1can",'Sales Transactions Raw Data'!J:J,"Finished Goods",'Sales Transactions Raw Data'!A:A,2025,'Sales Transactions Raw Data'!B:B,"November"))/3,0) -> 0 | J11: =IF(I11=0,"N/A",H11/I11) -> N/A | K11: =IF(I11=0,"⚪ No Sales",IF(J11="N/A","⚪ No Sales",IF(J11<1,"🔴 CRITICAL",IF(J11<2,"🟡 LOW",IF(J11<=6,"🟢 HEALTHY","🔵 OVERSTOCK"))))) -> ⚪ No Sales
A12: Ola-Mate-R-16oz-1can | B12: Raspberry 1can | C12: =SUMIFS('Inventory On Hand Raw Data'!E:E,'Inventory On Hand Raw Data'!B:B,"Ola-Mate-R-16oz-1can",'Inventory On Hand Raw Data'!A:A,"Amazon FBA") -> 0 | D12: =SUMIFS('Inventory On Hand Raw Data'!E:E,'Inventory On Hand Raw Data'!B:B,"Ola-Mate-R-16oz-1can",'Inventory On Hand Raw Data'!A:A,"Founders") -> 0 | E12: =SUMIFS('Inventory On Hand Raw Data'!E:E,'Inventory On Hand Raw Data'!B:B,"Ola-Mate-R-16oz-1can",'Inventory On Hand Raw Data'!A:A,"NJ Warehouse") -> 0 | F12: =SUMIFS('Inventory On Hand Raw Data'!E:E,'Inventory On Hand Raw Data'!B:B,"Ola-Mate-R-16oz-1can",'Inventory On Hand Raw Data'!A:A,"NY Warehouse") -> 0 | G12: =SUMIFS('Inventory On Hand Raw Data'!E:E,'Inventory On Hand Raw Data'!B:B,"Ola-Mate-R-16oz-1can",'Inventory On Hand Raw Data'!A:A,"NOBL") -> 0 | H12: =SUM(C12:G12) -> 0 | I12: =IFERROR((SUMIFS('Sales Transactions Raw Data'!T:T,'Sales Transactions Raw Data'!G:G,"Ola-Mate-R-16oz-1can",'Sales Transactions Raw Data'!J:J,"Finished Goods",'Sales Transactions Raw Data'!A:A,2025,'Sales Transactions Raw Data'!B:B,"September")+SUMIFS('Sales Transactions Raw Data'!T:T,'Sales Transactions Raw Data'!G:G,"Ola-Mate-R-16oz-1can",'Sales Transactions Raw Data'!J:J,"Finished Goods",'Sales Transactions Raw Data'!A:A,2025,'Sales Transactions Raw Data'!B:B,"October")+SUMIFS('Sales Transactions Raw Data'!T:T,'Sales Transactions Raw Data'!G:G,"Ola-Mate-R-16oz-1can",'Sales Transactions Raw Data'!J:J,"Finished Goods",'Sales Transactions Raw Data'!A:A,2025,'Sales Transactions Raw Data'!B:B,"November"))/3,0) -> 0 | J12: =IF(I12=0,"N/A",H12/I12) -> N/A | K12: =IF(I12=0,"⚪ No Sales",IF(J12="N/A","⚪ No Sales",IF(J12<1,"🔴 CRITICAL",IF(J12<2,"🟡 LOW",IF(J12<=6,"🟢 HEALTHY","🔵 OVERSTOCK"))))) -> ⚪ No Sales
A14: STOCK ALERT SUMMARY
A15: Alert Level | B15: Count | C15: SKUs | D15: Action Required
A16: 🔴 CRITICAL (< 1 month) | B16: =COUNTIF(K5:K12,"*CRITICAL*") -> 0 | D16: Order immediately!
A17: 🟡 LOW (1–2 months) | B17: =COUNTIF(K5:K12,"*LOW*") -> 0 | C17: {=IFERROR(_xlfn.TEXTJOIN(", ",TRUE,IF(K5:K12="🟡 LOW",A5:A12,"")),"None")} | D17: Plan reorder soon
A18: 🟢 HEALTHY (2–6 months) | B18: =COUNTIF(K5:K12,"*HEALTHY*") -> 0 | D18: Monitor only
A19: 🔵 OVERSTOCK (> 6 months) | B19: =COUNTIF(K5:K12,"*OVERSTOCK*") -> 0 | D19: Review slow movers
A21: Note: MOS uses last 3 months (Sep-Nov 2025) average unit sales. Update month references as new data is added.

Sheet Inventory Movements
A1: Inventory Movements — Monthly Stock Flow by SKU
A2: Formula: Ending Stock = Beginning + Purchases Received − Units Sold | Data from Sales & Purchase Transactions
A4: SKU / Product | B4: Metric | C4: March | D4: July | E4: August | F4: September | G4: October | H4: November
A5: 16oz Variety 12pk
A6: Ola-Mate-VP1-16oz-12pk | B6: Units Sold | C6: =SUMIFS('Sales Transactions Raw Data'!T:T,'Sales Transactions Raw Data'!G:G,"Ola-Mate-VP1-16oz-12pk",'Sales Transactions Raw Data'!B:B,"March",'Sales Transactions Raw Data'!A:A,2025,'Sales Transactions Raw Data'!J:J,"Finished Goods") -> 0 | D6: =SUMIFS('Sales Transactions Raw Data'!T:T,'Sales Transactions Raw Data'!G:G,"Ola-Mate-VP1-16oz-12pk",'Sales Transactions Raw Data'!B:B,"July",'Sales Transactions Raw Data'!A:A,2025,'Sales Transactions Raw Data'!J:J,"Finished Goods") -> 0 | E6: =SUMIFS('Sales Transactions Raw Data'!T:T,'Sales Transactions Raw Data'!G:G,"Ola-Mate-VP1-16oz-12pk",'Sales Transactions Raw Data'!B:B,"August",'Sales Transactions Raw Data'!A:A,2025,'Sales Transactions Raw Data'!J:J,"Finished Goods") -> 0 | F6: =SUMIFS('Sales Transactions Raw Data'!T:T,'Sales Transactions Raw Data'!G:G,"Ola-Mate-VP1-16oz-12pk",'Sales Transactions Raw Data'!B:B,"September",'Sales Transactions Raw Data'!A:A,2025,'Sales Transactions Raw Data'!J:J,"Finished Goods") -> 0 | G6: =SUMIFS('Sales Transactions Raw Data'!T:T,'Sales Transactions Raw Data'!G:G,"Ola-Mate-VP1-16oz-12pk",'Sales Transactions Raw Data'!B:B,"October",'Sales Transactions Raw Data'!A:A,2025,'Sales Transactions Raw Data'!J:J,"Finished Goods") -> 0 | H6: =SUMIFS('Sales Transactions Raw Data'!T:T,'Sales Transactions Raw Data'!G:G,"Ola-Mate-VP1-16oz-12pk",'Sales Transactions Raw Data'!B:B,"November",'Sales Transactions Raw Data'!A:A,2025,'Sales Transactions Raw Data'!J:J,"Finished Goods") -> 0
A7: Ola-Mate-VP1-16oz-12pk | B7: Units Purchased | C7: =SUMIFS('Purchase Transactions Raw data'!F:F,'Purchase Transactions Raw data'!B:B,"Ola-Mate-VP1-16oz-12pk",'Purchase Transactions Raw data'!H:H,"March") -> 0 | D7: =SUMIFS('Purchase Transactions Raw data'!F:F,'Purchase Transactions Raw data'!B:B,"Ola-Mate-VP1-16oz-12pk",'Purchase Transactions Raw data'!H:H,"July") -> 0 | E7: =SUMIFS('Purchase Transactions Raw data'!F:F,'Purchase Transactions Raw data'!B:B,"Ola-Mate-VP1-16oz-12pk",'Purchase Transactions Raw data'!H:H,"August") -> 0 | F7: =SUMIFS('Purchase Transactions Raw data'!F:F,'Purchase Transactions Raw data'!B:B,"Ola-Mate-VP1-16oz-12pk",'Purchase Transactions Raw data'!H:H,"September") -> 0 | G7: =SUMIFS('Purchase Transactions Raw data'!F:F,'Purchase Transactions Raw data'!B:B,"Ola-Mate-VP1-16oz-12pk",'Purchase Transactions Raw data'!H:H,"October") -> 0 | H7: =SUMIFS('Purchase Transactions Raw data'!F:F,'Purchase Transactions Raw data'!B:B,"Ola-Mate-VP1-16oz-12pk",'Purchase Transactions Raw data'!H:H,"November") -> 0
A8: Ola-Mate-VP1-16oz-12pk | B8: Net Movement | C8: =C7-C6 -> 0 | D8: =D7-D6 -> 0 | E8: =E7-E6 -> 0 | F8: =F7-F6 -> 0 | G8: =G7-G6 -> 0 | H8: =H7-H6 -> 0
A9: 16oz Berry Coconut 12pk
A10: Ola-Mate-BC-16oz-12PK | B10: Units Sold | C10: =SUMIFS('Sales Transactions Raw Data'!T:T,'Sales Transactions Raw Data'!G:G,"Ola-Mate-BC-16oz-12PK",'Sales Transactions Raw Data'!B:B,"March",'Sales Transactions Raw Data'!A:A,2025,'Sales Transactions Raw Data'!J:J,"Finished Goods") -> 0 | D10: =SUMIFS('Sales Transactions Raw Data'!T:T,'Sales Transactions Raw Data'!G:G,"Ola-Mate-BC-16oz-12PK",'Sales Transactions Raw Data'!B:B,"July",'Sales Transactions Raw Data'!A:A,2025,'Sales Transactions Raw Data'!J:J,"Finished Goods") -> 0 | E10: =SUMIFS('Sales Transactions Raw Data'!T:T,'Sales Transactions Raw Data'!G:G,"Ola-Mate-BC-16oz-12PK",'Sales Transactions Raw Data'!B:B,"August",'Sales Transactions Raw Data'!A:A,2025,'Sales Transactions Raw Data'!J:J,"Finished Goods") -> 0 | F10: =SUMIFS('Sales Transactions Raw Data'!T:T,'Sales Transactions Raw Data'!G:G,"Ola-Mate-BC-16oz-12PK",'Sales Transactions Raw Data'!B:B,"September",'Sales Transactions Raw Data'!A:A,2025,'Sales Transactions Raw Data'!J:J,"Finished Goods") -> 0 | G10: =SUMIFS('Sales Transactions Raw Data'!T:T,'Sales Transactions Raw Data'!G:G,"Ola-Mate-BC-16oz-12PK",'Sales Transactions Raw Data'!B:B,"October",'Sales Transactions Raw Data'!A:A,2025,'Sales Transactions Raw Data'!J:J,"Finished Goods") -> 0 | H10: =SUMIFS('Sales Transactions Raw Data'!T:T,'Sales Transactions Raw Data'!G:G,"Ola-Mate-BC-16oz-12PK",'Sales Transactions Raw Data'!B:B,"November",'Sales Transactions Raw Data'!A:A,2025,'Sales Transactions Raw Data'!J:J,"Finished Goods") -> 0
A11: Ola-Mate-BC-16oz-12PK | B11: Units Purchased | C11: =SUMIFS('Purchase Transactions Raw data'!F:F,'Purchase Transactions Raw data'!B:B,"Ola-Mate-BC-16oz-12PK",'Purchase Transactions Raw data'!H:H,"March") -> 0 | D11: =SUMIFS('Purchase Transactions Raw data'!F:F,'Purchase Transactions Raw data'!B:B,"Ola-Mate-BC-16oz-12PK",'Purchase Transactions Raw data'!H:H,"July") -> 0 | E11: =SUMIFS('Purchase Transactions Raw data'!F:F,'Purchase Transactions Raw data'!B:B,"Ola-Mate-BC-16oz-12PK",'Purchase Transactions Raw data'!H:H,"August") -> 0 | F11: =SUMIFS('Purchase Transactions Raw data'!F:F,'Purchase Transactions Raw data'!B:B,"Ola-Mate-BC-16oz-12PK",'Purchase Transactions Raw data'!H:H,"September") -> 0 | G11: =SUMIFS('Purchase Transactions Raw data'!F:F,'Purchase Transactions Raw data'!B:B,"Ola-Mate-BC-16oz-12PK",'Purchase Transactions Raw data'!H:H,"October") -> 0 | H11: =SUMIFS('Purchase Transactions Raw data'!F:F,'Purchase Transactions Raw data'!B:B,"Ola-Mate-BC-16oz-12PK",'Purchase Transactions Raw data'!H:H,"November") -> 0
A12: Ola-Mate-BC-16oz-12PK | B12: Net Movement | C12: =C11-C10 -> 0 | D12: =D11-D10 -> 0 | E12: =E11-E10 -> 0 | F12: =F11-F10 -> 0 | G12: =G11-G10 -> 0 | H12: =H11-H10 -> 0
A13: 16oz Grapefruit Ginger 12pk
A14: Ola-Mate-GG-16oz-12pk | B14: Units Sold | C14: =SUMIFS('Sales Transactions Raw Data'!T:T,'Sales Transactions Raw Data'!G:G,"Ola-Mate-GG-16oz-12pk",'Sales Transactions Raw Data'!B:B,"March",'Sales Transactions Raw Data'!A:A,2025,'Sales Transactions Raw Data'!J:J,"Finished Goods") -> 0 | D14: =SUMIFS('Sales Transactions Raw Data'!T:T,'Sales Transactions Raw Data'!G:G,"Ola-Mate-GG-16oz-12pk",'Sales Transactions Raw Data'!B:B,"July",'Sales Transactions Raw Data'!A:A,2025,'Sales Transactions Raw Data'!J:J,"Finished Goods") -> 0 | E14: =SUMIFS('Sales Transactions Raw Data'!T:T,'Sales Transactions Raw Data'!G:G,"Ola-Mate-GG-16oz-12pk",'Sales Transactions Raw Data'!B:B,"August",'Sales Transactions Raw Data'!A:A,2025,'Sales Transactions Raw Data'!J:J,"Finished Goods") -> 0 | F14: =SUMIFS('Sales Transactions Raw Data'!T:T,'Sales Transactions Raw Data'!G:G,"Ola-Mate-GG-16oz-12pk",'Sales Transactions Raw Data'!B:B,"September",'Sales Transactions Raw Data'!A:A,2025,'Sales Transactions Raw Data'!J:J,"Finished Goods") -> 0 | G14: =SUMIFS('Sales Transactions Raw Data'!T:T,'Sales Transactions Raw Data'!G:G,"Ola-Mate-GG-16oz-12pk",'Sales Transactions Raw Data'!B:B,"October",'Sales Transactions Raw Data'!A:A,2025,'Sales Transactions Raw Data'!J:J,"Finished Goods") -> 0 | H14: =SUMIFS('Sales Transactions Raw Data'!T:T,'Sales Transactions Raw Data'!G:G,"Ola-Mate-GG-16oz-12pk",'Sales Transactions Raw Data'!B:B,"November",'Sales Transactions Raw Data'!A:A,2025,'Sales Transactions Raw Data'!J:J,"Finished Goods") -> 0
A15: Ola-Mate-GG-16oz-12pk | B15: Units Purchased | C15: =SUMIFS('Purchase Transactions Raw data'!F:F,'Purchase Transactions Raw data'!B:B,"Ola-Mate-GG-16oz-12pk",'Purchase Transactions Raw data'!H:H,"March") -> 0 | D15: =SUMIFS('Purchase Transactions Raw data'!F:F,'Purchase Transactions Raw data'!B:B,"Ola-Mate-GG-16oz-12pk",'Purchase Transactions Raw data'!H:H,"July") -> 0 | E15: =SUMIFS('Purchase Transactions Raw data'!F:F,'Purchase Transactions Raw data'!B:B,"Ola-Mate-GG-16oz-12pk",'Purchase Transactions Raw data'!H:H,"August") -> 0 | F15: =SUMIFS('Purchase Transactions Raw data'!F:F,'Purchase Transactions Raw data'!B:B,"Ola-Mate-GG-16oz-12pk",'Purchase Transactions Raw data'!H:H,"September") -> 0 | G15: =SUMIFS('Purchase Transactions Raw data'!F:F,'Purchase Transactions Raw data'!B:B,"Ola-Mate-GG-16oz-12pk",'Purchase Transactions Raw data'!H:H,"October") -> 0 | H15: =SUMIFS('Purchase Transactions Raw data'!F:F,'Purchase Transactions Raw data'!B:B,"Ola-Mate-GG-16oz-12pk",'Purchase Transactions Raw data'!H:H,"November") -> 0
A16: Ola-Mate-GG-16oz-12pk | B16: Net Movement | C16: =C15-C14 -> 0 | D16: =D15-D14 -> 0 | E16: =E15-E14 -> 0 | F16: =F15-F14 -> 0 | G16: =G15-G14 -> 0 | H16: =H15-H14 -> 0
A17: 16oz Raspberry 12pk
A18: Ola-Mate-R-16oz-12pk | B18: Units Sold | C18: =SUMIFS('Sales Transactions Raw Data'!T:T,'Sales Transactions Raw Data'!G:G,"Ola-Mate-R-16oz-12pk",'Sales Transactions Raw Data'!B:B,"March",'Sales Transactions Raw Data'!A:A,2025,'Sales Transactions Raw Data'!J:J,"Finished Goods") -> 0 | D18: =SUMIFS('Sales Transactions Raw Data'!T:T,'Sales Transactions Raw Data'!G:G,"Ola-Mate-R-16oz-12pk",'Sales Transactions Raw Data'!B:B,"July",'Sales Transactions Raw Data'!A:A,2025,'Sales Transactions Raw Data'!J:J,"Finished Goods") -> 0 | E18: =SUMIFS('Sales Transactions Raw Data'!T:T,'Sales Transactions Raw Data'!G:G,"Ola-Mate-R-16oz-12pk",'Sales Transactions Raw Data'!B:B,"August",'Sales Transactions Raw Data'!A:A,2025,'Sales Transactions Raw Data'!J:J,"Finished Goods") -> 0 | F18: =SUMIFS('Sales Transactions Raw Data'!T:T,'Sales Transactions Raw Data'!G:G,"Ola-Mate-R-16oz-12pk",'Sales Transactions Raw Data'!B:B,"September",'Sales Transactions Raw Data'!A:A,2025,'Sales Transactions Raw Data'!J:J,"Finished Goods") -> 0 | G18: =SUMIFS('Sales Transactions Raw Data'!T:T,'Sales Transactions Raw Data'!G:G,"Ola-Mate-R-16oz-12pk",'Sales Transactions Raw Data'!B:B,"October",'Sales Transactions Raw Data'!A:A,2025,'Sales Transactions Raw Data'!J:J,"Finished Goods") -> 0 | H18: =SUMIFS('Sales Transactions Raw Data'!T:T,'Sales Transactions Raw Data'!G:G,"Ola-Mate-R-16oz-12pk",'Sales Transactions Raw Data'!B:B,"November",'Sales Transactions Raw Data'!A:A,2025,'Sales Transactions Raw Data'!J:J,"Finished Goods") -> 0
A19: Ola-Mate-R-16oz-12pk | B19: Units Purchased | C19: =SUMIFS('Purchase Transactions Raw data'!F:F,'Purchase Transactions Raw data'!B:B,"Ola-Mate-R-16oz-12pk",'Purchase Transactions Raw data'!H:H,"March") -> 0 | D19: =SUMIFS('Purchase Transactions Raw data'!F:F,'Purchase Transactions Raw data'!B:B,"Ola-Mate-R-16oz-12pk",'Purchase Transactions Raw data'!H:H,"July") -> 0 | E19: =SUMIFS('Purchase Transactions Raw data'!F:F,'Purchase Transactions Raw data'!B:B,"Ola-Mate-R-16oz-12pk",'Purchase Transactions Raw data'!H:H,"August") -> 0 | F19: =SUMIFS('Purchase Transactions Raw data'!F:F,'Purchase Transactions Raw data'!B:B,"Ola-Mate-R-16oz-12pk",'Purchase Transactions Raw data'!H:H,"September") -> 0 | G19: =SUMIFS('Purchase Transactions Raw data'!F:F,'Purchase Transactions Raw data'!B:B,"Ola-Mate-R-16oz-12pk",'Purchase Transactions Raw data'!H:H,"October") -> 0 | H19: =SUMIFS('Purchase Transactions Raw data'!F:F,'Purchase Transactions Raw data'!B:B,"Ola-Mate-R-16oz-12pk",'Purchase Transactions Raw data'!H:H,"November") -> 0
A20: Ola-Mate-R-16oz-12pk | B20: Net Movement | C20: =C19-C18 -> 0 | D20: =D19-D18 -> 0 | E20: =E19-E18 -> 0 | F20: =F19-F18 -> 0 | G20: =G19-G18 -> 0 | H20: =H19-H18 -> 0
A21: 16oz Starter 4pk
A22: Ola-Mate-SP1-16oz-4pk | B22: Units Sold | C22: =SUMIFS('Sales Transactions Raw Data'!T:T,'Sales Transactions Raw Data'!G:G,"Ola-Mate-SP1-16oz-4pk",'Sales Transactions Raw Data'!B:B,"March",'Sales Transactions Raw Data'!A:A,2025,'Sales Transactions Raw Data'!J:J,"Finished Goods") -> 0 | D22: =SUMIFS('Sales Transactions Raw Data'!T:T,'Sales Transactions Raw Data'!G:G,"Ola-Mate-SP1-16oz-4pk",'Sales Transactions Raw Data'!B:B,"July",'Sales Transactions Raw Data'!A:A,2025,'Sales Transactions Raw Data'!J:J,"Finished Goods") -> 0 | E22: =SUMIFS('Sales Transactions Raw Data'!T:T,'Sales Transactions Raw Data'!G:G,"Ola-Mate-SP1-16oz-4pk",'Sales Transactions Raw Data'!B:B,"August",'Sales Transactions Raw Data'!A:A,2025,'Sales Transactions Raw Data'!J:J,"Finished Goods") -> 0 | F22: =SUMIFS('Sales Transactions Raw Data'!T:T,'Sales Transactions Raw Data'!G:G,"Ola-Mate-SP1-16oz-4pk",'Sales Transactions Raw Data'!B:B,"September",'Sales Transactions Raw Data'!A:A,2025,'Sales Transactions Raw Data'!J:J,"Finished Goods") -> 0 | G22: =SUMIFS('Sales Transactions Raw Data'!T:T,'Sales Transactions Raw Data'!G:G,"Ola-Mate-SP1-16oz-4pk",'Sales Transactions Raw Data'!B:B,"October",'Sales Transactions Raw Data'!A:A,2025,'Sales Transactions Raw Data'!J:J,"Finished Goods") -> 0 | H22: =SUMIFS('Sales Transactions Raw Data'!T:T,'Sales Transactions Raw Data'!G:G,"Ola-Mate-SP1-16oz-4pk",'Sales Transactions Raw Data'!B:B,"November",'Sales Transactions Raw Data'!A:A,2025,'Sales Transactions Raw Data'!J:J,"Finished Goods") -> 0
A23: Ola-Mate-SP1-16oz-4pk | B23: Units Purchased | C23: =SUMIFS('Purchase Transactions Raw data'!F:F,'Purchase Transactions Raw data'!B:B,"Ola-Mate-SP1-16oz-4pk",'Purchase Transactions Raw data'!H:H,"March") -> 0 | D23: =SUMIFS('Purchase Transactions Raw data'!F:F,'Purchase Transactions Raw data'!B:B,"Ola-Mate-SP1-16oz-4pk",'Purchase Transactions Raw data'!H:H,"July") -> 0 | E23: =SUMIFS('Purchase Transactions Raw data'!F:F,'Purchase Transactions Raw data'!B:B,"Ola-Mate-SP1-16oz-4pk",'Purchase Transactions Raw data'!H:H,"August") -> 0 | F23: =SUMIFS('Purchase Transactions Raw data'!F:F,'Purchase Transactions Raw data'!B:B,"Ola-Mate-SP1-16oz-4pk",'Purchase Transactions Raw data'!H:H,"September") -> 0 | G23: =SUMIFS('Purchase Transactions Raw data'!F:F,'Purchase Transactions Raw data'!B:B,"Ola-Mate-SP1-16oz-4pk",'Purchase Transactions Raw data'!H:H,"October") -> 0 | H23: =SUMIFS('Purchase Transactions Raw data'!F:F,'Purchase Transactions Raw data'!B:B,"Ola-Mate-SP1-16oz-4pk",'Purchase Transactions Raw data'!H:H,"November") -> 0
A24: Ola-Mate-SP1-16oz-4pk | B24: Net Movement | C24: =C23-C22 -> 0 | D24: =D23-D22 -> 0 | E24: =E23-E22 -> 0 | F24: =F23-F22 -> 0 | G24: =G23-G22 -> 0 | H24: =H23-H22 -> 0
A25: Berry Coconut 1can
A26: Ola-Mate-BC-16oz-1can | B26: Units Sold | C26: =SUMIFS('Sales Transactions Raw Data'!T:T,'Sales Transactions Raw Data'!G:G,"Ola-Mate-BC-16oz-1can",'Sales Transactions Raw Data'!B:B,"March",'Sales Transactions Raw Data'!A:A,2025,'Sales Transactions Raw Data'!J:J,"Finished Goods") -> 0 | D26: =SUMIFS('Sales Transactions Raw Data'!T:T,'Sales Transactions Raw Data'!G:G,"Ola-Mate-BC-16oz-1can",'Sales Transactions Raw Data'!B:B,"July",'Sales Transactions Raw Data'!A:A,2025,'Sales Transactions Raw Data'!J:J,"Finished Goods") -> 0 | E26: =SUMIFS('Sales Transactions Raw Data'!T:T,'Sales Transactions Raw Data'!G:G,"Ola-Mate-BC-16oz-1can",'Sales Transactions Raw Data'!B:B,"August",'Sales Transactions Raw Data'!A:A,2025,'Sales Transactions Raw Data'!J:J,"Finished Goods") -> 0 | F26: =SUMIFS('Sales Transactions Raw Data'!T:T,'Sales Transactions Raw Data'!G:G,"Ola-Mate-BC-16oz-1can",'Sales Transactions Raw Data'!B:B,"September",'Sales Transactions Raw Data'!A:A,2025,'Sales Transactions Raw Data'!J:J,"Finished Goods") -> 0 | G26: =SUMIFS('Sales Transactions Raw Data'!T:T,'Sales Transactions Raw Data'!G:G,"Ola-Mate-BC-16oz-1can",'Sales Transactions Raw Data'!B:B,"October",'Sales Transactions Raw Data'!A:A,2025,'Sales Transactions Raw Data'!J:J,"Finished Goods") -> 0 | H26: =SUMIFS('Sales Transactions Raw Data'!T:T,'Sales Transactions Raw Data'!G:G,"Ola-Mate-BC-16oz-1can",'Sales Transactions Raw Data'!B:B,"November",'Sales Transactions Raw Data'!A:A,2025,'Sales Transactions Raw Data'!J:J,"Finished Goods") -> 0
A27: Ola-Mate-BC-16oz-1can | B27: Units Purchased | C27: =SUMIFS('Purchase Transactions Raw data'!F:F,'Purchase Transactions Raw data'!B:B,"Ola-Mate-BC-16oz-1can",'Purchase Transactions Raw data'!H:H,"March") -> 0 | D27: =SUMIFS('Purchase Transactions Raw data'!F:F,'Purchase Transactions Raw data'!B:B,"Ola-Mate-BC-16oz-1can",'Purchase Transactions Raw data'!H:H,"July") -> 0 | E27: =SUMIFS('Purchase Transactions Raw data'!F:F,'Purchase Transactions Raw data'!B:B,"Ola-Mate-BC-16oz-1can",'Purchase Transactions Raw data'!H:H,"August") -> 0 | F27: =SUMIFS('Purchase Transactions Raw data'!F:F,'Purchase Transactions Raw data'!B:B,"Ola-Mate-BC-16oz-1can",'Purchase Transactions Raw data'!H:H,"September") -> 0 | G27: =SUMIFS('Purchase Transactions Raw data'!F:F,'Purchase Transactions Raw data'!B:B,"Ola-Mate-BC-16oz-1can",'Purchase Transactions Raw data'!H:H,"October") -> 0 | H27: =SUMIFS('Purchase Transactions Raw data'!F:F,'Purchase Transactions Raw data'!B:B,"Ola-Mate-BC-16oz-1can",'Purchase Transactions Raw data'!H:H,"November") -> 0
A28: Ola-Mate-BC-16oz-1can | B28: Net Movement | C28: =C27-C26 -> 0 | D28: =D27-D26 -> 0 | E28: =E27-E26 -> 0 | F28: =F27-F26 -> 0 | G28: =G27-G26 -> 0 | H28: =H27-H26 -> 0
A29: Grapefruit Ginger 1can
A30: Ola-Mate-GG-16oz-1can | B30: Units Sold | C30: =SUMIFS('Sales Transactions Raw Data'!T:T,'Sales Transactions Raw Data'!G:G,"Ola-Mate-GG-16oz-1can",'Sales Transactions Raw Data'!B:B,"March",'Sales Transactions Raw Data'!A:A,2025,'Sales Transactions Raw Data'!J:J,"Finished Goods") -> 0 | D30: =SUMIFS('Sales Transactions Raw Data'!T:T,'Sales Transactions Raw Data'!G:G,"Ola-Mate-GG-16oz-1can",'Sales Transactions Raw Data'!B:B,"July",'Sales Transactions Raw Data'!A:A,2025,'Sales Transactions Raw Data'!J:J,"Finished Goods") -> 0 | E30: =SUMIFS('Sales Transactions Raw Data'!T:T,'Sales Transactions Raw Data'!G:G,"Ola-Mate-GG-16oz-1can",'Sales Transactions Raw Data'!B:B,"August",'Sales Transactions Raw Data'!A:A,2025,'Sales Transactions Raw Data'!J:J,"Finished Goods") -> 0 | F30: =SUMIFS('Sales Transactions Raw Data'!T:T,'Sales Transactions Raw Data'!G:G,"Ola-Mate-GG-16oz-1can",'Sales Transactions Raw Data'!B:B,"September",'Sales Transactions Raw Data'!A:A,2025,'Sales Transactions Raw Data'!J:J,"Finished Goods") -> 0 | G30: =SUMIFS('Sales Transactions Raw Data'!T:T,'Sales Transactions Raw Data'!G:G,"Ola-Mate-GG-16oz-1can",'Sales Transactions Raw Data'!B:B,"October",'Sales Transactions Raw Data'!A:A,2025,'Sales Transactions Raw Data'!J:J,"Finished Goods") -> 0 | H30: =SUMIFS('Sales Transactions Raw Data'!T:T,'Sales Transactions Raw Data'!G:G,"Ola-Mate-GG-16oz-1can",'Sales Transactions Raw Data'!B:B,"November",'Sales Transactions Raw Data'!A:A,2025,'Sales Transactions Raw Data'!J:J,"Finished Goods") -> 0
A31: Ola-Mate-GG-16oz-1can | B31: Units Purchased | C31: =SUMIFS('Purchase Transactions Raw data'!F:F,'Purchase Transactions Raw data'!B:B,"Ola-Mate-GG-16oz-1can",'Purchase Transactions Raw data'!H:H,"March") -> 0 | D31: =SUMIFS('Purchase Transactions Raw data'!F:F,'Purchase Transactions Raw data'!B:B,"Ola-Mate-GG-16oz-1can",'Purchase Transactions Raw data'!H:H,"July") -> 0 | E31: =SUMIFS('Purchase Transactions Raw data'!F:F,'Purchase Transactions Raw data'!B:B,"Ola-Mate-GG-16oz-1can",'Purchase Transactions Raw data'!H:H,"August") -> 0 | F31: =SUMIFS('Purchase Transactions Raw data'!F:F,'Purchase Transactions Raw data'!B:B,"Ola-Mate-GG-16oz-1can",'Purchase Transactions Raw data'!H:H,"September") -> 0 | G31: =SUMIFS('Purchase Transactions Raw data'!F:F,'Purchase Transactions Raw data'!B:B,"Ola-Mate-GG-16oz-1can",'Purchase Transactions Raw data'!H:H,"October") -> 0 | H31: =SUMIFS('Purchase Transactions Raw data'!F:F,'Purchase Transactions Raw data'!B:B,"Ola-Mate-GG-16oz-1can",'Purchase Transactions Raw data'!H:H,"November") -> 0
A32: Ola-Mate-GG-16oz-1can | B32: Net Movement | C32: =C31-C30 -> 0 | D32: =D31-D30 -> 0 | E32: =E31-E30 -> 0 | F32: =F31-F30 -> 0 | G32: =G31-G30 -> 0 | H32: =H31-H30 -> 0
A33: Raspberry 1can
A34: Ola-Mate-R-16oz-1can | B34: Units Sold | C34: =SUMIFS('Sales Transactions Raw Data'!T:T,'Sales Transactions Raw Data'!G:G,"Ola-Mate-R-16oz-1can",'Sales Transactions Raw Data'!B:B,"March",'Sales Transactions Raw Data'!A:A,2025,'Sales Transactions Raw Data'!J:J,"Finished Goods") -> 0 | D34: =SUMIFS('Sales Transactions Raw Data'!T:T,'Sales Transactions Raw Data'!G:G,"Ola-Mate-R-16oz-1can",'Sales Transactions Raw Data'!B:B,"July",'Sales Transactions Raw Data'!A:A,2025,'Sales Transactions Raw Data'!J:J,"Finished Goods") -> 0 | E34: =SUMIFS('Sales Transactions Raw Data'!T:T,'Sales Transactions Raw Data'!G:G,"Ola-Mate-R-16oz-1can",'Sales Transactions Raw Data'!B:B,"August",'Sales Transactions Raw Data'!A:A,2025,'Sales Transactions Raw Data'!J:J,"Finished Goods") -> 0 | F34: =SUMIFS('Sales Transactions Raw Data'!T:T,'Sales Transactions Raw Data'!G:G,"Ola-Mate-R-16oz-1can",'Sales Transactions Raw Data'!B:B,"September",'Sales Transactions Raw Data'!A:A,2025,'Sales Transactions Raw Data'!J:J,"Finished Goods") -> 0 | G34: =SUMIFS('Sales Transactions Raw Data'!T:T,'Sales Transactions Raw Data'!G:G,"Ola-Mate-R-16oz-1can",'Sales Transactions Raw Data'!B:B,"October",'Sales Transactions Raw Data'!A:A,2025,'Sales Transactions Raw Data'!J:J,"Finished Goods") -> 0 | H34: =SUMIFS('Sales Transactions Raw Data'!T:T,'Sales Transactions Raw Data'!G:G,"Ola-Mate-R-16oz-1can",'Sales Transactions Raw Data'!B:B,"November",'Sales Transactions Raw Data'!A:A,2025,'Sales Transactions Raw Data'!J:J,"Finished Goods") -> 0
A35: Ola-Mate-R-16oz-1can | B35: Units Purchased | C35: =SUMIFS('Purchase Transactions Raw data'!F:F,'Purchase Transactions Raw data'!B:B,"Ola-Mate-R-16oz-1can",'Purchase Transactions Raw data'!H:H,"March") -> 0 | D35: =SUMIFS('Purchase Transactions Raw data'!F:F,'Purchase Transactions Raw data'!B:B,"Ola-Mate-R-16oz-1can",'Purchase Transactions Raw data'!H:H,"July") -> 0 | E35: =SUMIFS('Purchase Transactions Raw data'!F:F,'Purchase Transactions Raw data'!B:B,"Ola-Mate-R-16oz-1can",'Purchase Transactions Raw data'!H:H,"August") -> 0 | F35: =SUMIFS('Purchase Transactions Raw data'!F:F,'Purchase Transactions Raw data'!B:B,"Ola-Mate-R-16oz-1can",'Purchase Transactions Raw data'!H:H,"September") -> 0 | G35: =SUMIFS('Purchase Transactions Raw data'!F:F,'Purchase Transactions Raw data'!B:B,"Ola-Mate-R-16oz-1can",'Purchase Transactions Raw data'!H:H,"October") -> 0 | H35: =SUMIFS('Purchase Transactions Raw data'!F:F,'Purchase Transactions Raw data'!B:B,"Ola-Mate-R-16oz-1can",'Purchase Transactions Raw data'!H:H,"November") -> 0
A36: Ola-Mate-R-16oz-1can | B36: Net Movement | C36: =C35-C34 -> 0 | D36: =D35-D34 -> 0 | E36: =E35-E34 -> 0 | F36: =F35-F34 -> 0 | G36: =G35-G34 -> 0 | H36: =H35-H34 -> 0
A38: TOTAL UNITS SOLD — ALL SKUs
A39: TOTAL | B39: Units Sold | C39: =SUMIFS('Sales Transactions Raw Data'!T:T,'Sales Transactions Raw Data'!B:B,"March",'Sales Transactions Raw Data'!A:A,2025,'Sales Transactions Raw Data'!J:J,"Finished Goods") -> 0 | D39: =SUMIFS('Sales Transactions Raw Data'!T:T,'Sales Transactions Raw Data'!B:B,"July",'Sales Transactions Raw Data'!A:A,2025,'Sales Transactions Raw Data'!J:J,"Finished Goods") -> 0 | E39: =SUMIFS('Sales Transactions Raw Data'!T:T,'Sales Transactions Raw Data'!B:B,"August",'Sales Transactions Raw Data'!A:A,2025,'Sales Transactions Raw Data'!J:J,"Finished Goods") -> 0 | F39: =SUMIFS('Sales Transactions Raw Data'!T:T,'Sales Transactions Raw Data'!B:B,"September",'Sales Transactions Raw Data'!A:A,2025,'Sales Transactions Raw Data'!J:J,"Finished Goods") -> 0 | G39: =SUMIFS('Sales Transactions Raw Data'!T:T,'Sales Transactions Raw Data'!B:B,"October",'Sales Transactions Raw Data'!A:A,2025,'Sales Transactions Raw Data'!J:J,"Finished Goods") -> 0 | H39: =SUMIFS('Sales Transactions Raw Data'!T:T,'Sales Transactions Raw Data'!B:B,"November",'Sales Transactions Raw Data'!A:A,2025,'Sales Transactions Raw Data'!J:J,"Finished Goods") -> 0

Sheet Profitability Dashboard
A1: Profitability Dashboard — Net Contribution by Channel
A2: Revenue → COGS → Gross Profit → Ad Spend (Cost Inputs) → Fulfillment → Net Contribution
A4: P&L SUMMARY (All Periods) | B4: Amazon | C4: Amazon Retail | D4: Shopify Web | E4: Shopify POS | F4: Shopify Admin | G4: Subs (contract) | H4: Subs (checkout) | I4: Wholesale 296... | J4: Faire | K4: TikTok | L4: TOTAL
A5: Revenue | B5: =SUMIFS('Sales Transactions Raw Data'!V:V,'Sales Transactions Raw Data'!S:S,"amazon",'Sales Transactions Raw Data'!J:J,"Finished Goods") -> 0 | C5: =SUMIFS('Sales Transactions Raw Data'!V:V,'Sales Transactions Raw Data'!S:S,"amazon-us",'Sales Transactions Raw Data'!J:J,"Finished Goods") -> 0 | D5: =SUMIFS('Sales Transactions Raw Data'!V:V,'Sales Transactions Raw Data'!S:S,"Shopify web",'Sales Transactions Raw Data'!J:J,"Finished Goods") -> 0 | E5: =SUMIFS('Sales Transactions Raw Data'!V:V,'Sales Transactions Raw Data'!S:S,"Shopify POS",'Sales Transactions Raw Data'!J:J,"Finished Goods") -> 0 | F5: =SUMIFS('Sales Transactions Raw Data'!V:V,'Sales Transactions Raw Data'!S:S,"Shopify admin",'Sales Transactions Raw Data'!J:J,"Finished Goods") -> 0 | G5: =SUMIFS('Sales Transactions Raw Data'!V:V,'Sales Transactions Raw Data'!S:S,"subscription_contract",'Sales Transactions Raw Data'!J:J,"Finished Goods") -> 0 | H5: =SUMIFS('Sales Transactions Raw Data'!V:V,'Sales Transactions Raw Data'!S:S,"subscription_contract_checkout_one",'Sales Transactions Raw Data'!J:J,"Finished Goods") -> 0 | I5: =SUMIFS('Sales Transactions Raw Data'!V:V,'Sales Transactions Raw Data'!S:S,"296827748353",'Sales Transactions Raw Data'!J:J,"Finished Goods") -> 0 | J5: =SUMIFS('Sales Transactions Raw Data'!V:V,'Sales Transactions Raw Data'!S:S,"faire",'Sales Transactions Raw Data'!J:J,"Finished Goods") -> 0 | K5: =SUMIFS('Sales Transactions Raw Data'!V:V,'Sales Transactions Raw Data'!S:S,"tiktok",'Sales Transactions Raw Data'!J:J,"Finished Goods") -> 0 | L5: =SUM(B5:K5) -> 0
A6: COGS | B6: =SUMIFS('Sales Transactions Raw Data'!W:W,'Sales Transactions Raw Data'!S:S,"amazon",'Sales Transactions Raw Data'!J:J,"Finished Goods") -> 0 | C6: =SUMIFS('Sales Transactions Raw Data'!W:W,'Sales Transactions Raw Data'!S:S,"amazon-us",'Sales Transactions Raw Data'!J:J,"Finished Goods") -> 0 | D6: =SUMIFS('Sales Transactions Raw Data'!W:W,'Sales Transactions Raw Data'!S:S,"Shopify web",'Sales Transactions Raw Data'!J:J,"Finished Goods") -> 0 | E6: =SUMIFS('Sales Transactions Raw Data'!W:W,'Sales Transactions Raw Data'!S:S,"Shopify POS",'Sales Transactions Raw Data'!J:J,"Finished Goods") -> 0 | F6: =SUMIFS('Sales Transactions Raw Data'!W:W,'Sales Transactions Raw Data'!S:S,"Shopify admin",'Sales Transactions Raw Data'!J:J,"Finished Goods") -> 0 | G6: =SUMIFS('Sales Transactions Raw Data'!W:W,'Sales Transactions Raw Data'!S:S,"subscription_contract",'Sales Transactions Raw Data'!J:J,"Finished Goods") -> 0 | H6: =SUMIFS('Sales Transactions Raw Data'!W:W,'Sales Transactions Raw Data'!S:S,"subscription_contract_checkout_one",'Sales Transactions Raw Data'!J:J,"Finished Goods") -> 0 | I6: =SUMIFS('Sales Transactions Raw Data'!W:W,'Sales Transactions Raw Data'!S:S,"296827748353",'Sales Transactions Raw Data'!J:J,"Finished Goods") -> 0 | J6: =SUMIFS('Sales Transactions Raw Data'!W:W,'Sales Transactions Raw Data'!S:S,"faire",'Sales Transactions Raw Data'!J:J,"Finished Goods") -> 0 | K6: =SUMIFS('Sales Transactions Raw Data'!W:W,'Sales Transactions Raw Data'!S:S,"tiktok",'Sales Transactions Raw Data'!J:J,"Finished Goods") -> 0 | L6: =SUM(B6:K6) -> 0
A7: Gross Profit | B7: =B5-B6 -> 0 | C7: =C5-C6 -> 0 | D7: =D5-D6 -> 0 | E7: =E5-E6 -> 0 | F7: =F5-F6 -> 0 | G7: =G5-G6 -> 0 | H7: =H5-H6 -> 0 | I7: =I5-I6 -> 0 | ... K7: =K5-K6 -> 0 | L7: =SUM(B7:K7) -> 0
A8: GM% | B8: =IF(B5=0,"-",B7/B5) -> - | C8: =IF(C5=0,"-",C7/C5) -> - | D8: =IF(D5=0,"-",D7/D5) -> - | E8: =IF(E5=0,"-",E7/E5) -> - | F8: =IF(F5=0,"-",F7/F5) -> - | G8: =IF(G5=0,"-",G7/G5) -> - | H8: =IF(H5=0,"-",H7/H5) -> - | I8: =IF(I5=0,"-",I7/I5) -> - | ... L8: =IF(L5=0,"-",L7/L5) -> -
A9: — Ad Spend & Fulfillment Costs (enter in Cost Inputs sheet) —
A10: Ad Spend (from Cost Inputs) | B10: =SUM('Cost Inputs'!B5:N5) -> 0 | C10: =SUM('Cost Inputs'!B5:N5) -> 0 | D10: =SUM('Cost Inputs'!B6:N6) -> 0 | E10: =SUM('Cost Inputs'!B6:N6) -> 0 | F10: 0 | G10: 0 | H10: 0 | I10: 0 | J10: 0 | K10: =SUM('Cost Inputs'!B7:N7) -> 0 | L10: =SUM(B10:K10) -> 0
A11: Fulfillment / Warehouse (rev-share alloc) | B11: =IFERROR(B5/L5*(SUM('Cost Inputs'!B13:N18)),0) -> 0 | C11: =IFERROR(C5/L5*(SUM('Cost Inputs'!B13:N18)),0) -> 0 | D11: =IFERROR(D5/L5*(SUM('Cost Inputs'!B13:N18)),0) -> 0 | E11: =IFERROR(E5/L5*(SUM('Cost Inputs'!B13:N18)),0) -> 0 | F11: =IFERROR(F5/L5*(SUM('Cost Inputs'!B13:N18)),0) -> 0 | G11: =IFERROR(G5/L5*(SUM('Cost Inputs'!B13:N18)),0) -> 0 | H11: =IFERROR(H5/L5*(SUM('Cost Inputs'!B13:N18)),0) -> 0 | I11: =IFERROR(I5/L5*(SUM('Cost Inputs'!B13:N18)),0) -> 0 | J11: =IFERROR(J5/L5*(SUM('Cost Inputs'!B13:N18)),0) -> 0 | K11: =IFERROR(K5/L5*(SUM('Cost Inputs'!B13:N18)),0) -> 0 | L11: =SUM(B11:K11) -> 0
A12: Net Contribution | B12: =B7-B10-B11 -> 0 | C12: =C7-C10-C11 -> 0 | D12: =D7-D10-D11 -> 0 | E12: =E7-E10-E11 -> 0 | F12: =F7-F10-F11 -> 0 | G12: =G7-G10-G11 -> 0 | H12: =H7-H10-H11 -> 0 | I12: =I7-I10-I11 -> 0 | ... L12: =L7-L10-L11 -> 0
A13: Net Margin % | B13: =IF(B5=0,"-",B12/B5) -> - | C13: =IF(C5=0,"-",C12/C5) -> - | D13: =IF(D5=0,"-",D12/D5) -> - | E13: =IF(E5=0,"-",E12/E5) -> - | F13: =IF(F5=0,"-",F12/F5) -> - | G13: =IF(G5=0,"-",G12/G5) -> - | H13: =IF(H5=0,"-",H12/H5) -> - | I13: =IF(I5=0,"-",I12/I5) -> - | ... L13: =IF(L5=0,"-",L12/L5) -> -
A14: Revenue Mix % | B14: =IF(L5=0,"-",B5/L5) -> - | C14: =IF(L5=0,"-",C5/L5) -> - | D14: =IF(L5=0,"-",D5/L5) -> - | E14: =IF(L5=0,"-",E5/L5) -> - | F14: =IF(L5=0,"-",F5/L5) -> - | G14: =IF(L5=0,"-",G5/L5) -> - | H14: =IF(L5=0,"-",H5/L5) -> - | I14: =IF(L5=0,"-",I5/L5) -> - | J14: =IF(L5=0,"-",J5/L5) -> - | K14: =IF(L5=0,"-",K5/L5) -> - | L14: 1
A16: 💡 Enter Ad Spend & Fulfillment costs monthly in 'Cost Inputs' sheet. Fulfillment allocated proportionally by revenue share.

Sheet Sales Dashboard
A1: Sales Dashboard — {{COMPANY_NAME}} Revenue Overview
A2: Finished Goods only | Data from Sales Transactions Raw Data
A4: CHART DATA 1: Revenue by Channel (All Periods)
A5: Channel | B5: Revenue
A6: Amazon | B6: =SUMIFS('Sales Transactions Raw Data'!V:V,'Sales Transactions Raw Data'!S:S,"amazon",'Sales Transactions Raw Data'!J:J,"Finished Goods") -> 0
A7: Shopify Web | B7: =SUMIFS('Sales Transactions Raw Data'!V:V,'Sales Transactions Raw Data'!S:S,"Shopify web",'Sales Transactions Raw Data'!J:J,"Finished Goods") -> 0
A8: Shopify POS | B8: =SUMIFS('Sales Transactions Raw Data'!V:V,'Sales Transactions Raw Data'!S:S,"Shopify POS",'Sales Transactions Raw Data'!J:J,"Finished Goods") -> 0
A9: Shopify Admin | B9: =SUMIFS('Sales Transactions Raw Data'!V:V,'Sales Transactions Raw Data'!S:S,"Shopify admin",'Sales Transactions Raw Data'!J:J,"Finished Goods") -> 0
A10: Subscriptions | B10: =SUMIFS('Sales Transactions Raw Data'!V:V,'Sales Transactions Raw Data'!S:S,"subscription_contract",'Sales Transactions Raw Data'!J:J,"Finished Goods") -> 0
A11: Wholesale | B11: =SUMIFS('Sales Transactions Raw Data'!V:V,'Sales Transactions Raw Data'!S:S,"3890849",'Sales Transactions Raw Data'!J:J,"Finished Goods") -> 0
A14: CHART DATA 2: Monthly Revenue Trend
A15: Month | B15: Revenue | C15: Gross Profit
A16: 46106 | B16: =SUMIFS('Sales Transactions Raw Data'!V:V,'Sales Transactions Raw Data'!B:B,"March",'Sales Transactions Raw Data'!A:A,2025,'Sales Transactions Raw Data'!J:J,"Finished Goods") -> 0 | C16: =B16-SUMIFS('Sales Transactions Raw Data'!W:W,'Sales Transactions Raw Data'!B:B,"March",'Sales Transactions Raw Data'!A:A,2025,'Sales Transactions Raw Data'!J:J,"Finished Goods") -> 0
A17: 46228 | B17: =SUMIFS('Sales Transactions Raw Data'!V:V,'Sales Transactions Raw Data'!B:B,"July",'Sales Transactions Raw Data'!A:A,2025,'Sales Transactions Raw Data'!J:J,"Finished Goods") -> 0 | C17: =B17-SUMIFS('Sales Transactions Raw Data'!W:W,'Sales Transactions Raw Data'!B:B,"July",'Sales Transactions Raw Data'!A:A,2025,'Sales Transactions Raw Data'!J:J,"Finished Goods") -> 0
A18: 46259 | B18: =SUMIFS('Sales Transactions Raw Data'!V:V,'Sales Transactions Raw Data'!B:B,"August",'Sales Transactions Raw Data'!A:A,2025,'Sales Transactions Raw Data'!J:J,"Finished Goods") -> 0 | C18: =B18-SUMIFS('Sales Transactions Raw Data'!W:W,'Sales Transactions Raw Data'!B:B,"August",'Sales Transactions Raw Data'!A:A,2025,'Sales Transactions Raw Data'!J:J,"Finished Goods") -> 0
A19: 46290 | B19: =SUMIFS('Sales Transactions Raw Data'!V:V,'Sales Transactions Raw Data'!B:B,"September",'Sales Transactions Raw Data'!A:A,2025,'Sales Transactions Raw Data'!J:J,"Finished Goods") -> 0 | C19: =B19-SUMIFS('Sales Transactions Raw Data'!W:W,'Sales Transactions Raw Data'!B:B,"September",'Sales Transactions Raw Data'!A:A,2025,'Sales Transactions Raw Data'!J:J,"Finished Goods") -> 0
A20: 46320 | B20: =SUMIFS('Sales Transactions Raw Data'!V:V,'Sales Transactions Raw Data'!B:B,"October",'Sales Transactions Raw Data'!A:A,2025,'Sales Transactions Raw Data'!J:J,"Finished Goods") -> 0 | C20: =B20-SUMIFS('Sales Transactions Raw Data'!W:W,'Sales Transactions Raw Data'!B:B,"October",'Sales Transactions Raw Data'!A:A,2025,'Sales Transactions Raw Data'!J:J,"Finished Goods") -> 0
A21: 46351 | B21: =SUMIFS('Sales Transactions Raw Data'!V:V,'Sales Transactions Raw Data'!B:B,"November",'Sales Transactions Raw Data'!A:A,2025,'Sales Transactions Raw Data'!J:J,"Finished Goods") -> 0 | C21: =B21-SUMIFS('Sales Transactions Raw Data'!W:W,'Sales Transactions Raw Data'!B:B,"November",'Sales Transactions Raw Data'!A:A,2025,'Sales Transactions Raw Data'!J:J,"Finished Goods") -> 0
A24: CHART DATA 3: Revenue by Product
A25: Product | B25: Revenue
A26: 16oz Variety 12pk | B26: ='Product Margin Analysis'!C5 -> 0
A27: 16oz Berry Coconut 12pk | B27: ='Product Margin Analysis'!C6 -> 0
A28: 16oz Raspberry 12pk | B28: ='Product Margin Analysis'!C7 -> 0
A29: 16oz Grapefruit Ginger 12pk | B29: ='Product Margin Analysis'!C8 -> 0
A30: 16oz Starter 4pk | B30: ='Product Margin Analysis'!C9 -> 0
A31: Loose Cans | B31: ='Product Margin Analysis'!C10 -> 0

Sheet Sheet1
A3: Count of SKU | B3: Column Labels
A4: Row Labels | B4: (blank) | C4: Grand Total
A5: (blank)
A6: (blank)
A7: Grand Total

Sheet Sales Transactions Raw Data
A1: ⚡ CIN7 ENTERPRISE ANALYTICS SUITE | CIN7 SYNC PLATFORM | B1: {{DATA_PERIOD}} | D1: {{SYNC_STATUS}} | L1: {{SYNC_STATUS}}
A2: 📋 Cover & Index | B2: KPI Dashboard | C2: KPI dashboards | D2: Weekly Order Tracker | E2: Sales Trend Analysis | F2: Product Margin Analysis
A3: TIMELINE PERIOD: | B3: {{DATA_PERIOD}} | D3: {{SYNC_STATUS}}
A4: Show COGS: Only COGS within the date range
T5: Grand Total | U5: Grand Total | V5: Grand Total | W5: Grand Total | X5: Grand Total | Y5: Grand Total | Z5: Grand Total
A6: Month | B6: Order date | C6: Order # | D6: Invoice date | E6: Document # | F6: SKU | G6: Product | H6: Brand | I6: Category | J6: Family | K6: Product tags | L6: Customer | M6: Invoice status | N6: Unit | O6: Shipment status | P6: Customer tags | Q6: Sales representative | R6: Sales Channel | S6: Quantity | T6: Invoice | U6: Sale | V6: COGS | W6: Profit less journals | X6: Journals | Y6: Profit | Z6: Profit
A7: 2026-08 | B7: 2026-08-20 | C7: ORD-2026-001 | D7: 2026-08-20 | E7: INV-ORD-2026-001 | F7: SKU-SO-892101 | G7: Cin7 Commercial Item (ORD-2026-001) | H7: VNC Commercial | I7: General Goods | J7: Finished Goods | K7: Synced | L7: Acme Logistics Ltd | M7: Complete | N7: each | O7: FULFILLED | P7: Enterprise | Q7: Cin7 Automated Sync | R7: Shopify web | S7: 1 | T7: 14500 | U7: 14500 | V7: 7975 | W7: 6525 | X7: 0 | Y7: 6525 | Z7: 0.45
A8: 2026-08 | B8: 2026-08-21 | C8: ORD-2026-002 | D8: 2026-08-21 | E8: INV-ORD-2026-002 | F8: SKU-SO-892102 | G8: Cin7 Commercial Item (ORD-2026-002) | H8: VNC Commercial | I8: General Goods | J8: Finished Goods | K8: Synced | L8: Global Business Edge | M8: Complete | N8: each | O8: FULFILLED | P8: Enterprise | Q8: Cin7 Automated Sync | R8: Shopify web | S8: 1 | T8: 8900.5 | U8: 8900.5 | V8: 4895.28 | W8: 4005.22 | X8: 0 | Y8: 4005.22 | Z8: 0.45
A9: 2026-08 | B9: 2026-08-22 | C9: ORD-2026-003 | D9: 2026-08-22 | E9: INV-ORD-2026-003 | F9: SKU-SO-892103 | G9: Cin7 Commercial Item (ORD-2026-003) | H9: VNC Commercial | I9: General Goods | J9: Finished Goods | K9: Synced | L9: Apex Trading Co | M9: Pending | N9: each | O9: FULFILLED | P9: Enterprise | Q9: Cin7 Automated Sync | R9: Shopify web | S9: 1 | T9: 3200 | U9: 3200 | V9: 1760 | W9: 1440 | X9: 0 | Y9: 1440 | Z9: 0.45
A10: 2026-08 | B10: 2026-08-23 | C10: ORD-2026-004 | D10: 2026-08-23 | E10: INV-ORD-2026-004 | F10: SKU-SO-892104 | G10: Cin7 Commercial Item (ORD-2026-004) | H10: VNC Commercial | I10: General Goods | J10: Finished Goods | K10: Synced | L10: VNC Enterprise Hub | M10: Complete | N10: each | O10: FULFILLED | P10: Enterprise | Q10: Cin7 Automated Sync | R10: Shopify web | S10: 1 | T10: 27400.75 | U10: 27400.75 | V10: 15070.41 | W10: 12330.34 | X10: 0 | Y10: 12330.34 | Z10: 0.45
A11: 2026-08 | B11: 2026-08-24 | C11: ORD-2026-005 | D11: 2026-08-24 | E11: INV-ORD-2026-005 | F11: SKU-SO-892105 | G11: Cin7 Commercial Item (ORD-2026-005) | H11: VNC Commercial | I11: General Goods | J11: Finished Goods | K11: Synced | L11: Pacific Retailers | M11: Active | N11: each | O11: FULFILLED | P11: Enterprise | Q11: Cin7 Automated Sync | R11: Shopify web | S11: 1 | T11: 11250 | U11: 11250 | V11: 6187.5 | W11: 5062.5 | X11: 0 | Y11: 5062.5 | Z11: 0.45

Sheet Inventory On Hand Raw Data
A1: ⚡ CIN7 ENTERPRISE ANALYTICS SUITE | CIN7 SYNC PLATFORM | B1: {{DATA_PERIOD}} | C1: Products Stock Level Report | D1: {{SYNC_STATUS}} | L1: {{SYNC_STATUS}}
A2: 📋 Cover & Index | B2: KPI Dashboard | C2: KPI dashboards | D2: Weekly Order Tracker | E2: Sales Trend Analysis | F2: Product Margin Analysis | G2: Grand Total | H2: Grand Total | I2: Grand Total | J2: Grand Total | K2: Grand Total
A3: TIMELINE PERIOD: | B3: {{DATA_PERIOD}} | C3: Product | D3: {{SYNC_STATUS}} | E3: Quantity on hand | F3: Allocated | G3: On order | H3: In transit | I3: Unit cost | J3: Stock on hand | K3: Available
A6: Location | B6: SKU | C6: Product | D6: Unit | E6: Quantity on hand | F6: Allocated | G6: On order | H6: In transit | I6: Unit cost | J6: Stock on hand | K6: Available

Sheet Purchase Transactions Raw data
A1: ⚡ CIN7 ENTERPRISE ANALYTICS SUITE | CIN7 SYNC PLATFORM | B1: {{DATA_PERIOD}} | D1: {{SYNC_STATUS}} | L1: {{SYNC_STATUS}}
A2: 📋 Cover & Index | B2: KPI Dashboard | C2: KPI dashboards | D2: Weekly Order Tracker | E2: Sales Trend Analysis | F2: Product Margin Analysis
A3: TIMELINE PERIOD: | B3: {{DATA_PERIOD}} | D3: {{SYNC_STATUS}}
A4: Currency: Base Currency
P5: Grand Total | Q5: Grand Total | R5: Grand Total | S5: Grand Total | T5: Grand Total
A6: Year | B6: Month | C6: Supplier | D6: Expiry date | E6: PO # | F6: Invoice # | G6: Brand | H6: Category | I6: Family | J6: SKU | K6: Product | L6: Unit | M6: Location | N6: Batch # | O6: Status | P6: Quantity | Q6: Main cost | R6: Additional cost | S6: Journal cost | T6: Tax

Sheet Cost Inputs
A1: {{COMPANY_NAME}} - Monthly Cost Inputs
A2: Enter monthly costs from accounting invoices. These feed into Profitability Dashboard.
A4: AD SPEND BY CHANNEL | B4: 46106 | C4: 46228 | D4: 46259 | E4: 46290 | F4: 46320 | G4: 46351 | H4: 46381 | I4: 46048 | J4: 46079 | K4: 46107 | M4: Total | N4: Notes
A5: Amazon Ads | B5: 0 | C5: 0 | D5: 0 | E5: 0 | F5: 0 | G5: 0 | H5: 0 | I5: 0 | J5: 0 | K5: 0 | M5: =SUM(B5:K5) -> 0 | N5: From Amazon Advertising invoices
A6: Shopify / Google Ads | B6: 0 | C6: 0 | D6: 0 | E6: 0 | F6: 0 | G6: 0 | H6: 0 | I6: 0 | J6: 0 | K6: 0 | M6: =SUM(B6:K6) -> 0 | N6: From Google Ads / Meta invoices
A7: TikTok Ads | B7: 0 | C7: 0 | D7: 0 | E7: 0 | F7: 0 | G7: 0 | H7: 0 | I7: 0 | J7: 0 | K7: 0 | M7: =SUM(B7:K7) -> 0 | N7: From TikTok Shop invoices
A8: Other Ad Spend | B8: 0 | C8: 0 | D8: 0 | E8: 0 | F8: 0 | G8: 0 | H8: 0 | I8: 0 | J8: 0 | K8: 0 | M8: =SUM(B8:K8) -> 0 | N8: Influencer, PR, etc.
A9: Total Ad Spend | B9: =SUM(B5:B8) -> 0 | C9: =SUM(C5:C8) -> 0 | D9: =SUM(D5:D8) -> 0 | E9: =SUM(E5:E8) -> 0 | F9: =SUM(F5:F8) -> 0 | G9: =SUM(G5:G8) -> 0 | H9: =SUM(H5:H8) -> 0 | I9: =SUM(I5:I8) -> 0 | ... K9: =SUM(K5:K8) -> 0 | M9: =SUM(B9:K9) -> 0
A11: WAREHOUSE & FULFILLMENT COSTS | B11: 46106 | C11: 46228 | D11: 46259 | E11: 46290 | F11: 46320 | G11: 46351 | H11: 46381 | I11: 46048 | J11: 46079 | K11: 46107 | M11: Total | N11: Notes
A12: Amazon FBA Fees | B12: 0 | C12: 0 | D12: 0 | E12: 0 | F12: 0 | G12: 0 | H12: 0 | I12: 0 | J12: 0 | K12: 0 | M12: =SUM(B12:K12) -> 0 | N12: FBA storage, pick & pack, shipping
A13: 3PL / Warehouse Fees | B13: 0 | C13: 0 | D13: 0 | E13: 0 | F13: 0 | G13: 0 | H13: 0 | I13: 0 | J13: 0 | K13: 0 | M13: =SUM(B13:K13) -> 0 | N13: NJ/NY warehouse invoices
A14: Shipping / Freight Out | B14: 0 | C14: 0 | D14: 0 | E14: 0 | F14: 0 | G14: 0 | H14: 0 | I14: 0 | J14: 0 | K14: 0 | M14: =SUM(B14:K14) -> 0 | N14: Carrier invoices (UPS, FedEx, etc.)
A15: Co-Pack / Production Fees | B15: 0 | C15: 0 | D15: 0 | E15: 0 | F15: 0 | G15: 0 | H15: 0 | I15: 0 | J15: 0 | K15: 0 | M15: =SUM(B15:K15) -> 0 | N15: NOBL co-packing fees
A16: Other Fulfillment | B16: 0 | C16: 0 | D16: 0 | E16: 0 | F16: 0 | G16: 0 | H16: 0 | I16: 0 | J16: 0 | K16: 0 | M16: =SUM(B16:K16) -> 0 | N16: Returns processing, packaging, etc.
A17: Total Fulfillment Costs | B17: =SUM(B12:B16) -> 0 | C17: =SUM(C12:C16) -> 0 | D17: =SUM(D12:D16) -> 0 | E17: =SUM(E12:E16) -> 0 | F17: =SUM(F12:F16) -> 0 | G17: =SUM(G12:G16) -> 0 | H17: =SUM(H12:H16) -> 0 | I17: =SUM(I12:I16) -> 0 | ... K17: =SUM(K12:K16) -> 0 | M17: =SUM(B17:K17) -> 0
A18: TOTAL OPERATING COSTS | B18: =B9+B17 -> 0 | C18: =C9+C17 -> 0 | D18: =D9+D17 -> 0 | E18: =E9+E17 -> 0 | F18: =F9+F17 -> 0 | G18: =G9+G17 -> 0 | H18: =H9+H17 -> 0 | I18: =I9+I17 -> 0 | ... K18: =K9+K17 -> 0 | M18: =SUM(B18:K18) -> 0
F40: =SUM(F36:F39) -> 0 | G40: =SUM(G36:G39) -> 0 | H40: =SUM(H36:H39) -> 0 | I40: =SUM(I36:I39) -> 0 | J40: =SUM(J36:J39) -> 0 | K40: =SUM(K36:K39) -> 0

Sheet Sync Log
A1: ⚡ CIN7 SYNC AUDIT LOG | CIN7 SYNC PLATFORM | L1: {{SYNC_STATUS}}
A2: 📋 Cover & Index | B2: KPI Dashboard | C2: KPI dashboards | D2: Weekly Order Tracker | E2: Sales Trend Analysis | F2: Product Margin Analysis
A4: Date & Time | B4: Status | C4: Timeline Period | D4: Rows Synced / Reason | E4: Run ID
